package kotlinx.coroutines.selects;

import kotlin.coroutines.c;
import kotlin.coroutines.jvm.internal.ContinuationImpl;
import kotlin.coroutines.jvm.internal.d;

public final class WhileSelectKt
{
  /* Error */
  public static final Object a(kotlin.jvm.b.l<? super a<? super Boolean>, kotlin.p> paraml, c<? super kotlin.p> paramc)
  {
    // Byte code:
    //   0: aload_1
    //   1: instanceof 6
    //   4: ifeq +33 -> 37
    //   7: aload_1
    //   8: checkcast 6	kotlinx/coroutines/selects/WhileSelectKt$whileSelect$1
    //   11: astore_2
    //   12: aload_2
    //   13: getfield 12	kotlinx/coroutines/selects/WhileSelectKt$whileSelect$1:label	I
    //   16: istore_3
    //   17: iload_3
    //   18: ldc 13
    //   20: iand
    //   21: ifeq +16 -> 37
    //   24: aload_2
    //   25: iload_3
    //   26: ldc 13
    //   28: iadd
    //   29: putfield 12	kotlinx/coroutines/selects/WhileSelectKt$whileSelect$1:label	I
    //   32: aload_2
    //   33: astore_1
    //   34: goto +12 -> 46
    //   37: new 6	kotlinx/coroutines/selects/WhileSelectKt$whileSelect$1
    //   40: dup
    //   41: aload_1
    //   42: invokespecial 17	kotlinx/coroutines/selects/WhileSelectKt$whileSelect$1:<init>	(Lkotlin/coroutines/c;)V
    //   45: astore_1
    //   46: aload_1
    //   47: getfield 21	kotlinx/coroutines/selects/WhileSelectKt$whileSelect$1:result	Ljava/lang/Object;
    //   50: astore_2
    //   51: invokestatic 27	kotlin/coroutines/intrinsics/a:d	()Ljava/lang/Object;
    //   54: astore 4
    //   56: aload_1
    //   57: getfield 12	kotlinx/coroutines/selects/WhileSelectKt$whileSelect$1:label	I
    //   60: istore_3
    //   61: iload_3
    //   62: ifeq +33 -> 95
    //   65: iload_3
    //   66: iconst_1
    //   67: if_icmpne +18 -> 85
    //   70: aload_1
    //   71: getfield 30	kotlinx/coroutines/selects/WhileSelectKt$whileSelect$1:L$0	Ljava/lang/Object;
    //   74: checkcast 32	kotlin/jvm/b/l
    //   77: astore_0
    //   78: aload_2
    //   79: invokestatic 38	kotlin/k:b	(Ljava/lang/Object;)V
    //   82: goto +86 -> 168
    //   85: new 40	java/lang/IllegalStateException
    //   88: dup
    //   89: ldc 42
    //   91: invokespecial 45	java/lang/IllegalStateException:<init>	(Ljava/lang/String;)V
    //   94: athrow
    //   95: aload_2
    //   96: invokestatic 38	kotlin/k:b	(Ljava/lang/Object;)V
    //   99: aload_1
    //   100: aload_0
    //   101: putfield 30	kotlinx/coroutines/selects/WhileSelectKt$whileSelect$1:L$0	Ljava/lang/Object;
    //   104: aload_1
    //   105: iconst_1
    //   106: putfield 12	kotlinx/coroutines/selects/WhileSelectKt$whileSelect$1:label	I
    //   109: new 47	kotlinx/coroutines/selects/b
    //   112: dup
    //   113: aload_1
    //   114: invokespecial 48	kotlinx/coroutines/selects/b:<init>	(Lkotlin/coroutines/c;)V
    //   117: astore_2
    //   118: aload_0
    //   119: aload_2
    //   120: invokeinterface 52 2 0
    //   125: pop
    //   126: goto +11 -> 137
    //   129: astore 5
    //   131: aload_2
    //   132: aload 5
    //   134: invokevirtual 56	kotlinx/coroutines/selects/b:P	(Ljava/lang/Throwable;)V
    //   137: aload_2
    //   138: invokevirtual 59	kotlinx/coroutines/selects/b:N	()Ljava/lang/Object;
    //   141: astore 5
    //   143: aload 5
    //   145: invokestatic 27	kotlin/coroutines/intrinsics/a:d	()Ljava/lang/Object;
    //   148: if_acmpne +7 -> 155
    //   151: aload_1
    //   152: invokestatic 64	kotlin/coroutines/jvm/internal/f:c	(Lkotlin/coroutines/c;)V
    //   155: aload 5
    //   157: astore_2
    //   158: aload 5
    //   160: aload 4
    //   162: if_acmpne +6 -> 168
    //   165: aload 4
    //   167: areturn
    //   168: aload_2
    //   169: checkcast 66	java/lang/Boolean
    //   172: invokevirtual 70	java/lang/Boolean:booleanValue	()Z
    //   175: ifeq +6 -> 181
    //   178: goto -79 -> 99
    //   181: getstatic 75	kotlin/p:a	Lkotlin/p;
    //   184: areturn
    // Local variable table:
    //   start	length	slot	name	signature
    //   0	185	0	paraml	kotlin.jvm.b.l<? super a<? super Boolean>, kotlin.p>
    //   0	185	1	paramc	c<? super kotlin.p>
    //   11	158	2	localObject1	Object
    //   16	52	3	i	int
    //   54	112	4	localObject2	Object
    //   129	4	5	localThrowable	Throwable
    //   141	18	5	localObject3	Object
    // Exception table:
    //   from	to	target	type
    //   118	126	129	finally
  }
}


/* Location:              C:\Users\User\Desktop\decompile\jdgui110\Tapojar.jar!\kotlinx\coroutines\selects\WhileSelectKt.class
 * Java compiler version: 6 (50.0)
 * JD-Core Version:       0.7.1
 */