package com.tplink.libtpanalytics.utils.l;

public class e
{
  /* Error */
  public static java.security.PrivateKey a(android.content.Context paramContext, String paramString)
  {
    // Byte code:
    //   0: aload_0
    //   1: invokevirtual 19	android/content/Context:getAssets	()Landroid/content/res/AssetManager;
    //   4: astore_0
    //   5: new 21	java/lang/StringBuilder
    //   8: dup
    //   9: invokespecial 24	java/lang/StringBuilder:<init>	()V
    //   12: astore_2
    //   13: aconst_null
    //   14: astore_3
    //   15: aload_0
    //   16: aload_1
    //   17: invokevirtual 30	android/content/res/AssetManager:open	(Ljava/lang/String;)Ljava/io/InputStream;
    //   20: astore_0
    //   21: new 32	java/io/BufferedReader
    //   24: astore 4
    //   26: new 34	java/io/InputStreamReader
    //   29: astore_1
    //   30: aload_1
    //   31: aload_0
    //   32: invokespecial 37	java/io/InputStreamReader:<init>	(Ljava/io/InputStream;)V
    //   35: aload 4
    //   37: aload_1
    //   38: invokespecial 40	java/io/BufferedReader:<init>	(Ljava/io/Reader;)V
    //   41: aload_0
    //   42: astore_1
    //   43: aload 4
    //   45: astore_3
    //   46: aload 4
    //   48: invokevirtual 44	java/io/BufferedReader:readLine	()Ljava/lang/String;
    //   51: astore 5
    //   53: aload 5
    //   55: ifnull +30 -> 85
    //   58: aload_0
    //   59: astore_1
    //   60: aload 4
    //   62: astore_3
    //   63: aload_2
    //   64: aload 5
    //   66: invokevirtual 48	java/lang/StringBuilder:append	(Ljava/lang/String;)Ljava/lang/StringBuilder;
    //   69: pop
    //   70: aload_0
    //   71: astore_1
    //   72: aload 4
    //   74: astore_3
    //   75: aload_2
    //   76: bipush 10
    //   78: invokevirtual 51	java/lang/StringBuilder:append	(C)Ljava/lang/StringBuilder;
    //   81: pop
    //   82: goto -41 -> 41
    //   85: aload_0
    //   86: astore_1
    //   87: aload 4
    //   89: astore_3
    //   90: new 53	org/bouncycastle/openssl/e
    //   93: astore 6
    //   95: aload_0
    //   96: astore_1
    //   97: aload 4
    //   99: astore_3
    //   100: new 55	java/io/StringReader
    //   103: astore 5
    //   105: aload_0
    //   106: astore_1
    //   107: aload 4
    //   109: astore_3
    //   110: aload 5
    //   112: aload_2
    //   113: invokevirtual 58	java/lang/StringBuilder:toString	()Ljava/lang/String;
    //   116: invokespecial 61	java/io/StringReader:<init>	(Ljava/lang/String;)V
    //   119: aload_0
    //   120: astore_1
    //   121: aload 4
    //   123: astore_3
    //   124: aload 6
    //   126: aload 5
    //   128: invokespecial 62	org/bouncycastle/openssl/e:<init>	(Ljava/io/Reader;)V
    //   131: aload_0
    //   132: astore_1
    //   133: aload 4
    //   135: astore_3
    //   136: new 53	org/bouncycastle/openssl/e
    //   139: astore 5
    //   141: aload_0
    //   142: astore_1
    //   143: aload 4
    //   145: astore_3
    //   146: new 55	java/io/StringReader
    //   149: astore 7
    //   151: aload_0
    //   152: astore_1
    //   153: aload 4
    //   155: astore_3
    //   156: aload 7
    //   158: aload_2
    //   159: invokevirtual 58	java/lang/StringBuilder:toString	()Ljava/lang/String;
    //   162: invokespecial 61	java/io/StringReader:<init>	(Ljava/lang/String;)V
    //   165: aload_0
    //   166: astore_1
    //   167: aload 4
    //   169: astore_3
    //   170: aload 5
    //   172: aload 7
    //   174: invokespecial 62	org/bouncycastle/openssl/e:<init>	(Ljava/io/Reader;)V
    //   177: aload_0
    //   178: astore_1
    //   179: aload 4
    //   181: astore_3
    //   182: aload 6
    //   184: invokevirtual 66	org/bouncycastle/openssl/e:readObject	()Ljava/lang/Object;
    //   187: checkcast 68	org/bouncycastle/asn1/n2/h
    //   190: astore 6
    //   192: aload_0
    //   193: astore_1
    //   194: aload 4
    //   196: astore_3
    //   197: new 70	org/bouncycastle/openssl/g/a
    //   200: astore_2
    //   201: aload_0
    //   202: astore_1
    //   203: aload 4
    //   205: astore_3
    //   206: aload_2
    //   207: invokespecial 71	org/bouncycastle/openssl/g/a:<init>	()V
    //   210: aload_0
    //   211: astore_1
    //   212: aload 4
    //   214: astore_3
    //   215: aload_2
    //   216: aload 6
    //   218: invokevirtual 75	org/bouncycastle/openssl/g/a:c	(Lorg/bouncycastle/asn1/n2/h;)Ljava/security/PrivateKey;
    //   221: astore_2
    //   222: aload 4
    //   224: invokevirtual 78	java/io/BufferedReader:close	()V
    //   227: aload_0
    //   228: ifnull +15 -> 243
    //   231: aload_0
    //   232: invokevirtual 81	java/io/InputStream:close	()V
    //   235: goto +8 -> 243
    //   238: astore_0
    //   239: aload_0
    //   240: invokevirtual 84	java/io/IOException:printStackTrace	()V
    //   243: aload_2
    //   244: areturn
    //   245: astore_2
    //   246: aload_0
    //   247: astore_1
    //   248: aload 4
    //   250: astore_3
    //   251: aload_2
    //   252: invokevirtual 85	java/lang/Exception:printStackTrace	()V
    //   255: aload_0
    //   256: astore_1
    //   257: aload 4
    //   259: astore_3
    //   260: aload 5
    //   262: invokevirtual 66	org/bouncycastle/openssl/e:readObject	()Ljava/lang/Object;
    //   265: checkcast 87	org/bouncycastle/openssl/c
    //   268: astore 5
    //   270: aload_0
    //   271: astore_1
    //   272: aload 4
    //   274: astore_3
    //   275: new 70	org/bouncycastle/openssl/g/a
    //   278: astore_2
    //   279: aload_0
    //   280: astore_1
    //   281: aload 4
    //   283: astore_3
    //   284: aload_2
    //   285: invokespecial 71	org/bouncycastle/openssl/g/a:<init>	()V
    //   288: aload_0
    //   289: astore_1
    //   290: aload 4
    //   292: astore_3
    //   293: aload_2
    //   294: aload 5
    //   296: invokevirtual 91	org/bouncycastle/openssl/g/a:b	(Lorg/bouncycastle/openssl/c;)Ljava/security/KeyPair;
    //   299: invokevirtual 97	java/security/KeyPair:getPrivate	()Ljava/security/PrivateKey;
    //   302: astore_2
    //   303: aload 4
    //   305: invokevirtual 78	java/io/BufferedReader:close	()V
    //   308: aload_0
    //   309: ifnull +15 -> 324
    //   312: aload_0
    //   313: invokevirtual 81	java/io/InputStream:close	()V
    //   316: goto +8 -> 324
    //   319: astore_0
    //   320: aload_0
    //   321: invokevirtual 84	java/io/IOException:printStackTrace	()V
    //   324: aload_2
    //   325: areturn
    //   326: astore 5
    //   328: aload_0
    //   329: astore_2
    //   330: aload 4
    //   332: astore_0
    //   333: goto +30 -> 363
    //   336: astore_1
    //   337: goto +72 -> 409
    //   340: astore 5
    //   342: aconst_null
    //   343: astore_1
    //   344: aload_0
    //   345: astore_2
    //   346: aload_1
    //   347: astore_0
    //   348: goto +15 -> 363
    //   351: astore_1
    //   352: aconst_null
    //   353: astore_0
    //   354: goto +55 -> 409
    //   357: astore 5
    //   359: aconst_null
    //   360: astore_2
    //   361: aload_2
    //   362: astore_0
    //   363: aload_2
    //   364: astore_1
    //   365: aload_0
    //   366: astore_3
    //   367: aload 5
    //   369: invokevirtual 85	java/lang/Exception:printStackTrace	()V
    //   372: aload_0
    //   373: ifnull +14 -> 387
    //   376: aload_0
    //   377: invokevirtual 78	java/io/BufferedReader:close	()V
    //   380: goto +7 -> 387
    //   383: astore_0
    //   384: goto +14 -> 398
    //   387: aload_2
    //   388: ifnull +14 -> 402
    //   391: aload_2
    //   392: invokevirtual 81	java/io/InputStream:close	()V
    //   395: goto +7 -> 402
    //   398: aload_0
    //   399: invokevirtual 84	java/io/IOException:printStackTrace	()V
    //   402: aconst_null
    //   403: areturn
    //   404: astore_2
    //   405: aload_1
    //   406: astore_0
    //   407: aload_2
    //   408: astore_1
    //   409: aload_3
    //   410: ifnull +14 -> 424
    //   413: aload_3
    //   414: invokevirtual 78	java/io/BufferedReader:close	()V
    //   417: goto +7 -> 424
    //   420: astore_0
    //   421: goto +14 -> 435
    //   424: aload_0
    //   425: ifnull +14 -> 439
    //   428: aload_0
    //   429: invokevirtual 81	java/io/InputStream:close	()V
    //   432: goto +7 -> 439
    //   435: aload_0
    //   436: invokevirtual 84	java/io/IOException:printStackTrace	()V
    //   439: aload_1
    //   440: athrow
    // Local variable table:
    //   start	length	slot	name	signature
    //   0	441	0	paramContext	android.content.Context
    //   0	441	1	paramString	String
    //   12	232	2	localObject1	Object
    //   245	7	2	localException1	Exception
    //   278	114	2	localObject2	Object
    //   404	4	2	localObject3	Object
    //   14	400	3	localObject4	Object
    //   24	307	4	localBufferedReader	java.io.BufferedReader
    //   51	244	5	localObject5	Object
    //   326	1	5	localException2	Exception
    //   340	1	5	localException3	Exception
    //   357	11	5	localException4	Exception
    //   93	124	6	localObject6	Object
    //   149	24	7	localStringReader	java.io.StringReader
    // Exception table:
    //   from	to	target	type
    //   222	227	238	java/io/IOException
    //   231	235	238	java/io/IOException
    //   182	192	245	java/lang/Exception
    //   197	201	245	java/lang/Exception
    //   206	210	245	java/lang/Exception
    //   215	222	245	java/lang/Exception
    //   303	308	319	java/io/IOException
    //   312	316	319	java/io/IOException
    //   46	53	326	java/lang/Exception
    //   63	70	326	java/lang/Exception
    //   75	82	326	java/lang/Exception
    //   90	95	326	java/lang/Exception
    //   100	105	326	java/lang/Exception
    //   110	119	326	java/lang/Exception
    //   124	131	326	java/lang/Exception
    //   136	141	326	java/lang/Exception
    //   146	151	326	java/lang/Exception
    //   156	165	326	java/lang/Exception
    //   170	177	326	java/lang/Exception
    //   251	255	326	java/lang/Exception
    //   260	270	326	java/lang/Exception
    //   275	279	326	java/lang/Exception
    //   284	288	326	java/lang/Exception
    //   293	303	326	java/lang/Exception
    //   21	41	336	finally
    //   21	41	340	java/lang/Exception
    //   15	21	351	finally
    //   15	21	357	java/lang/Exception
    //   376	380	383	java/io/IOException
    //   391	395	383	java/io/IOException
    //   46	53	404	finally
    //   63	70	404	finally
    //   75	82	404	finally
    //   90	95	404	finally
    //   100	105	404	finally
    //   110	119	404	finally
    //   124	131	404	finally
    //   136	141	404	finally
    //   146	151	404	finally
    //   156	165	404	finally
    //   170	177	404	finally
    //   182	192	404	finally
    //   197	201	404	finally
    //   206	210	404	finally
    //   215	222	404	finally
    //   251	255	404	finally
    //   260	270	404	finally
    //   275	279	404	finally
    //   284	288	404	finally
    //   293	303	404	finally
    //   367	372	404	finally
    //   413	417	420	java/io/IOException
    //   428	432	420	java/io/IOException
  }
  
  /* Error */
  public static java.security.PublicKey b(android.content.Context paramContext, String paramString)
  {
    // Byte code:
    //   0: aload_0
    //   1: invokevirtual 19	android/content/Context:getAssets	()Landroid/content/res/AssetManager;
    //   4: astore_0
    //   5: new 21	java/lang/StringBuilder
    //   8: dup
    //   9: invokespecial 24	java/lang/StringBuilder:<init>	()V
    //   12: astore_2
    //   13: aconst_null
    //   14: astore_3
    //   15: aload_0
    //   16: aload_1
    //   17: invokevirtual 30	android/content/res/AssetManager:open	(Ljava/lang/String;)Ljava/io/InputStream;
    //   20: astore_0
    //   21: new 32	java/io/BufferedReader
    //   24: astore 4
    //   26: new 34	java/io/InputStreamReader
    //   29: astore_1
    //   30: aload_1
    //   31: aload_0
    //   32: invokespecial 37	java/io/InputStreamReader:<init>	(Ljava/io/InputStream;)V
    //   35: aload 4
    //   37: aload_1
    //   38: invokespecial 40	java/io/BufferedReader:<init>	(Ljava/io/Reader;)V
    //   41: aload_0
    //   42: astore_1
    //   43: aload 4
    //   45: astore_3
    //   46: aload 4
    //   48: invokevirtual 44	java/io/BufferedReader:readLine	()Ljava/lang/String;
    //   51: astore 5
    //   53: aload 5
    //   55: ifnull +30 -> 85
    //   58: aload_0
    //   59: astore_1
    //   60: aload 4
    //   62: astore_3
    //   63: aload_2
    //   64: aload 5
    //   66: invokevirtual 48	java/lang/StringBuilder:append	(Ljava/lang/String;)Ljava/lang/StringBuilder;
    //   69: pop
    //   70: aload_0
    //   71: astore_1
    //   72: aload 4
    //   74: astore_3
    //   75: aload_2
    //   76: bipush 10
    //   78: invokevirtual 51	java/lang/StringBuilder:append	(C)Ljava/lang/StringBuilder;
    //   81: pop
    //   82: goto -41 -> 41
    //   85: aload_0
    //   86: astore_1
    //   87: aload 4
    //   89: astore_3
    //   90: new 53	org/bouncycastle/openssl/e
    //   93: astore 6
    //   95: aload_0
    //   96: astore_1
    //   97: aload 4
    //   99: astore_3
    //   100: new 55	java/io/StringReader
    //   103: astore 5
    //   105: aload_0
    //   106: astore_1
    //   107: aload 4
    //   109: astore_3
    //   110: aload 5
    //   112: aload_2
    //   113: invokevirtual 58	java/lang/StringBuilder:toString	()Ljava/lang/String;
    //   116: invokespecial 61	java/io/StringReader:<init>	(Ljava/lang/String;)V
    //   119: aload_0
    //   120: astore_1
    //   121: aload 4
    //   123: astore_3
    //   124: aload 6
    //   126: aload 5
    //   128: invokespecial 62	org/bouncycastle/openssl/e:<init>	(Ljava/io/Reader;)V
    //   131: aload_0
    //   132: astore_1
    //   133: aload 4
    //   135: astore_3
    //   136: new 53	org/bouncycastle/openssl/e
    //   139: astore 5
    //   141: aload_0
    //   142: astore_1
    //   143: aload 4
    //   145: astore_3
    //   146: new 55	java/io/StringReader
    //   149: astore 7
    //   151: aload_0
    //   152: astore_1
    //   153: aload 4
    //   155: astore_3
    //   156: aload 7
    //   158: aload_2
    //   159: invokevirtual 58	java/lang/StringBuilder:toString	()Ljava/lang/String;
    //   162: invokespecial 61	java/io/StringReader:<init>	(Ljava/lang/String;)V
    //   165: aload_0
    //   166: astore_1
    //   167: aload 4
    //   169: astore_3
    //   170: aload 5
    //   172: aload 7
    //   174: invokespecial 62	org/bouncycastle/openssl/e:<init>	(Ljava/io/Reader;)V
    //   177: aload_0
    //   178: astore_1
    //   179: aload 4
    //   181: astore_3
    //   182: aload 6
    //   184: invokevirtual 66	org/bouncycastle/openssl/e:readObject	()Ljava/lang/Object;
    //   187: checkcast 100	org/bouncycastle/asn1/x509/w
    //   190: astore 6
    //   192: aload_0
    //   193: astore_1
    //   194: aload 4
    //   196: astore_3
    //   197: new 70	org/bouncycastle/openssl/g/a
    //   200: astore_2
    //   201: aload_0
    //   202: astore_1
    //   203: aload 4
    //   205: astore_3
    //   206: aload_2
    //   207: invokespecial 71	org/bouncycastle/openssl/g/a:<init>	()V
    //   210: aload_0
    //   211: astore_1
    //   212: aload 4
    //   214: astore_3
    //   215: aload_2
    //   216: aload 6
    //   218: invokevirtual 104	org/bouncycastle/openssl/g/a:d	(Lorg/bouncycastle/asn1/x509/w;)Ljava/security/PublicKey;
    //   221: astore_2
    //   222: aload 4
    //   224: invokevirtual 78	java/io/BufferedReader:close	()V
    //   227: aload_0
    //   228: ifnull +15 -> 243
    //   231: aload_0
    //   232: invokevirtual 81	java/io/InputStream:close	()V
    //   235: goto +8 -> 243
    //   238: astore_0
    //   239: aload_0
    //   240: invokevirtual 84	java/io/IOException:printStackTrace	()V
    //   243: aload_2
    //   244: areturn
    //   245: astore_2
    //   246: aload_0
    //   247: astore_1
    //   248: aload 4
    //   250: astore_3
    //   251: aload_2
    //   252: invokevirtual 85	java/lang/Exception:printStackTrace	()V
    //   255: aload_0
    //   256: astore_1
    //   257: aload 4
    //   259: astore_3
    //   260: aload 5
    //   262: invokevirtual 66	org/bouncycastle/openssl/e:readObject	()Ljava/lang/Object;
    //   265: checkcast 87	org/bouncycastle/openssl/c
    //   268: astore 5
    //   270: aload_0
    //   271: astore_1
    //   272: aload 4
    //   274: astore_3
    //   275: new 70	org/bouncycastle/openssl/g/a
    //   278: astore_2
    //   279: aload_0
    //   280: astore_1
    //   281: aload 4
    //   283: astore_3
    //   284: aload_2
    //   285: invokespecial 71	org/bouncycastle/openssl/g/a:<init>	()V
    //   288: aload_0
    //   289: astore_1
    //   290: aload 4
    //   292: astore_3
    //   293: aload_2
    //   294: aload 5
    //   296: invokevirtual 91	org/bouncycastle/openssl/g/a:b	(Lorg/bouncycastle/openssl/c;)Ljava/security/KeyPair;
    //   299: invokevirtual 108	java/security/KeyPair:getPublic	()Ljava/security/PublicKey;
    //   302: astore_2
    //   303: aload 4
    //   305: invokevirtual 78	java/io/BufferedReader:close	()V
    //   308: aload_0
    //   309: ifnull +15 -> 324
    //   312: aload_0
    //   313: invokevirtual 81	java/io/InputStream:close	()V
    //   316: goto +8 -> 324
    //   319: astore_0
    //   320: aload_0
    //   321: invokevirtual 84	java/io/IOException:printStackTrace	()V
    //   324: aload_2
    //   325: areturn
    //   326: astore_2
    //   327: aload_0
    //   328: astore 5
    //   330: aload 4
    //   332: astore_0
    //   333: goto +31 -> 364
    //   336: astore_1
    //   337: goto +75 -> 412
    //   340: astore_2
    //   341: aconst_null
    //   342: astore_1
    //   343: aload_0
    //   344: astore 5
    //   346: aload_1
    //   347: astore_0
    //   348: goto +16 -> 364
    //   351: astore_1
    //   352: aconst_null
    //   353: astore_0
    //   354: goto +58 -> 412
    //   357: astore_2
    //   358: aconst_null
    //   359: astore 5
    //   361: aload 5
    //   363: astore_0
    //   364: aload 5
    //   366: astore_1
    //   367: aload_0
    //   368: astore_3
    //   369: aload_2
    //   370: invokevirtual 85	java/lang/Exception:printStackTrace	()V
    //   373: aload_0
    //   374: ifnull +14 -> 388
    //   377: aload_0
    //   378: invokevirtual 78	java/io/BufferedReader:close	()V
    //   381: goto +7 -> 388
    //   384: astore_0
    //   385: goto +16 -> 401
    //   388: aload 5
    //   390: ifnull +15 -> 405
    //   393: aload 5
    //   395: invokevirtual 81	java/io/InputStream:close	()V
    //   398: goto +7 -> 405
    //   401: aload_0
    //   402: invokevirtual 84	java/io/IOException:printStackTrace	()V
    //   405: aconst_null
    //   406: areturn
    //   407: astore_2
    //   408: aload_1
    //   409: astore_0
    //   410: aload_2
    //   411: astore_1
    //   412: aload_3
    //   413: ifnull +14 -> 427
    //   416: aload_3
    //   417: invokevirtual 78	java/io/BufferedReader:close	()V
    //   420: goto +7 -> 427
    //   423: astore_0
    //   424: goto +14 -> 438
    //   427: aload_0
    //   428: ifnull +14 -> 442
    //   431: aload_0
    //   432: invokevirtual 81	java/io/InputStream:close	()V
    //   435: goto +7 -> 442
    //   438: aload_0
    //   439: invokevirtual 84	java/io/IOException:printStackTrace	()V
    //   442: aload_1
    //   443: athrow
    // Local variable table:
    //   start	length	slot	name	signature
    //   0	444	0	paramContext	android.content.Context
    //   0	444	1	paramString	String
    //   12	232	2	localObject1	Object
    //   245	7	2	localException1	Exception
    //   278	47	2	localObject2	Object
    //   326	1	2	localException2	Exception
    //   340	1	2	localException3	Exception
    //   357	13	2	localException4	Exception
    //   407	4	2	localObject3	Object
    //   14	403	3	localObject4	Object
    //   24	307	4	localBufferedReader	java.io.BufferedReader
    //   51	343	5	localObject5	Object
    //   93	124	6	localObject6	Object
    //   149	24	7	localStringReader	java.io.StringReader
    // Exception table:
    //   from	to	target	type
    //   222	227	238	java/io/IOException
    //   231	235	238	java/io/IOException
    //   182	192	245	java/lang/Exception
    //   197	201	245	java/lang/Exception
    //   206	210	245	java/lang/Exception
    //   215	222	245	java/lang/Exception
    //   303	308	319	java/io/IOException
    //   312	316	319	java/io/IOException
    //   46	53	326	java/lang/Exception
    //   63	70	326	java/lang/Exception
    //   75	82	326	java/lang/Exception
    //   90	95	326	java/lang/Exception
    //   100	105	326	java/lang/Exception
    //   110	119	326	java/lang/Exception
    //   124	131	326	java/lang/Exception
    //   136	141	326	java/lang/Exception
    //   146	151	326	java/lang/Exception
    //   156	165	326	java/lang/Exception
    //   170	177	326	java/lang/Exception
    //   251	255	326	java/lang/Exception
    //   260	270	326	java/lang/Exception
    //   275	279	326	java/lang/Exception
    //   284	288	326	java/lang/Exception
    //   293	303	326	java/lang/Exception
    //   21	41	336	finally
    //   21	41	340	java/lang/Exception
    //   15	21	351	finally
    //   15	21	357	java/lang/Exception
    //   377	381	384	java/io/IOException
    //   393	398	384	java/io/IOException
    //   46	53	407	finally
    //   63	70	407	finally
    //   75	82	407	finally
    //   90	95	407	finally
    //   100	105	407	finally
    //   110	119	407	finally
    //   124	131	407	finally
    //   136	141	407	finally
    //   146	151	407	finally
    //   156	165	407	finally
    //   170	177	407	finally
    //   182	192	407	finally
    //   197	201	407	finally
    //   206	210	407	finally
    //   215	222	407	finally
    //   251	255	407	finally
    //   260	270	407	finally
    //   275	279	407	finally
    //   284	288	407	finally
    //   293	303	407	finally
    //   369	373	407	finally
    //   416	420	423	java/io/IOException
    //   431	435	423	java/io/IOException
  }
}


/* Location:              C:\Users\User\Desktop\decompile\jdgui110\Tapojar.jar!\com\tplink\libtpanalytics\utils\l\e.class
 * Java compiler version: 6 (50.0)
 * JD-Core Version:       0.7.1
 */