package io.reactivex.observers;

import io.reactivex.v;

public final class c<T>
  implements v<T>, io.reactivex.e0.c
{
  final v<? super T> c;
  io.reactivex.e0.c d;
  boolean f;
  
  public c(v<? super T> paramv)
  {
    this.c = paramv;
  }
  
  /* Error */
  void a()
  {
    // Byte code:
    //   0: new 29	java/lang/NullPointerException
    //   3: dup
    //   4: ldc 31
    //   6: invokespecial 34	java/lang/NullPointerException:<init>	(Ljava/lang/String;)V
    //   9: astore_1
    //   10: aload_0
    //   11: getfield 23	io/reactivex/observers/c:c	Lio/reactivex/v;
    //   14: getstatic 40	io/reactivex/internal/disposables/EmptyDisposable:INSTANCE	Lio/reactivex/internal/disposables/EmptyDisposable;
    //   17: invokeinterface 44 2 0
    //   22: aload_0
    //   23: getfield 23	io/reactivex/observers/c:c	Lio/reactivex/v;
    //   26: aload_1
    //   27: invokeinterface 48 2 0
    //   32: goto +30 -> 62
    //   35: astore_2
    //   36: aload_2
    //   37: invokestatic 53	io/reactivex/exceptions/a:b	(Ljava/lang/Throwable;)V
    //   40: new 55	io/reactivex/exceptions/CompositeException
    //   43: dup
    //   44: iconst_2
    //   45: anewarray 57	java/lang/Throwable
    //   48: dup
    //   49: iconst_0
    //   50: aload_1
    //   51: aastore
    //   52: dup
    //   53: iconst_1
    //   54: aload_2
    //   55: aastore
    //   56: invokespecial 60	io/reactivex/exceptions/CompositeException:<init>	([Ljava/lang/Throwable;)V
    //   59: invokestatic 65	io/reactivex/j0/a:r	(Ljava/lang/Throwable;)V
    //   62: return
    //   63: astore_2
    //   64: aload_2
    //   65: invokestatic 53	io/reactivex/exceptions/a:b	(Ljava/lang/Throwable;)V
    //   68: new 55	io/reactivex/exceptions/CompositeException
    //   71: dup
    //   72: iconst_2
    //   73: anewarray 57	java/lang/Throwable
    //   76: dup
    //   77: iconst_0
    //   78: aload_1
    //   79: aastore
    //   80: dup
    //   81: iconst_1
    //   82: aload_2
    //   83: aastore
    //   84: invokespecial 60	io/reactivex/exceptions/CompositeException:<init>	([Ljava/lang/Throwable;)V
    //   87: invokestatic 65	io/reactivex/j0/a:r	(Ljava/lang/Throwable;)V
    //   90: return
    // Local variable table:
    //   start	length	slot	name	signature
    //   0	91	0	this	c
    //   9	70	1	localNullPointerException	NullPointerException
    //   35	20	2	localThrowable1	Throwable
    //   63	20	2	localThrowable2	Throwable
    // Exception table:
    //   from	to	target	type
    //   22	32	35	finally
    //   10	22	63	finally
  }
  
  /* Error */
  void b()
  {
    // Byte code:
    //   0: aload_0
    //   1: iconst_1
    //   2: putfield 67	io/reactivex/observers/c:f	Z
    //   5: new 29	java/lang/NullPointerException
    //   8: dup
    //   9: ldc 31
    //   11: invokespecial 34	java/lang/NullPointerException:<init>	(Ljava/lang/String;)V
    //   14: astore_1
    //   15: aload_0
    //   16: getfield 23	io/reactivex/observers/c:c	Lio/reactivex/v;
    //   19: getstatic 40	io/reactivex/internal/disposables/EmptyDisposable:INSTANCE	Lio/reactivex/internal/disposables/EmptyDisposable;
    //   22: invokeinterface 44 2 0
    //   27: aload_0
    //   28: getfield 23	io/reactivex/observers/c:c	Lio/reactivex/v;
    //   31: aload_1
    //   32: invokeinterface 48 2 0
    //   37: goto +30 -> 67
    //   40: astore_2
    //   41: aload_2
    //   42: invokestatic 53	io/reactivex/exceptions/a:b	(Ljava/lang/Throwable;)V
    //   45: new 55	io/reactivex/exceptions/CompositeException
    //   48: dup
    //   49: iconst_2
    //   50: anewarray 57	java/lang/Throwable
    //   53: dup
    //   54: iconst_0
    //   55: aload_1
    //   56: aastore
    //   57: dup
    //   58: iconst_1
    //   59: aload_2
    //   60: aastore
    //   61: invokespecial 60	io/reactivex/exceptions/CompositeException:<init>	([Ljava/lang/Throwable;)V
    //   64: invokestatic 65	io/reactivex/j0/a:r	(Ljava/lang/Throwable;)V
    //   67: return
    //   68: astore_2
    //   69: aload_2
    //   70: invokestatic 53	io/reactivex/exceptions/a:b	(Ljava/lang/Throwable;)V
    //   73: new 55	io/reactivex/exceptions/CompositeException
    //   76: dup
    //   77: iconst_2
    //   78: anewarray 57	java/lang/Throwable
    //   81: dup
    //   82: iconst_0
    //   83: aload_1
    //   84: aastore
    //   85: dup
    //   86: iconst_1
    //   87: aload_2
    //   88: aastore
    //   89: invokespecial 60	io/reactivex/exceptions/CompositeException:<init>	([Ljava/lang/Throwable;)V
    //   92: invokestatic 65	io/reactivex/j0/a:r	(Ljava/lang/Throwable;)V
    //   95: return
    // Local variable table:
    //   start	length	slot	name	signature
    //   0	96	0	this	c
    //   14	70	1	localNullPointerException	NullPointerException
    //   40	20	2	localThrowable1	Throwable
    //   68	20	2	localThrowable2	Throwable
    // Exception table:
    //   from	to	target	type
    //   27	37	40	finally
    //   15	27	68	finally
  }
  
  public void dispose()
  {
    this.d.dispose();
  }
  
  public boolean isDisposed()
  {
    return this.d.isDisposed();
  }
  
  /* Error */
  public void onComplete()
  {
    // Byte code:
    //   0: aload_0
    //   1: getfield 67	io/reactivex/observers/c:f	Z
    //   4: ifeq +4 -> 8
    //   7: return
    //   8: aload_0
    //   9: iconst_1
    //   10: putfield 67	io/reactivex/observers/c:f	Z
    //   13: aload_0
    //   14: getfield 70	io/reactivex/observers/c:d	Lio/reactivex/e0/c;
    //   17: ifnonnull +8 -> 25
    //   20: aload_0
    //   21: invokevirtual 79	io/reactivex/observers/c:a	()V
    //   24: return
    //   25: aload_0
    //   26: getfield 23	io/reactivex/observers/c:c	Lio/reactivex/v;
    //   29: invokeinterface 81 1 0
    //   34: goto +12 -> 46
    //   37: astore_1
    //   38: aload_1
    //   39: invokestatic 53	io/reactivex/exceptions/a:b	(Ljava/lang/Throwable;)V
    //   42: aload_1
    //   43: invokestatic 65	io/reactivex/j0/a:r	(Ljava/lang/Throwable;)V
    //   46: return
    // Local variable table:
    //   start	length	slot	name	signature
    //   0	47	0	this	c
    //   37	6	1	localThrowable	Throwable
    // Exception table:
    //   from	to	target	type
    //   25	34	37	finally
  }
  
  /* Error */
  public void onError(Throwable paramThrowable)
  {
    // Byte code:
    //   0: aload_0
    //   1: getfield 67	io/reactivex/observers/c:f	Z
    //   4: ifeq +8 -> 12
    //   7: aload_1
    //   8: invokestatic 65	io/reactivex/j0/a:r	(Ljava/lang/Throwable;)V
    //   11: return
    //   12: aload_0
    //   13: iconst_1
    //   14: putfield 67	io/reactivex/observers/c:f	Z
    //   17: aload_0
    //   18: getfield 70	io/reactivex/observers/c:d	Lio/reactivex/e0/c;
    //   21: ifnonnull +127 -> 148
    //   24: new 29	java/lang/NullPointerException
    //   27: dup
    //   28: ldc 31
    //   30: invokespecial 34	java/lang/NullPointerException:<init>	(Ljava/lang/String;)V
    //   33: astore_2
    //   34: aload_0
    //   35: getfield 23	io/reactivex/observers/c:c	Lio/reactivex/v;
    //   38: getstatic 40	io/reactivex/internal/disposables/EmptyDisposable:INSTANCE	Lio/reactivex/internal/disposables/EmptyDisposable;
    //   41: invokeinterface 44 2 0
    //   46: aload_0
    //   47: getfield 23	io/reactivex/observers/c:c	Lio/reactivex/v;
    //   50: astore_3
    //   51: new 55	io/reactivex/exceptions/CompositeException
    //   54: astore 4
    //   56: aload 4
    //   58: iconst_2
    //   59: anewarray 57	java/lang/Throwable
    //   62: dup
    //   63: iconst_0
    //   64: aload_1
    //   65: aastore
    //   66: dup
    //   67: iconst_1
    //   68: aload_2
    //   69: aastore
    //   70: invokespecial 60	io/reactivex/exceptions/CompositeException:<init>	([Ljava/lang/Throwable;)V
    //   73: aload_3
    //   74: aload 4
    //   76: invokeinterface 48 2 0
    //   81: goto +34 -> 115
    //   84: astore_3
    //   85: aload_3
    //   86: invokestatic 53	io/reactivex/exceptions/a:b	(Ljava/lang/Throwable;)V
    //   89: new 55	io/reactivex/exceptions/CompositeException
    //   92: dup
    //   93: iconst_3
    //   94: anewarray 57	java/lang/Throwable
    //   97: dup
    //   98: iconst_0
    //   99: aload_1
    //   100: aastore
    //   101: dup
    //   102: iconst_1
    //   103: aload_2
    //   104: aastore
    //   105: dup
    //   106: iconst_2
    //   107: aload_3
    //   108: aastore
    //   109: invokespecial 60	io/reactivex/exceptions/CompositeException:<init>	([Ljava/lang/Throwable;)V
    //   112: invokestatic 65	io/reactivex/j0/a:r	(Ljava/lang/Throwable;)V
    //   115: return
    //   116: astore_3
    //   117: aload_3
    //   118: invokestatic 53	io/reactivex/exceptions/a:b	(Ljava/lang/Throwable;)V
    //   121: new 55	io/reactivex/exceptions/CompositeException
    //   124: dup
    //   125: iconst_3
    //   126: anewarray 57	java/lang/Throwable
    //   129: dup
    //   130: iconst_0
    //   131: aload_1
    //   132: aastore
    //   133: dup
    //   134: iconst_1
    //   135: aload_2
    //   136: aastore
    //   137: dup
    //   138: iconst_2
    //   139: aload_3
    //   140: aastore
    //   141: invokespecial 60	io/reactivex/exceptions/CompositeException:<init>	([Ljava/lang/Throwable;)V
    //   144: invokestatic 65	io/reactivex/j0/a:r	(Ljava/lang/Throwable;)V
    //   147: return
    //   148: aload_1
    //   149: astore_2
    //   150: aload_1
    //   151: ifnonnull +13 -> 164
    //   154: new 29	java/lang/NullPointerException
    //   157: dup
    //   158: ldc 83
    //   160: invokespecial 34	java/lang/NullPointerException:<init>	(Ljava/lang/String;)V
    //   163: astore_2
    //   164: aload_0
    //   165: getfield 23	io/reactivex/observers/c:c	Lio/reactivex/v;
    //   168: aload_2
    //   169: invokeinterface 48 2 0
    //   174: goto +30 -> 204
    //   177: astore_1
    //   178: aload_1
    //   179: invokestatic 53	io/reactivex/exceptions/a:b	(Ljava/lang/Throwable;)V
    //   182: new 55	io/reactivex/exceptions/CompositeException
    //   185: dup
    //   186: iconst_2
    //   187: anewarray 57	java/lang/Throwable
    //   190: dup
    //   191: iconst_0
    //   192: aload_2
    //   193: aastore
    //   194: dup
    //   195: iconst_1
    //   196: aload_1
    //   197: aastore
    //   198: invokespecial 60	io/reactivex/exceptions/CompositeException:<init>	([Ljava/lang/Throwable;)V
    //   201: invokestatic 65	io/reactivex/j0/a:r	(Ljava/lang/Throwable;)V
    //   204: return
    // Local variable table:
    //   start	length	slot	name	signature
    //   0	205	0	this	c
    //   0	205	1	paramThrowable	Throwable
    //   33	160	2	localObject	Object
    //   50	24	3	localv	v
    //   84	24	3	localThrowable1	Throwable
    //   116	24	3	localThrowable2	Throwable
    //   54	21	4	localCompositeException	io.reactivex.exceptions.CompositeException
    // Exception table:
    //   from	to	target	type
    //   46	81	84	finally
    //   34	46	116	finally
    //   164	174	177	finally
  }
  
  /* Error */
  public void onNext(T paramT)
  {
    // Byte code:
    //   0: aload_0
    //   1: getfield 67	io/reactivex/observers/c:f	Z
    //   4: ifeq +4 -> 8
    //   7: return
    //   8: aload_0
    //   9: getfield 70	io/reactivex/observers/c:d	Lio/reactivex/e0/c;
    //   12: ifnonnull +8 -> 20
    //   15: aload_0
    //   16: invokevirtual 87	io/reactivex/observers/c:b	()V
    //   19: return
    //   20: aload_1
    //   21: ifnonnull +57 -> 78
    //   24: new 29	java/lang/NullPointerException
    //   27: dup
    //   28: ldc 89
    //   30: invokespecial 34	java/lang/NullPointerException:<init>	(Ljava/lang/String;)V
    //   33: astore_2
    //   34: aload_0
    //   35: getfield 70	io/reactivex/observers/c:d	Lio/reactivex/e0/c;
    //   38: invokeinterface 72 1 0
    //   43: aload_0
    //   44: aload_2
    //   45: invokevirtual 90	io/reactivex/observers/c:onError	(Ljava/lang/Throwable;)V
    //   48: return
    //   49: astore_1
    //   50: aload_1
    //   51: invokestatic 53	io/reactivex/exceptions/a:b	(Ljava/lang/Throwable;)V
    //   54: aload_0
    //   55: new 55	io/reactivex/exceptions/CompositeException
    //   58: dup
    //   59: iconst_2
    //   60: anewarray 57	java/lang/Throwable
    //   63: dup
    //   64: iconst_0
    //   65: aload_2
    //   66: aastore
    //   67: dup
    //   68: iconst_1
    //   69: aload_1
    //   70: aastore
    //   71: invokespecial 60	io/reactivex/exceptions/CompositeException:<init>	([Ljava/lang/Throwable;)V
    //   74: invokevirtual 90	io/reactivex/observers/c:onError	(Ljava/lang/Throwable;)V
    //   77: return
    //   78: aload_0
    //   79: getfield 23	io/reactivex/observers/c:c	Lio/reactivex/v;
    //   82: aload_1
    //   83: invokeinterface 92 2 0
    //   88: goto +22 -> 110
    //   91: astore_2
    //   92: aload_2
    //   93: invokestatic 53	io/reactivex/exceptions/a:b	(Ljava/lang/Throwable;)V
    //   96: aload_0
    //   97: getfield 70	io/reactivex/observers/c:d	Lio/reactivex/e0/c;
    //   100: invokeinterface 72 1 0
    //   105: aload_0
    //   106: aload_2
    //   107: invokevirtual 90	io/reactivex/observers/c:onError	(Ljava/lang/Throwable;)V
    //   110: return
    //   111: astore_1
    //   112: aload_1
    //   113: invokestatic 53	io/reactivex/exceptions/a:b	(Ljava/lang/Throwable;)V
    //   116: aload_0
    //   117: new 55	io/reactivex/exceptions/CompositeException
    //   120: dup
    //   121: iconst_2
    //   122: anewarray 57	java/lang/Throwable
    //   125: dup
    //   126: iconst_0
    //   127: aload_2
    //   128: aastore
    //   129: dup
    //   130: iconst_1
    //   131: aload_1
    //   132: aastore
    //   133: invokespecial 60	io/reactivex/exceptions/CompositeException:<init>	([Ljava/lang/Throwable;)V
    //   136: invokevirtual 90	io/reactivex/observers/c:onError	(Ljava/lang/Throwable;)V
    //   139: return
    // Local variable table:
    //   start	length	slot	name	signature
    //   0	140	0	this	c
    //   0	140	1	paramT	T
    //   33	33	2	localNullPointerException	NullPointerException
    //   91	37	2	localThrowable	Throwable
    // Exception table:
    //   from	to	target	type
    //   34	43	49	finally
    //   78	88	91	finally
    //   96	105	111	finally
  }
  
  /* Error */
  public void onSubscribe(io.reactivex.e0.c paramc)
  {
    // Byte code:
    //   0: aload_0
    //   1: getfield 70	io/reactivex/observers/c:d	Lio/reactivex/e0/c;
    //   4: aload_1
    //   5: invokestatic 99	io/reactivex/internal/disposables/DisposableHelper:validate	(Lio/reactivex/e0/c;Lio/reactivex/e0/c;)Z
    //   8: ifeq +71 -> 79
    //   11: aload_0
    //   12: aload_1
    //   13: putfield 70	io/reactivex/observers/c:d	Lio/reactivex/e0/c;
    //   16: aload_0
    //   17: getfield 23	io/reactivex/observers/c:c	Lio/reactivex/v;
    //   20: aload_0
    //   21: invokeinterface 44 2 0
    //   26: goto +53 -> 79
    //   29: astore_2
    //   30: aload_2
    //   31: invokestatic 53	io/reactivex/exceptions/a:b	(Ljava/lang/Throwable;)V
    //   34: aload_0
    //   35: iconst_1
    //   36: putfield 67	io/reactivex/observers/c:f	Z
    //   39: aload_1
    //   40: invokeinterface 72 1 0
    //   45: aload_2
    //   46: invokestatic 65	io/reactivex/j0/a:r	(Ljava/lang/Throwable;)V
    //   49: goto +30 -> 79
    //   52: astore_1
    //   53: aload_1
    //   54: invokestatic 53	io/reactivex/exceptions/a:b	(Ljava/lang/Throwable;)V
    //   57: new 55	io/reactivex/exceptions/CompositeException
    //   60: dup
    //   61: iconst_2
    //   62: anewarray 57	java/lang/Throwable
    //   65: dup
    //   66: iconst_0
    //   67: aload_2
    //   68: aastore
    //   69: dup
    //   70: iconst_1
    //   71: aload_1
    //   72: aastore
    //   73: invokespecial 60	io/reactivex/exceptions/CompositeException:<init>	([Ljava/lang/Throwable;)V
    //   76: invokestatic 65	io/reactivex/j0/a:r	(Ljava/lang/Throwable;)V
    //   79: return
    // Local variable table:
    //   start	length	slot	name	signature
    //   0	80	0	this	c
    //   0	80	1	paramc	io.reactivex.e0.c
    //   29	39	2	localThrowable	Throwable
    // Exception table:
    //   from	to	target	type
    //   16	26	29	finally
    //   39	45	52	finally
  }
}


/* Location:              C:\Users\User\Desktop\decompile\jdgui110\Tapojar.jar!\io\reactivex\observers\c.class
 * Java compiler version: 6 (50.0)
 * JD-Core Version:       0.7.1
 */