package b.d.o.b;

import io.reactivex.e0.c;

public class g
  extends d
{
  private String U3 = "UserLiveStreamConnection";
  private String V3;
  private String W3;
  private c X3;
  protected final Object Y3 = new Object();
  
  public g(String paramString1, String paramString2)
  {
    super(paramString1, paramString2);
  }
  
  public void B(String paramString)
  {
    this.W3 = paramString;
  }
  
  public void C(String paramString)
  {
    this.V3 = paramString;
  }
  
  public void f(String paramString)
  {
    super.f(paramString);
  }
  
  /* Error */
  public Boolean l()
  {
    // Byte code:
    //   0: aload_0
    //   1: invokevirtual 71	b/d/o/b/d:m	()V
    //   4: aload_0
    //   5: getfield 55	b/d/o/b/g:V3	Ljava/lang/String;
    //   8: invokestatic 77	android/text/TextUtils:isEmpty	(Ljava/lang/CharSequence;)Z
    //   11: ifeq +9 -> 20
    //   14: aload_0
    //   15: ldc 79
    //   17: putfield 55	b/d/o/b/g:V3	Ljava/lang/String;
    //   20: aload_0
    //   21: getfield 52	b/d/o/b/g:W3	Ljava/lang/String;
    //   24: invokestatic 77	android/text/TextUtils:isEmpty	(Ljava/lang/CharSequence;)Z
    //   27: ifeq +64 -> 91
    //   30: aload_0
    //   31: getfield 83	b/d/o/b/d:p3	Lb/d/o/b/c;
    //   34: astore_1
    //   35: aload_1
    //   36: ifnull +20 -> 56
    //   39: aload_1
    //   40: aload_0
    //   41: getfield 88	b/d/i/a/a/f:c	Ljava/lang/String;
    //   44: new 31	java/lang/Exception
    //   47: dup
    //   48: invokespecial 89	java/lang/Exception:<init>	()V
    //   51: invokeinterface 95 3 0
    //   56: aload_0
    //   57: getfield 99	b/d/o/b/d:H3	Lb/d/o/b/f;
    //   60: astore_1
    //   61: aload_1
    //   62: ifnull +25 -> 87
    //   65: aload_1
    //   66: aload_0
    //   67: getfield 88	b/d/i/a/a/f:c	Ljava/lang/String;
    //   70: aload_0
    //   71: getfield 102	b/d/i/a/a/f:x	I
    //   74: iconst_0
    //   75: new 31	java/lang/Exception
    //   78: dup
    //   79: invokespecial 89	java/lang/Exception:<init>	()V
    //   82: invokeinterface 108 5 0
    //   87: getstatic 114	java/lang/Boolean:FALSE	Ljava/lang/Boolean;
    //   90: areturn
    //   91: aload_0
    //   92: getfield 20	b/d/o/b/g:U3	Ljava/lang/String;
    //   95: astore_1
    //   96: new 116	java/lang/StringBuilder
    //   99: dup
    //   100: invokespecial 117	java/lang/StringBuilder:<init>	()V
    //   103: astore_2
    //   104: aload_2
    //   105: ldc 119
    //   107: invokevirtual 123	java/lang/StringBuilder:append	(Ljava/lang/String;)Ljava/lang/StringBuilder;
    //   110: pop
    //   111: aload_2
    //   112: aload_0
    //   113: getfield 55	b/d/o/b/g:V3	Ljava/lang/String;
    //   116: invokevirtual 123	java/lang/StringBuilder:append	(Ljava/lang/String;)Ljava/lang/StringBuilder;
    //   119: pop
    //   120: aload_2
    //   121: ldc 125
    //   123: invokevirtual 123	java/lang/StringBuilder:append	(Ljava/lang/String;)Ljava/lang/StringBuilder;
    //   126: pop
    //   127: aload_2
    //   128: aload_0
    //   129: getfield 52	b/d/o/b/g:W3	Ljava/lang/String;
    //   132: invokevirtual 123	java/lang/StringBuilder:append	(Ljava/lang/String;)Ljava/lang/StringBuilder;
    //   135: pop
    //   136: aload_2
    //   137: ldc 127
    //   139: invokevirtual 123	java/lang/StringBuilder:append	(Ljava/lang/String;)Ljava/lang/StringBuilder;
    //   142: pop
    //   143: aload_2
    //   144: aload_0
    //   145: invokevirtual 131	b/d/i/a/a/f:a	()I
    //   148: invokevirtual 134	java/lang/StringBuilder:append	(I)Ljava/lang/StringBuilder;
    //   151: pop
    //   152: aload_1
    //   153: aload_2
    //   154: invokevirtual 138	java/lang/StringBuilder:toString	()Ljava/lang/String;
    //   157: invokestatic 142	b/d/p/d:a	(Ljava/lang/String;Ljava/lang/String;)V
    //   160: new 144	java/util/HashMap
    //   163: dup
    //   164: invokespecial 145	java/util/HashMap:<init>	()V
    //   167: astore_2
    //   168: aload_2
    //   169: ldc -109
    //   171: ldc -107
    //   173: invokeinterface 155 3 0
    //   178: pop
    //   179: aload_0
    //   180: getfield 158	b/d/i/a/a/f:d	Ljava/lang/String;
    //   183: aload_0
    //   184: getfield 160	b/d/i/a/a/f:f	I
    //   187: invokestatic 166	com/tplink/libtpstreamconnectionsocket/a:o	(Ljava/lang/String;I)Ljava/lang/String;
    //   190: astore_1
    //   191: invokestatic 171	b/d/i/a/c/a:a	()Lb/d/i/a/c/a;
    //   194: aload_1
    //   195: aload_0
    //   196: getfield 55	b/d/o/b/g:V3	Ljava/lang/String;
    //   199: aload_0
    //   200: getfield 52	b/d/o/b/g:W3	Ljava/lang/String;
    //   203: ldc -83
    //   205: aload_2
    //   206: invokevirtual 176	b/d/i/a/c/a:c	(Ljava/lang/String;Ljava/lang/String;Ljava/lang/String;Ljava/lang/String;Ljava/util/Map;)Ljava/lang/String;
    //   209: astore_1
    //   210: aload_0
    //   211: getfield 20	b/d/o/b/g:U3	Ljava/lang/String;
    //   214: astore_3
    //   215: new 116	java/lang/StringBuilder
    //   218: dup
    //   219: invokespecial 117	java/lang/StringBuilder:<init>	()V
    //   222: astore_2
    //   223: aload_2
    //   224: ldc -78
    //   226: invokevirtual 123	java/lang/StringBuilder:append	(Ljava/lang/String;)Ljava/lang/StringBuilder;
    //   229: pop
    //   230: aload_2
    //   231: aload_1
    //   232: invokevirtual 123	java/lang/StringBuilder:append	(Ljava/lang/String;)Ljava/lang/StringBuilder;
    //   235: pop
    //   236: aload_2
    //   237: ldc 127
    //   239: invokevirtual 123	java/lang/StringBuilder:append	(Ljava/lang/String;)Ljava/lang/StringBuilder;
    //   242: pop
    //   243: aload_2
    //   244: aload_0
    //   245: invokevirtual 131	b/d/i/a/a/f:a	()I
    //   248: invokevirtual 134	java/lang/StringBuilder:append	(I)Ljava/lang/StringBuilder;
    //   251: pop
    //   252: aload_3
    //   253: aload_2
    //   254: invokevirtual 138	java/lang/StringBuilder:toString	()Ljava/lang/String;
    //   257: invokestatic 142	b/d/p/d:a	(Ljava/lang/String;Ljava/lang/String;)V
    //   260: aload_1
    //   261: invokestatic 77	android/text/TextUtils:isEmpty	(Ljava/lang/CharSequence;)Z
    //   264: ifeq +125 -> 389
    //   267: aload_0
    //   268: getfield 83	b/d/o/b/d:p3	Lb/d/o/b/c;
    //   271: ifnull +83 -> 354
    //   274: aload_0
    //   275: getfield 102	b/d/i/a/a/f:x	I
    //   278: bipush 17
    //   280: if_icmpeq +74 -> 354
    //   283: invokestatic 171	b/d/i/a/c/a:a	()Lb/d/i/a/c/a;
    //   286: invokevirtual 181	b/d/i/a/c/a:b	()Ljava/util/List;
    //   289: astore_1
    //   290: aload_1
    //   291: invokeinterface 186 1 0
    //   296: ifne +36 -> 332
    //   299: aload_0
    //   300: getfield 83	b/d/o/b/d:p3	Lb/d/o/b/c;
    //   303: aload_0
    //   304: getfield 88	b/d/i/a/a/f:c	Ljava/lang/String;
    //   307: aload_1
    //   308: aload_1
    //   309: invokeinterface 189 1 0
    //   314: iconst_1
    //   315: isub
    //   316: invokeinterface 193 2 0
    //   321: checkcast 31	java/lang/Exception
    //   324: invokeinterface 95 3 0
    //   329: goto +25 -> 354
    //   332: aload_0
    //   333: getfield 83	b/d/o/b/d:p3	Lb/d/o/b/c;
    //   336: aload_0
    //   337: getfield 88	b/d/i/a/a/f:c	Ljava/lang/String;
    //   340: new 31	java/lang/Exception
    //   343: dup
    //   344: ldc -61
    //   346: invokespecial 197	java/lang/Exception:<init>	(Ljava/lang/String;)V
    //   349: invokeinterface 95 3 0
    //   354: aload_0
    //   355: getfield 99	b/d/o/b/d:H3	Lb/d/o/b/f;
    //   358: astore_1
    //   359: aload_1
    //   360: ifnull +25 -> 385
    //   363: aload_1
    //   364: aload_0
    //   365: getfield 88	b/d/i/a/a/f:c	Ljava/lang/String;
    //   368: aload_0
    //   369: getfield 102	b/d/i/a/a/f:x	I
    //   372: iconst_0
    //   373: new 31	java/lang/Exception
    //   376: dup
    //   377: invokespecial 89	java/lang/Exception:<init>	()V
    //   380: invokeinterface 108 5 0
    //   385: getstatic 200	java/lang/Boolean:TRUE	Ljava/lang/Boolean;
    //   388: areturn
    //   389: new 162	com/tplink/libtpstreamconnectionsocket/a
    //   392: astore_2
    //   393: aload_2
    //   394: aload_0
    //   395: getfield 158	b/d/i/a/a/f:d	Ljava/lang/String;
    //   398: aload_0
    //   399: getfield 160	b/d/i/a/a/f:f	I
    //   402: invokespecial 203	com/tplink/libtpstreamconnectionsocket/a:<init>	(Ljava/lang/String;I)V
    //   405: aload_0
    //   406: aload_2
    //   407: putfield 207	b/d/o/b/d:K3	Lcom/tplink/libtpstreamconnectionsocket/a;
    //   410: aload_2
    //   411: sipush 30000
    //   414: invokevirtual 211	com/tplink/libtpstreamconnectionsocket/a:F	(I)Lcom/tplink/libtpstreamconnectionsocket/a;
    //   417: pop
    //   418: aload_0
    //   419: getfield 207	b/d/o/b/d:K3	Lcom/tplink/libtpstreamconnectionsocket/a;
    //   422: sipush 15000
    //   425: invokevirtual 214	com/tplink/libtpstreamconnectionsocket/a:H	(I)Lcom/tplink/libtpstreamconnectionsocket/a;
    //   428: pop
    //   429: aload_0
    //   430: getfield 207	b/d/o/b/d:K3	Lcom/tplink/libtpstreamconnectionsocket/a;
    //   433: ldc -83
    //   435: invokevirtual 218	com/tplink/libtpstreamconnectionsocket/a:G	(Ljava/lang/String;)Lcom/tplink/libtpstreamconnectionsocket/a;
    //   438: pop
    //   439: bipush 17
    //   441: aload_0
    //   442: invokevirtual 131	b/d/i/a/a/f:a	()I
    //   445: if_icmpne +18 -> 463
    //   448: aload_0
    //   449: getfield 207	b/d/o/b/d:K3	Lcom/tplink/libtpstreamconnectionsocket/a;
    //   452: aload_0
    //   453: getfield 88	b/d/i/a/a/f:c	Ljava/lang/String;
    //   456: invokevirtual 221	com/tplink/libtpstreamconnectionsocket/a:e	(Ljava/lang/String;)Lcom/tplink/libtpstreamconnectionsocket/a;
    //   459: pop
    //   460: goto +11 -> 471
    //   463: aload_0
    //   464: getfield 207	b/d/o/b/d:K3	Lcom/tplink/libtpstreamconnectionsocket/a;
    //   467: invokevirtual 224	com/tplink/libtpstreamconnectionsocket/a:d	()Lcom/tplink/libtpstreamconnectionsocket/a;
    //   470: pop
    //   471: aload_0
    //   472: getfield 207	b/d/o/b/d:K3	Lcom/tplink/libtpstreamconnectionsocket/a;
    //   475: aload_1
    //   476: iconst_0
    //   477: invokevirtual 228	com/tplink/libtpstreamconnectionsocket/a:q	(Ljava/lang/String;Z)I
    //   480: istore 4
    //   482: iload 4
    //   484: sipush 200
    //   487: if_icmpne +308 -> 795
    //   490: aload_0
    //   491: getfield 88	b/d/i/a/a/f:c	Ljava/lang/String;
    //   494: invokestatic 233	b/d/d/d/c:a	(Ljava/lang/String;)Lio/reactivex/q;
    //   497: ldc2_w 234
    //   500: getstatic 241	java/util/concurrent/TimeUnit:SECONDS	Ljava/util/concurrent/TimeUnit;
    //   503: invokevirtual 247	io/reactivex/q:T0	(JLjava/util/concurrent/TimeUnit;)Lio/reactivex/q;
    //   506: astore_2
    //   507: new 249	b/d/o/b/a
    //   510: astore_1
    //   511: aload_1
    //   512: aload_0
    //   513: invokespecial 252	b/d/o/b/a:<init>	(Lb/d/o/b/g;)V
    //   516: aload_2
    //   517: aload_1
    //   518: invokevirtual 256	io/reactivex/q:y	(Lio/reactivex/g0/a;)Lio/reactivex/q;
    //   521: astore_2
    //   522: new 258	b/d/o/b/b
    //   525: astore_1
    //   526: aload_1
    //   527: aload_0
    //   528: invokespecial 259	b/d/o/b/b:<init>	(Lb/d/o/b/g;)V
    //   531: aload_0
    //   532: aload_2
    //   533: aload_1
    //   534: invokevirtual 263	io/reactivex/q:G0	(Lio/reactivex/g0/g;)Lio/reactivex/e0/c;
    //   537: putfield 265	b/d/o/b/g:X3	Lio/reactivex/e0/c;
    //   540: aload_0
    //   541: getfield 41	b/d/o/b/d:N3	Lb/d/p/a;
    //   544: astore_1
    //   545: aload_1
    //   546: ifnonnull +46 -> 592
    //   549: aload_0
    //   550: getfield 27	b/d/o/b/g:Y3	Ljava/lang/Object;
    //   553: astore_2
    //   554: aload_2
    //   555: monitorenter
    //   556: aload_0
    //   557: getfield 27	b/d/o/b/g:Y3	Ljava/lang/Object;
    //   560: invokevirtual 34	java/lang/Object:notifyAll	()V
    //   563: aload_0
    //   564: getfield 27	b/d/o/b/g:Y3	Ljava/lang/Object;
    //   567: invokevirtual 268	java/lang/Object:wait	()V
    //   570: aload_2
    //   571: monitorexit
    //   572: goto +20 -> 592
    //   575: astore_1
    //   576: aload_2
    //   577: monitorexit
    //   578: aload_1
    //   579: athrow
    //   580: astore_1
    //   581: aload_0
    //   582: getfield 20	b/d/o/b/g:U3	Ljava/lang/String;
    //   585: aload_1
    //   586: invokevirtual 269	java/lang/InterruptedException:toString	()Ljava/lang/String;
    //   589: invokestatic 142	b/d/p/d:a	(Ljava/lang/String;Ljava/lang/String;)V
    //   592: aload_0
    //   593: getfield 41	b/d/o/b/d:N3	Lb/d/p/a;
    //   596: ifnonnull +199 -> 795
    //   599: aload_0
    //   600: getfield 20	b/d/o/b/g:U3	Ljava/lang/String;
    //   603: astore_1
    //   604: new 116	java/lang/StringBuilder
    //   607: astore_2
    //   608: aload_2
    //   609: invokespecial 117	java/lang/StringBuilder:<init>	()V
    //   612: aload_2
    //   613: ldc_w 271
    //   616: invokevirtual 123	java/lang/StringBuilder:append	(Ljava/lang/String;)Ljava/lang/StringBuilder;
    //   619: pop
    //   620: aload_2
    //   621: aload_0
    //   622: getfield 88	b/d/i/a/a/f:c	Ljava/lang/String;
    //   625: invokevirtual 123	java/lang/StringBuilder:append	(Ljava/lang/String;)Ljava/lang/StringBuilder;
    //   628: pop
    //   629: aload_2
    //   630: ldc_w 273
    //   633: invokevirtual 123	java/lang/StringBuilder:append	(Ljava/lang/String;)Ljava/lang/StringBuilder;
    //   636: pop
    //   637: aload_1
    //   638: aload_2
    //   639: invokevirtual 138	java/lang/StringBuilder:toString	()Ljava/lang/String;
    //   642: invokestatic 142	b/d/p/d:a	(Ljava/lang/String;Ljava/lang/String;)V
    //   645: aload_0
    //   646: getfield 83	b/d/o/b/d:p3	Lb/d/o/b/c;
    //   649: astore_3
    //   650: aload_3
    //   651: ifnull +27 -> 678
    //   654: aload_0
    //   655: getfield 88	b/d/i/a/a/f:c	Ljava/lang/String;
    //   658: astore_2
    //   659: new 31	java/lang/Exception
    //   662: astore_1
    //   663: aload_1
    //   664: ldc_w 275
    //   667: invokespecial 197	java/lang/Exception:<init>	(Ljava/lang/String;)V
    //   670: aload_3
    //   671: aload_2
    //   672: aload_1
    //   673: invokeinterface 95 3 0
    //   678: aload_0
    //   679: getfield 99	b/d/o/b/d:H3	Lb/d/o/b/f;
    //   682: astore_2
    //   683: aload_2
    //   684: ifnull +33 -> 717
    //   687: aload_0
    //   688: getfield 88	b/d/i/a/a/f:c	Ljava/lang/String;
    //   691: astore_1
    //   692: aload_0
    //   693: getfield 102	b/d/i/a/a/f:x	I
    //   696: istore 4
    //   698: new 31	java/lang/Exception
    //   701: astore_3
    //   702: aload_3
    //   703: invokespecial 89	java/lang/Exception:<init>	()V
    //   706: aload_2
    //   707: aload_1
    //   708: iload 4
    //   710: iconst_0
    //   711: aload_3
    //   712: invokeinterface 108 5 0
    //   717: getstatic 114	java/lang/Boolean:FALSE	Ljava/lang/Boolean;
    //   720: astore_2
    //   721: aload_0
    //   722: getfield 20	b/d/o/b/g:U3	Ljava/lang/String;
    //   725: astore_1
    //   726: new 116	java/lang/StringBuilder
    //   729: dup
    //   730: invokespecial 117	java/lang/StringBuilder:<init>	()V
    //   733: astore_3
    //   734: aload_3
    //   735: ldc_w 271
    //   738: invokevirtual 123	java/lang/StringBuilder:append	(Ljava/lang/String;)Ljava/lang/StringBuilder;
    //   741: pop
    //   742: aload_3
    //   743: aload_0
    //   744: getfield 88	b/d/i/a/a/f:c	Ljava/lang/String;
    //   747: invokevirtual 123	java/lang/StringBuilder:append	(Ljava/lang/String;)Ljava/lang/StringBuilder;
    //   750: pop
    //   751: aload_3
    //   752: ldc_w 277
    //   755: invokevirtual 123	java/lang/StringBuilder:append	(Ljava/lang/String;)Ljava/lang/StringBuilder;
    //   758: pop
    //   759: aload_3
    //   760: aload_0
    //   761: invokevirtual 131	b/d/i/a/a/f:a	()I
    //   764: invokevirtual 134	java/lang/StringBuilder:append	(I)Ljava/lang/StringBuilder;
    //   767: pop
    //   768: aload_1
    //   769: aload_3
    //   770: invokevirtual 138	java/lang/StringBuilder:toString	()Ljava/lang/String;
    //   773: invokestatic 142	b/d/p/d:a	(Ljava/lang/String;Ljava/lang/String;)V
    //   776: aload_0
    //   777: iconst_0
    //   778: putfield 280	b/d/o/b/d:M3	Z
    //   781: aload_0
    //   782: invokevirtual 283	b/d/o/b/d:r	()V
    //   785: aload_0
    //   786: invokevirtual 285	b/d/o/b/d:q	()V
    //   789: aload_0
    //   790: invokevirtual 288	b/d/o/b/d:n	()V
    //   793: aload_2
    //   794: areturn
    //   795: iload 4
    //   797: sipush 200
    //   800: if_icmpeq +203 -> 1003
    //   803: iload 4
    //   805: sipush 204
    //   808: if_icmpeq +195 -> 1003
    //   811: aload_0
    //   812: getfield 20	b/d/o/b/g:U3	Ljava/lang/String;
    //   815: astore_2
    //   816: new 116	java/lang/StringBuilder
    //   819: astore_1
    //   820: aload_1
    //   821: invokespecial 117	java/lang/StringBuilder:<init>	()V
    //   824: aload_1
    //   825: ldc_w 271
    //   828: invokevirtual 123	java/lang/StringBuilder:append	(Ljava/lang/String;)Ljava/lang/StringBuilder;
    //   831: pop
    //   832: aload_1
    //   833: aload_0
    //   834: getfield 88	b/d/i/a/a/f:c	Ljava/lang/String;
    //   837: invokevirtual 123	java/lang/StringBuilder:append	(Ljava/lang/String;)Ljava/lang/StringBuilder;
    //   840: pop
    //   841: aload_1
    //   842: ldc_w 290
    //   845: invokevirtual 123	java/lang/StringBuilder:append	(Ljava/lang/String;)Ljava/lang/StringBuilder;
    //   848: pop
    //   849: aload_1
    //   850: iload 4
    //   852: invokevirtual 134	java/lang/StringBuilder:append	(I)Ljava/lang/StringBuilder;
    //   855: pop
    //   856: aload_1
    //   857: ldc 127
    //   859: invokevirtual 123	java/lang/StringBuilder:append	(Ljava/lang/String;)Ljava/lang/StringBuilder;
    //   862: pop
    //   863: aload_1
    //   864: aload_0
    //   865: invokevirtual 131	b/d/i/a/a/f:a	()I
    //   868: invokevirtual 134	java/lang/StringBuilder:append	(I)Ljava/lang/StringBuilder;
    //   871: pop
    //   872: aload_2
    //   873: aload_1
    //   874: invokevirtual 138	java/lang/StringBuilder:toString	()Ljava/lang/String;
    //   877: invokestatic 142	b/d/p/d:a	(Ljava/lang/String;Ljava/lang/String;)V
    //   880: iload 4
    //   882: sipush 401
    //   885: if_icmpne +108 -> 993
    //   888: aload_0
    //   889: getfield 83	b/d/o/b/d:p3	Lb/d/o/b/c;
    //   892: astore_3
    //   893: aload_3
    //   894: ifnull +27 -> 921
    //   897: aload_0
    //   898: getfield 88	b/d/i/a/a/f:c	Ljava/lang/String;
    //   901: astore_1
    //   902: new 292	com/tplink/libtpstreamconnectionsocket/UserEncryptException
    //   905: astore_2
    //   906: aload_2
    //   907: ldc_w 294
    //   910: invokespecial 295	com/tplink/libtpstreamconnectionsocket/UserEncryptException:<init>	(Ljava/lang/String;)V
    //   913: aload_3
    //   914: aload_1
    //   915: aload_2
    //   916: invokeinterface 95 3 0
    //   921: aload_0
    //   922: getfield 99	b/d/o/b/d:H3	Lb/d/o/b/f;
    //   925: astore_3
    //   926: aload_3
    //   927: ifnull +33 -> 960
    //   930: aload_0
    //   931: getfield 88	b/d/i/a/a/f:c	Ljava/lang/String;
    //   934: astore_1
    //   935: aload_0
    //   936: getfield 102	b/d/i/a/a/f:x	I
    //   939: istore 4
    //   941: new 31	java/lang/Exception
    //   944: astore_2
    //   945: aload_2
    //   946: invokespecial 89	java/lang/Exception:<init>	()V
    //   949: aload_3
    //   950: aload_1
    //   951: iload 4
    //   953: iconst_0
    //   954: aload_2
    //   955: invokeinterface 108 5 0
    //   960: aload_0
    //   961: getfield 207	b/d/o/b/d:K3	Lcom/tplink/libtpstreamconnectionsocket/a;
    //   964: astore_1
    //   965: aload_1
    //   966: ifnull +7 -> 973
    //   969: aload_1
    //   970: invokevirtual 297	com/tplink/libtpstreamconnectionsocket/a:f	()V
    //   973: getstatic 114	java/lang/Boolean:FALSE	Ljava/lang/Boolean;
    //   976: astore_2
    //   977: aload_0
    //   978: getfield 20	b/d/o/b/g:U3	Ljava/lang/String;
    //   981: astore_1
    //   982: new 116	java/lang/StringBuilder
    //   985: dup
    //   986: invokespecial 117	java/lang/StringBuilder:<init>	()V
    //   989: astore_3
    //   990: goto -256 -> 734
    //   993: new 299	java/io/IOException
    //   996: astore_1
    //   997: aload_1
    //   998: invokespecial 300	java/io/IOException:<init>	()V
    //   1001: aload_1
    //   1002: athrow
    //   1003: aload_0
    //   1004: getfield 20	b/d/o/b/g:U3	Ljava/lang/String;
    //   1007: astore_2
    //   1008: new 116	java/lang/StringBuilder
    //   1011: astore_1
    //   1012: aload_1
    //   1013: invokespecial 117	java/lang/StringBuilder:<init>	()V
    //   1016: aload_1
    //   1017: ldc_w 271
    //   1020: invokevirtual 123	java/lang/StringBuilder:append	(Ljava/lang/String;)Ljava/lang/StringBuilder;
    //   1023: pop
    //   1024: aload_1
    //   1025: aload_0
    //   1026: getfield 88	b/d/i/a/a/f:c	Ljava/lang/String;
    //   1029: invokevirtual 123	java/lang/StringBuilder:append	(Ljava/lang/String;)Ljava/lang/StringBuilder;
    //   1032: pop
    //   1033: aload_1
    //   1034: ldc_w 302
    //   1037: invokevirtual 123	java/lang/StringBuilder:append	(Ljava/lang/String;)Ljava/lang/StringBuilder;
    //   1040: pop
    //   1041: aload_1
    //   1042: aload_0
    //   1043: invokevirtual 131	b/d/i/a/a/f:a	()I
    //   1046: invokevirtual 134	java/lang/StringBuilder:append	(I)Ljava/lang/StringBuilder;
    //   1049: pop
    //   1050: aload_2
    //   1051: aload_1
    //   1052: invokevirtual 138	java/lang/StringBuilder:toString	()Ljava/lang/String;
    //   1055: invokestatic 142	b/d/p/d:a	(Ljava/lang/String;Ljava/lang/String;)V
    //   1058: aload_0
    //   1059: invokevirtual 304	b/d/o/b/d:o	()V
    //   1062: aload_0
    //   1063: getfield 20	b/d/o/b/g:U3	Ljava/lang/String;
    //   1066: astore_1
    //   1067: new 116	java/lang/StringBuilder
    //   1070: dup
    //   1071: invokespecial 117	java/lang/StringBuilder:<init>	()V
    //   1074: astore_2
    //   1075: goto +293 -> 1368
    //   1078: astore_1
    //   1079: goto +352 -> 1431
    //   1082: astore_1
    //   1083: aload_0
    //   1084: getfield 20	b/d/o/b/g:U3	Ljava/lang/String;
    //   1087: astore_2
    //   1088: new 116	java/lang/StringBuilder
    //   1091: astore_3
    //   1092: aload_3
    //   1093: invokespecial 117	java/lang/StringBuilder:<init>	()V
    //   1096: aload_3
    //   1097: ldc_w 271
    //   1100: invokevirtual 123	java/lang/StringBuilder:append	(Ljava/lang/String;)Ljava/lang/StringBuilder;
    //   1103: pop
    //   1104: aload_3
    //   1105: aload_0
    //   1106: getfield 88	b/d/i/a/a/f:c	Ljava/lang/String;
    //   1109: invokevirtual 123	java/lang/StringBuilder:append	(Ljava/lang/String;)Ljava/lang/StringBuilder;
    //   1112: pop
    //   1113: aload_3
    //   1114: ldc_w 306
    //   1117: invokevirtual 123	java/lang/StringBuilder:append	(Ljava/lang/String;)Ljava/lang/StringBuilder;
    //   1120: pop
    //   1121: aload_3
    //   1122: aload_1
    //   1123: invokevirtual 307	java/lang/Exception:toString	()Ljava/lang/String;
    //   1126: invokevirtual 123	java/lang/StringBuilder:append	(Ljava/lang/String;)Ljava/lang/StringBuilder;
    //   1129: pop
    //   1130: aload_3
    //   1131: ldc 127
    //   1133: invokevirtual 123	java/lang/StringBuilder:append	(Ljava/lang/String;)Ljava/lang/StringBuilder;
    //   1136: pop
    //   1137: aload_3
    //   1138: aload_0
    //   1139: invokevirtual 131	b/d/i/a/a/f:a	()I
    //   1142: invokevirtual 134	java/lang/StringBuilder:append	(I)Ljava/lang/StringBuilder;
    //   1145: pop
    //   1146: aload_2
    //   1147: aload_3
    //   1148: invokevirtual 138	java/lang/StringBuilder:toString	()Ljava/lang/String;
    //   1151: invokestatic 142	b/d/p/d:a	(Ljava/lang/String;Ljava/lang/String;)V
    //   1154: aload_1
    //   1155: invokevirtual 310	java/lang/Exception:getMessage	()Ljava/lang/String;
    //   1158: ifnull +39 -> 1197
    //   1161: aload_1
    //   1162: invokevirtual 310	java/lang/Exception:getMessage	()Ljava/lang/String;
    //   1165: ldc_w 312
    //   1168: invokevirtual 317	java/lang/String:contains	(Ljava/lang/CharSequence;)Z
    //   1171: ifeq +26 -> 1197
    //   1174: aload_0
    //   1175: getfield 83	b/d/o/b/d:p3	Lb/d/o/b/c;
    //   1178: astore_2
    //   1179: aload_2
    //   1180: ifnull +42 -> 1222
    //   1183: aload_2
    //   1184: aload_0
    //   1185: getfield 88	b/d/i/a/a/f:c	Ljava/lang/String;
    //   1188: aload_1
    //   1189: invokeinterface 95 3 0
    //   1194: goto +28 -> 1222
    //   1197: aload_0
    //   1198: getfield 99	b/d/o/b/d:H3	Lb/d/o/b/f;
    //   1201: astore_2
    //   1202: aload_2
    //   1203: ifnull +19 -> 1222
    //   1206: aload_2
    //   1207: aload_0
    //   1208: getfield 88	b/d/i/a/a/f:c	Ljava/lang/String;
    //   1211: aload_0
    //   1212: getfield 102	b/d/i/a/a/f:x	I
    //   1215: iconst_1
    //   1216: aload_1
    //   1217: invokeinterface 108 5 0
    //   1222: aload_0
    //   1223: getfield 20	b/d/o/b/g:U3	Ljava/lang/String;
    //   1226: astore_1
    //   1227: new 116	java/lang/StringBuilder
    //   1230: dup
    //   1231: invokespecial 117	java/lang/StringBuilder:<init>	()V
    //   1234: astore_2
    //   1235: goto +133 -> 1368
    //   1238: astore_1
    //   1239: aload_0
    //   1240: getfield 20	b/d/o/b/g:U3	Ljava/lang/String;
    //   1243: astore_3
    //   1244: new 116	java/lang/StringBuilder
    //   1247: astore_2
    //   1248: aload_2
    //   1249: invokespecial 117	java/lang/StringBuilder:<init>	()V
    //   1252: aload_2
    //   1253: ldc_w 271
    //   1256: invokevirtual 123	java/lang/StringBuilder:append	(Ljava/lang/String;)Ljava/lang/StringBuilder;
    //   1259: pop
    //   1260: aload_2
    //   1261: aload_0
    //   1262: getfield 88	b/d/i/a/a/f:c	Ljava/lang/String;
    //   1265: invokevirtual 123	java/lang/StringBuilder:append	(Ljava/lang/String;)Ljava/lang/StringBuilder;
    //   1268: pop
    //   1269: aload_2
    //   1270: ldc_w 319
    //   1273: invokevirtual 123	java/lang/StringBuilder:append	(Ljava/lang/String;)Ljava/lang/StringBuilder;
    //   1276: pop
    //   1277: aload_2
    //   1278: aload_1
    //   1279: invokevirtual 320	java/net/MalformedURLException:toString	()Ljava/lang/String;
    //   1282: invokevirtual 123	java/lang/StringBuilder:append	(Ljava/lang/String;)Ljava/lang/StringBuilder;
    //   1285: pop
    //   1286: aload_2
    //   1287: ldc 127
    //   1289: invokevirtual 123	java/lang/StringBuilder:append	(Ljava/lang/String;)Ljava/lang/StringBuilder;
    //   1292: pop
    //   1293: aload_2
    //   1294: aload_0
    //   1295: invokevirtual 131	b/d/i/a/a/f:a	()I
    //   1298: invokevirtual 134	java/lang/StringBuilder:append	(I)Ljava/lang/StringBuilder;
    //   1301: pop
    //   1302: aload_3
    //   1303: aload_2
    //   1304: invokevirtual 138	java/lang/StringBuilder:toString	()Ljava/lang/String;
    //   1307: invokestatic 142	b/d/p/d:a	(Ljava/lang/String;Ljava/lang/String;)V
    //   1310: aload_0
    //   1311: getfield 83	b/d/o/b/d:p3	Lb/d/o/b/c;
    //   1314: astore_2
    //   1315: aload_2
    //   1316: ifnull +14 -> 1330
    //   1319: aload_2
    //   1320: aload_0
    //   1321: getfield 88	b/d/i/a/a/f:c	Ljava/lang/String;
    //   1324: aload_1
    //   1325: invokeinterface 95 3 0
    //   1330: aload_0
    //   1331: getfield 99	b/d/o/b/d:H3	Lb/d/o/b/f;
    //   1334: astore_2
    //   1335: aload_2
    //   1336: ifnull +19 -> 1355
    //   1339: aload_2
    //   1340: aload_0
    //   1341: getfield 88	b/d/i/a/a/f:c	Ljava/lang/String;
    //   1344: aload_0
    //   1345: getfield 102	b/d/i/a/a/f:x	I
    //   1348: iconst_0
    //   1349: aload_1
    //   1350: invokeinterface 108 5 0
    //   1355: aload_0
    //   1356: getfield 20	b/d/o/b/g:U3	Ljava/lang/String;
    //   1359: astore_1
    //   1360: new 116	java/lang/StringBuilder
    //   1363: dup
    //   1364: invokespecial 117	java/lang/StringBuilder:<init>	()V
    //   1367: astore_2
    //   1368: aload_2
    //   1369: ldc_w 271
    //   1372: invokevirtual 123	java/lang/StringBuilder:append	(Ljava/lang/String;)Ljava/lang/StringBuilder;
    //   1375: pop
    //   1376: aload_2
    //   1377: aload_0
    //   1378: getfield 88	b/d/i/a/a/f:c	Ljava/lang/String;
    //   1381: invokevirtual 123	java/lang/StringBuilder:append	(Ljava/lang/String;)Ljava/lang/StringBuilder;
    //   1384: pop
    //   1385: aload_2
    //   1386: ldc_w 277
    //   1389: invokevirtual 123	java/lang/StringBuilder:append	(Ljava/lang/String;)Ljava/lang/StringBuilder;
    //   1392: pop
    //   1393: aload_2
    //   1394: aload_0
    //   1395: invokevirtual 131	b/d/i/a/a/f:a	()I
    //   1398: invokevirtual 134	java/lang/StringBuilder:append	(I)Ljava/lang/StringBuilder;
    //   1401: pop
    //   1402: aload_1
    //   1403: aload_2
    //   1404: invokevirtual 138	java/lang/StringBuilder:toString	()Ljava/lang/String;
    //   1407: invokestatic 142	b/d/p/d:a	(Ljava/lang/String;Ljava/lang/String;)V
    //   1410: aload_0
    //   1411: iconst_0
    //   1412: putfield 280	b/d/o/b/d:M3	Z
    //   1415: aload_0
    //   1416: invokevirtual 283	b/d/o/b/d:r	()V
    //   1419: aload_0
    //   1420: invokevirtual 285	b/d/o/b/d:q	()V
    //   1423: aload_0
    //   1424: invokevirtual 288	b/d/o/b/d:n	()V
    //   1427: getstatic 200	java/lang/Boolean:TRUE	Ljava/lang/Boolean;
    //   1430: areturn
    //   1431: aload_0
    //   1432: getfield 20	b/d/o/b/g:U3	Ljava/lang/String;
    //   1435: astore_3
    //   1436: new 116	java/lang/StringBuilder
    //   1439: dup
    //   1440: invokespecial 117	java/lang/StringBuilder:<init>	()V
    //   1443: astore_2
    //   1444: aload_2
    //   1445: ldc_w 271
    //   1448: invokevirtual 123	java/lang/StringBuilder:append	(Ljava/lang/String;)Ljava/lang/StringBuilder;
    //   1451: pop
    //   1452: aload_2
    //   1453: aload_0
    //   1454: getfield 88	b/d/i/a/a/f:c	Ljava/lang/String;
    //   1457: invokevirtual 123	java/lang/StringBuilder:append	(Ljava/lang/String;)Ljava/lang/StringBuilder;
    //   1460: pop
    //   1461: aload_2
    //   1462: ldc_w 277
    //   1465: invokevirtual 123	java/lang/StringBuilder:append	(Ljava/lang/String;)Ljava/lang/StringBuilder;
    //   1468: pop
    //   1469: aload_2
    //   1470: aload_0
    //   1471: invokevirtual 131	b/d/i/a/a/f:a	()I
    //   1474: invokevirtual 134	java/lang/StringBuilder:append	(I)Ljava/lang/StringBuilder;
    //   1477: pop
    //   1478: aload_3
    //   1479: aload_2
    //   1480: invokevirtual 138	java/lang/StringBuilder:toString	()Ljava/lang/String;
    //   1483: invokestatic 142	b/d/p/d:a	(Ljava/lang/String;Ljava/lang/String;)V
    //   1486: aload_0
    //   1487: iconst_0
    //   1488: putfield 280	b/d/o/b/d:M3	Z
    //   1491: aload_0
    //   1492: invokevirtual 283	b/d/o/b/d:r	()V
    //   1495: aload_0
    //   1496: invokevirtual 285	b/d/o/b/d:q	()V
    //   1499: aload_0
    //   1500: invokevirtual 288	b/d/o/b/d:n	()V
    //   1503: aload_1
    //   1504: athrow
    // Local variable table:
    //   start	length	slot	name	signature
    //   0	1505	0	this	g
    //   34	512	1	localObject1	Object
    //   575	4	1	localObject2	Object
    //   580	6	1	localInterruptedException	InterruptedException
    //   603	464	1	localObject3	Object
    //   1078	1	1	localObject4	Object
    //   1082	135	1	localException	Exception
    //   1226	1	1	str1	String
    //   1238	112	1	localMalformedURLException	java.net.MalformedURLException
    //   1359	145	1	str2	String
    //   103	1377	2	localObject5	Object
    //   214	1265	3	localObject6	Object
    //   480	472	4	i	int
    // Exception table:
    //   from	to	target	type
    //   556	572	575	finally
    //   576	578	575	finally
    //   549	556	580	java/lang/InterruptedException
    //   578	580	580	java/lang/InterruptedException
    //   389	460	1078	finally
    //   463	471	1078	finally
    //   471	482	1078	finally
    //   490	545	1078	finally
    //   549	556	1078	finally
    //   578	580	1078	finally
    //   581	592	1078	finally
    //   592	650	1078	finally
    //   654	678	1078	finally
    //   678	683	1078	finally
    //   687	717	1078	finally
    //   717	721	1078	finally
    //   811	880	1078	finally
    //   888	893	1078	finally
    //   897	921	1078	finally
    //   921	926	1078	finally
    //   930	960	1078	finally
    //   960	965	1078	finally
    //   969	973	1078	finally
    //   973	977	1078	finally
    //   993	1003	1078	finally
    //   1003	1062	1078	finally
    //   1083	1179	1078	finally
    //   1183	1194	1078	finally
    //   1197	1202	1078	finally
    //   1206	1222	1078	finally
    //   1239	1315	1078	finally
    //   1319	1330	1078	finally
    //   1330	1335	1078	finally
    //   1339	1355	1078	finally
    //   389	460	1082	java/lang/Exception
    //   463	471	1082	java/lang/Exception
    //   471	482	1082	java/lang/Exception
    //   490	545	1082	java/lang/Exception
    //   549	556	1082	java/lang/Exception
    //   578	580	1082	java/lang/Exception
    //   581	592	1082	java/lang/Exception
    //   592	650	1082	java/lang/Exception
    //   654	678	1082	java/lang/Exception
    //   678	683	1082	java/lang/Exception
    //   687	717	1082	java/lang/Exception
    //   717	721	1082	java/lang/Exception
    //   811	880	1082	java/lang/Exception
    //   888	893	1082	java/lang/Exception
    //   897	921	1082	java/lang/Exception
    //   921	926	1082	java/lang/Exception
    //   930	960	1082	java/lang/Exception
    //   960	965	1082	java/lang/Exception
    //   969	973	1082	java/lang/Exception
    //   973	977	1082	java/lang/Exception
    //   993	1003	1082	java/lang/Exception
    //   1003	1062	1082	java/lang/Exception
    //   389	460	1238	java/net/MalformedURLException
    //   463	471	1238	java/net/MalformedURLException
    //   471	482	1238	java/net/MalformedURLException
    //   490	545	1238	java/net/MalformedURLException
    //   549	556	1238	java/net/MalformedURLException
    //   578	580	1238	java/net/MalformedURLException
    //   581	592	1238	java/net/MalformedURLException
    //   592	650	1238	java/net/MalformedURLException
    //   654	678	1238	java/net/MalformedURLException
    //   678	683	1238	java/net/MalformedURLException
    //   687	717	1238	java/net/MalformedURLException
    //   717	721	1238	java/net/MalformedURLException
    //   811	880	1238	java/net/MalformedURLException
    //   888	893	1238	java/net/MalformedURLException
    //   897	921	1238	java/net/MalformedURLException
    //   921	926	1238	java/net/MalformedURLException
    //   930	960	1238	java/net/MalformedURLException
    //   960	965	1238	java/net/MalformedURLException
    //   969	973	1238	java/net/MalformedURLException
    //   973	977	1238	java/net/MalformedURLException
    //   993	1003	1238	java/net/MalformedURLException
    //   1003	1062	1238	java/net/MalformedURLException
  }
  
  public void p()
  {
    super.p();
    c localc = this.X3;
    if (localc != null) {
      localc.dispose();
    }
  }
}


/* Location:              C:\Users\User\Desktop\decompile\jdgui110\Tapojar.jar!\b\d\o\b\g.class
 * Java compiler version: 6 (50.0)
 * JD-Core Version:       0.7.1
 */