package kotlinx.coroutines.d2;

public final class a
{
  /* Error */
  public static final <T> void a(kotlin.jvm.b.l<? super kotlin.coroutines.c<? super T>, ? extends Object> paraml, kotlin.coroutines.c<? super T> paramc)
  {
    // Byte code:
    //   0: aload_0
    //   1: ldc 8
    //   3: invokestatic 14	kotlin/jvm/internal/j:f	(Ljava/lang/Object;Ljava/lang/String;)V
    //   6: aload_1
    //   7: ldc 16
    //   9: invokestatic 14	kotlin/jvm/internal/j:f	(Ljava/lang/Object;Ljava/lang/String;)V
    //   12: aload_0
    //   13: aload_1
    //   14: invokestatic 21	kotlin/coroutines/intrinsics/a:a	(Lkotlin/jvm/b/l;Lkotlin/coroutines/c;)Lkotlin/coroutines/c;
    //   17: invokestatic 25	kotlin/coroutines/intrinsics/a:c	(Lkotlin/coroutines/c;)Lkotlin/coroutines/c;
    //   20: getstatic 30	kotlin/p:a	Lkotlin/p;
    //   23: invokestatic 36	kotlinx/coroutines/l0:d	(Lkotlin/coroutines/c;Ljava/lang/Object;)V
    //   26: goto +21 -> 47
    //   29: astore_2
    //   30: getstatic 42	kotlin/Result:Companion	Lkotlin/Result$a;
    //   33: astore_0
    //   34: aload_1
    //   35: aload_2
    //   36: invokestatic 47	kotlin/k:a	(Ljava/lang/Throwable;)Ljava/lang/Object;
    //   39: invokestatic 51	kotlin/Result:constructor-impl	(Ljava/lang/Object;)Ljava/lang/Object;
    //   42: invokeinterface 57 2 0
    //   47: return
    // Local variable table:
    //   start	length	slot	name	signature
    //   0	48	0	paraml	kotlin.jvm.b.l<? super kotlin.coroutines.c<? super T>, ? extends Object>
    //   0	48	1	paramc	kotlin.coroutines.c<? super T>
    //   29	7	2	localThrowable	Throwable
    // Exception table:
    //   from	to	target	type
    //   12	26	29	finally
  }
  
  /* Error */
  public static final <R, T> void b(kotlin.jvm.b.p<? super R, ? super kotlin.coroutines.c<? super T>, ? extends Object> paramp, R paramR, kotlin.coroutines.c<? super T> paramc)
  {
    // Byte code:
    //   0: aload_0
    //   1: ldc 8
    //   3: invokestatic 14	kotlin/jvm/internal/j:f	(Ljava/lang/Object;Ljava/lang/String;)V
    //   6: aload_2
    //   7: ldc 16
    //   9: invokestatic 14	kotlin/jvm/internal/j:f	(Ljava/lang/Object;Ljava/lang/String;)V
    //   12: aload_0
    //   13: aload_1
    //   14: aload_2
    //   15: invokestatic 65	kotlin/coroutines/intrinsics/a:b	(Lkotlin/jvm/b/p;Ljava/lang/Object;Lkotlin/coroutines/c;)Lkotlin/coroutines/c;
    //   18: invokestatic 25	kotlin/coroutines/intrinsics/a:c	(Lkotlin/coroutines/c;)Lkotlin/coroutines/c;
    //   21: getstatic 30	kotlin/p:a	Lkotlin/p;
    //   24: invokestatic 36	kotlinx/coroutines/l0:d	(Lkotlin/coroutines/c;Ljava/lang/Object;)V
    //   27: goto +21 -> 48
    //   30: astore_0
    //   31: getstatic 42	kotlin/Result:Companion	Lkotlin/Result$a;
    //   34: astore_1
    //   35: aload_2
    //   36: aload_0
    //   37: invokestatic 47	kotlin/k:a	(Ljava/lang/Throwable;)Ljava/lang/Object;
    //   40: invokestatic 51	kotlin/Result:constructor-impl	(Ljava/lang/Object;)Ljava/lang/Object;
    //   43: invokeinterface 57 2 0
    //   48: return
    // Local variable table:
    //   start	length	slot	name	signature
    //   0	49	0	paramp	kotlin.jvm.b.p<? super R, ? super kotlin.coroutines.c<? super T>, ? extends Object>
    //   0	49	1	paramR	R
    //   0	49	2	paramc	kotlin.coroutines.c<? super T>
    // Exception table:
    //   from	to	target	type
    //   12	27	30	finally
  }
}


/* Location:              C:\Users\User\Desktop\decompile\jdgui110\Tapojar.jar!\kotlinx\coroutines\d2\a.class
 * Java compiler version: 6 (50.0)
 * JD-Core Version:       0.7.1
 */