package com.google.android.gms.measurement.internal;

import androidx.annotation.WorkerThread;
import com.google.android.gms.common.internal.Preconditions;
import java.net.URL;
import java.util.Map;

@WorkerThread
final class zzer
  implements Runnable
{
  private final URL zzb;
  private final byte[] zzc;
  private final zzep zzd;
  private final String zze;
  private final Map<String, String> zzf;
  
  public zzer(String paramString, URL paramURL, byte[] paramArrayOfByte, Map<String, String> paramMap, zzep paramzzep)
  {
    Preconditions.checkNotEmpty(paramURL);
    Preconditions.checkNotNull(paramArrayOfByte);
    Object localObject;
    Preconditions.checkNotNull(localObject);
    this.zzb = paramArrayOfByte;
    this.zzc = paramMap;
    this.zzd = ((zzep)localObject);
    this.zze = paramURL;
    this.zzf = paramzzep;
  }
  
  /* Error */
  public final void run()
  {
    // Byte code:
    //   0: aload_0
    //   1: getfield 24	com/google/android/gms/measurement/internal/zzer:zza	Lcom/google/android/gms/measurement/internal/zzes;
    //   4: invokevirtual 58	com/google/android/gms/measurement/internal/zzgn:zzaw	()V
    //   7: aconst_null
    //   8: astore_1
    //   9: aconst_null
    //   10: astore_2
    //   11: aconst_null
    //   12: astore_3
    //   13: aconst_null
    //   14: astore 4
    //   16: aload_0
    //   17: getfield 24	com/google/android/gms/measurement/internal/zzer:zza	Lcom/google/android/gms/measurement/internal/zzes;
    //   20: aload_0
    //   21: getfield 39	com/google/android/gms/measurement/internal/zzer:zzb	Ljava/net/URL;
    //   24: invokevirtual 63	com/google/android/gms/measurement/internal/zzes:zzc	(Ljava/net/URL;)Ljava/net/HttpURLConnection;
    //   27: astore 5
    //   29: aload_0
    //   30: getfield 47	com/google/android/gms/measurement/internal/zzer:zzf	Ljava/util/Map;
    //   33: astore 6
    //   35: aload 6
    //   37: ifnull +67 -> 104
    //   40: aload 6
    //   42: invokeinterface 69 1 0
    //   47: invokeinterface 75 1 0
    //   52: astore 6
    //   54: aload 6
    //   56: invokeinterface 81 1 0
    //   61: ifeq +43 -> 104
    //   64: aload 6
    //   66: invokeinterface 85 1 0
    //   71: checkcast 87	java/util/Map$Entry
    //   74: astore 7
    //   76: aload 5
    //   78: aload 7
    //   80: invokeinterface 90 1 0
    //   85: checkcast 92	java/lang/String
    //   88: aload 7
    //   90: invokeinterface 95 1 0
    //   95: checkcast 92	java/lang/String
    //   98: invokevirtual 101	java/net/HttpURLConnection:addRequestProperty	(Ljava/lang/String;Ljava/lang/String;)V
    //   101: goto -47 -> 54
    //   104: aload_0
    //   105: getfield 41	com/google/android/gms/measurement/internal/zzer:zzc	[B
    //   108: ifnull +119 -> 227
    //   111: aload_0
    //   112: getfield 24	com/google/android/gms/measurement/internal/zzer:zza	Lcom/google/android/gms/measurement/internal/zzes;
    //   115: getfield 106	com/google/android/gms/measurement/internal/zzkd:zzf	Lcom/google/android/gms/measurement/internal/zzkn;
    //   118: invokevirtual 112	com/google/android/gms/measurement/internal/zzkn:zzm	()Lcom/google/android/gms/measurement/internal/zzkp;
    //   121: aload_0
    //   122: getfield 41	com/google/android/gms/measurement/internal/zzer:zzc	[B
    //   125: invokevirtual 118	com/google/android/gms/measurement/internal/zzkp:zzs	([B)[B
    //   128: astore 7
    //   130: aload_0
    //   131: getfield 24	com/google/android/gms/measurement/internal/zzer:zza	Lcom/google/android/gms/measurement/internal/zzes;
    //   134: getfield 121	com/google/android/gms/measurement/internal/zzgn:zzs	Lcom/google/android/gms/measurement/internal/zzfu;
    //   137: invokevirtual 127	com/google/android/gms/measurement/internal/zzfu:zzau	()Lcom/google/android/gms/measurement/internal/zzem;
    //   140: invokevirtual 133	com/google/android/gms/measurement/internal/zzem:zzk	()Lcom/google/android/gms/measurement/internal/zzek;
    //   143: astore 6
    //   145: aload 7
    //   147: arraylength
    //   148: istore 8
    //   150: aload 6
    //   152: ldc -121
    //   154: iload 8
    //   156: invokestatic 141	java/lang/Integer:valueOf	(I)Ljava/lang/Integer;
    //   159: invokevirtual 146	com/google/android/gms/measurement/internal/zzek:zzb	(Ljava/lang/String;Ljava/lang/Object;)V
    //   162: aload 5
    //   164: iconst_1
    //   165: invokevirtual 150	java/net/HttpURLConnection:setDoOutput	(Z)V
    //   168: aload 5
    //   170: ldc -104
    //   172: ldc -102
    //   174: invokevirtual 101	java/net/HttpURLConnection:addRequestProperty	(Ljava/lang/String;Ljava/lang/String;)V
    //   177: aload 5
    //   179: iload 8
    //   181: invokevirtual 158	java/net/HttpURLConnection:setFixedLengthStreamingMode	(I)V
    //   184: aload 5
    //   186: invokevirtual 161	java/net/HttpURLConnection:connect	()V
    //   189: aload 5
    //   191: invokevirtual 165	java/net/HttpURLConnection:getOutputStream	()Ljava/io/OutputStream;
    //   194: astore 6
    //   196: aload 6
    //   198: aload 7
    //   200: invokevirtual 171	java/io/OutputStream:write	([B)V
    //   203: aload 6
    //   205: invokevirtual 174	java/io/OutputStream:close	()V
    //   208: goto +19 -> 227
    //   211: astore_2
    //   212: aload 5
    //   214: astore 7
    //   216: aload_2
    //   217: astore 5
    //   219: goto +230 -> 449
    //   222: astore 7
    //   224: goto +332 -> 556
    //   227: aload 5
    //   229: invokevirtual 178	java/net/HttpURLConnection:getResponseCode	()I
    //   232: istore 8
    //   234: aload 5
    //   236: invokevirtual 182	java/net/HttpURLConnection:getHeaderFields	()Ljava/util/Map;
    //   239: astore 6
    //   241: new 184	java/io/ByteArrayOutputStream
    //   244: astore 7
    //   246: aload 7
    //   248: invokespecial 185	java/io/ByteArrayOutputStream:<init>	()V
    //   251: aload 5
    //   253: invokevirtual 189	java/net/HttpURLConnection:getInputStream	()Ljava/io/InputStream;
    //   256: astore_2
    //   257: sipush 1024
    //   260: newarray <illegal type>
    //   262: astore 4
    //   264: aload_2
    //   265: aload 4
    //   267: invokevirtual 195	java/io/InputStream:read	([B)I
    //   270: istore 9
    //   272: iload 9
    //   274: ifle +16 -> 290
    //   277: aload 7
    //   279: aload 4
    //   281: iconst_0
    //   282: iload 9
    //   284: invokevirtual 198	java/io/ByteArrayOutputStream:write	([BII)V
    //   287: goto -23 -> 264
    //   290: aload 7
    //   292: invokevirtual 202	java/io/ByteArrayOutputStream:toByteArray	()[B
    //   295: astore 7
    //   297: aload_2
    //   298: invokevirtual 203	java/io/InputStream:close	()V
    //   301: aload 5
    //   303: invokevirtual 206	java/net/HttpURLConnection:disconnect	()V
    //   306: aload_0
    //   307: getfield 24	com/google/android/gms/measurement/internal/zzer:zza	Lcom/google/android/gms/measurement/internal/zzes;
    //   310: getfield 121	com/google/android/gms/measurement/internal/zzgn:zzs	Lcom/google/android/gms/measurement/internal/zzfu;
    //   313: invokevirtual 210	com/google/android/gms/measurement/internal/zzfu:zzav	()Lcom/google/android/gms/measurement/internal/zzfr;
    //   316: astore 5
    //   318: new 212	com/google/android/gms/measurement/internal/zzeq
    //   321: dup
    //   322: aload_0
    //   323: getfield 45	com/google/android/gms/measurement/internal/zzer:zze	Ljava/lang/String;
    //   326: aload_0
    //   327: getfield 43	com/google/android/gms/measurement/internal/zzer:zzd	Lcom/google/android/gms/measurement/internal/zzep;
    //   330: iload 8
    //   332: aconst_null
    //   333: aload 7
    //   335: aload 6
    //   337: aconst_null
    //   338: invokespecial 215	com/google/android/gms/measurement/internal/zzeq:<init>	(Ljava/lang/String;Lcom/google/android/gms/measurement/internal/zzep;ILjava/lang/Throwable;[BLjava/util/Map;Lcom/google/android/gms/measurement/internal/zzeo;)V
    //   341: astore 6
    //   343: aload 5
    //   345: aload 6
    //   347: invokevirtual 221	com/google/android/gms/measurement/internal/zzfr:zzh	(Ljava/lang/Runnable;)V
    //   350: return
    //   351: astore 7
    //   353: goto +7 -> 360
    //   356: astore 7
    //   358: aconst_null
    //   359: astore_2
    //   360: aload_2
    //   361: ifnull +7 -> 368
    //   364: aload_2
    //   365: invokevirtual 203	java/io/InputStream:close	()V
    //   368: aload 7
    //   370: athrow
    //   371: astore_2
    //   372: aload_1
    //   373: astore_3
    //   374: aload 5
    //   376: astore 7
    //   378: aload_2
    //   379: astore 5
    //   381: aload 6
    //   383: astore_2
    //   384: goto +73 -> 457
    //   387: astore 7
    //   389: goto +25 -> 414
    //   392: astore 6
    //   394: aconst_null
    //   395: astore_2
    //   396: aload_1
    //   397: astore_3
    //   398: aload 5
    //   400: astore 7
    //   402: aload 6
    //   404: astore 5
    //   406: goto +51 -> 457
    //   409: astore 7
    //   411: aconst_null
    //   412: astore 6
    //   414: aload 6
    //   416: astore_2
    //   417: goto +147 -> 564
    //   420: astore_2
    //   421: aload 4
    //   423: astore 6
    //   425: aload 5
    //   427: astore 7
    //   429: aload_2
    //   430: astore 5
    //   432: goto +17 -> 449
    //   435: astore 6
    //   437: goto +112 -> 549
    //   440: astore 5
    //   442: aconst_null
    //   443: astore 7
    //   445: aload 4
    //   447: astore 6
    //   449: aconst_null
    //   450: astore_2
    //   451: iconst_0
    //   452: istore 8
    //   454: aload 6
    //   456: astore_3
    //   457: aload_3
    //   458: ifnull +39 -> 497
    //   461: aload_3
    //   462: invokevirtual 174	java/io/OutputStream:close	()V
    //   465: goto +32 -> 497
    //   468: astore 6
    //   470: aload_0
    //   471: getfield 24	com/google/android/gms/measurement/internal/zzer:zza	Lcom/google/android/gms/measurement/internal/zzes;
    //   474: getfield 121	com/google/android/gms/measurement/internal/zzgn:zzs	Lcom/google/android/gms/measurement/internal/zzfu;
    //   477: invokevirtual 127	com/google/android/gms/measurement/internal/zzfu:zzau	()Lcom/google/android/gms/measurement/internal/zzem;
    //   480: invokevirtual 223	com/google/android/gms/measurement/internal/zzem:zzb	()Lcom/google/android/gms/measurement/internal/zzek;
    //   483: ldc -31
    //   485: aload_0
    //   486: getfield 45	com/google/android/gms/measurement/internal/zzer:zze	Ljava/lang/String;
    //   489: invokestatic 229	com/google/android/gms/measurement/internal/zzem:zzl	(Ljava/lang/String;)Ljava/lang/Object;
    //   492: aload 6
    //   494: invokevirtual 232	com/google/android/gms/measurement/internal/zzek:zzc	(Ljava/lang/String;Ljava/lang/Object;Ljava/lang/Object;)V
    //   497: aload 7
    //   499: ifnull +8 -> 507
    //   502: aload 7
    //   504: invokevirtual 206	java/net/HttpURLConnection:disconnect	()V
    //   507: aload_0
    //   508: getfield 24	com/google/android/gms/measurement/internal/zzer:zza	Lcom/google/android/gms/measurement/internal/zzes;
    //   511: getfield 121	com/google/android/gms/measurement/internal/zzgn:zzs	Lcom/google/android/gms/measurement/internal/zzfu;
    //   514: invokevirtual 210	com/google/android/gms/measurement/internal/zzfu:zzav	()Lcom/google/android/gms/measurement/internal/zzfr;
    //   517: new 212	com/google/android/gms/measurement/internal/zzeq
    //   520: dup
    //   521: aload_0
    //   522: getfield 45	com/google/android/gms/measurement/internal/zzer:zze	Ljava/lang/String;
    //   525: aload_0
    //   526: getfield 43	com/google/android/gms/measurement/internal/zzer:zzd	Lcom/google/android/gms/measurement/internal/zzep;
    //   529: iload 8
    //   531: aconst_null
    //   532: aconst_null
    //   533: aload_2
    //   534: aconst_null
    //   535: invokespecial 215	com/google/android/gms/measurement/internal/zzeq:<init>	(Ljava/lang/String;Lcom/google/android/gms/measurement/internal/zzep;ILjava/lang/Throwable;[BLjava/util/Map;Lcom/google/android/gms/measurement/internal/zzeo;)V
    //   538: invokevirtual 221	com/google/android/gms/measurement/internal/zzfr:zzh	(Ljava/lang/Runnable;)V
    //   541: aload 5
    //   543: athrow
    //   544: astore 6
    //   546: aconst_null
    //   547: astore 5
    //   549: aload 6
    //   551: astore 7
    //   553: aload_2
    //   554: astore 6
    //   556: aconst_null
    //   557: astore_2
    //   558: iconst_0
    //   559: istore 8
    //   561: aload 6
    //   563: astore_3
    //   564: aload_3
    //   565: ifnull +39 -> 604
    //   568: aload_3
    //   569: invokevirtual 174	java/io/OutputStream:close	()V
    //   572: goto +32 -> 604
    //   575: astore 6
    //   577: aload_0
    //   578: getfield 24	com/google/android/gms/measurement/internal/zzer:zza	Lcom/google/android/gms/measurement/internal/zzes;
    //   581: getfield 121	com/google/android/gms/measurement/internal/zzgn:zzs	Lcom/google/android/gms/measurement/internal/zzfu;
    //   584: invokevirtual 127	com/google/android/gms/measurement/internal/zzfu:zzau	()Lcom/google/android/gms/measurement/internal/zzem;
    //   587: invokevirtual 223	com/google/android/gms/measurement/internal/zzem:zzb	()Lcom/google/android/gms/measurement/internal/zzek;
    //   590: ldc -31
    //   592: aload_0
    //   593: getfield 45	com/google/android/gms/measurement/internal/zzer:zze	Ljava/lang/String;
    //   596: invokestatic 229	com/google/android/gms/measurement/internal/zzem:zzl	(Ljava/lang/String;)Ljava/lang/Object;
    //   599: aload 6
    //   601: invokevirtual 232	com/google/android/gms/measurement/internal/zzek:zzc	(Ljava/lang/String;Ljava/lang/Object;Ljava/lang/Object;)V
    //   604: aload 5
    //   606: ifnull +8 -> 614
    //   609: aload 5
    //   611: invokevirtual 206	java/net/HttpURLConnection:disconnect	()V
    //   614: aload_0
    //   615: getfield 24	com/google/android/gms/measurement/internal/zzer:zza	Lcom/google/android/gms/measurement/internal/zzes;
    //   618: getfield 121	com/google/android/gms/measurement/internal/zzgn:zzs	Lcom/google/android/gms/measurement/internal/zzfu;
    //   621: invokevirtual 210	com/google/android/gms/measurement/internal/zzfu:zzav	()Lcom/google/android/gms/measurement/internal/zzfr;
    //   624: astore 5
    //   626: new 212	com/google/android/gms/measurement/internal/zzeq
    //   629: dup
    //   630: aload_0
    //   631: getfield 45	com/google/android/gms/measurement/internal/zzer:zze	Ljava/lang/String;
    //   634: aload_0
    //   635: getfield 43	com/google/android/gms/measurement/internal/zzer:zzd	Lcom/google/android/gms/measurement/internal/zzep;
    //   638: iload 8
    //   640: aload 7
    //   642: aconst_null
    //   643: aload_2
    //   644: aconst_null
    //   645: invokespecial 215	com/google/android/gms/measurement/internal/zzeq:<init>	(Ljava/lang/String;Lcom/google/android/gms/measurement/internal/zzep;ILjava/lang/Throwable;[BLjava/util/Map;Lcom/google/android/gms/measurement/internal/zzeo;)V
    //   648: astore 6
    //   650: goto -307 -> 343
    // Local variable table:
    //   start	length	slot	name	signature
    //   0	653	0	this	zzer
    //   8	389	1	localObject1	Object
    //   10	1	2	localObject2	Object
    //   211	6	2	localObject3	Object
    //   256	109	2	localInputStream	java.io.InputStream
    //   371	8	2	localObject4	Object
    //   383	34	2	localObject5	Object
    //   420	10	2	localObject6	Object
    //   450	194	2	localMap1	Map
    //   12	557	3	localObject7	Object
    //   14	432	4	arrayOfByte1	byte[]
    //   27	404	5	localObject8	Object
    //   440	102	5	localObject9	Object
    //   547	78	5	localzzfr	zzfr
    //   33	349	6	localObject10	Object
    //   392	11	6	localObject11	Object
    //   412	12	6	arrayOfByte2	byte[]
    //   435	1	6	localIOException1	java.io.IOException
    //   447	8	6	arrayOfByte3	byte[]
    //   468	25	6	localIOException2	java.io.IOException
    //   544	6	6	localIOException3	java.io.IOException
    //   554	8	6	localMap2	Map
    //   575	25	6	localIOException4	java.io.IOException
    //   648	1	6	localzzeq	zzeq
    //   74	141	7	localObject12	Object
    //   222	1	7	localIOException5	java.io.IOException
    //   244	90	7	localObject13	Object
    //   351	1	7	localObject14	Object
    //   356	13	7	localObject15	Object
    //   376	1	7	localObject16	Object
    //   387	1	7	localIOException6	java.io.IOException
    //   400	1	7	localObject17	Object
    //   409	1	7	localIOException7	java.io.IOException
    //   427	214	7	localObject18	Object
    //   148	491	8	i	int
    //   270	13	9	j	int
    // Exception table:
    //   from	to	target	type
    //   196	208	211	finally
    //   196	208	222	java/io/IOException
    //   257	264	351	finally
    //   264	272	351	finally
    //   277	287	351	finally
    //   290	297	351	finally
    //   241	257	356	finally
    //   297	301	371	finally
    //   364	368	371	finally
    //   368	371	371	finally
    //   297	301	387	java/io/IOException
    //   364	368	387	java/io/IOException
    //   368	371	387	java/io/IOException
    //   234	241	392	finally
    //   234	241	409	java/io/IOException
    //   29	35	420	finally
    //   40	54	420	finally
    //   54	101	420	finally
    //   104	196	420	finally
    //   227	234	420	finally
    //   29	35	435	java/io/IOException
    //   40	54	435	java/io/IOException
    //   54	101	435	java/io/IOException
    //   104	196	435	java/io/IOException
    //   227	234	435	java/io/IOException
    //   16	29	440	finally
    //   461	465	468	java/io/IOException
    //   16	29	544	java/io/IOException
    //   568	572	575	java/io/IOException
  }
}


/* Location:              C:\Users\User\Desktop\decompile\jdgui110\Tapojar.jar!\com\google\android\gms\measurement\internal\zzer.class
 * Java compiler version: 6 (50.0)
 * JD-Core Version:       0.7.1
 */