package com.google.android.gms.measurement.internal;

import java.util.concurrent.atomic.AtomicReference;

final class zzhi
  implements Runnable
{
  zzhi(zzhw paramzzhw, AtomicReference paramAtomicReference) {}
  
  /* Error */
  public final void run()
  {
    // Byte code:
    //   0: aload_0
    //   1: getfield 16	com/google/android/gms/measurement/internal/zzhi:zza	Ljava/util/concurrent/atomic/AtomicReference;
    //   4: astore_1
    //   5: aload_1
    //   6: monitorenter
    //   7: aload_0
    //   8: getfield 16	com/google/android/gms/measurement/internal/zzhi:zza	Ljava/util/concurrent/atomic/AtomicReference;
    //   11: aload_0
    //   12: getfield 14	com/google/android/gms/measurement/internal/zzhi:zzb	Lcom/google/android/gms/measurement/internal/zzhw;
    //   15: getfield 27	com/google/android/gms/measurement/internal/zzgn:zzs	Lcom/google/android/gms/measurement/internal/zzfu;
    //   18: invokevirtual 33	com/google/android/gms/measurement/internal/zzfu:zzc	()Lcom/google/android/gms/measurement/internal/zzae;
    //   21: aload_0
    //   22: getfield 14	com/google/android/gms/measurement/internal/zzhi:zzb	Lcom/google/android/gms/measurement/internal/zzhw;
    //   25: getfield 27	com/google/android/gms/measurement/internal/zzgn:zzs	Lcom/google/android/gms/measurement/internal/zzfu;
    //   28: invokevirtual 37	com/google/android/gms/measurement/internal/zzfu:zzA	()Lcom/google/android/gms/measurement/internal/zzee;
    //   31: invokevirtual 43	com/google/android/gms/measurement/internal/zzee:zzi	()Ljava/lang/String;
    //   34: getstatic 49	com/google/android/gms/measurement/internal/zzea:zzJ	Lcom/google/android/gms/measurement/internal/zzdz;
    //   37: invokevirtual 55	com/google/android/gms/measurement/internal/zzae:zzn	(Ljava/lang/String;Lcom/google/android/gms/measurement/internal/zzdz;)Z
    //   40: invokestatic 61	java/lang/Boolean:valueOf	(Z)Ljava/lang/Boolean;
    //   43: invokevirtual 67	java/util/concurrent/atomic/AtomicReference:set	(Ljava/lang/Object;)V
    //   46: aload_0
    //   47: getfield 16	com/google/android/gms/measurement/internal/zzhi:zza	Ljava/util/concurrent/atomic/AtomicReference;
    //   50: invokevirtual 70	java/lang/Object:notify	()V
    //   53: aload_1
    //   54: monitorexit
    //   55: return
    //   56: astore_2
    //   57: aload_0
    //   58: getfield 16	com/google/android/gms/measurement/internal/zzhi:zza	Ljava/util/concurrent/atomic/AtomicReference;
    //   61: invokevirtual 70	java/lang/Object:notify	()V
    //   64: aload_2
    //   65: athrow
    //   66: astore_2
    //   67: aload_1
    //   68: monitorexit
    //   69: aload_2
    //   70: athrow
    // Local variable table:
    //   start	length	slot	name	signature
    //   0	71	0	this	zzhi
    //   4	64	1	localAtomicReference	AtomicReference
    //   56	9	2	localObject1	Object
    //   66	4	2	localObject2	Object
    // Exception table:
    //   from	to	target	type
    //   7	46	56	finally
    //   46	55	66	finally
    //   57	66	66	finally
    //   67	69	66	finally
  }
}


/* Location:              C:\Users\User\Desktop\decompile\jdgui110\Tapojar.jar!\com\google\android\gms\measurement\internal\zzhi.class
 * Java compiler version: 6 (50.0)
 * JD-Core Version:       0.7.1
 */