package com.google.android.gms.measurement.internal;

import com.google.android.gms.internal.measurement.zzcf;

final class zzil
  implements Runnable
{
  zzil(zzjk paramzzjk, String paramString1, String paramString2, zzp paramzzp, boolean paramBoolean, zzcf paramzzcf) {}
  
  /* Error */
  public final void run()
  {
    // Byte code:
    //   0: new 40	android/os/Bundle
    //   3: dup
    //   4: invokespecial 41	android/os/Bundle:<init>	()V
    //   7: astore_1
    //   8: aload_0
    //   9: getfield 21	com/google/android/gms/measurement/internal/zzil:zzf	Lcom/google/android/gms/measurement/internal/zzjk;
    //   12: invokestatic 47	com/google/android/gms/measurement/internal/zzjk:zzM	(Lcom/google/android/gms/measurement/internal/zzjk;)Lcom/google/android/gms/measurement/internal/zzed;
    //   15: astore_2
    //   16: aload_2
    //   17: ifnonnull +48 -> 65
    //   20: aload_0
    //   21: getfield 21	com/google/android/gms/measurement/internal/zzil:zzf	Lcom/google/android/gms/measurement/internal/zzjk;
    //   24: getfield 53	com/google/android/gms/measurement/internal/zzgn:zzs	Lcom/google/android/gms/measurement/internal/zzfu;
    //   27: invokevirtual 59	com/google/android/gms/measurement/internal/zzfu:zzau	()Lcom/google/android/gms/measurement/internal/zzem;
    //   30: invokevirtual 64	com/google/android/gms/measurement/internal/zzem:zzb	()Lcom/google/android/gms/measurement/internal/zzek;
    //   33: ldc 66
    //   35: aload_0
    //   36: getfield 23	com/google/android/gms/measurement/internal/zzil:zza	Ljava/lang/String;
    //   39: aload_0
    //   40: getfield 25	com/google/android/gms/measurement/internal/zzil:zzb	Ljava/lang/String;
    //   43: invokevirtual 71	com/google/android/gms/measurement/internal/zzek:zzc	(Ljava/lang/String;Ljava/lang/Object;Ljava/lang/Object;)V
    //   46: aload_0
    //   47: getfield 21	com/google/android/gms/measurement/internal/zzil:zzf	Lcom/google/android/gms/measurement/internal/zzjk;
    //   50: getfield 53	com/google/android/gms/measurement/internal/zzgn:zzs	Lcom/google/android/gms/measurement/internal/zzfu;
    //   53: invokevirtual 75	com/google/android/gms/measurement/internal/zzfu:zzl	()Lcom/google/android/gms/measurement/internal/zzku;
    //   56: aload_0
    //   57: getfield 31	com/google/android/gms/measurement/internal/zzil:zze	Lcom/google/android/gms/internal/measurement/zzcf;
    //   60: aload_1
    //   61: invokevirtual 81	com/google/android/gms/measurement/internal/zzku:zzai	(Lcom/google/android/gms/internal/measurement/zzcf;Landroid/os/Bundle;)V
    //   64: return
    //   65: aload_0
    //   66: getfield 27	com/google/android/gms/measurement/internal/zzil:zzc	Lcom/google/android/gms/measurement/internal/zzp;
    //   69: invokestatic 87	com/google/android/gms/common/internal/Preconditions:checkNotNull	(Ljava/lang/Object;)Ljava/lang/Object;
    //   72: pop
    //   73: aload_2
    //   74: aload_0
    //   75: getfield 23	com/google/android/gms/measurement/internal/zzil:zza	Ljava/lang/String;
    //   78: aload_0
    //   79: getfield 25	com/google/android/gms/measurement/internal/zzil:zzb	Ljava/lang/String;
    //   82: aload_0
    //   83: getfield 29	com/google/android/gms/measurement/internal/zzil:zzd	Z
    //   86: aload_0
    //   87: getfield 27	com/google/android/gms/measurement/internal/zzil:zzc	Lcom/google/android/gms/measurement/internal/zzp;
    //   90: invokeinterface 93 5 0
    //   95: astore_3
    //   96: new 40	android/os/Bundle
    //   99: astore_2
    //   100: aload_2
    //   101: invokespecial 41	android/os/Bundle:<init>	()V
    //   104: aload_3
    //   105: ifnonnull +6 -> 111
    //   108: goto +110 -> 218
    //   111: aload_3
    //   112: invokeinterface 99 1 0
    //   117: astore 4
    //   119: aload 4
    //   121: invokeinterface 105 1 0
    //   126: ifeq +92 -> 218
    //   129: aload 4
    //   131: invokeinterface 109 1 0
    //   136: checkcast 111	com/google/android/gms/measurement/internal/zzkq
    //   139: astore_3
    //   140: aload_3
    //   141: getfield 113	com/google/android/gms/measurement/internal/zzkq:zze	Ljava/lang/String;
    //   144: astore 5
    //   146: aload 5
    //   148: ifnull +16 -> 164
    //   151: aload_2
    //   152: aload_3
    //   153: getfield 114	com/google/android/gms/measurement/internal/zzkq:zzb	Ljava/lang/String;
    //   156: aload 5
    //   158: invokevirtual 118	android/os/Bundle:putString	(Ljava/lang/String;Ljava/lang/String;)V
    //   161: goto -42 -> 119
    //   164: aload_3
    //   165: getfield 121	com/google/android/gms/measurement/internal/zzkq:zzd	Ljava/lang/Long;
    //   168: astore 5
    //   170: aload 5
    //   172: ifnull +19 -> 191
    //   175: aload_2
    //   176: aload_3
    //   177: getfield 114	com/google/android/gms/measurement/internal/zzkq:zzb	Ljava/lang/String;
    //   180: aload 5
    //   182: invokevirtual 127	java/lang/Long:longValue	()J
    //   185: invokevirtual 131	android/os/Bundle:putLong	(Ljava/lang/String;J)V
    //   188: goto -69 -> 119
    //   191: aload_3
    //   192: getfield 135	com/google/android/gms/measurement/internal/zzkq:zzg	Ljava/lang/Double;
    //   195: astore 5
    //   197: aload 5
    //   199: ifnull -80 -> 119
    //   202: aload_2
    //   203: aload_3
    //   204: getfield 114	com/google/android/gms/measurement/internal/zzkq:zzb	Ljava/lang/String;
    //   207: aload 5
    //   209: invokevirtual 141	java/lang/Double:doubleValue	()D
    //   212: invokevirtual 145	android/os/Bundle:putDouble	(Ljava/lang/String;D)V
    //   215: goto -96 -> 119
    //   218: aload_2
    //   219: astore_1
    //   220: aload_0
    //   221: getfield 21	com/google/android/gms/measurement/internal/zzil:zzf	Lcom/google/android/gms/measurement/internal/zzjk;
    //   224: invokestatic 149	com/google/android/gms/measurement/internal/zzjk:zzN	(Lcom/google/android/gms/measurement/internal/zzjk;)V
    //   227: aload_0
    //   228: getfield 21	com/google/android/gms/measurement/internal/zzil:zzf	Lcom/google/android/gms/measurement/internal/zzjk;
    //   231: getfield 53	com/google/android/gms/measurement/internal/zzgn:zzs	Lcom/google/android/gms/measurement/internal/zzfu;
    //   234: invokevirtual 75	com/google/android/gms/measurement/internal/zzfu:zzl	()Lcom/google/android/gms/measurement/internal/zzku;
    //   237: aload_0
    //   238: getfield 31	com/google/android/gms/measurement/internal/zzil:zze	Lcom/google/android/gms/internal/measurement/zzcf;
    //   241: aload_2
    //   242: invokevirtual 81	com/google/android/gms/measurement/internal/zzku:zzai	(Lcom/google/android/gms/internal/measurement/zzcf;Landroid/os/Bundle;)V
    //   245: return
    //   246: astore_3
    //   247: goto +14 -> 261
    //   250: astore_2
    //   251: aload_1
    //   252: astore_3
    //   253: aload_2
    //   254: astore_1
    //   255: goto +55 -> 310
    //   258: astore_3
    //   259: aload_1
    //   260: astore_2
    //   261: aload_2
    //   262: astore_1
    //   263: aload_0
    //   264: getfield 21	com/google/android/gms/measurement/internal/zzil:zzf	Lcom/google/android/gms/measurement/internal/zzjk;
    //   267: getfield 53	com/google/android/gms/measurement/internal/zzgn:zzs	Lcom/google/android/gms/measurement/internal/zzfu;
    //   270: invokevirtual 59	com/google/android/gms/measurement/internal/zzfu:zzau	()Lcom/google/android/gms/measurement/internal/zzem;
    //   273: invokevirtual 64	com/google/android/gms/measurement/internal/zzem:zzb	()Lcom/google/android/gms/measurement/internal/zzek;
    //   276: ldc -105
    //   278: aload_0
    //   279: getfield 23	com/google/android/gms/measurement/internal/zzil:zza	Ljava/lang/String;
    //   282: aload_3
    //   283: invokevirtual 71	com/google/android/gms/measurement/internal/zzek:zzc	(Ljava/lang/String;Ljava/lang/Object;Ljava/lang/Object;)V
    //   286: aload_0
    //   287: getfield 21	com/google/android/gms/measurement/internal/zzil:zzf	Lcom/google/android/gms/measurement/internal/zzjk;
    //   290: getfield 53	com/google/android/gms/measurement/internal/zzgn:zzs	Lcom/google/android/gms/measurement/internal/zzfu;
    //   293: invokevirtual 75	com/google/android/gms/measurement/internal/zzfu:zzl	()Lcom/google/android/gms/measurement/internal/zzku;
    //   296: aload_0
    //   297: getfield 31	com/google/android/gms/measurement/internal/zzil:zze	Lcom/google/android/gms/internal/measurement/zzcf;
    //   300: aload_2
    //   301: invokevirtual 81	com/google/android/gms/measurement/internal/zzku:zzai	(Lcom/google/android/gms/internal/measurement/zzcf;Landroid/os/Bundle;)V
    //   304: return
    //   305: astore_2
    //   306: aload_1
    //   307: astore_3
    //   308: aload_2
    //   309: astore_1
    //   310: aload_0
    //   311: getfield 21	com/google/android/gms/measurement/internal/zzil:zzf	Lcom/google/android/gms/measurement/internal/zzjk;
    //   314: getfield 53	com/google/android/gms/measurement/internal/zzgn:zzs	Lcom/google/android/gms/measurement/internal/zzfu;
    //   317: invokevirtual 75	com/google/android/gms/measurement/internal/zzfu:zzl	()Lcom/google/android/gms/measurement/internal/zzku;
    //   320: aload_0
    //   321: getfield 31	com/google/android/gms/measurement/internal/zzil:zze	Lcom/google/android/gms/internal/measurement/zzcf;
    //   324: aload_3
    //   325: invokevirtual 81	com/google/android/gms/measurement/internal/zzku:zzai	(Lcom/google/android/gms/internal/measurement/zzcf;Landroid/os/Bundle;)V
    //   328: aload_1
    //   329: athrow
    // Local variable table:
    //   start	length	slot	name	signature
    //   0	330	0	this	zzil
    //   7	322	1	localObject1	Object
    //   15	227	2	localObject2	Object
    //   250	4	2	localObject3	Object
    //   260	41	2	localObject4	Object
    //   305	4	2	localObject5	Object
    //   95	109	3	localObject6	Object
    //   246	1	3	localRemoteException1	android.os.RemoteException
    //   252	1	3	localObject7	Object
    //   258	25	3	localRemoteException2	android.os.RemoteException
    //   307	18	3	localObject8	Object
    //   117	13	4	localIterator	java.util.Iterator
    //   144	64	5	localObject9	Object
    // Exception table:
    //   from	to	target	type
    //   220	227	246	android/os/RemoteException
    //   8	16	250	finally
    //   20	46	250	finally
    //   65	104	250	finally
    //   111	119	250	finally
    //   119	146	250	finally
    //   151	161	250	finally
    //   164	170	250	finally
    //   175	188	250	finally
    //   191	197	250	finally
    //   202	215	250	finally
    //   8	16	258	android/os/RemoteException
    //   20	46	258	android/os/RemoteException
    //   65	104	258	android/os/RemoteException
    //   111	119	258	android/os/RemoteException
    //   119	146	258	android/os/RemoteException
    //   151	161	258	android/os/RemoteException
    //   164	170	258	android/os/RemoteException
    //   175	188	258	android/os/RemoteException
    //   191	197	258	android/os/RemoteException
    //   202	215	258	android/os/RemoteException
    //   220	227	305	finally
    //   263	286	305	finally
  }
}


/* Location:              C:\Users\User\Desktop\decompile\jdgui110\Tapojar.jar!\com\google\android\gms\measurement\internal\zzil.class
 * Java compiler version: 6 (50.0)
 * JD-Core Version:       0.7.1
 */