package com.google.android.gms.measurement.internal;

import java.util.concurrent.atomic.AtomicReference;

final class zzip
  implements Runnable
{
  zzip(zzjk paramzzjk, AtomicReference paramAtomicReference, zzp paramzzp) {}
  
  /* Error */
  public final void run()
  {
    // Byte code:
    //   0: aload_0
    //   1: getfield 18	com/google/android/gms/measurement/internal/zzip:zza	Ljava/util/concurrent/atomic/AtomicReference;
    //   4: astore_1
    //   5: aload_1
    //   6: monitorenter
    //   7: aload_0
    //   8: getfield 16	com/google/android/gms/measurement/internal/zzip:zzc	Lcom/google/android/gms/measurement/internal/zzjk;
    //   11: getfield 33	com/google/android/gms/measurement/internal/zzgn:zzs	Lcom/google/android/gms/measurement/internal/zzfu;
    //   14: invokevirtual 39	com/google/android/gms/measurement/internal/zzfu:zzd	()Lcom/google/android/gms/measurement/internal/zzfb;
    //   17: invokevirtual 45	com/google/android/gms/measurement/internal/zzfb:zzi	()Lcom/google/android/gms/measurement/internal/zzaf;
    //   20: invokevirtual 51	com/google/android/gms/measurement/internal/zzaf:zzh	()Z
    //   23: ifne +70 -> 93
    //   26: aload_0
    //   27: getfield 16	com/google/android/gms/measurement/internal/zzip:zzc	Lcom/google/android/gms/measurement/internal/zzjk;
    //   30: getfield 33	com/google/android/gms/measurement/internal/zzgn:zzs	Lcom/google/android/gms/measurement/internal/zzfu;
    //   33: invokevirtual 55	com/google/android/gms/measurement/internal/zzfu:zzau	()Lcom/google/android/gms/measurement/internal/zzem;
    //   36: invokevirtual 60	com/google/android/gms/measurement/internal/zzem:zzh	()Lcom/google/android/gms/measurement/internal/zzek;
    //   39: ldc 62
    //   41: invokevirtual 67	com/google/android/gms/measurement/internal/zzek:zza	(Ljava/lang/String;)V
    //   44: aload_0
    //   45: getfield 16	com/google/android/gms/measurement/internal/zzip:zzc	Lcom/google/android/gms/measurement/internal/zzjk;
    //   48: getfield 33	com/google/android/gms/measurement/internal/zzgn:zzs	Lcom/google/android/gms/measurement/internal/zzfu;
    //   51: invokevirtual 71	com/google/android/gms/measurement/internal/zzfu:zzk	()Lcom/google/android/gms/measurement/internal/zzhw;
    //   54: aconst_null
    //   55: invokevirtual 76	com/google/android/gms/measurement/internal/zzhw:zzE	(Ljava/lang/String;)V
    //   58: aload_0
    //   59: getfield 16	com/google/android/gms/measurement/internal/zzip:zzc	Lcom/google/android/gms/measurement/internal/zzjk;
    //   62: getfield 33	com/google/android/gms/measurement/internal/zzgn:zzs	Lcom/google/android/gms/measurement/internal/zzfu;
    //   65: invokevirtual 39	com/google/android/gms/measurement/internal/zzfu:zzd	()Lcom/google/android/gms/measurement/internal/zzfb;
    //   68: getfield 80	com/google/android/gms/measurement/internal/zzfb:zze	Lcom/google/android/gms/measurement/internal/zzfa;
    //   71: aconst_null
    //   72: invokevirtual 84	com/google/android/gms/measurement/internal/zzfa:zzb	(Ljava/lang/String;)V
    //   75: aload_0
    //   76: getfield 18	com/google/android/gms/measurement/internal/zzip:zza	Ljava/util/concurrent/atomic/AtomicReference;
    //   79: aconst_null
    //   80: invokevirtual 90	java/util/concurrent/atomic/AtomicReference:set	(Ljava/lang/Object;)V
    //   83: aload_0
    //   84: getfield 18	com/google/android/gms/measurement/internal/zzip:zza	Ljava/util/concurrent/atomic/AtomicReference;
    //   87: invokevirtual 93	java/lang/Object:notify	()V
    //   90: aload_1
    //   91: monitorexit
    //   92: return
    //   93: aload_0
    //   94: getfield 16	com/google/android/gms/measurement/internal/zzip:zzc	Lcom/google/android/gms/measurement/internal/zzjk;
    //   97: invokestatic 99	com/google/android/gms/measurement/internal/zzjk:zzM	(Lcom/google/android/gms/measurement/internal/zzjk;)Lcom/google/android/gms/measurement/internal/zzed;
    //   100: astore_2
    //   101: aload_2
    //   102: ifnonnull +31 -> 133
    //   105: aload_0
    //   106: getfield 16	com/google/android/gms/measurement/internal/zzip:zzc	Lcom/google/android/gms/measurement/internal/zzjk;
    //   109: getfield 33	com/google/android/gms/measurement/internal/zzgn:zzs	Lcom/google/android/gms/measurement/internal/zzfu;
    //   112: invokevirtual 55	com/google/android/gms/measurement/internal/zzfu:zzau	()Lcom/google/android/gms/measurement/internal/zzem;
    //   115: invokevirtual 101	com/google/android/gms/measurement/internal/zzem:zzb	()Lcom/google/android/gms/measurement/internal/zzek;
    //   118: ldc 103
    //   120: invokevirtual 67	com/google/android/gms/measurement/internal/zzek:zza	(Ljava/lang/String;)V
    //   123: aload_0
    //   124: getfield 18	com/google/android/gms/measurement/internal/zzip:zza	Ljava/util/concurrent/atomic/AtomicReference;
    //   127: invokevirtual 93	java/lang/Object:notify	()V
    //   130: aload_1
    //   131: monitorexit
    //   132: return
    //   133: aload_0
    //   134: getfield 20	com/google/android/gms/measurement/internal/zzip:zzb	Lcom/google/android/gms/measurement/internal/zzp;
    //   137: invokestatic 109	com/google/android/gms/common/internal/Preconditions:checkNotNull	(Ljava/lang/Object;)Ljava/lang/Object;
    //   140: pop
    //   141: aload_0
    //   142: getfield 18	com/google/android/gms/measurement/internal/zzip:zza	Ljava/util/concurrent/atomic/AtomicReference;
    //   145: aload_2
    //   146: aload_0
    //   147: getfield 20	com/google/android/gms/measurement/internal/zzip:zzb	Lcom/google/android/gms/measurement/internal/zzp;
    //   150: invokeinterface 115 2 0
    //   155: invokevirtual 90	java/util/concurrent/atomic/AtomicReference:set	(Ljava/lang/Object;)V
    //   158: aload_0
    //   159: getfield 18	com/google/android/gms/measurement/internal/zzip:zza	Ljava/util/concurrent/atomic/AtomicReference;
    //   162: invokevirtual 119	java/util/concurrent/atomic/AtomicReference:get	()Ljava/lang/Object;
    //   165: checkcast 121	java/lang/String
    //   168: astore_2
    //   169: aload_2
    //   170: ifnull +34 -> 204
    //   173: aload_0
    //   174: getfield 16	com/google/android/gms/measurement/internal/zzip:zzc	Lcom/google/android/gms/measurement/internal/zzjk;
    //   177: getfield 33	com/google/android/gms/measurement/internal/zzgn:zzs	Lcom/google/android/gms/measurement/internal/zzfu;
    //   180: invokevirtual 71	com/google/android/gms/measurement/internal/zzfu:zzk	()Lcom/google/android/gms/measurement/internal/zzhw;
    //   183: aload_2
    //   184: invokevirtual 76	com/google/android/gms/measurement/internal/zzhw:zzE	(Ljava/lang/String;)V
    //   187: aload_0
    //   188: getfield 16	com/google/android/gms/measurement/internal/zzip:zzc	Lcom/google/android/gms/measurement/internal/zzjk;
    //   191: getfield 33	com/google/android/gms/measurement/internal/zzgn:zzs	Lcom/google/android/gms/measurement/internal/zzfu;
    //   194: invokevirtual 39	com/google/android/gms/measurement/internal/zzfu:zzd	()Lcom/google/android/gms/measurement/internal/zzfb;
    //   197: getfield 80	com/google/android/gms/measurement/internal/zzfb:zze	Lcom/google/android/gms/measurement/internal/zzfa;
    //   200: aload_2
    //   201: invokevirtual 84	com/google/android/gms/measurement/internal/zzfa:zzb	(Ljava/lang/String;)V
    //   204: aload_0
    //   205: getfield 16	com/google/android/gms/measurement/internal/zzip:zzc	Lcom/google/android/gms/measurement/internal/zzjk;
    //   208: invokestatic 125	com/google/android/gms/measurement/internal/zzjk:zzN	(Lcom/google/android/gms/measurement/internal/zzjk;)V
    //   211: aload_0
    //   212: getfield 18	com/google/android/gms/measurement/internal/zzip:zza	Ljava/util/concurrent/atomic/AtomicReference;
    //   215: astore_2
    //   216: aload_2
    //   217: invokevirtual 93	java/lang/Object:notify	()V
    //   220: goto +35 -> 255
    //   223: astore_2
    //   224: goto +34 -> 258
    //   227: astore_2
    //   228: aload_0
    //   229: getfield 16	com/google/android/gms/measurement/internal/zzip:zzc	Lcom/google/android/gms/measurement/internal/zzjk;
    //   232: getfield 33	com/google/android/gms/measurement/internal/zzgn:zzs	Lcom/google/android/gms/measurement/internal/zzfu;
    //   235: invokevirtual 55	com/google/android/gms/measurement/internal/zzfu:zzau	()Lcom/google/android/gms/measurement/internal/zzem;
    //   238: invokevirtual 101	com/google/android/gms/measurement/internal/zzem:zzb	()Lcom/google/android/gms/measurement/internal/zzek;
    //   241: ldc 103
    //   243: aload_2
    //   244: invokevirtual 128	com/google/android/gms/measurement/internal/zzek:zzb	(Ljava/lang/String;Ljava/lang/Object;)V
    //   247: aload_0
    //   248: getfield 18	com/google/android/gms/measurement/internal/zzip:zza	Ljava/util/concurrent/atomic/AtomicReference;
    //   251: astore_2
    //   252: goto -36 -> 216
    //   255: aload_1
    //   256: monitorexit
    //   257: return
    //   258: aload_0
    //   259: getfield 18	com/google/android/gms/measurement/internal/zzip:zza	Ljava/util/concurrent/atomic/AtomicReference;
    //   262: invokevirtual 93	java/lang/Object:notify	()V
    //   265: aload_2
    //   266: athrow
    //   267: astore_2
    //   268: aload_1
    //   269: monitorexit
    //   270: aload_2
    //   271: athrow
    // Local variable table:
    //   start	length	slot	name	signature
    //   0	272	0	this	zzip
    //   100	117	2	localObject1	Object
    //   223	1	2	localObject2	Object
    //   227	17	2	localRemoteException	android.os.RemoteException
    //   251	15	2	localAtomicReference2	AtomicReference
    //   267	4	2	localObject3	Object
    // Exception table:
    //   from	to	target	type
    //   7	83	223	finally
    //   93	101	223	finally
    //   105	123	223	finally
    //   133	169	223	finally
    //   173	204	223	finally
    //   204	211	223	finally
    //   228	247	223	finally
    //   7	83	227	android/os/RemoteException
    //   93	101	227	android/os/RemoteException
    //   105	123	227	android/os/RemoteException
    //   133	169	227	android/os/RemoteException
    //   173	204	227	android/os/RemoteException
    //   204	211	227	android/os/RemoteException
    //   83	92	267	finally
    //   123	132	267	finally
    //   211	216	267	finally
    //   216	220	267	finally
    //   247	252	267	finally
    //   255	257	267	finally
    //   258	267	267	finally
    //   268	270	267	finally
  }
}


/* Location:              C:\Users\User\Desktop\decompile\jdgui110\Tapojar.jar!\com\google\android\gms\measurement\internal\zzip.class
 * Java compiler version: 6 (50.0)
 * JD-Core Version:       0.7.1
 */