package com.google.android.gms.measurement.internal;

import com.google.android.gms.internal.measurement.zzcf;

final class zziv
  implements Runnable
{
  zziv(zzjk paramzzjk, zzas paramzzas, String paramString, zzcf paramzzcf) {}
  
  /* Error */
  public final void run()
  {
    // Byte code:
    //   0: aconst_null
    //   1: astore_1
    //   2: aconst_null
    //   3: astore_2
    //   4: aconst_null
    //   5: astore_3
    //   6: aload_1
    //   7: astore 4
    //   9: aload_2
    //   10: astore 5
    //   12: aload_0
    //   13: getfield 18	com/google/android/gms/measurement/internal/zziv:zzd	Lcom/google/android/gms/measurement/internal/zzjk;
    //   16: invokestatic 37	com/google/android/gms/measurement/internal/zzjk:zzM	(Lcom/google/android/gms/measurement/internal/zzjk;)Lcom/google/android/gms/measurement/internal/zzed;
    //   19: astore 6
    //   21: aload 6
    //   23: ifnonnull +54 -> 77
    //   26: aload_1
    //   27: astore 4
    //   29: aload_2
    //   30: astore 5
    //   32: aload_0
    //   33: getfield 18	com/google/android/gms/measurement/internal/zziv:zzd	Lcom/google/android/gms/measurement/internal/zzjk;
    //   36: getfield 43	com/google/android/gms/measurement/internal/zzgn:zzs	Lcom/google/android/gms/measurement/internal/zzfu;
    //   39: invokevirtual 49	com/google/android/gms/measurement/internal/zzfu:zzau	()Lcom/google/android/gms/measurement/internal/zzem;
    //   42: invokevirtual 54	com/google/android/gms/measurement/internal/zzem:zzb	()Lcom/google/android/gms/measurement/internal/zzek;
    //   45: ldc 56
    //   47: invokevirtual 61	com/google/android/gms/measurement/internal/zzek:zza	(Ljava/lang/String;)V
    //   50: aload_0
    //   51: getfield 18	com/google/android/gms/measurement/internal/zziv:zzd	Lcom/google/android/gms/measurement/internal/zzjk;
    //   54: getfield 43	com/google/android/gms/measurement/internal/zzgn:zzs	Lcom/google/android/gms/measurement/internal/zzfu;
    //   57: astore 4
    //   59: aload_3
    //   60: astore 5
    //   62: aload 4
    //   64: invokevirtual 65	com/google/android/gms/measurement/internal/zzfu:zzl	()Lcom/google/android/gms/measurement/internal/zzku;
    //   67: aload_0
    //   68: getfield 24	com/google/android/gms/measurement/internal/zziv:zzc	Lcom/google/android/gms/internal/measurement/zzcf;
    //   71: aload 5
    //   73: invokevirtual 71	com/google/android/gms/measurement/internal/zzku:zzag	(Lcom/google/android/gms/internal/measurement/zzcf;[B)V
    //   76: return
    //   77: aload_1
    //   78: astore 4
    //   80: aload_2
    //   81: astore 5
    //   83: aload 6
    //   85: aload_0
    //   86: getfield 20	com/google/android/gms/measurement/internal/zziv:zza	Lcom/google/android/gms/measurement/internal/zzas;
    //   89: aload_0
    //   90: getfield 22	com/google/android/gms/measurement/internal/zziv:zzb	Ljava/lang/String;
    //   93: invokeinterface 77 3 0
    //   98: astore_3
    //   99: aload_3
    //   100: astore 4
    //   102: aload_3
    //   103: astore 5
    //   105: aload_0
    //   106: getfield 18	com/google/android/gms/measurement/internal/zziv:zzd	Lcom/google/android/gms/measurement/internal/zzjk;
    //   109: invokestatic 81	com/google/android/gms/measurement/internal/zzjk:zzN	(Lcom/google/android/gms/measurement/internal/zzjk;)V
    //   112: aload_0
    //   113: getfield 18	com/google/android/gms/measurement/internal/zziv:zzd	Lcom/google/android/gms/measurement/internal/zzjk;
    //   116: getfield 43	com/google/android/gms/measurement/internal/zzgn:zzs	Lcom/google/android/gms/measurement/internal/zzfu;
    //   119: astore 4
    //   121: aload_3
    //   122: astore 5
    //   124: goto -62 -> 62
    //   127: astore 5
    //   129: goto +39 -> 168
    //   132: astore_3
    //   133: aload 5
    //   135: astore 4
    //   137: aload_0
    //   138: getfield 18	com/google/android/gms/measurement/internal/zziv:zzd	Lcom/google/android/gms/measurement/internal/zzjk;
    //   141: getfield 43	com/google/android/gms/measurement/internal/zzgn:zzs	Lcom/google/android/gms/measurement/internal/zzfu;
    //   144: invokevirtual 49	com/google/android/gms/measurement/internal/zzfu:zzau	()Lcom/google/android/gms/measurement/internal/zzem;
    //   147: invokevirtual 54	com/google/android/gms/measurement/internal/zzem:zzb	()Lcom/google/android/gms/measurement/internal/zzek;
    //   150: ldc 83
    //   152: aload_3
    //   153: invokevirtual 86	com/google/android/gms/measurement/internal/zzek:zzb	(Ljava/lang/String;Ljava/lang/Object;)V
    //   156: aload_0
    //   157: getfield 18	com/google/android/gms/measurement/internal/zziv:zzd	Lcom/google/android/gms/measurement/internal/zzjk;
    //   160: getfield 43	com/google/android/gms/measurement/internal/zzgn:zzs	Lcom/google/android/gms/measurement/internal/zzfu;
    //   163: astore 4
    //   165: goto -103 -> 62
    //   168: aload_0
    //   169: getfield 18	com/google/android/gms/measurement/internal/zziv:zzd	Lcom/google/android/gms/measurement/internal/zzjk;
    //   172: getfield 43	com/google/android/gms/measurement/internal/zzgn:zzs	Lcom/google/android/gms/measurement/internal/zzfu;
    //   175: invokevirtual 65	com/google/android/gms/measurement/internal/zzfu:zzl	()Lcom/google/android/gms/measurement/internal/zzku;
    //   178: aload_0
    //   179: getfield 24	com/google/android/gms/measurement/internal/zziv:zzc	Lcom/google/android/gms/internal/measurement/zzcf;
    //   182: aload 4
    //   184: invokevirtual 71	com/google/android/gms/measurement/internal/zzku:zzag	(Lcom/google/android/gms/internal/measurement/zzcf;[B)V
    //   187: aload 5
    //   189: athrow
    // Local variable table:
    //   start	length	slot	name	signature
    //   0	190	0	this	zziv
    //   1	77	1	localObject1	Object
    //   3	78	2	localObject2	Object
    //   5	117	3	arrayOfByte	byte[]
    //   132	21	3	localRemoteException	android.os.RemoteException
    //   7	176	4	localObject3	Object
    //   10	113	5	localObject4	Object
    //   127	61	5	localObject5	Object
    //   19	65	6	localzzed	zzed
    // Exception table:
    //   from	to	target	type
    //   12	21	127	finally
    //   32	50	127	finally
    //   83	99	127	finally
    //   105	112	127	finally
    //   137	156	127	finally
    //   12	21	132	android/os/RemoteException
    //   32	50	132	android/os/RemoteException
    //   83	99	132	android/os/RemoteException
    //   105	112	132	android/os/RemoteException
  }
}


/* Location:              C:\Users\User\Desktop\decompile\jdgui110\Tapojar.jar!\com\google\android\gms\measurement\internal\zziv.class
 * Java compiler version: 6 (50.0)
 * JD-Core Version:       0.7.1
 */