package com.google.android.gms.measurement.internal;

import com.google.android.gms.internal.measurement.zzcf;

final class zzjc
  implements Runnable
{
  zzjc(zzjk paramzzjk, String paramString1, String paramString2, zzp paramzzp, zzcf paramzzcf) {}
  
  /* Error */
  public final void run()
  {
    // Byte code:
    //   0: new 36	java/util/ArrayList
    //   3: dup
    //   4: invokespecial 37	java/util/ArrayList:<init>	()V
    //   7: astore_1
    //   8: aload_1
    //   9: astore_2
    //   10: aload_1
    //   11: astore_3
    //   12: aload_0
    //   13: getfield 19	com/google/android/gms/measurement/internal/zzjc:zze	Lcom/google/android/gms/measurement/internal/zzjk;
    //   16: invokestatic 43	com/google/android/gms/measurement/internal/zzjk:zzM	(Lcom/google/android/gms/measurement/internal/zzjk;)Lcom/google/android/gms/measurement/internal/zzed;
    //   19: astore 4
    //   21: aload 4
    //   23: ifnonnull +56 -> 79
    //   26: aload_1
    //   27: astore_2
    //   28: aload_1
    //   29: astore_3
    //   30: aload_0
    //   31: getfield 19	com/google/android/gms/measurement/internal/zzjc:zze	Lcom/google/android/gms/measurement/internal/zzjk;
    //   34: getfield 49	com/google/android/gms/measurement/internal/zzgn:zzs	Lcom/google/android/gms/measurement/internal/zzfu;
    //   37: invokevirtual 55	com/google/android/gms/measurement/internal/zzfu:zzau	()Lcom/google/android/gms/measurement/internal/zzem;
    //   40: invokevirtual 60	com/google/android/gms/measurement/internal/zzem:zzb	()Lcom/google/android/gms/measurement/internal/zzek;
    //   43: ldc 62
    //   45: aload_0
    //   46: getfield 21	com/google/android/gms/measurement/internal/zzjc:zza	Ljava/lang/String;
    //   49: aload_0
    //   50: getfield 23	com/google/android/gms/measurement/internal/zzjc:zzb	Ljava/lang/String;
    //   53: invokevirtual 67	com/google/android/gms/measurement/internal/zzek:zzc	(Ljava/lang/String;Ljava/lang/Object;Ljava/lang/Object;)V
    //   56: aload_0
    //   57: getfield 19	com/google/android/gms/measurement/internal/zzjc:zze	Lcom/google/android/gms/measurement/internal/zzjk;
    //   60: getfield 49	com/google/android/gms/measurement/internal/zzgn:zzs	Lcom/google/android/gms/measurement/internal/zzfu;
    //   63: astore_2
    //   64: aload_1
    //   65: astore_3
    //   66: aload_2
    //   67: invokevirtual 71	com/google/android/gms/measurement/internal/zzfu:zzl	()Lcom/google/android/gms/measurement/internal/zzku;
    //   70: aload_0
    //   71: getfield 27	com/google/android/gms/measurement/internal/zzjc:zzd	Lcom/google/android/gms/internal/measurement/zzcf;
    //   74: aload_3
    //   75: invokevirtual 77	com/google/android/gms/measurement/internal/zzku:zzaj	(Lcom/google/android/gms/internal/measurement/zzcf;Ljava/util/ArrayList;)V
    //   78: return
    //   79: aload_1
    //   80: astore_2
    //   81: aload_1
    //   82: astore_3
    //   83: aload_0
    //   84: getfield 25	com/google/android/gms/measurement/internal/zzjc:zzc	Lcom/google/android/gms/measurement/internal/zzp;
    //   87: invokestatic 83	com/google/android/gms/common/internal/Preconditions:checkNotNull	(Ljava/lang/Object;)Ljava/lang/Object;
    //   90: pop
    //   91: aload_1
    //   92: astore_2
    //   93: aload_1
    //   94: astore_3
    //   95: aload 4
    //   97: aload_0
    //   98: getfield 21	com/google/android/gms/measurement/internal/zzjc:zza	Ljava/lang/String;
    //   101: aload_0
    //   102: getfield 23	com/google/android/gms/measurement/internal/zzjc:zzb	Ljava/lang/String;
    //   105: aload_0
    //   106: getfield 25	com/google/android/gms/measurement/internal/zzjc:zzc	Lcom/google/android/gms/measurement/internal/zzp;
    //   109: invokeinterface 89 4 0
    //   114: invokestatic 93	com/google/android/gms/measurement/internal/zzku:zzak	(Ljava/util/List;)Ljava/util/ArrayList;
    //   117: astore_1
    //   118: aload_1
    //   119: astore_2
    //   120: aload_1
    //   121: astore_3
    //   122: aload_0
    //   123: getfield 19	com/google/android/gms/measurement/internal/zzjc:zze	Lcom/google/android/gms/measurement/internal/zzjk;
    //   126: invokestatic 97	com/google/android/gms/measurement/internal/zzjk:zzN	(Lcom/google/android/gms/measurement/internal/zzjk;)V
    //   129: aload_0
    //   130: getfield 19	com/google/android/gms/measurement/internal/zzjc:zze	Lcom/google/android/gms/measurement/internal/zzjk;
    //   133: getfield 49	com/google/android/gms/measurement/internal/zzgn:zzs	Lcom/google/android/gms/measurement/internal/zzfu;
    //   136: astore_2
    //   137: aload_1
    //   138: astore_3
    //   139: goto -73 -> 66
    //   142: astore_3
    //   143: goto +44 -> 187
    //   146: astore_1
    //   147: aload_3
    //   148: astore_2
    //   149: aload_0
    //   150: getfield 19	com/google/android/gms/measurement/internal/zzjc:zze	Lcom/google/android/gms/measurement/internal/zzjk;
    //   153: getfield 49	com/google/android/gms/measurement/internal/zzgn:zzs	Lcom/google/android/gms/measurement/internal/zzfu;
    //   156: invokevirtual 55	com/google/android/gms/measurement/internal/zzfu:zzau	()Lcom/google/android/gms/measurement/internal/zzem;
    //   159: invokevirtual 60	com/google/android/gms/measurement/internal/zzem:zzb	()Lcom/google/android/gms/measurement/internal/zzek;
    //   162: ldc 99
    //   164: aload_0
    //   165: getfield 21	com/google/android/gms/measurement/internal/zzjc:zza	Ljava/lang/String;
    //   168: aload_0
    //   169: getfield 23	com/google/android/gms/measurement/internal/zzjc:zzb	Ljava/lang/String;
    //   172: aload_1
    //   173: invokevirtual 102	com/google/android/gms/measurement/internal/zzek:zzd	(Ljava/lang/String;Ljava/lang/Object;Ljava/lang/Object;Ljava/lang/Object;)V
    //   176: aload_0
    //   177: getfield 19	com/google/android/gms/measurement/internal/zzjc:zze	Lcom/google/android/gms/measurement/internal/zzjk;
    //   180: getfield 49	com/google/android/gms/measurement/internal/zzgn:zzs	Lcom/google/android/gms/measurement/internal/zzfu;
    //   183: astore_2
    //   184: goto -118 -> 66
    //   187: aload_0
    //   188: getfield 19	com/google/android/gms/measurement/internal/zzjc:zze	Lcom/google/android/gms/measurement/internal/zzjk;
    //   191: getfield 49	com/google/android/gms/measurement/internal/zzgn:zzs	Lcom/google/android/gms/measurement/internal/zzfu;
    //   194: invokevirtual 71	com/google/android/gms/measurement/internal/zzfu:zzl	()Lcom/google/android/gms/measurement/internal/zzku;
    //   197: aload_0
    //   198: getfield 27	com/google/android/gms/measurement/internal/zzjc:zzd	Lcom/google/android/gms/internal/measurement/zzcf;
    //   201: aload_2
    //   202: invokevirtual 77	com/google/android/gms/measurement/internal/zzku:zzaj	(Lcom/google/android/gms/internal/measurement/zzcf;Ljava/util/ArrayList;)V
    //   205: aload_3
    //   206: athrow
    // Local variable table:
    //   start	length	slot	name	signature
    //   0	207	0	this	zzjc
    //   7	131	1	localArrayList1	java.util.ArrayList
    //   146	27	1	localRemoteException	android.os.RemoteException
    //   9	193	2	localObject1	Object
    //   11	128	3	localArrayList2	java.util.ArrayList
    //   142	64	3	localObject2	Object
    //   19	77	4	localzzed	zzed
    // Exception table:
    //   from	to	target	type
    //   12	21	142	finally
    //   30	56	142	finally
    //   83	91	142	finally
    //   95	118	142	finally
    //   122	129	142	finally
    //   149	176	142	finally
    //   12	21	146	android/os/RemoteException
    //   30	56	146	android/os/RemoteException
    //   83	91	146	android/os/RemoteException
    //   95	118	146	android/os/RemoteException
    //   122	129	146	android/os/RemoteException
  }
}


/* Location:              C:\Users\User\Desktop\decompile\jdgui110\Tapojar.jar!\com\google\android\gms\measurement\internal\zzjc.class
 * Java compiler version: 6 (50.0)
 * JD-Core Version:       0.7.1
 */