package com.google.android.gms.measurement.internal;

import com.google.android.gms.internal.measurement.zzfo;

final class zzu
{
  private zzfo zzb;
  private Long zzc;
  private long zzd;
  
  /* Error */
  final zzfo zza(String paramString, zzfo paramzzfo)
  {
    // Byte code:
    //   0: aload_2
    //   1: invokevirtual 30	com/google/android/gms/internal/measurement/zzfo:zzd	()Ljava/lang/String;
    //   4: astore_3
    //   5: aload_2
    //   6: invokevirtual 33	com/google/android/gms/internal/measurement/zzfo:zza	()Ljava/util/List;
    //   9: astore 4
    //   11: aload_0
    //   12: getfield 16	com/google/android/gms/measurement/internal/zzu:zza	Lcom/google/android/gms/measurement/internal/zzy;
    //   15: getfield 39	com/google/android/gms/measurement/internal/zzkd:zzf	Lcom/google/android/gms/measurement/internal/zzkn;
    //   18: invokevirtual 45	com/google/android/gms/measurement/internal/zzkn:zzm	()Lcom/google/android/gms/measurement/internal/zzkp;
    //   21: pop
    //   22: aload_2
    //   23: ldc 47
    //   25: invokestatic 53	com/google/android/gms/measurement/internal/zzkp:zzB	(Lcom/google/android/gms/internal/measurement/zzfo;Ljava/lang/String;)Ljava/lang/Object;
    //   28: checkcast 55	java/lang/Long
    //   31: astore 5
    //   33: aload_3
    //   34: astore 6
    //   36: aload 4
    //   38: astore 7
    //   40: aload 5
    //   42: ifnull +855 -> 897
    //   45: aload_3
    //   46: ldc 57
    //   48: invokevirtual 63	java/lang/String:equals	(Ljava/lang/Object;)Z
    //   51: ifeq +712 -> 763
    //   54: aload 5
    //   56: invokestatic 69	com/google/android/gms/common/internal/Preconditions:checkNotNull	(Ljava/lang/Object;)Ljava/lang/Object;
    //   59: pop
    //   60: aload_0
    //   61: getfield 16	com/google/android/gms/measurement/internal/zzu:zza	Lcom/google/android/gms/measurement/internal/zzy;
    //   64: getfield 39	com/google/android/gms/measurement/internal/zzkd:zzf	Lcom/google/android/gms/measurement/internal/zzkn;
    //   67: invokevirtual 45	com/google/android/gms/measurement/internal/zzkn:zzm	()Lcom/google/android/gms/measurement/internal/zzkp;
    //   70: pop
    //   71: aload_2
    //   72: ldc 71
    //   74: invokestatic 53	com/google/android/gms/measurement/internal/zzkp:zzB	(Lcom/google/android/gms/internal/measurement/zzfo;Ljava/lang/String;)Ljava/lang/Object;
    //   77: checkcast 59	java/lang/String
    //   80: astore 8
    //   82: aload 8
    //   84: invokestatic 77	android/text/TextUtils:isEmpty	(Ljava/lang/CharSequence;)Z
    //   87: ifeq +25 -> 112
    //   90: aload_0
    //   91: getfield 16	com/google/android/gms/measurement/internal/zzu:zza	Lcom/google/android/gms/measurement/internal/zzy;
    //   94: getfield 83	com/google/android/gms/measurement/internal/zzgn:zzs	Lcom/google/android/gms/measurement/internal/zzfu;
    //   97: invokevirtual 89	com/google/android/gms/measurement/internal/zzfu:zzau	()Lcom/google/android/gms/measurement/internal/zzem;
    //   100: invokevirtual 94	com/google/android/gms/measurement/internal/zzem:zzc	()Lcom/google/android/gms/measurement/internal/zzek;
    //   103: ldc 96
    //   105: aload 5
    //   107: invokevirtual 101	com/google/android/gms/measurement/internal/zzek:zzb	(Ljava/lang/String;Ljava/lang/Object;)V
    //   110: aconst_null
    //   111: areturn
    //   112: aload_0
    //   113: getfield 103	com/google/android/gms/measurement/internal/zzu:zzb	Lcom/google/android/gms/internal/measurement/zzfo;
    //   116: ifnull +26 -> 142
    //   119: aload_0
    //   120: getfield 105	com/google/android/gms/measurement/internal/zzu:zzc	Ljava/lang/Long;
    //   123: ifnull +19 -> 142
    //   126: aload 5
    //   128: invokevirtual 109	java/lang/Long:longValue	()J
    //   131: aload_0
    //   132: getfield 105	com/google/android/gms/measurement/internal/zzu:zzc	Ljava/lang/Long;
    //   135: invokevirtual 109	java/lang/Long:longValue	()J
    //   138: lcmp
    //   139: ifeq +327 -> 466
    //   142: aload_0
    //   143: getfield 16	com/google/android/gms/measurement/internal/zzu:zza	Lcom/google/android/gms/measurement/internal/zzy;
    //   146: getfield 39	com/google/android/gms/measurement/internal/zzkd:zzf	Lcom/google/android/gms/measurement/internal/zzkn;
    //   149: invokevirtual 113	com/google/android/gms/measurement/internal/zzkn:zzi	()Lcom/google/android/gms/measurement/internal/zzai;
    //   152: astore 9
    //   154: aload 9
    //   156: invokevirtual 116	com/google/android/gms/measurement/internal/zzgn:zzg	()V
    //   159: aload 9
    //   161: invokevirtual 121	com/google/android/gms/measurement/internal/zzke:zzZ	()V
    //   164: aload 9
    //   166: invokevirtual 127	com/google/android/gms/measurement/internal/zzai:zze	()Landroid/database/sqlite/SQLiteDatabase;
    //   169: ldc -127
    //   171: iconst_2
    //   172: anewarray 59	java/lang/String
    //   175: dup
    //   176: iconst_0
    //   177: aload_1
    //   178: aastore
    //   179: dup
    //   180: iconst_1
    //   181: aload 5
    //   183: invokestatic 133	java/lang/String:valueOf	(Ljava/lang/Object;)Ljava/lang/String;
    //   186: aastore
    //   187: invokevirtual 139	android/database/sqlite/SQLiteDatabase:rawQuery	(Ljava/lang/String;[Ljava/lang/String;)Landroid/database/Cursor;
    //   190: astore 6
    //   192: aload 6
    //   194: astore 7
    //   196: aload 6
    //   198: invokeinterface 145 1 0
    //   203: ifne +36 -> 239
    //   206: aload 6
    //   208: astore 7
    //   210: aload 9
    //   212: getfield 83	com/google/android/gms/measurement/internal/zzgn:zzs	Lcom/google/android/gms/measurement/internal/zzfu;
    //   215: invokevirtual 89	com/google/android/gms/measurement/internal/zzfu:zzau	()Lcom/google/android/gms/measurement/internal/zzem;
    //   218: invokevirtual 148	com/google/android/gms/measurement/internal/zzem:zzk	()Lcom/google/android/gms/measurement/internal/zzek;
    //   221: ldc -106
    //   223: invokevirtual 153	com/google/android/gms/measurement/internal/zzek:zza	(Ljava/lang/String;)V
    //   226: aload 6
    //   228: invokeinterface 156 1 0
    //   233: aconst_null
    //   234: astore 6
    //   236: goto +159 -> 395
    //   239: aload 6
    //   241: astore 7
    //   243: aload 6
    //   245: iconst_0
    //   246: invokeinterface 160 2 0
    //   251: astore_3
    //   252: aload 6
    //   254: astore 7
    //   256: aload 6
    //   258: iconst_1
    //   259: invokeinterface 164 2 0
    //   264: lstore 10
    //   266: aload 6
    //   268: astore 7
    //   270: invokestatic 167	com/google/android/gms/internal/measurement/zzfo:zzk	()Lcom/google/android/gms/internal/measurement/zzfn;
    //   273: aload_3
    //   274: invokestatic 171	com/google/android/gms/measurement/internal/zzkp:zzt	(Lcom/google/android/gms/internal/measurement/zzlh;[B)Lcom/google/android/gms/internal/measurement/zzlh;
    //   277: checkcast 173	com/google/android/gms/internal/measurement/zzfn
    //   280: invokevirtual 179	com/google/android/gms/internal/measurement/zzjz:zzaA	()Lcom/google/android/gms/internal/measurement/zzkd;
    //   283: checkcast 27	com/google/android/gms/internal/measurement/zzfo
    //   286: astore_3
    //   287: aload 6
    //   289: astore 7
    //   291: aload_3
    //   292: lload 10
    //   294: invokestatic 182	java/lang/Long:valueOf	(J)Ljava/lang/Long;
    //   297: invokestatic 188	android/util/Pair:create	(Ljava/lang/Object;Ljava/lang/Object;)Landroid/util/Pair;
    //   300: astore_3
    //   301: aload 6
    //   303: invokeinterface 156 1 0
    //   308: aload_3
    //   309: astore 6
    //   311: goto +84 -> 395
    //   314: astore_3
    //   315: aload 6
    //   317: astore 7
    //   319: aload 9
    //   321: getfield 83	com/google/android/gms/measurement/internal/zzgn:zzs	Lcom/google/android/gms/measurement/internal/zzfu;
    //   324: invokevirtual 89	com/google/android/gms/measurement/internal/zzfu:zzau	()Lcom/google/android/gms/measurement/internal/zzem;
    //   327: invokevirtual 190	com/google/android/gms/measurement/internal/zzem:zzb	()Lcom/google/android/gms/measurement/internal/zzek;
    //   330: ldc -64
    //   332: aload_1
    //   333: invokestatic 196	com/google/android/gms/measurement/internal/zzem:zzl	(Ljava/lang/String;)Ljava/lang/Object;
    //   336: aload 5
    //   338: aload_3
    //   339: invokevirtual 199	com/google/android/gms/measurement/internal/zzek:zzd	(Ljava/lang/String;Ljava/lang/Object;Ljava/lang/Object;Ljava/lang/Object;)V
    //   342: goto +43 -> 385
    //   345: astore_3
    //   346: goto +13 -> 359
    //   349: astore_1
    //   350: aconst_null
    //   351: astore_2
    //   352: goto +399 -> 751
    //   355: astore_3
    //   356: aconst_null
    //   357: astore 6
    //   359: aload 6
    //   361: astore 7
    //   363: aload 9
    //   365: getfield 83	com/google/android/gms/measurement/internal/zzgn:zzs	Lcom/google/android/gms/measurement/internal/zzfu;
    //   368: invokevirtual 89	com/google/android/gms/measurement/internal/zzfu:zzau	()Lcom/google/android/gms/measurement/internal/zzem;
    //   371: invokevirtual 190	com/google/android/gms/measurement/internal/zzem:zzb	()Lcom/google/android/gms/measurement/internal/zzek;
    //   374: ldc -55
    //   376: aload_3
    //   377: invokevirtual 101	com/google/android/gms/measurement/internal/zzek:zzb	(Ljava/lang/String;Ljava/lang/Object;)V
    //   380: aload 6
    //   382: ifnull +10 -> 392
    //   385: aload 6
    //   387: invokeinterface 156 1 0
    //   392: aconst_null
    //   393: astore 6
    //   395: aload 6
    //   397: ifnull +325 -> 722
    //   400: aload 6
    //   402: getfield 205	android/util/Pair:first	Ljava/lang/Object;
    //   405: astore 7
    //   407: aload 7
    //   409: ifnonnull +6 -> 415
    //   412: goto +310 -> 722
    //   415: aload_0
    //   416: aload 7
    //   418: checkcast 27	com/google/android/gms/internal/measurement/zzfo
    //   421: putfield 103	com/google/android/gms/measurement/internal/zzu:zzb	Lcom/google/android/gms/internal/measurement/zzfo;
    //   424: aload_0
    //   425: aload 6
    //   427: getfield 208	android/util/Pair:second	Ljava/lang/Object;
    //   430: checkcast 55	java/lang/Long
    //   433: invokevirtual 109	java/lang/Long:longValue	()J
    //   436: putfield 210	com/google/android/gms/measurement/internal/zzu:zzd	J
    //   439: aload_0
    //   440: getfield 16	com/google/android/gms/measurement/internal/zzu:zza	Lcom/google/android/gms/measurement/internal/zzy;
    //   443: getfield 39	com/google/android/gms/measurement/internal/zzkd:zzf	Lcom/google/android/gms/measurement/internal/zzkn;
    //   446: invokevirtual 45	com/google/android/gms/measurement/internal/zzkn:zzm	()Lcom/google/android/gms/measurement/internal/zzkp;
    //   449: pop
    //   450: aload_0
    //   451: aload_0
    //   452: getfield 103	com/google/android/gms/measurement/internal/zzu:zzb	Lcom/google/android/gms/internal/measurement/zzfo;
    //   455: ldc 47
    //   457: invokestatic 53	com/google/android/gms/measurement/internal/zzkp:zzB	(Lcom/google/android/gms/internal/measurement/zzfo;Ljava/lang/String;)Ljava/lang/Object;
    //   460: checkcast 55	java/lang/Long
    //   463: putfield 105	com/google/android/gms/measurement/internal/zzu:zzc	Ljava/lang/Long;
    //   466: aload_0
    //   467: getfield 210	com/google/android/gms/measurement/internal/zzu:zzd	J
    //   470: lconst_1
    //   471: lsub
    //   472: lstore 10
    //   474: aload_0
    //   475: lload 10
    //   477: putfield 210	com/google/android/gms/measurement/internal/zzu:zzd	J
    //   480: lload 10
    //   482: lconst_0
    //   483: lcmp
    //   484: ifgt +79 -> 563
    //   487: aload_0
    //   488: getfield 16	com/google/android/gms/measurement/internal/zzu:zza	Lcom/google/android/gms/measurement/internal/zzy;
    //   491: getfield 39	com/google/android/gms/measurement/internal/zzkd:zzf	Lcom/google/android/gms/measurement/internal/zzkn;
    //   494: invokevirtual 113	com/google/android/gms/measurement/internal/zzkn:zzi	()Lcom/google/android/gms/measurement/internal/zzai;
    //   497: astore 6
    //   499: aload 6
    //   501: invokevirtual 116	com/google/android/gms/measurement/internal/zzgn:zzg	()V
    //   504: aload 6
    //   506: getfield 83	com/google/android/gms/measurement/internal/zzgn:zzs	Lcom/google/android/gms/measurement/internal/zzfu;
    //   509: invokevirtual 89	com/google/android/gms/measurement/internal/zzfu:zzau	()Lcom/google/android/gms/measurement/internal/zzem;
    //   512: invokevirtual 148	com/google/android/gms/measurement/internal/zzem:zzk	()Lcom/google/android/gms/measurement/internal/zzek;
    //   515: ldc -44
    //   517: aload_1
    //   518: invokevirtual 101	com/google/android/gms/measurement/internal/zzek:zzb	(Ljava/lang/String;Ljava/lang/Object;)V
    //   521: aload 6
    //   523: invokevirtual 127	com/google/android/gms/measurement/internal/zzai:zze	()Landroid/database/sqlite/SQLiteDatabase;
    //   526: ldc -42
    //   528: iconst_1
    //   529: anewarray 59	java/lang/String
    //   532: dup
    //   533: iconst_0
    //   534: aload_1
    //   535: aastore
    //   536: invokevirtual 218	android/database/sqlite/SQLiteDatabase:execSQL	(Ljava/lang/String;[Ljava/lang/Object;)V
    //   539: goto +49 -> 588
    //   542: astore_1
    //   543: aload 6
    //   545: getfield 83	com/google/android/gms/measurement/internal/zzgn:zzs	Lcom/google/android/gms/measurement/internal/zzfu;
    //   548: invokevirtual 89	com/google/android/gms/measurement/internal/zzfu:zzau	()Lcom/google/android/gms/measurement/internal/zzem;
    //   551: invokevirtual 190	com/google/android/gms/measurement/internal/zzem:zzb	()Lcom/google/android/gms/measurement/internal/zzek;
    //   554: ldc -36
    //   556: aload_1
    //   557: invokevirtual 101	com/google/android/gms/measurement/internal/zzek:zzb	(Ljava/lang/String;Ljava/lang/Object;)V
    //   560: goto +28 -> 588
    //   563: aload_0
    //   564: getfield 16	com/google/android/gms/measurement/internal/zzu:zza	Lcom/google/android/gms/measurement/internal/zzy;
    //   567: getfield 39	com/google/android/gms/measurement/internal/zzkd:zzf	Lcom/google/android/gms/measurement/internal/zzkn;
    //   570: invokevirtual 113	com/google/android/gms/measurement/internal/zzkn:zzi	()Lcom/google/android/gms/measurement/internal/zzai;
    //   573: aload_1
    //   574: aload 5
    //   576: aload_0
    //   577: getfield 210	com/google/android/gms/measurement/internal/zzu:zzd	J
    //   580: aload_0
    //   581: getfield 103	com/google/android/gms/measurement/internal/zzu:zzb	Lcom/google/android/gms/internal/measurement/zzfo;
    //   584: invokevirtual 224	com/google/android/gms/measurement/internal/zzai:zzJ	(Ljava/lang/String;Ljava/lang/Long;JLcom/google/android/gms/internal/measurement/zzfo;)Z
    //   587: pop
    //   588: new 226	java/util/ArrayList
    //   591: dup
    //   592: invokespecial 227	java/util/ArrayList:<init>	()V
    //   595: astore_1
    //   596: aload_0
    //   597: getfield 103	com/google/android/gms/measurement/internal/zzu:zzb	Lcom/google/android/gms/internal/measurement/zzfo;
    //   600: invokevirtual 33	com/google/android/gms/internal/measurement/zzfo:zza	()Ljava/util/List;
    //   603: invokeinterface 233 1 0
    //   608: astore 7
    //   610: aload 7
    //   612: invokeinterface 238 1 0
    //   617: ifeq +50 -> 667
    //   620: aload 7
    //   622: invokeinterface 242 1 0
    //   627: checkcast 244	com/google/android/gms/internal/measurement/zzfs
    //   630: astore 6
    //   632: aload_0
    //   633: getfield 16	com/google/android/gms/measurement/internal/zzu:zza	Lcom/google/android/gms/measurement/internal/zzy;
    //   636: getfield 39	com/google/android/gms/measurement/internal/zzkd:zzf	Lcom/google/android/gms/measurement/internal/zzkn;
    //   639: invokevirtual 45	com/google/android/gms/measurement/internal/zzkn:zzm	()Lcom/google/android/gms/measurement/internal/zzkp;
    //   642: pop
    //   643: aload_2
    //   644: aload 6
    //   646: invokevirtual 246	com/google/android/gms/internal/measurement/zzfs:zzb	()Ljava/lang/String;
    //   649: invokestatic 250	com/google/android/gms/measurement/internal/zzkp:zzA	(Lcom/google/android/gms/internal/measurement/zzfo;Ljava/lang/String;)Lcom/google/android/gms/internal/measurement/zzfs;
    //   652: ifnonnull -42 -> 610
    //   655: aload_1
    //   656: aload 6
    //   658: invokeinterface 253 2 0
    //   663: pop
    //   664: goto -54 -> 610
    //   667: aload_1
    //   668: invokeinterface 255 1 0
    //   673: ifne +15 -> 688
    //   676: aload_1
    //   677: aload 4
    //   679: invokeinterface 259 2 0
    //   684: pop
    //   685: goto +27 -> 712
    //   688: aload_0
    //   689: getfield 16	com/google/android/gms/measurement/internal/zzu:zza	Lcom/google/android/gms/measurement/internal/zzy;
    //   692: getfield 83	com/google/android/gms/measurement/internal/zzgn:zzs	Lcom/google/android/gms/measurement/internal/zzfu;
    //   695: invokevirtual 89	com/google/android/gms/measurement/internal/zzfu:zzau	()Lcom/google/android/gms/measurement/internal/zzem;
    //   698: invokevirtual 94	com/google/android/gms/measurement/internal/zzem:zzc	()Lcom/google/android/gms/measurement/internal/zzek;
    //   701: ldc_w 261
    //   704: aload 8
    //   706: invokevirtual 101	com/google/android/gms/measurement/internal/zzek:zzb	(Ljava/lang/String;Ljava/lang/Object;)V
    //   709: aload 4
    //   711: astore_1
    //   712: aload 8
    //   714: astore 6
    //   716: aload_1
    //   717: astore 7
    //   719: goto +178 -> 897
    //   722: aload_0
    //   723: getfield 16	com/google/android/gms/measurement/internal/zzu:zza	Lcom/google/android/gms/measurement/internal/zzy;
    //   726: getfield 83	com/google/android/gms/measurement/internal/zzgn:zzs	Lcom/google/android/gms/measurement/internal/zzfu;
    //   729: invokevirtual 89	com/google/android/gms/measurement/internal/zzfu:zzau	()Lcom/google/android/gms/measurement/internal/zzem;
    //   732: invokevirtual 94	com/google/android/gms/measurement/internal/zzem:zzc	()Lcom/google/android/gms/measurement/internal/zzek;
    //   735: ldc_w 263
    //   738: aload 8
    //   740: aload 5
    //   742: invokevirtual 266	com/google/android/gms/measurement/internal/zzek:zzc	(Ljava/lang/String;Ljava/lang/Object;Ljava/lang/Object;)V
    //   745: aconst_null
    //   746: areturn
    //   747: astore_1
    //   748: aload 7
    //   750: astore_2
    //   751: aload_2
    //   752: ifnull +9 -> 761
    //   755: aload_2
    //   756: invokeinterface 156 1 0
    //   761: aload_1
    //   762: athrow
    //   763: aload_0
    //   764: aload 5
    //   766: putfield 105	com/google/android/gms/measurement/internal/zzu:zzc	Ljava/lang/Long;
    //   769: aload_0
    //   770: aload_2
    //   771: putfield 103	com/google/android/gms/measurement/internal/zzu:zzb	Lcom/google/android/gms/internal/measurement/zzfo;
    //   774: aload_0
    //   775: getfield 16	com/google/android/gms/measurement/internal/zzu:zza	Lcom/google/android/gms/measurement/internal/zzy;
    //   778: getfield 39	com/google/android/gms/measurement/internal/zzkd:zzf	Lcom/google/android/gms/measurement/internal/zzkn;
    //   781: invokevirtual 45	com/google/android/gms/measurement/internal/zzkn:zzm	()Lcom/google/android/gms/measurement/internal/zzkp;
    //   784: pop
    //   785: lconst_0
    //   786: invokestatic 182	java/lang/Long:valueOf	(J)Ljava/lang/Long;
    //   789: astore 6
    //   791: aload_2
    //   792: ldc_w 268
    //   795: invokestatic 53	com/google/android/gms/measurement/internal/zzkp:zzB	(Lcom/google/android/gms/internal/measurement/zzfo;Ljava/lang/String;)Ljava/lang/Object;
    //   798: astore 7
    //   800: aload 7
    //   802: ifnull +7 -> 809
    //   805: aload 7
    //   807: astore 6
    //   809: aload 6
    //   811: checkcast 55	java/lang/Long
    //   814: invokevirtual 109	java/lang/Long:longValue	()J
    //   817: lstore 10
    //   819: aload_0
    //   820: lload 10
    //   822: putfield 210	com/google/android/gms/measurement/internal/zzu:zzd	J
    //   825: lload 10
    //   827: lconst_0
    //   828: lcmp
    //   829: ifgt +33 -> 862
    //   832: aload_0
    //   833: getfield 16	com/google/android/gms/measurement/internal/zzu:zza	Lcom/google/android/gms/measurement/internal/zzy;
    //   836: getfield 83	com/google/android/gms/measurement/internal/zzgn:zzs	Lcom/google/android/gms/measurement/internal/zzfu;
    //   839: invokevirtual 89	com/google/android/gms/measurement/internal/zzfu:zzau	()Lcom/google/android/gms/measurement/internal/zzem;
    //   842: invokevirtual 94	com/google/android/gms/measurement/internal/zzem:zzc	()Lcom/google/android/gms/measurement/internal/zzek;
    //   845: ldc_w 270
    //   848: aload_3
    //   849: invokevirtual 101	com/google/android/gms/measurement/internal/zzek:zzb	(Ljava/lang/String;Ljava/lang/Object;)V
    //   852: aload_3
    //   853: astore 6
    //   855: aload 4
    //   857: astore 7
    //   859: goto +38 -> 897
    //   862: aload_0
    //   863: getfield 16	com/google/android/gms/measurement/internal/zzu:zza	Lcom/google/android/gms/measurement/internal/zzy;
    //   866: getfield 39	com/google/android/gms/measurement/internal/zzkd:zzf	Lcom/google/android/gms/measurement/internal/zzkn;
    //   869: invokevirtual 113	com/google/android/gms/measurement/internal/zzkn:zzi	()Lcom/google/android/gms/measurement/internal/zzai;
    //   872: aload_1
    //   873: aload 5
    //   875: invokestatic 69	com/google/android/gms/common/internal/Preconditions:checkNotNull	(Ljava/lang/Object;)Ljava/lang/Object;
    //   878: checkcast 55	java/lang/Long
    //   881: aload_0
    //   882: getfield 210	com/google/android/gms/measurement/internal/zzu:zzd	J
    //   885: aload_2
    //   886: invokevirtual 224	com/google/android/gms/measurement/internal/zzai:zzJ	(Ljava/lang/String;Ljava/lang/Long;JLcom/google/android/gms/internal/measurement/zzfo;)Z
    //   889: pop
    //   890: aload 4
    //   892: astore 7
    //   894: aload_3
    //   895: astore 6
    //   897: aload_2
    //   898: invokevirtual 276	com/google/android/gms/internal/measurement/zzkd:zzbu	()Lcom/google/android/gms/internal/measurement/zzjz;
    //   901: checkcast 173	com/google/android/gms/internal/measurement/zzfn
    //   904: astore_1
    //   905: aload_1
    //   906: aload 6
    //   908: invokevirtual 279	com/google/android/gms/internal/measurement/zzfn:zzl	(Ljava/lang/String;)Lcom/google/android/gms/internal/measurement/zzfn;
    //   911: pop
    //   912: aload_1
    //   913: invokevirtual 281	com/google/android/gms/internal/measurement/zzfn:zzi	()Lcom/google/android/gms/internal/measurement/zzfn;
    //   916: pop
    //   917: aload_1
    //   918: aload 7
    //   920: invokevirtual 285	com/google/android/gms/internal/measurement/zzfn:zzh	(Ljava/lang/Iterable;)Lcom/google/android/gms/internal/measurement/zzfn;
    //   923: pop
    //   924: aload_1
    //   925: invokevirtual 179	com/google/android/gms/internal/measurement/zzjz:zzaA	()Lcom/google/android/gms/internal/measurement/zzkd;
    //   928: checkcast 27	com/google/android/gms/internal/measurement/zzfo
    //   931: areturn
    // Local variable table:
    //   start	length	slot	name	signature
    //   0	932	0	this	zzu
    //   0	932	1	paramString	String
    //   0	932	2	paramzzfo	zzfo
    //   4	305	3	localObject1	Object
    //   314	25	3	localIOException	java.io.IOException
    //   345	1	3	localSQLiteException1	android.database.sqlite.SQLiteException
    //   355	540	3	localSQLiteException2	android.database.sqlite.SQLiteException
    //   9	882	4	localList	java.util.List
    //   31	843	5	localLong	Long
    //   34	873	6	localObject2	Object
    //   38	881	7	localObject3	Object
    //   80	659	8	str	String
    //   152	212	9	localzzai	zzai
    //   264	562	10	l	long
    // Exception table:
    //   from	to	target	type
    //   270	287	314	java/io/IOException
    //   196	206	345	android/database/sqlite/SQLiteException
    //   210	226	345	android/database/sqlite/SQLiteException
    //   243	252	345	android/database/sqlite/SQLiteException
    //   256	266	345	android/database/sqlite/SQLiteException
    //   270	287	345	android/database/sqlite/SQLiteException
    //   291	301	345	android/database/sqlite/SQLiteException
    //   319	342	345	android/database/sqlite/SQLiteException
    //   164	192	349	finally
    //   164	192	355	android/database/sqlite/SQLiteException
    //   521	539	542	android/database/sqlite/SQLiteException
    //   196	206	747	finally
    //   210	226	747	finally
    //   243	252	747	finally
    //   256	266	747	finally
    //   270	287	747	finally
    //   291	301	747	finally
    //   319	342	747	finally
    //   363	380	747	finally
  }
}


/* Location:              C:\Users\User\Desktop\decompile\jdgui110\Tapojar.jar!\com\google\android\gms\measurement\internal\zzu.class
 * Java compiler version: 6 (50.0)
 * JD-Core Version:       0.7.1
 */