package com.google.android.gms.measurement.internal;

import java.util.BitSet;
import java.util.Map;
import java.util.Set;

final class zzy
  extends zzke
{
  private String zza;
  private Set<Integer> zzb;
  private Map<Integer, zzt> zzc;
  private Long zzd;
  private Long zze;
  
  zzy(zzkn paramzzkn)
  {
    super(paramzzkn);
  }
  
  private final zzt zzc(Integer paramInteger)
  {
    if (this.zzc.containsKey(paramInteger)) {
      return (zzt)this.zzc.get(paramInteger);
    }
    zzt localzzt = new zzt(this, this.zza, null);
    this.zzc.put(paramInteger, localzzt);
    return localzzt;
  }
  
  private final boolean zzd(int paramInt1, int paramInt2)
  {
    zzt localzzt = (zzt)this.zzc.get(Integer.valueOf(paramInt1));
    if (localzzt == null) {
      return false;
    }
    return zzt.zzc(localzzt).get(paramInt2);
  }
  
  protected final boolean zzaA()
  {
    return false;
  }
  
  /* Error */
  @androidx.annotation.WorkerThread
  final java.util.List<com.google.android.gms.internal.measurement.zzfk> zzb(String arg1, java.util.List<com.google.android.gms.internal.measurement.zzfo> arg2, java.util.List<com.google.android.gms.internal.measurement.zzgh> arg3, Long arg4, Long arg5)
  {
    // Byte code:
    //   0: ldc 69
    //   2: astore 6
    //   4: aload_1
    //   5: invokestatic 75	com/google/android/gms/common/internal/Preconditions:checkNotEmpty	(Ljava/lang/String;)Ljava/lang/String;
    //   8: pop
    //   9: aload_2
    //   10: invokestatic 78	com/google/android/gms/common/internal/Preconditions:checkNotNull	(Ljava/lang/Object;)Ljava/lang/Object;
    //   13: pop
    //   14: aload_3
    //   15: invokestatic 78	com/google/android/gms/common/internal/Preconditions:checkNotNull	(Ljava/lang/Object;)Ljava/lang/Object;
    //   18: pop
    //   19: aload_0
    //   20: aload_1
    //   21: putfield 37	com/google/android/gms/measurement/internal/zzy:zza	Ljava/lang/String;
    //   24: aload_0
    //   25: new 80	java/util/HashSet
    //   28: dup
    //   29: invokespecial 83	java/util/HashSet:<init>	()V
    //   32: putfield 85	com/google/android/gms/measurement/internal/zzy:zzb	Ljava/util/Set;
    //   35: aload_0
    //   36: new 87	androidx/collection/ArrayMap
    //   39: dup
    //   40: invokespecial 88	androidx/collection/ArrayMap:<init>	()V
    //   43: putfield 23	com/google/android/gms/measurement/internal/zzy:zzc	Ljava/util/Map;
    //   46: aload_0
    //   47: aload 4
    //   49: putfield 90	com/google/android/gms/measurement/internal/zzy:zzd	Ljava/lang/Long;
    //   52: aload_0
    //   53: aload 5
    //   55: putfield 92	com/google/android/gms/measurement/internal/zzy:zze	Ljava/lang/Long;
    //   58: aload_2
    //   59: invokeinterface 98 1 0
    //   64: astore_1
    //   65: aload_1
    //   66: invokeinterface 103 1 0
    //   71: ifeq +29 -> 100
    //   74: ldc 105
    //   76: aload_1
    //   77: invokeinterface 109 1 0
    //   82: checkcast 111	com/google/android/gms/internal/measurement/zzfo
    //   85: invokevirtual 114	com/google/android/gms/internal/measurement/zzfo:zzd	()Ljava/lang/String;
    //   88: invokevirtual 119	java/lang/String:equals	(Ljava/lang/Object;)Z
    //   91: ifeq -26 -> 65
    //   94: iconst_1
    //   95: istore 7
    //   97: goto +6 -> 103
    //   100: iconst_0
    //   101: istore 7
    //   103: invokestatic 123	com/google/android/gms/internal/measurement/zzog:zzb	()Z
    //   106: pop
    //   107: aload_0
    //   108: getfield 129	com/google/android/gms/measurement/internal/zzgn:zzs	Lcom/google/android/gms/measurement/internal/zzfu;
    //   111: invokevirtual 134	com/google/android/gms/measurement/internal/zzfu:zzc	()Lcom/google/android/gms/measurement/internal/zzae;
    //   114: aload_0
    //   115: getfield 37	com/google/android/gms/measurement/internal/zzy:zza	Ljava/lang/String;
    //   118: getstatic 140	com/google/android/gms/measurement/internal/zzea:zzZ	Lcom/google/android/gms/measurement/internal/zzdz;
    //   121: invokevirtual 146	com/google/android/gms/measurement/internal/zzae:zzn	(Ljava/lang/String;Lcom/google/android/gms/measurement/internal/zzdz;)Z
    //   124: istore 8
    //   126: invokestatic 123	com/google/android/gms/internal/measurement/zzog:zzb	()Z
    //   129: pop
    //   130: aload_0
    //   131: getfield 129	com/google/android/gms/measurement/internal/zzgn:zzs	Lcom/google/android/gms/measurement/internal/zzfu;
    //   134: invokevirtual 134	com/google/android/gms/measurement/internal/zzfu:zzc	()Lcom/google/android/gms/measurement/internal/zzae;
    //   137: aload_0
    //   138: getfield 37	com/google/android/gms/measurement/internal/zzy:zza	Ljava/lang/String;
    //   141: getstatic 149	com/google/android/gms/measurement/internal/zzea:zzY	Lcom/google/android/gms/measurement/internal/zzdz;
    //   144: invokevirtual 146	com/google/android/gms/measurement/internal/zzae:zzn	(Ljava/lang/String;Lcom/google/android/gms/measurement/internal/zzdz;)Z
    //   147: istore 9
    //   149: iload 7
    //   151: ifeq +102 -> 253
    //   154: aload_0
    //   155: getfield 155	com/google/android/gms/measurement/internal/zzkd:zzf	Lcom/google/android/gms/measurement/internal/zzkn;
    //   158: invokevirtual 161	com/google/android/gms/measurement/internal/zzkn:zzi	()Lcom/google/android/gms/measurement/internal/zzai;
    //   161: astore 4
    //   163: aload_0
    //   164: getfield 37	com/google/android/gms/measurement/internal/zzy:zza	Ljava/lang/String;
    //   167: astore_1
    //   168: aload 4
    //   170: invokevirtual 163	com/google/android/gms/measurement/internal/zzke:zzZ	()V
    //   173: aload 4
    //   175: invokevirtual 166	com/google/android/gms/measurement/internal/zzgn:zzg	()V
    //   178: aload_1
    //   179: invokestatic 75	com/google/android/gms/common/internal/Preconditions:checkNotEmpty	(Ljava/lang/String;)Ljava/lang/String;
    //   182: pop
    //   183: new 168	android/content/ContentValues
    //   186: dup
    //   187: invokespecial 169	android/content/ContentValues:<init>	()V
    //   190: astore 5
    //   192: aload 5
    //   194: ldc -85
    //   196: iconst_0
    //   197: invokestatic 51	java/lang/Integer:valueOf	(I)Ljava/lang/Integer;
    //   200: invokevirtual 174	android/content/ContentValues:put	(Ljava/lang/String;Ljava/lang/Integer;)V
    //   203: aload 4
    //   205: invokevirtual 179	com/google/android/gms/measurement/internal/zzai:zze	()Landroid/database/sqlite/SQLiteDatabase;
    //   208: ldc -75
    //   210: aload 5
    //   212: ldc -73
    //   214: iconst_1
    //   215: anewarray 116	java/lang/String
    //   218: dup
    //   219: iconst_0
    //   220: aload_1
    //   221: aastore
    //   222: invokevirtual 189	android/database/sqlite/SQLiteDatabase:update	(Ljava/lang/String;Landroid/content/ContentValues;Ljava/lang/String;[Ljava/lang/String;)I
    //   225: pop
    //   226: goto +27 -> 253
    //   229: astore 5
    //   231: aload 4
    //   233: getfield 129	com/google/android/gms/measurement/internal/zzgn:zzs	Lcom/google/android/gms/measurement/internal/zzfu;
    //   236: invokevirtual 193	com/google/android/gms/measurement/internal/zzfu:zzau	()Lcom/google/android/gms/measurement/internal/zzem;
    //   239: invokevirtual 198	com/google/android/gms/measurement/internal/zzem:zzb	()Lcom/google/android/gms/measurement/internal/zzek;
    //   242: ldc -56
    //   244: aload_1
    //   245: invokestatic 204	com/google/android/gms/measurement/internal/zzem:zzl	(Ljava/lang/String;)Ljava/lang/Object;
    //   248: aload 5
    //   250: invokevirtual 209	com/google/android/gms/measurement/internal/zzek:zzc	(Ljava/lang/String;Ljava/lang/Object;Ljava/lang/Object;)V
    //   253: invokestatic 215	java/util/Collections:emptyMap	()Ljava/util/Map;
    //   256: astore_1
    //   257: ldc -39
    //   259: astore 10
    //   261: ldc -37
    //   263: astore 11
    //   265: ldc -35
    //   267: astore 12
    //   269: ldc -33
    //   271: astore 13
    //   273: aload_1
    //   274: astore 4
    //   276: iload 9
    //   278: ifeq +389 -> 667
    //   281: aload_1
    //   282: astore 4
    //   284: iload 8
    //   286: ifeq +381 -> 667
    //   289: aload_0
    //   290: getfield 155	com/google/android/gms/measurement/internal/zzkd:zzf	Lcom/google/android/gms/measurement/internal/zzkn;
    //   293: invokevirtual 161	com/google/android/gms/measurement/internal/zzkn:zzi	()Lcom/google/android/gms/measurement/internal/zzai;
    //   296: astore 14
    //   298: aload_0
    //   299: getfield 37	com/google/android/gms/measurement/internal/zzy:zza	Ljava/lang/String;
    //   302: astore 15
    //   304: aload 15
    //   306: invokestatic 75	com/google/android/gms/common/internal/Preconditions:checkNotEmpty	(Ljava/lang/String;)Ljava/lang/String;
    //   309: pop
    //   310: new 87	androidx/collection/ArrayMap
    //   313: dup
    //   314: invokespecial 88	androidx/collection/ArrayMap:<init>	()V
    //   317: astore 16
    //   319: aload 14
    //   321: invokevirtual 179	com/google/android/gms/measurement/internal/zzai:zze	()Landroid/database/sqlite/SQLiteDatabase;
    //   324: astore_1
    //   325: aload_1
    //   326: ldc -31
    //   328: iconst_2
    //   329: anewarray 116	java/lang/String
    //   332: dup
    //   333: iconst_0
    //   334: ldc -33
    //   336: aastore
    //   337: dup
    //   338: iconst_1
    //   339: ldc -35
    //   341: aastore
    //   342: ldc -29
    //   344: iconst_1
    //   345: anewarray 116	java/lang/String
    //   348: dup
    //   349: iconst_0
    //   350: aload 15
    //   352: aastore
    //   353: aconst_null
    //   354: aconst_null
    //   355: aconst_null
    //   356: invokevirtual 231	android/database/sqlite/SQLiteDatabase:query	(Ljava/lang/String;[Ljava/lang/String;Ljava/lang/String;[Ljava/lang/String;Ljava/lang/String;Ljava/lang/String;Ljava/lang/String;)Landroid/database/Cursor;
    //   359: astore_1
    //   360: aload_1
    //   361: astore 4
    //   363: aload_1
    //   364: invokeinterface 236 1 0
    //   369: ifeq +194 -> 563
    //   372: aload_1
    //   373: astore 4
    //   375: aload_1
    //   376: iconst_1
    //   377: invokeinterface 240 2 0
    //   382: astore 5
    //   384: aload_1
    //   385: astore 4
    //   387: invokestatic 245	com/google/android/gms/internal/measurement/zzej:zzn	()Lcom/google/android/gms/internal/measurement/zzei;
    //   390: aload 5
    //   392: invokestatic 251	com/google/android/gms/measurement/internal/zzkp:zzt	(Lcom/google/android/gms/internal/measurement/zzlh;[B)Lcom/google/android/gms/internal/measurement/zzlh;
    //   395: checkcast 253	com/google/android/gms/internal/measurement/zzei
    //   398: invokevirtual 258	com/google/android/gms/internal/measurement/zzjz:zzaA	()Lcom/google/android/gms/internal/measurement/zzkd;
    //   401: checkcast 242	com/google/android/gms/internal/measurement/zzej
    //   404: astore 17
    //   406: aload_1
    //   407: astore 4
    //   409: aload 17
    //   411: invokevirtual 260	com/google/android/gms/internal/measurement/zzej:zzg	()Z
    //   414: ifne +6 -> 420
    //   417: goto +118 -> 535
    //   420: aload_1
    //   421: astore 4
    //   423: aload_1
    //   424: iconst_0
    //   425: invokeinterface 264 2 0
    //   430: invokestatic 51	java/lang/Integer:valueOf	(I)Ljava/lang/Integer;
    //   433: astore 18
    //   435: aload_1
    //   436: astore 4
    //   438: aload 16
    //   440: aload 18
    //   442: invokeinterface 33 2 0
    //   447: checkcast 94	java/util/List
    //   450: astore 5
    //   452: aload 5
    //   454: ifnonnull +37 -> 491
    //   457: aload_1
    //   458: astore 4
    //   460: new 266	java/util/ArrayList
    //   463: astore 5
    //   465: aload_1
    //   466: astore 4
    //   468: aload 5
    //   470: invokespecial 267	java/util/ArrayList:<init>	()V
    //   473: aload_1
    //   474: astore 4
    //   476: aload 16
    //   478: aload 18
    //   480: aload 5
    //   482: invokeinterface 44 3 0
    //   487: pop
    //   488: goto +3 -> 491
    //   491: aload_1
    //   492: astore 4
    //   494: aload 5
    //   496: aload 17
    //   498: invokeinterface 270 2 0
    //   503: pop
    //   504: goto +31 -> 535
    //   507: astore 5
    //   509: aload_1
    //   510: astore 4
    //   512: aload 14
    //   514: getfield 129	com/google/android/gms/measurement/internal/zzgn:zzs	Lcom/google/android/gms/measurement/internal/zzfu;
    //   517: invokevirtual 193	com/google/android/gms/measurement/internal/zzfu:zzau	()Lcom/google/android/gms/measurement/internal/zzem;
    //   520: invokevirtual 198	com/google/android/gms/measurement/internal/zzem:zzb	()Lcom/google/android/gms/measurement/internal/zzek;
    //   523: ldc -39
    //   525: aload 15
    //   527: invokestatic 204	com/google/android/gms/measurement/internal/zzem:zzl	(Ljava/lang/String;)Ljava/lang/Object;
    //   530: aload 5
    //   532: invokevirtual 209	com/google/android/gms/measurement/internal/zzek:zzc	(Ljava/lang/String;Ljava/lang/Object;Ljava/lang/Object;)V
    //   535: aload_1
    //   536: astore 4
    //   538: aload_1
    //   539: invokeinterface 273 1 0
    //   544: istore 19
    //   546: iload 19
    //   548: ifne +12 -> 560
    //   551: aload_1
    //   552: invokeinterface 276 1 0
    //   557: goto +114 -> 671
    //   560: goto -188 -> 372
    //   563: aload_1
    //   564: astore 4
    //   566: invokestatic 215	java/util/Collections:emptyMap	()Ljava/util/Map;
    //   569: astore 5
    //   571: aload 5
    //   573: astore 4
    //   575: aload_1
    //   576: invokeinterface 276 1 0
    //   581: goto +86 -> 667
    //   584: astore_1
    //   585: goto +68 -> 653
    //   588: astore 5
    //   590: goto +14 -> 604
    //   593: astore_1
    //   594: aconst_null
    //   595: astore 4
    //   597: goto +56 -> 653
    //   600: astore 5
    //   602: aconst_null
    //   603: astore_1
    //   604: aload_1
    //   605: astore 4
    //   607: aload 14
    //   609: getfield 129	com/google/android/gms/measurement/internal/zzgn:zzs	Lcom/google/android/gms/measurement/internal/zzfu;
    //   612: invokevirtual 193	com/google/android/gms/measurement/internal/zzfu:zzau	()Lcom/google/android/gms/measurement/internal/zzem;
    //   615: invokevirtual 198	com/google/android/gms/measurement/internal/zzem:zzb	()Lcom/google/android/gms/measurement/internal/zzek;
    //   618: ldc -37
    //   620: aload 15
    //   622: invokestatic 204	com/google/android/gms/measurement/internal/zzem:zzl	(Ljava/lang/String;)Ljava/lang/Object;
    //   625: aload 5
    //   627: invokevirtual 209	com/google/android/gms/measurement/internal/zzek:zzc	(Ljava/lang/String;Ljava/lang/Object;Ljava/lang/Object;)V
    //   630: aload_1
    //   631: astore 4
    //   633: invokestatic 215	java/util/Collections:emptyMap	()Ljava/util/Map;
    //   636: astore 5
    //   638: aload 5
    //   640: astore 4
    //   642: aload_1
    //   643: ifnull +24 -> 667
    //   646: aload 5
    //   648: astore 4
    //   650: goto -75 -> 575
    //   653: aload 4
    //   655: ifnull +10 -> 665
    //   658: aload 4
    //   660: invokeinterface 276 1 0
    //   665: aload_1
    //   666: athrow
    //   667: aload 4
    //   669: astore 16
    //   671: aload_0
    //   672: getfield 155	com/google/android/gms/measurement/internal/zzkd:zzf	Lcom/google/android/gms/measurement/internal/zzkn;
    //   675: invokevirtual 161	com/google/android/gms/measurement/internal/zzkn:zzi	()Lcom/google/android/gms/measurement/internal/zzai;
    //   678: astore 20
    //   680: aload_0
    //   681: getfield 37	com/google/android/gms/measurement/internal/zzy:zza	Ljava/lang/String;
    //   684: astore 21
    //   686: aload 20
    //   688: invokevirtual 163	com/google/android/gms/measurement/internal/zzke:zzZ	()V
    //   691: aload 20
    //   693: invokevirtual 166	com/google/android/gms/measurement/internal/zzgn:zzg	()V
    //   696: aload 21
    //   698: invokestatic 75	com/google/android/gms/common/internal/Preconditions:checkNotEmpty	(Ljava/lang/String;)Ljava/lang/String;
    //   701: pop
    //   702: aload 20
    //   704: invokevirtual 179	com/google/android/gms/measurement/internal/zzai:zze	()Landroid/database/sqlite/SQLiteDatabase;
    //   707: astore_1
    //   708: aload_1
    //   709: ldc_w 278
    //   712: iconst_2
    //   713: anewarray 116	java/lang/String
    //   716: dup
    //   717: iconst_0
    //   718: ldc -33
    //   720: aastore
    //   721: dup
    //   722: iconst_1
    //   723: ldc 69
    //   725: aastore
    //   726: ldc -29
    //   728: iconst_1
    //   729: anewarray 116	java/lang/String
    //   732: dup
    //   733: iconst_0
    //   734: aload 21
    //   736: aastore
    //   737: aconst_null
    //   738: aconst_null
    //   739: aconst_null
    //   740: invokevirtual 231	android/database/sqlite/SQLiteDatabase:query	(Ljava/lang/String;[Ljava/lang/String;Ljava/lang/String;[Ljava/lang/String;Ljava/lang/String;Ljava/lang/String;Ljava/lang/String;)Landroid/database/Cursor;
    //   743: astore 17
    //   745: aload 13
    //   747: astore 14
    //   749: aload 12
    //   751: astore 5
    //   753: aload 17
    //   755: astore 15
    //   757: aload 17
    //   759: invokeinterface 236 1 0
    //   764: ifne +37 -> 801
    //   767: aload 13
    //   769: astore 14
    //   771: aload 12
    //   773: astore 5
    //   775: aload 17
    //   777: astore 15
    //   779: invokestatic 215	java/util/Collections:emptyMap	()Ljava/util/Map;
    //   782: astore_1
    //   783: aload 17
    //   785: invokeinterface 276 1 0
    //   790: ldc -33
    //   792: astore 13
    //   794: ldc -35
    //   796: astore 5
    //   798: goto +371 -> 1169
    //   801: aload 13
    //   803: astore 14
    //   805: aload 12
    //   807: astore 5
    //   809: aload 17
    //   811: astore 15
    //   813: new 87	androidx/collection/ArrayMap
    //   816: astore 18
    //   818: aload 13
    //   820: astore 14
    //   822: aload 12
    //   824: astore 5
    //   826: aload 17
    //   828: astore 15
    //   830: aload 18
    //   832: invokespecial 88	androidx/collection/ArrayMap:<init>	()V
    //   835: aload 12
    //   837: astore_1
    //   838: aload 13
    //   840: astore 4
    //   842: aload 18
    //   844: astore 13
    //   846: aload 4
    //   848: astore 14
    //   850: aload_1
    //   851: astore 5
    //   853: aload 17
    //   855: astore 15
    //   857: aload 17
    //   859: iconst_0
    //   860: invokeinterface 264 2 0
    //   865: istore 22
    //   867: aload 4
    //   869: astore 14
    //   871: aload_1
    //   872: astore 5
    //   874: aload 17
    //   876: astore 15
    //   878: aload 17
    //   880: iconst_1
    //   881: invokeinterface 240 2 0
    //   886: astore 12
    //   888: aload 4
    //   890: astore 14
    //   892: aload_1
    //   893: astore 5
    //   895: aload 17
    //   897: astore 15
    //   899: invokestatic 284	com/google/android/gms/internal/measurement/zzgd:zzk	()Lcom/google/android/gms/internal/measurement/zzgc;
    //   902: aload 12
    //   904: invokestatic 251	com/google/android/gms/measurement/internal/zzkp:zzt	(Lcom/google/android/gms/internal/measurement/zzlh;[B)Lcom/google/android/gms/internal/measurement/zzlh;
    //   907: checkcast 286	com/google/android/gms/internal/measurement/zzgc
    //   910: invokevirtual 258	com/google/android/gms/internal/measurement/zzjz:zzaA	()Lcom/google/android/gms/internal/measurement/zzkd;
    //   913: checkcast 280	com/google/android/gms/internal/measurement/zzgd
    //   916: astore 12
    //   918: aload 4
    //   920: astore 14
    //   922: aload_1
    //   923: astore 5
    //   925: aload 17
    //   927: astore 15
    //   929: aload 13
    //   931: iload 22
    //   933: invokestatic 51	java/lang/Integer:valueOf	(I)Ljava/lang/Integer;
    //   936: aload 12
    //   938: invokeinterface 44 3 0
    //   943: pop
    //   944: goto +65 -> 1009
    //   947: astore 18
    //   949: aload 4
    //   951: astore 14
    //   953: aload_1
    //   954: astore 5
    //   956: aload 17
    //   958: astore 15
    //   960: aload 20
    //   962: getfield 129	com/google/android/gms/measurement/internal/zzgn:zzs	Lcom/google/android/gms/measurement/internal/zzfu;
    //   965: invokevirtual 193	com/google/android/gms/measurement/internal/zzfu:zzau	()Lcom/google/android/gms/measurement/internal/zzem;
    //   968: invokevirtual 198	com/google/android/gms/measurement/internal/zzem:zzb	()Lcom/google/android/gms/measurement/internal/zzek;
    //   971: astore 12
    //   973: aload 4
    //   975: astore 5
    //   977: aload 17
    //   979: astore 15
    //   981: aload 21
    //   983: invokestatic 204	com/google/android/gms/measurement/internal/zzem:zzl	(Ljava/lang/String;)Ljava/lang/Object;
    //   986: astore 14
    //   988: aload 17
    //   990: astore 15
    //   992: aload 12
    //   994: ldc_w 288
    //   997: aload 14
    //   999: iload 22
    //   1001: invokestatic 51	java/lang/Integer:valueOf	(I)Ljava/lang/Integer;
    //   1004: aload 18
    //   1006: invokevirtual 291	com/google/android/gms/measurement/internal/zzek:zzd	(Ljava/lang/String;Ljava/lang/Object;Ljava/lang/Object;Ljava/lang/Object;)V
    //   1009: aload_1
    //   1010: astore 5
    //   1012: aload 4
    //   1014: astore 14
    //   1016: aload 17
    //   1018: astore 15
    //   1020: aload 17
    //   1022: invokeinterface 273 1 0
    //   1027: istore 19
    //   1029: iload 19
    //   1031: ifne +20 -> 1051
    //   1034: aload 17
    //   1036: invokeinterface 276 1 0
    //   1041: aload 13
    //   1043: astore_1
    //   1044: aload 14
    //   1046: astore 13
    //   1048: goto +121 -> 1169
    //   1051: aload 14
    //   1053: astore 4
    //   1055: aload 5
    //   1057: astore_1
    //   1058: goto -212 -> 846
    //   1061: aload_1
    //   1062: astore 5
    //   1064: aload 4
    //   1066: astore 13
    //   1068: astore 4
    //   1070: aload 17
    //   1072: astore_1
    //   1073: goto +48 -> 1121
    //   1076: astore 4
    //   1078: aload 5
    //   1080: astore 13
    //   1082: goto +12 -> 1094
    //   1085: astore 4
    //   1087: aload 14
    //   1089: astore 13
    //   1091: aload 5
    //   1093: astore_1
    //   1094: aload_1
    //   1095: astore 5
    //   1097: aload 17
    //   1099: astore_1
    //   1100: goto +21 -> 1121
    //   1103: astore_1
    //   1104: aconst_null
    //   1105: astore_2
    //   1106: goto +3921 -> 5027
    //   1109: astore 4
    //   1111: ldc -33
    //   1113: astore 13
    //   1115: ldc -35
    //   1117: astore 5
    //   1119: aconst_null
    //   1120: astore_1
    //   1121: aload_1
    //   1122: astore 15
    //   1124: aload 20
    //   1126: getfield 129	com/google/android/gms/measurement/internal/zzgn:zzs	Lcom/google/android/gms/measurement/internal/zzfu;
    //   1129: invokevirtual 193	com/google/android/gms/measurement/internal/zzfu:zzau	()Lcom/google/android/gms/measurement/internal/zzem;
    //   1132: invokevirtual 198	com/google/android/gms/measurement/internal/zzem:zzb	()Lcom/google/android/gms/measurement/internal/zzek;
    //   1135: ldc_w 293
    //   1138: aload 21
    //   1140: invokestatic 204	com/google/android/gms/measurement/internal/zzem:zzl	(Ljava/lang/String;)Ljava/lang/Object;
    //   1143: aload 4
    //   1145: invokevirtual 209	com/google/android/gms/measurement/internal/zzek:zzc	(Ljava/lang/String;Ljava/lang/Object;Ljava/lang/Object;)V
    //   1148: aload_1
    //   1149: astore 15
    //   1151: invokestatic 215	java/util/Collections:emptyMap	()Ljava/util/Map;
    //   1154: astore 4
    //   1156: aload_1
    //   1157: ifnull +9 -> 1166
    //   1160: aload_1
    //   1161: invokeinterface 276 1 0
    //   1166: aload 4
    //   1168: astore_1
    //   1169: aload_1
    //   1170: invokeinterface 296 1 0
    //   1175: ifeq +17 -> 1192
    //   1178: aload 10
    //   1180: astore 16
    //   1182: aload 16
    //   1184: astore_1
    //   1185: aload 5
    //   1187: astore 4
    //   1189: goto +1414 -> 2603
    //   1192: new 80	java/util/HashSet
    //   1195: dup
    //   1196: aload_1
    //   1197: invokeinterface 300 1 0
    //   1202: invokespecial 303	java/util/HashSet:<init>	(Ljava/util/Collection;)V
    //   1205: astore 20
    //   1207: iload 7
    //   1209: ifeq +686 -> 1895
    //   1212: aload_0
    //   1213: getfield 37	com/google/android/gms/measurement/internal/zzy:zza	Ljava/lang/String;
    //   1216: astore 23
    //   1218: aload 23
    //   1220: invokestatic 75	com/google/android/gms/common/internal/Preconditions:checkNotEmpty	(Ljava/lang/String;)Ljava/lang/String;
    //   1223: pop
    //   1224: aload_1
    //   1225: invokestatic 78	com/google/android/gms/common/internal/Preconditions:checkNotNull	(Ljava/lang/Object;)Ljava/lang/Object;
    //   1228: pop
    //   1229: new 87	androidx/collection/ArrayMap
    //   1232: dup
    //   1233: invokespecial 88	androidx/collection/ArrayMap:<init>	()V
    //   1236: astore 17
    //   1238: aload_1
    //   1239: invokeinterface 296 1 0
    //   1244: ifeq +6 -> 1250
    //   1247: goto +627 -> 1874
    //   1250: aload_0
    //   1251: getfield 155	com/google/android/gms/measurement/internal/zzkd:zzf	Lcom/google/android/gms/measurement/internal/zzkn;
    //   1254: invokevirtual 161	com/google/android/gms/measurement/internal/zzkn:zzi	()Lcom/google/android/gms/measurement/internal/zzai;
    //   1257: astore 21
    //   1259: aload 21
    //   1261: invokevirtual 163	com/google/android/gms/measurement/internal/zzke:zzZ	()V
    //   1264: aload 21
    //   1266: invokevirtual 166	com/google/android/gms/measurement/internal/zzgn:zzg	()V
    //   1269: aload 23
    //   1271: invokestatic 75	com/google/android/gms/common/internal/Preconditions:checkNotEmpty	(Ljava/lang/String;)Ljava/lang/String;
    //   1274: pop
    //   1275: new 87	androidx/collection/ArrayMap
    //   1278: dup
    //   1279: invokespecial 88	androidx/collection/ArrayMap:<init>	()V
    //   1282: astore 12
    //   1284: aload 21
    //   1286: invokevirtual 179	com/google/android/gms/measurement/internal/zzai:zze	()Landroid/database/sqlite/SQLiteDatabase;
    //   1289: astore 4
    //   1291: aload 4
    //   1293: ldc_w 305
    //   1296: iconst_2
    //   1297: anewarray 116	java/lang/String
    //   1300: dup
    //   1301: iconst_0
    //   1302: aload 23
    //   1304: aastore
    //   1305: dup
    //   1306: iconst_1
    //   1307: aload 23
    //   1309: aastore
    //   1310: invokevirtual 309	android/database/sqlite/SQLiteDatabase:rawQuery	(Ljava/lang/String;[Ljava/lang/String;)Landroid/database/Cursor;
    //   1313: astore 4
    //   1315: aload 4
    //   1317: astore 15
    //   1319: aload 4
    //   1321: invokeinterface 236 1 0
    //   1326: ifeq +136 -> 1462
    //   1329: aload 4
    //   1331: astore 15
    //   1333: aload 4
    //   1335: iconst_0
    //   1336: invokeinterface 264 2 0
    //   1341: invokestatic 51	java/lang/Integer:valueOf	(I)Ljava/lang/Integer;
    //   1344: astore 24
    //   1346: aload 4
    //   1348: astore 15
    //   1350: aload 12
    //   1352: aload 24
    //   1354: invokeinterface 33 2 0
    //   1359: checkcast 94	java/util/List
    //   1362: astore 18
    //   1364: aload 18
    //   1366: astore 14
    //   1368: aload 18
    //   1370: ifnonnull +37 -> 1407
    //   1373: aload 4
    //   1375: astore 15
    //   1377: new 266	java/util/ArrayList
    //   1380: astore 14
    //   1382: aload 4
    //   1384: astore 15
    //   1386: aload 14
    //   1388: invokespecial 267	java/util/ArrayList:<init>	()V
    //   1391: aload 4
    //   1393: astore 15
    //   1395: aload 12
    //   1397: aload 24
    //   1399: aload 14
    //   1401: invokeinterface 44 3 0
    //   1406: pop
    //   1407: aload 4
    //   1409: astore 15
    //   1411: aload 14
    //   1413: aload 4
    //   1415: iconst_1
    //   1416: invokeinterface 264 2 0
    //   1421: invokestatic 51	java/lang/Integer:valueOf	(I)Ljava/lang/Integer;
    //   1424: invokeinterface 270 2 0
    //   1429: pop
    //   1430: aload 4
    //   1432: astore 15
    //   1434: aload 4
    //   1436: invokeinterface 273 1 0
    //   1441: istore 19
    //   1443: iload 19
    //   1445: ifne -116 -> 1329
    //   1448: aload 12
    //   1450: astore 15
    //   1452: aload 4
    //   1454: invokeinterface 276 1 0
    //   1459: goto +93 -> 1552
    //   1462: aload 4
    //   1464: astore 15
    //   1466: invokestatic 215	java/util/Collections:emptyMap	()Ljava/util/Map;
    //   1469: astore 14
    //   1471: aload 14
    //   1473: astore 15
    //   1475: goto -23 -> 1452
    //   1478: astore_1
    //   1479: goto +402 -> 1881
    //   1482: astore 14
    //   1484: goto +15 -> 1499
    //   1487: astore_1
    //   1488: aconst_null
    //   1489: astore 15
    //   1491: goto +390 -> 1881
    //   1494: astore 14
    //   1496: aconst_null
    //   1497: astore 4
    //   1499: aload 4
    //   1501: astore 15
    //   1503: aload 21
    //   1505: getfield 129	com/google/android/gms/measurement/internal/zzgn:zzs	Lcom/google/android/gms/measurement/internal/zzfu;
    //   1508: invokevirtual 193	com/google/android/gms/measurement/internal/zzfu:zzau	()Lcom/google/android/gms/measurement/internal/zzem;
    //   1511: invokevirtual 198	com/google/android/gms/measurement/internal/zzem:zzb	()Lcom/google/android/gms/measurement/internal/zzek;
    //   1514: ldc_w 311
    //   1517: aload 23
    //   1519: invokestatic 204	com/google/android/gms/measurement/internal/zzem:zzl	(Ljava/lang/String;)Ljava/lang/Object;
    //   1522: aload 14
    //   1524: invokevirtual 209	com/google/android/gms/measurement/internal/zzek:zzc	(Ljava/lang/String;Ljava/lang/Object;Ljava/lang/Object;)V
    //   1527: aload 4
    //   1529: astore 15
    //   1531: invokestatic 215	java/util/Collections:emptyMap	()Ljava/util/Map;
    //   1534: astore 14
    //   1536: aload 14
    //   1538: astore 15
    //   1540: aload 4
    //   1542: ifnull +10 -> 1552
    //   1545: aload 14
    //   1547: astore 15
    //   1549: goto -97 -> 1452
    //   1552: aload_1
    //   1553: invokeinterface 300 1 0
    //   1558: invokeinterface 314 1 0
    //   1563: astore 14
    //   1565: aload 15
    //   1567: astore 4
    //   1569: aload 14
    //   1571: invokeinterface 103 1 0
    //   1576: ifeq +298 -> 1874
    //   1579: aload 14
    //   1581: invokeinterface 109 1 0
    //   1586: checkcast 47	java/lang/Integer
    //   1589: invokevirtual 318	java/lang/Integer:intValue	()I
    //   1592: istore 22
    //   1594: iload 22
    //   1596: invokestatic 51	java/lang/Integer:valueOf	(I)Ljava/lang/Integer;
    //   1599: astore 18
    //   1601: aload_1
    //   1602: aload 18
    //   1604: invokeinterface 33 2 0
    //   1609: checkcast 280	com/google/android/gms/internal/measurement/zzgd
    //   1612: astore 12
    //   1614: aload 4
    //   1616: aload 18
    //   1618: invokeinterface 33 2 0
    //   1623: checkcast 94	java/util/List
    //   1626: astore 15
    //   1628: aload 15
    //   1630: ifnull +229 -> 1859
    //   1633: aload 15
    //   1635: invokeinterface 319 1 0
    //   1640: ifeq +6 -> 1646
    //   1643: goto +216 -> 1859
    //   1646: aload_0
    //   1647: getfield 155	com/google/android/gms/measurement/internal/zzkd:zzf	Lcom/google/android/gms/measurement/internal/zzkn;
    //   1650: invokevirtual 323	com/google/android/gms/measurement/internal/zzkn:zzm	()Lcom/google/android/gms/measurement/internal/zzkp;
    //   1653: aload 12
    //   1655: invokevirtual 326	com/google/android/gms/internal/measurement/zzgd:zzc	()Ljava/util/List;
    //   1658: aload 15
    //   1660: invokevirtual 330	com/google/android/gms/measurement/internal/zzkp:zzo	(Ljava/util/List;Ljava/util/List;)Ljava/util/List;
    //   1663: astore 21
    //   1665: aload 21
    //   1667: invokeinterface 319 1 0
    //   1672: ifne +184 -> 1856
    //   1675: aload 12
    //   1677: invokevirtual 336	com/google/android/gms/internal/measurement/zzkd:zzbu	()Lcom/google/android/gms/internal/measurement/zzjz;
    //   1680: checkcast 286	com/google/android/gms/internal/measurement/zzgc
    //   1683: astore 18
    //   1685: aload 18
    //   1687: invokevirtual 338	com/google/android/gms/internal/measurement/zzgc:zzd	()Lcom/google/android/gms/internal/measurement/zzgc;
    //   1690: pop
    //   1691: aload 18
    //   1693: aload 21
    //   1695: invokevirtual 341	com/google/android/gms/internal/measurement/zzgc:zzc	(Ljava/lang/Iterable;)Lcom/google/android/gms/internal/measurement/zzgc;
    //   1698: pop
    //   1699: aload_0
    //   1700: getfield 155	com/google/android/gms/measurement/internal/zzkd:zzf	Lcom/google/android/gms/measurement/internal/zzkn;
    //   1703: invokevirtual 323	com/google/android/gms/measurement/internal/zzkn:zzm	()Lcom/google/android/gms/measurement/internal/zzkp;
    //   1706: aload 12
    //   1708: invokevirtual 343	com/google/android/gms/internal/measurement/zzgd:zza	()Ljava/util/List;
    //   1711: aload 15
    //   1713: invokevirtual 330	com/google/android/gms/measurement/internal/zzkp:zzo	(Ljava/util/List;Ljava/util/List;)Ljava/util/List;
    //   1716: astore 21
    //   1718: aload 18
    //   1720: invokevirtual 345	com/google/android/gms/internal/measurement/zzgc:zzb	()Lcom/google/android/gms/internal/measurement/zzgc;
    //   1723: pop
    //   1724: aload 18
    //   1726: aload 21
    //   1728: invokevirtual 347	com/google/android/gms/internal/measurement/zzgc:zza	(Ljava/lang/Iterable;)Lcom/google/android/gms/internal/measurement/zzgc;
    //   1731: pop
    //   1732: iconst_0
    //   1733: istore 7
    //   1735: iload 7
    //   1737: aload 12
    //   1739: invokevirtual 349	com/google/android/gms/internal/measurement/zzgd:zzf	()I
    //   1742: if_icmpge +40 -> 1782
    //   1745: aload 15
    //   1747: aload 12
    //   1749: iload 7
    //   1751: invokevirtual 352	com/google/android/gms/internal/measurement/zzgd:zzg	(I)Lcom/google/android/gms/internal/measurement/zzfm;
    //   1754: invokevirtual 356	com/google/android/gms/internal/measurement/zzfm:zzb	()I
    //   1757: invokestatic 51	java/lang/Integer:valueOf	(I)Ljava/lang/Integer;
    //   1760: invokeinterface 359 2 0
    //   1765: ifeq +11 -> 1776
    //   1768: aload 18
    //   1770: iload 7
    //   1772: invokevirtual 362	com/google/android/gms/internal/measurement/zzgc:zzf	(I)Lcom/google/android/gms/internal/measurement/zzgc;
    //   1775: pop
    //   1776: iinc 7 1
    //   1779: goto -44 -> 1735
    //   1782: iconst_0
    //   1783: istore 7
    //   1785: iload 7
    //   1787: aload 12
    //   1789: invokevirtual 364	com/google/android/gms/internal/measurement/zzgd:zzi	()I
    //   1792: if_icmpge +40 -> 1832
    //   1795: aload 15
    //   1797: aload 12
    //   1799: iload 7
    //   1801: invokevirtual 368	com/google/android/gms/internal/measurement/zzgd:zzj	(I)Lcom/google/android/gms/internal/measurement/zzgf;
    //   1804: invokevirtual 371	com/google/android/gms/internal/measurement/zzgf:zzb	()I
    //   1807: invokestatic 51	java/lang/Integer:valueOf	(I)Ljava/lang/Integer;
    //   1810: invokeinterface 359 2 0
    //   1815: ifeq +11 -> 1826
    //   1818: aload 18
    //   1820: iload 7
    //   1822: invokevirtual 374	com/google/android/gms/internal/measurement/zzgc:zzh	(I)Lcom/google/android/gms/internal/measurement/zzgc;
    //   1825: pop
    //   1826: iinc 7 1
    //   1829: goto -44 -> 1785
    //   1832: aload 17
    //   1834: iload 22
    //   1836: invokestatic 51	java/lang/Integer:valueOf	(I)Ljava/lang/Integer;
    //   1839: aload 18
    //   1841: invokevirtual 258	com/google/android/gms/internal/measurement/zzjz:zzaA	()Lcom/google/android/gms/internal/measurement/zzkd;
    //   1844: checkcast 280	com/google/android/gms/internal/measurement/zzgd
    //   1847: invokeinterface 44 3 0
    //   1852: pop
    //   1853: goto +18 -> 1871
    //   1856: goto -287 -> 1569
    //   1859: aload 17
    //   1861: aload 18
    //   1863: aload 12
    //   1865: invokeinterface 44 3 0
    //   1870: pop
    //   1871: goto -302 -> 1569
    //   1874: aload 17
    //   1876: astore 15
    //   1878: goto +20 -> 1898
    //   1881: aload 15
    //   1883: ifnull +10 -> 1893
    //   1886: aload 15
    //   1888: invokeinterface 276 1 0
    //   1893: aload_1
    //   1894: athrow
    //   1895: aload_1
    //   1896: astore 15
    //   1898: aload 20
    //   1900: invokeinterface 314 1 0
    //   1905: astore 18
    //   1907: aload_1
    //   1908: astore 12
    //   1910: aload 16
    //   1912: astore 17
    //   1914: aload 10
    //   1916: astore 4
    //   1918: aload 11
    //   1920: astore_1
    //   1921: aload_1
    //   1922: astore 11
    //   1924: aload 4
    //   1926: astore 16
    //   1928: aload 18
    //   1930: invokeinterface 103 1 0
    //   1935: ifeq -753 -> 1182
    //   1938: aload 18
    //   1940: invokeinterface 109 1 0
    //   1945: checkcast 47	java/lang/Integer
    //   1948: invokevirtual 318	java/lang/Integer:intValue	()I
    //   1951: istore 22
    //   1953: aload 15
    //   1955: iload 22
    //   1957: invokestatic 51	java/lang/Integer:valueOf	(I)Ljava/lang/Integer;
    //   1960: invokeinterface 33 2 0
    //   1965: checkcast 280	com/google/android/gms/internal/measurement/zzgd
    //   1968: astore 23
    //   1970: new 56	java/util/BitSet
    //   1973: dup
    //   1974: invokespecial 375	java/util/BitSet:<init>	()V
    //   1977: astore 10
    //   1979: new 56	java/util/BitSet
    //   1982: dup
    //   1983: invokespecial 375	java/util/BitSet:<init>	()V
    //   1986: astore 11
    //   1988: new 87	androidx/collection/ArrayMap
    //   1991: dup
    //   1992: invokespecial 88	androidx/collection/ArrayMap:<init>	()V
    //   1995: astore 20
    //   1997: aload 23
    //   1999: ifnull +105 -> 2104
    //   2002: aload 23
    //   2004: invokevirtual 349	com/google/android/gms/internal/measurement/zzgd:zzf	()I
    //   2007: ifne +6 -> 2013
    //   2010: goto +94 -> 2104
    //   2013: aload 23
    //   2015: invokevirtual 377	com/google/android/gms/internal/measurement/zzgd:zze	()Ljava/util/List;
    //   2018: invokeinterface 98 1 0
    //   2023: astore 14
    //   2025: aload 14
    //   2027: invokeinterface 103 1 0
    //   2032: ifeq +72 -> 2104
    //   2035: aload 14
    //   2037: invokeinterface 109 1 0
    //   2042: checkcast 354	com/google/android/gms/internal/measurement/zzfm
    //   2045: astore 16
    //   2047: aload 16
    //   2049: invokevirtual 379	com/google/android/gms/internal/measurement/zzfm:zza	()Z
    //   2052: ifeq -27 -> 2025
    //   2055: aload 16
    //   2057: invokevirtual 356	com/google/android/gms/internal/measurement/zzfm:zzb	()I
    //   2060: istore 7
    //   2062: aload 16
    //   2064: invokevirtual 381	com/google/android/gms/internal/measurement/zzfm:zzc	()Z
    //   2067: ifeq +16 -> 2083
    //   2070: aload 16
    //   2072: invokevirtual 384	com/google/android/gms/internal/measurement/zzfm:zzd	()J
    //   2075: invokestatic 389	java/lang/Long:valueOf	(J)Ljava/lang/Long;
    //   2078: astore 16
    //   2080: goto +6 -> 2086
    //   2083: aconst_null
    //   2084: astore 16
    //   2086: aload 20
    //   2088: iload 7
    //   2090: invokestatic 51	java/lang/Integer:valueOf	(I)Ljava/lang/Integer;
    //   2093: aload 16
    //   2095: invokeinterface 44 3 0
    //   2100: pop
    //   2101: goto -76 -> 2025
    //   2104: new 87	androidx/collection/ArrayMap
    //   2107: dup
    //   2108: invokespecial 88	androidx/collection/ArrayMap:<init>	()V
    //   2111: astore 21
    //   2113: aload 15
    //   2115: astore 16
    //   2117: aload 23
    //   2119: ifnull +106 -> 2225
    //   2122: aload 23
    //   2124: invokevirtual 364	com/google/android/gms/internal/measurement/zzgd:zzi	()I
    //   2127: ifne +10 -> 2137
    //   2130: aload 15
    //   2132: astore 16
    //   2134: goto +91 -> 2225
    //   2137: aload 23
    //   2139: invokevirtual 391	com/google/android/gms/internal/measurement/zzgd:zzh	()Ljava/util/List;
    //   2142: invokeinterface 98 1 0
    //   2147: astore 14
    //   2149: aload 15
    //   2151: astore 16
    //   2153: aload 14
    //   2155: invokeinterface 103 1 0
    //   2160: ifeq +65 -> 2225
    //   2163: aload 14
    //   2165: invokeinterface 109 1 0
    //   2170: checkcast 370	com/google/android/gms/internal/measurement/zzgf
    //   2173: astore 16
    //   2175: aload 16
    //   2177: invokevirtual 392	com/google/android/gms/internal/measurement/zzgf:zza	()Z
    //   2180: ifeq -31 -> 2149
    //   2183: aload 16
    //   2185: invokevirtual 394	com/google/android/gms/internal/measurement/zzgf:zzd	()I
    //   2188: ifle -39 -> 2149
    //   2191: aload 21
    //   2193: aload 16
    //   2195: invokevirtual 371	com/google/android/gms/internal/measurement/zzgf:zzb	()I
    //   2198: invokestatic 51	java/lang/Integer:valueOf	(I)Ljava/lang/Integer;
    //   2201: aload 16
    //   2203: aload 16
    //   2205: invokevirtual 394	com/google/android/gms/internal/measurement/zzgf:zzd	()I
    //   2208: iconst_1
    //   2209: isub
    //   2210: invokevirtual 397	com/google/android/gms/internal/measurement/zzgf:zze	(I)J
    //   2213: invokestatic 389	java/lang/Long:valueOf	(J)Ljava/lang/Long;
    //   2216: invokeinterface 44 3 0
    //   2221: pop
    //   2222: goto -73 -> 2149
    //   2225: aload_1
    //   2226: astore 14
    //   2228: aload 4
    //   2230: astore 15
    //   2232: aload 23
    //   2234: ifnull +114 -> 2348
    //   2237: iconst_0
    //   2238: istore 7
    //   2240: aload_1
    //   2241: astore 14
    //   2243: aload 4
    //   2245: astore 15
    //   2247: iload 7
    //   2249: aload 23
    //   2251: invokevirtual 398	com/google/android/gms/internal/measurement/zzgd:zzb	()I
    //   2254: bipush 64
    //   2256: imul
    //   2257: if_icmpge +91 -> 2348
    //   2260: aload 23
    //   2262: invokevirtual 343	com/google/android/gms/internal/measurement/zzgd:zza	()Ljava/util/List;
    //   2265: iload 7
    //   2267: invokestatic 401	com/google/android/gms/measurement/internal/zzkp:zzm	(Ljava/util/List;I)Z
    //   2270: ifeq +59 -> 2329
    //   2273: aload_0
    //   2274: getfield 129	com/google/android/gms/measurement/internal/zzgn:zzs	Lcom/google/android/gms/measurement/internal/zzfu;
    //   2277: invokevirtual 193	com/google/android/gms/measurement/internal/zzfu:zzau	()Lcom/google/android/gms/measurement/internal/zzem;
    //   2280: invokevirtual 403	com/google/android/gms/measurement/internal/zzem:zzk	()Lcom/google/android/gms/measurement/internal/zzek;
    //   2283: ldc_w 405
    //   2286: iload 22
    //   2288: invokestatic 51	java/lang/Integer:valueOf	(I)Ljava/lang/Integer;
    //   2291: iload 7
    //   2293: invokestatic 51	java/lang/Integer:valueOf	(I)Ljava/lang/Integer;
    //   2296: invokevirtual 209	com/google/android/gms/measurement/internal/zzek:zzc	(Ljava/lang/String;Ljava/lang/Object;Ljava/lang/Object;)V
    //   2299: aload 11
    //   2301: iload 7
    //   2303: invokevirtual 409	java/util/BitSet:set	(I)V
    //   2306: aload 23
    //   2308: invokevirtual 326	com/google/android/gms/internal/measurement/zzgd:zzc	()Ljava/util/List;
    //   2311: iload 7
    //   2313: invokestatic 401	com/google/android/gms/measurement/internal/zzkp:zzm	(Ljava/util/List;I)Z
    //   2316: ifeq +13 -> 2329
    //   2319: aload 10
    //   2321: iload 7
    //   2323: invokevirtual 409	java/util/BitSet:set	(I)V
    //   2326: goto +16 -> 2342
    //   2329: aload 20
    //   2331: iload 7
    //   2333: invokestatic 51	java/lang/Integer:valueOf	(I)Ljava/lang/Integer;
    //   2336: invokeinterface 412 2 0
    //   2341: pop
    //   2342: iinc 7 1
    //   2345: goto -105 -> 2240
    //   2348: iload 22
    //   2350: invokestatic 51	java/lang/Integer:valueOf	(I)Ljava/lang/Integer;
    //   2353: astore 4
    //   2355: aload 12
    //   2357: aload 4
    //   2359: invokeinterface 33 2 0
    //   2364: checkcast 280	com/google/android/gms/internal/measurement/zzgd
    //   2367: astore_1
    //   2368: iload 9
    //   2370: ifeq +180 -> 2550
    //   2373: iload 8
    //   2375: ifeq +175 -> 2550
    //   2378: aload 17
    //   2380: aload 4
    //   2382: invokeinterface 33 2 0
    //   2387: checkcast 94	java/util/List
    //   2390: astore 4
    //   2392: aload 4
    //   2394: ifnull +156 -> 2550
    //   2397: aload_0
    //   2398: getfield 92	com/google/android/gms/measurement/internal/zzy:zze	Ljava/lang/Long;
    //   2401: ifnull +149 -> 2550
    //   2404: aload_0
    //   2405: getfield 90	com/google/android/gms/measurement/internal/zzy:zzd	Ljava/lang/Long;
    //   2408: ifnonnull +6 -> 2414
    //   2411: goto +139 -> 2550
    //   2414: aload 4
    //   2416: invokeinterface 98 1 0
    //   2421: astore 4
    //   2423: aload 4
    //   2425: invokeinterface 103 1 0
    //   2430: ifeq +120 -> 2550
    //   2433: aload 4
    //   2435: invokeinterface 109 1 0
    //   2440: checkcast 242	com/google/android/gms/internal/measurement/zzej
    //   2443: astore 23
    //   2445: aload 23
    //   2447: invokevirtual 413	com/google/android/gms/internal/measurement/zzej:zzb	()I
    //   2450: istore 7
    //   2452: aload_0
    //   2453: getfield 92	com/google/android/gms/measurement/internal/zzy:zze	Ljava/lang/Long;
    //   2456: invokevirtual 416	java/lang/Long:longValue	()J
    //   2459: ldc2_w 417
    //   2462: ldiv
    //   2463: lstore 25
    //   2465: aload 23
    //   2467: invokevirtual 420	com/google/android/gms/internal/measurement/zzej:zzj	()Z
    //   2470: ifeq +16 -> 2486
    //   2473: aload_0
    //   2474: getfield 90	com/google/android/gms/measurement/internal/zzy:zzd	Ljava/lang/Long;
    //   2477: invokevirtual 416	java/lang/Long:longValue	()J
    //   2480: ldc2_w 417
    //   2483: ldiv
    //   2484: lstore 25
    //   2486: iload 7
    //   2488: invokestatic 51	java/lang/Integer:valueOf	(I)Ljava/lang/Integer;
    //   2491: astore 23
    //   2493: aload 20
    //   2495: aload 23
    //   2497: invokeinterface 29 2 0
    //   2502: ifeq +18 -> 2520
    //   2505: aload 20
    //   2507: aload 23
    //   2509: lload 25
    //   2511: invokestatic 389	java/lang/Long:valueOf	(J)Ljava/lang/Long;
    //   2514: invokeinterface 44 3 0
    //   2519: pop
    //   2520: aload 21
    //   2522: aload 23
    //   2524: invokeinterface 29 2 0
    //   2529: ifeq -106 -> 2423
    //   2532: aload 21
    //   2534: aload 23
    //   2536: lload 25
    //   2538: invokestatic 389	java/lang/Long:valueOf	(J)Ljava/lang/Long;
    //   2541: invokeinterface 44 3 0
    //   2546: pop
    //   2547: goto -124 -> 2423
    //   2550: new 35	com/google/android/gms/measurement/internal/zzt
    //   2553: dup
    //   2554: aload_0
    //   2555: aload_0
    //   2556: getfield 37	com/google/android/gms/measurement/internal/zzy:zza	Ljava/lang/String;
    //   2559: aload_1
    //   2560: aload 10
    //   2562: aload 11
    //   2564: aload 20
    //   2566: aload 21
    //   2568: aconst_null
    //   2569: invokespecial 423	com/google/android/gms/measurement/internal/zzt:<init>	(Lcom/google/android/gms/measurement/internal/zzy;Ljava/lang/String;Lcom/google/android/gms/internal/measurement/zzgd;Ljava/util/BitSet;Ljava/util/BitSet;Ljava/util/Map;Ljava/util/Map;Lcom/google/android/gms/measurement/internal/zzs;)V
    //   2572: astore_1
    //   2573: aload_0
    //   2574: getfield 23	com/google/android/gms/measurement/internal/zzy:zzc	Ljava/util/Map;
    //   2577: iload 22
    //   2579: invokestatic 51	java/lang/Integer:valueOf	(I)Ljava/lang/Integer;
    //   2582: aload_1
    //   2583: invokeinterface 44 3 0
    //   2588: pop
    //   2589: aload 14
    //   2591: astore_1
    //   2592: aload 15
    //   2594: astore 4
    //   2596: aload 16
    //   2598: astore 15
    //   2600: goto -679 -> 1921
    //   2603: aload_2
    //   2604: invokeinterface 319 1 0
    //   2609: ifeq +14 -> 2623
    //   2612: aload 4
    //   2614: astore 15
    //   2616: aload 6
    //   2618: astore 16
    //   2620: goto +1164 -> 3784
    //   2623: new 425	com/google/android/gms/measurement/internal/zzu
    //   2626: dup
    //   2627: aload_0
    //   2628: aconst_null
    //   2629: invokespecial 428	com/google/android/gms/measurement/internal/zzu:<init>	(Lcom/google/android/gms/measurement/internal/zzy;Lcom/google/android/gms/measurement/internal/zzs;)V
    //   2632: astore 15
    //   2634: new 87	androidx/collection/ArrayMap
    //   2637: dup
    //   2638: invokespecial 88	androidx/collection/ArrayMap:<init>	()V
    //   2641: astore 20
    //   2643: aload_2
    //   2644: invokeinterface 98 1 0
    //   2649: astore 10
    //   2651: aload 13
    //   2653: astore_2
    //   2654: aload 6
    //   2656: astore 5
    //   2658: aload 15
    //   2660: astore 6
    //   2662: aload 5
    //   2664: astore 16
    //   2666: aload_2
    //   2667: astore 13
    //   2669: aload 4
    //   2671: astore 15
    //   2673: aload 10
    //   2675: invokeinterface 103 1 0
    //   2680: ifeq -60 -> 2620
    //   2683: aload 10
    //   2685: invokeinterface 109 1 0
    //   2690: checkcast 111	com/google/android/gms/internal/measurement/zzfo
    //   2693: astore 18
    //   2695: aload 6
    //   2697: aload_0
    //   2698: getfield 37	com/google/android/gms/measurement/internal/zzy:zza	Ljava/lang/String;
    //   2701: aload 18
    //   2703: invokevirtual 431	com/google/android/gms/measurement/internal/zzu:zza	(Ljava/lang/String;Lcom/google/android/gms/internal/measurement/zzfo;)Lcom/google/android/gms/internal/measurement/zzfo;
    //   2706: astore 21
    //   2708: aload 6
    //   2710: astore 12
    //   2712: aload 10
    //   2714: astore 17
    //   2716: aload 5
    //   2718: astore 14
    //   2720: aload_2
    //   2721: astore 16
    //   2723: aload 4
    //   2725: astore 15
    //   2727: aload_1
    //   2728: astore 13
    //   2730: aload 21
    //   2732: ifnull +1027 -> 3759
    //   2735: aload_0
    //   2736: getfield 155	com/google/android/gms/measurement/internal/zzkd:zzf	Lcom/google/android/gms/measurement/internal/zzkn;
    //   2739: invokevirtual 161	com/google/android/gms/measurement/internal/zzkn:zzi	()Lcom/google/android/gms/measurement/internal/zzai;
    //   2742: astore 15
    //   2744: aload_0
    //   2745: getfield 37	com/google/android/gms/measurement/internal/zzy:zza	Ljava/lang/String;
    //   2748: astore 16
    //   2750: aload 21
    //   2752: invokevirtual 114	com/google/android/gms/internal/measurement/zzfo:zzd	()Ljava/lang/String;
    //   2755: astore 13
    //   2757: aload 15
    //   2759: aload 16
    //   2761: aload 18
    //   2763: invokevirtual 114	com/google/android/gms/internal/measurement/zzfo:zzd	()Ljava/lang/String;
    //   2766: invokevirtual 434	com/google/android/gms/measurement/internal/zzai:zzf	(Ljava/lang/String;Ljava/lang/String;)Lcom/google/android/gms/measurement/internal/zzao;
    //   2769: astore 14
    //   2771: aload 14
    //   2773: ifnonnull +70 -> 2843
    //   2776: aload 15
    //   2778: getfield 129	com/google/android/gms/measurement/internal/zzgn:zzs	Lcom/google/android/gms/measurement/internal/zzfu;
    //   2781: invokevirtual 193	com/google/android/gms/measurement/internal/zzfu:zzau	()Lcom/google/android/gms/measurement/internal/zzem;
    //   2784: invokevirtual 436	com/google/android/gms/measurement/internal/zzem:zze	()Lcom/google/android/gms/measurement/internal/zzek;
    //   2787: ldc_w 438
    //   2790: aload 16
    //   2792: invokestatic 204	com/google/android/gms/measurement/internal/zzem:zzl	(Ljava/lang/String;)Ljava/lang/Object;
    //   2795: aload 15
    //   2797: getfield 129	com/google/android/gms/measurement/internal/zzgn:zzs	Lcom/google/android/gms/measurement/internal/zzfu;
    //   2800: invokevirtual 441	com/google/android/gms/measurement/internal/zzfu:zzm	()Lcom/google/android/gms/measurement/internal/zzeh;
    //   2803: aload 13
    //   2805: invokevirtual 445	com/google/android/gms/measurement/internal/zzeh:zzc	(Ljava/lang/String;)Ljava/lang/String;
    //   2808: invokevirtual 209	com/google/android/gms/measurement/internal/zzek:zzc	(Ljava/lang/String;Ljava/lang/Object;Ljava/lang/Object;)V
    //   2811: new 447	com/google/android/gms/measurement/internal/zzao
    //   2814: dup
    //   2815: aload 16
    //   2817: aload 18
    //   2819: invokevirtual 114	com/google/android/gms/internal/measurement/zzfo:zzd	()Ljava/lang/String;
    //   2822: lconst_1
    //   2823: lconst_1
    //   2824: lconst_1
    //   2825: aload 18
    //   2827: invokevirtual 449	com/google/android/gms/internal/measurement/zzfo:zzf	()J
    //   2830: lconst_0
    //   2831: aconst_null
    //   2832: aconst_null
    //   2833: aconst_null
    //   2834: aconst_null
    //   2835: invokespecial 452	com/google/android/gms/measurement/internal/zzao:<init>	(Ljava/lang/String;Ljava/lang/String;JJJJJLjava/lang/Long;Ljava/lang/Long;Ljava/lang/Long;Ljava/lang/Boolean;)V
    //   2838: astore 12
    //   2840: goto +73 -> 2913
    //   2843: new 447	com/google/android/gms/measurement/internal/zzao
    //   2846: dup
    //   2847: aload 14
    //   2849: getfield 453	com/google/android/gms/measurement/internal/zzao:zza	Ljava/lang/String;
    //   2852: aload 14
    //   2854: getfield 455	com/google/android/gms/measurement/internal/zzao:zzb	Ljava/lang/String;
    //   2857: aload 14
    //   2859: getfield 458	com/google/android/gms/measurement/internal/zzao:zzc	J
    //   2862: lconst_1
    //   2863: ladd
    //   2864: aload 14
    //   2866: getfield 460	com/google/android/gms/measurement/internal/zzao:zzd	J
    //   2869: lconst_1
    //   2870: ladd
    //   2871: aload 14
    //   2873: getfield 462	com/google/android/gms/measurement/internal/zzao:zze	J
    //   2876: lconst_1
    //   2877: ladd
    //   2878: aload 14
    //   2880: getfield 464	com/google/android/gms/measurement/internal/zzao:zzf	J
    //   2883: aload 14
    //   2885: getfield 466	com/google/android/gms/measurement/internal/zzao:zzg	J
    //   2888: aload 14
    //   2890: getfield 468	com/google/android/gms/measurement/internal/zzao:zzh	Ljava/lang/Long;
    //   2893: aload 14
    //   2895: getfield 470	com/google/android/gms/measurement/internal/zzao:zzi	Ljava/lang/Long;
    //   2898: aload 14
    //   2900: getfield 472	com/google/android/gms/measurement/internal/zzao:zzj	Ljava/lang/Long;
    //   2903: aload 14
    //   2905: getfield 475	com/google/android/gms/measurement/internal/zzao:zzk	Ljava/lang/Boolean;
    //   2908: invokespecial 452	com/google/android/gms/measurement/internal/zzao:<init>	(Ljava/lang/String;Ljava/lang/String;JJJJJLjava/lang/Long;Ljava/lang/Long;Ljava/lang/Long;Ljava/lang/Boolean;)V
    //   2911: astore 12
    //   2913: aload_0
    //   2914: getfield 155	com/google/android/gms/measurement/internal/zzkd:zzf	Lcom/google/android/gms/measurement/internal/zzkn;
    //   2917: invokevirtual 161	com/google/android/gms/measurement/internal/zzkn:zzi	()Lcom/google/android/gms/measurement/internal/zzai;
    //   2920: aload 12
    //   2922: invokevirtual 478	com/google/android/gms/measurement/internal/zzai:zzh	(Lcom/google/android/gms/measurement/internal/zzao;)V
    //   2925: aload 12
    //   2927: getfield 458	com/google/android/gms/measurement/internal/zzao:zzc	J
    //   2930: lstore 25
    //   2932: aload 21
    //   2934: invokevirtual 114	com/google/android/gms/internal/measurement/zzfo:zzd	()Ljava/lang/String;
    //   2937: astore 23
    //   2939: aload 20
    //   2941: aload 23
    //   2943: invokeinterface 33 2 0
    //   2948: checkcast 25	java/util/Map
    //   2951: astore 13
    //   2953: aload 13
    //   2955: ifnonnull +539 -> 3494
    //   2958: aload_0
    //   2959: getfield 155	com/google/android/gms/measurement/internal/zzkd:zzf	Lcom/google/android/gms/measurement/internal/zzkn;
    //   2962: invokevirtual 161	com/google/android/gms/measurement/internal/zzkn:zzi	()Lcom/google/android/gms/measurement/internal/zzai;
    //   2965: astore 24
    //   2967: aload_0
    //   2968: getfield 37	com/google/android/gms/measurement/internal/zzy:zza	Ljava/lang/String;
    //   2971: astore 27
    //   2973: aload 24
    //   2975: invokevirtual 163	com/google/android/gms/measurement/internal/zzke:zzZ	()V
    //   2978: aload 24
    //   2980: invokevirtual 166	com/google/android/gms/measurement/internal/zzgn:zzg	()V
    //   2983: aload 27
    //   2985: invokestatic 75	com/google/android/gms/common/internal/Preconditions:checkNotEmpty	(Ljava/lang/String;)Ljava/lang/String;
    //   2988: pop
    //   2989: aload 23
    //   2991: invokestatic 75	com/google/android/gms/common/internal/Preconditions:checkNotEmpty	(Ljava/lang/String;)Ljava/lang/String;
    //   2994: pop
    //   2995: new 87	androidx/collection/ArrayMap
    //   2998: dup
    //   2999: invokespecial 88	androidx/collection/ArrayMap:<init>	()V
    //   3002: astore 17
    //   3004: aload 24
    //   3006: invokevirtual 179	com/google/android/gms/measurement/internal/zzai:zze	()Landroid/database/sqlite/SQLiteDatabase;
    //   3009: astore 15
    //   3011: aload_2
    //   3012: astore 13
    //   3014: aload 15
    //   3016: ldc -31
    //   3018: iconst_2
    //   3019: anewarray 116	java/lang/String
    //   3022: dup
    //   3023: iconst_0
    //   3024: aload 13
    //   3026: aastore
    //   3027: dup
    //   3028: iconst_1
    //   3029: aload 4
    //   3031: aastore
    //   3032: ldc_w 480
    //   3035: iconst_2
    //   3036: anewarray 116	java/lang/String
    //   3039: dup
    //   3040: iconst_0
    //   3041: aload 27
    //   3043: aastore
    //   3044: dup
    //   3045: iconst_1
    //   3046: aload 23
    //   3048: aastore
    //   3049: aconst_null
    //   3050: aconst_null
    //   3051: aconst_null
    //   3052: invokevirtual 231	android/database/sqlite/SQLiteDatabase:query	(Ljava/lang/String;[Ljava/lang/String;Ljava/lang/String;[Ljava/lang/String;Ljava/lang/String;Ljava/lang/String;Ljava/lang/String;)Landroid/database/Cursor;
    //   3055: astore 16
    //   3057: aload 16
    //   3059: astore 14
    //   3061: aload 16
    //   3063: invokeinterface 236 1 0
    //   3068: istore 8
    //   3070: iload 8
    //   3072: ifeq +249 -> 3321
    //   3075: aload 13
    //   3077: astore_2
    //   3078: aload 16
    //   3080: astore 14
    //   3082: aload 16
    //   3084: iconst_1
    //   3085: invokeinterface 240 2 0
    //   3090: astore 13
    //   3092: aload 16
    //   3094: astore 14
    //   3096: invokestatic 245	com/google/android/gms/internal/measurement/zzej:zzn	()Lcom/google/android/gms/internal/measurement/zzei;
    //   3099: aload 13
    //   3101: invokestatic 251	com/google/android/gms/measurement/internal/zzkp:zzt	(Lcom/google/android/gms/internal/measurement/zzlh;[B)Lcom/google/android/gms/internal/measurement/zzlh;
    //   3104: checkcast 253	com/google/android/gms/internal/measurement/zzei
    //   3107: invokevirtual 258	com/google/android/gms/internal/measurement/zzjz:zzaA	()Lcom/google/android/gms/internal/measurement/zzkd;
    //   3110: checkcast 242	com/google/android/gms/internal/measurement/zzej
    //   3113: astore 15
    //   3115: aload 16
    //   3117: astore 14
    //   3119: aload 16
    //   3121: iconst_0
    //   3122: invokeinterface 264 2 0
    //   3127: invokestatic 51	java/lang/Integer:valueOf	(I)Ljava/lang/Integer;
    //   3130: astore 18
    //   3132: aload 16
    //   3134: astore 14
    //   3136: aload 17
    //   3138: aload 18
    //   3140: invokeinterface 33 2 0
    //   3145: checkcast 94	java/util/List
    //   3148: astore 13
    //   3150: aload 13
    //   3152: ifnonnull +40 -> 3192
    //   3155: aload 16
    //   3157: astore 14
    //   3159: new 266	java/util/ArrayList
    //   3162: astore 13
    //   3164: aload 16
    //   3166: astore 14
    //   3168: aload 13
    //   3170: invokespecial 267	java/util/ArrayList:<init>	()V
    //   3173: aload 16
    //   3175: astore 14
    //   3177: aload 17
    //   3179: aload 18
    //   3181: aload 13
    //   3183: invokeinterface 44 3 0
    //   3188: pop
    //   3189: goto +3 -> 3192
    //   3192: aload 16
    //   3194: astore 14
    //   3196: aload 13
    //   3198: aload 15
    //   3200: invokeinterface 270 2 0
    //   3205: pop
    //   3206: goto +58 -> 3264
    //   3209: astore 28
    //   3211: aload_2
    //   3212: astore 15
    //   3214: aload 16
    //   3216: astore 14
    //   3218: aload 24
    //   3220: getfield 129	com/google/android/gms/measurement/internal/zzgn:zzs	Lcom/google/android/gms/measurement/internal/zzfu;
    //   3223: invokevirtual 193	com/google/android/gms/measurement/internal/zzfu:zzau	()Lcom/google/android/gms/measurement/internal/zzem;
    //   3226: invokevirtual 198	com/google/android/gms/measurement/internal/zzem:zzb	()Lcom/google/android/gms/measurement/internal/zzek;
    //   3229: astore 29
    //   3231: aload 16
    //   3233: astore 14
    //   3235: aload 27
    //   3237: invokestatic 204	com/google/android/gms/measurement/internal/zzem:zzl	(Ljava/lang/String;)Ljava/lang/Object;
    //   3240: astore 30
    //   3242: aload_1
    //   3243: astore 18
    //   3245: aload 18
    //   3247: astore 13
    //   3249: aload 16
    //   3251: astore 14
    //   3253: aload 29
    //   3255: aload 18
    //   3257: aload 30
    //   3259: aload 28
    //   3261: invokevirtual 209	com/google/android/gms/measurement/internal/zzek:zzc	(Ljava/lang/String;Ljava/lang/Object;Ljava/lang/Object;)V
    //   3264: aload_1
    //   3265: astore 13
    //   3267: aload_2
    //   3268: astore 15
    //   3270: aload 16
    //   3272: astore 14
    //   3274: aload 16
    //   3276: invokeinterface 273 1 0
    //   3281: istore 8
    //   3283: iload 8
    //   3285: ifne +23 -> 3308
    //   3288: aload 16
    //   3290: invokeinterface 276 1 0
    //   3295: aload 17
    //   3297: astore 13
    //   3299: aload_1
    //   3300: astore 15
    //   3302: aload_2
    //   3303: astore 14
    //   3305: goto +155 -> 3460
    //   3308: goto -230 -> 3078
    //   3311: astore 13
    //   3313: goto +66 -> 3379
    //   3316: astore 13
    //   3318: goto +61 -> 3379
    //   3321: aload 13
    //   3323: astore_2
    //   3324: aload_1
    //   3325: astore 13
    //   3327: aload_2
    //   3328: astore 15
    //   3330: aload 16
    //   3332: astore 14
    //   3334: invokestatic 215	java/util/Collections:emptyMap	()Ljava/util/Map;
    //   3337: astore 17
    //   3339: aload 17
    //   3341: astore 13
    //   3343: aload 16
    //   3345: invokeinterface 276 1 0
    //   3350: aload_1
    //   3351: astore 15
    //   3353: aload_2
    //   3354: astore 14
    //   3356: goto +104 -> 3460
    //   3359: astore 17
    //   3361: aload 13
    //   3363: astore_1
    //   3364: aload 15
    //   3366: astore_2
    //   3367: goto +35 -> 3402
    //   3370: astore 15
    //   3372: aload 13
    //   3374: astore_2
    //   3375: aload 15
    //   3377: astore 13
    //   3379: aload 13
    //   3381: astore 17
    //   3383: goto +19 -> 3402
    //   3386: astore 17
    //   3388: goto +11 -> 3399
    //   3391: astore_1
    //   3392: aconst_null
    //   3393: astore_2
    //   3394: goto +88 -> 3482
    //   3397: astore 13
    //   3399: aconst_null
    //   3400: astore 16
    //   3402: aload 16
    //   3404: astore 14
    //   3406: aload 24
    //   3408: getfield 129	com/google/android/gms/measurement/internal/zzgn:zzs	Lcom/google/android/gms/measurement/internal/zzfu;
    //   3411: invokevirtual 193	com/google/android/gms/measurement/internal/zzfu:zzau	()Lcom/google/android/gms/measurement/internal/zzem;
    //   3414: invokevirtual 198	com/google/android/gms/measurement/internal/zzem:zzb	()Lcom/google/android/gms/measurement/internal/zzek;
    //   3417: aload 11
    //   3419: aload 27
    //   3421: invokestatic 204	com/google/android/gms/measurement/internal/zzem:zzl	(Ljava/lang/String;)Ljava/lang/Object;
    //   3424: aload 17
    //   3426: invokevirtual 209	com/google/android/gms/measurement/internal/zzek:zzc	(Ljava/lang/String;Ljava/lang/Object;Ljava/lang/Object;)V
    //   3429: aload 16
    //   3431: astore 14
    //   3433: invokestatic 215	java/util/Collections:emptyMap	()Ljava/util/Map;
    //   3436: astore 17
    //   3438: aload 17
    //   3440: astore 13
    //   3442: aload_1
    //   3443: astore 15
    //   3445: aload_2
    //   3446: astore 14
    //   3448: aload 16
    //   3450: ifnull +10 -> 3460
    //   3453: aload 17
    //   3455: astore 13
    //   3457: goto -114 -> 3343
    //   3460: aload 20
    //   3462: aload 23
    //   3464: aload 13
    //   3466: invokeinterface 44 3 0
    //   3471: pop
    //   3472: aload 14
    //   3474: astore_2
    //   3475: goto +22 -> 3497
    //   3478: astore_1
    //   3479: aload 14
    //   3481: astore_2
    //   3482: aload_2
    //   3483: ifnull +9 -> 3492
    //   3486: aload_2
    //   3487: invokeinterface 276 1 0
    //   3492: aload_1
    //   3493: athrow
    //   3494: aload_1
    //   3495: astore 15
    //   3497: aload 13
    //   3499: invokeinterface 300 1 0
    //   3504: invokeinterface 314 1 0
    //   3509: astore_1
    //   3510: aload_1
    //   3511: invokeinterface 103 1 0
    //   3516: ifeq +220 -> 3736
    //   3519: aload_1
    //   3520: invokeinterface 109 1 0
    //   3525: checkcast 47	java/lang/Integer
    //   3528: invokevirtual 318	java/lang/Integer:intValue	()I
    //   3531: istore 7
    //   3533: aload_0
    //   3534: getfield 85	com/google/android/gms/measurement/internal/zzy:zzb	Ljava/util/Set;
    //   3537: astore 14
    //   3539: iload 7
    //   3541: invokestatic 51	java/lang/Integer:valueOf	(I)Ljava/lang/Integer;
    //   3544: astore 16
    //   3546: aload 14
    //   3548: aload 16
    //   3550: invokeinterface 481 2 0
    //   3555: ifeq +24 -> 3579
    //   3558: aload_0
    //   3559: getfield 129	com/google/android/gms/measurement/internal/zzgn:zzs	Lcom/google/android/gms/measurement/internal/zzfu;
    //   3562: invokevirtual 193	com/google/android/gms/measurement/internal/zzfu:zzau	()Lcom/google/android/gms/measurement/internal/zzem;
    //   3565: invokevirtual 403	com/google/android/gms/measurement/internal/zzem:zzk	()Lcom/google/android/gms/measurement/internal/zzek;
    //   3568: ldc_w 483
    //   3571: aload 16
    //   3573: invokevirtual 486	com/google/android/gms/measurement/internal/zzek:zzb	(Ljava/lang/String;Ljava/lang/Object;)V
    //   3576: goto -66 -> 3510
    //   3579: aload 13
    //   3581: aload 16
    //   3583: invokeinterface 33 2 0
    //   3588: checkcast 94	java/util/List
    //   3591: invokeinterface 98 1 0
    //   3596: astore 16
    //   3598: iconst_1
    //   3599: istore 8
    //   3601: aload 16
    //   3603: invokeinterface 103 1 0
    //   3608: ifeq +105 -> 3713
    //   3611: aload 16
    //   3613: invokeinterface 109 1 0
    //   3618: checkcast 242	com/google/android/gms/internal/measurement/zzej
    //   3621: astore 14
    //   3623: new 488	com/google/android/gms/measurement/internal/zzv
    //   3626: dup
    //   3627: aload_0
    //   3628: aload_0
    //   3629: getfield 37	com/google/android/gms/measurement/internal/zzy:zza	Ljava/lang/String;
    //   3632: iload 7
    //   3634: aload 14
    //   3636: invokespecial 491	com/google/android/gms/measurement/internal/zzv:<init>	(Lcom/google/android/gms/measurement/internal/zzy;Ljava/lang/String;ILcom/google/android/gms/internal/measurement/zzej;)V
    //   3639: astore 17
    //   3641: aload 17
    //   3643: aload_0
    //   3644: getfield 90	com/google/android/gms/measurement/internal/zzy:zzd	Ljava/lang/Long;
    //   3647: aload_0
    //   3648: getfield 92	com/google/android/gms/measurement/internal/zzy:zze	Ljava/lang/Long;
    //   3651: aload 21
    //   3653: lload 25
    //   3655: aload 12
    //   3657: aload_0
    //   3658: iload 7
    //   3660: aload 14
    //   3662: invokevirtual 413	com/google/android/gms/internal/measurement/zzej:zzb	()I
    //   3665: invokespecial 493	com/google/android/gms/measurement/internal/zzy:zzd	(II)Z
    //   3668: invokevirtual 496	com/google/android/gms/measurement/internal/zzv:zzd	(Ljava/lang/Long;Ljava/lang/Long;Lcom/google/android/gms/internal/measurement/zzfo;JLcom/google/android/gms/measurement/internal/zzao;Z)Z
    //   3671: istore 8
    //   3673: iload 8
    //   3675: ifeq +20 -> 3695
    //   3678: aload_0
    //   3679: iload 7
    //   3681: invokestatic 51	java/lang/Integer:valueOf	(I)Ljava/lang/Integer;
    //   3684: invokespecial 498	com/google/android/gms/measurement/internal/zzy:zzc	(Ljava/lang/Integer;)Lcom/google/android/gms/measurement/internal/zzt;
    //   3687: aload 17
    //   3689: invokevirtual 501	com/google/android/gms/measurement/internal/zzt:zza	(Lcom/google/android/gms/measurement/internal/zzw;)V
    //   3692: goto -91 -> 3601
    //   3695: aload_0
    //   3696: getfield 85	com/google/android/gms/measurement/internal/zzy:zzb	Ljava/util/Set;
    //   3699: iload 7
    //   3701: invokestatic 51	java/lang/Integer:valueOf	(I)Ljava/lang/Integer;
    //   3704: invokeinterface 502 2 0
    //   3709: pop
    //   3710: goto +3 -> 3713
    //   3713: iload 8
    //   3715: ifne +18 -> 3733
    //   3718: aload_0
    //   3719: getfield 85	com/google/android/gms/measurement/internal/zzy:zzb	Ljava/util/Set;
    //   3722: iload 7
    //   3724: invokestatic 51	java/lang/Integer:valueOf	(I)Ljava/lang/Integer;
    //   3727: invokeinterface 502 2 0
    //   3732: pop
    //   3733: goto -223 -> 3510
    //   3736: aload 15
    //   3738: astore 13
    //   3740: aload 4
    //   3742: astore 15
    //   3744: aload_2
    //   3745: astore 16
    //   3747: aload 5
    //   3749: astore 14
    //   3751: aload 10
    //   3753: astore 17
    //   3755: aload 6
    //   3757: astore 12
    //   3759: aload 12
    //   3761: astore 6
    //   3763: aload 17
    //   3765: astore 10
    //   3767: aload 14
    //   3769: astore 5
    //   3771: aload 16
    //   3773: astore_2
    //   3774: aload 15
    //   3776: astore 4
    //   3778: aload 13
    //   3780: astore_1
    //   3781: goto -1119 -> 2662
    //   3784: aload_3
    //   3785: invokeinterface 319 1 0
    //   3790: ifeq +9 -> 3799
    //   3793: aload 13
    //   3795: astore_2
    //   3796: goto +948 -> 4744
    //   3799: new 87	androidx/collection/ArrayMap
    //   3802: dup
    //   3803: invokespecial 88	androidx/collection/ArrayMap:<init>	()V
    //   3806: astore 6
    //   3808: aload_3
    //   3809: invokeinterface 98 1 0
    //   3814: astore_1
    //   3815: aload 13
    //   3817: astore_2
    //   3818: aload_1
    //   3819: invokeinterface 103 1 0
    //   3824: ifeq -28 -> 3796
    //   3827: aload_1
    //   3828: invokeinterface 109 1 0
    //   3833: checkcast 504	com/google/android/gms/internal/measurement/zzgh
    //   3836: astore 10
    //   3838: aload 10
    //   3840: invokevirtual 506	com/google/android/gms/internal/measurement/zzgh:zzc	()Ljava/lang/String;
    //   3843: astore 17
    //   3845: aload 6
    //   3847: aload 17
    //   3849: invokeinterface 33 2 0
    //   3854: checkcast 25	java/util/Map
    //   3857: astore_2
    //   3858: aload_2
    //   3859: ifnonnull +455 -> 4314
    //   3862: aload_0
    //   3863: getfield 155	com/google/android/gms/measurement/internal/zzkd:zzf	Lcom/google/android/gms/measurement/internal/zzkn;
    //   3866: invokevirtual 161	com/google/android/gms/measurement/internal/zzkn:zzi	()Lcom/google/android/gms/measurement/internal/zzai;
    //   3869: astore 12
    //   3871: aload_0
    //   3872: getfield 37	com/google/android/gms/measurement/internal/zzy:zza	Ljava/lang/String;
    //   3875: astore 18
    //   3877: aload 12
    //   3879: invokevirtual 163	com/google/android/gms/measurement/internal/zzke:zzZ	()V
    //   3882: aload 12
    //   3884: invokevirtual 166	com/google/android/gms/measurement/internal/zzgn:zzg	()V
    //   3887: aload 18
    //   3889: invokestatic 75	com/google/android/gms/common/internal/Preconditions:checkNotEmpty	(Ljava/lang/String;)Ljava/lang/String;
    //   3892: pop
    //   3893: aload 17
    //   3895: invokestatic 75	com/google/android/gms/common/internal/Preconditions:checkNotEmpty	(Ljava/lang/String;)Ljava/lang/String;
    //   3898: pop
    //   3899: new 87	androidx/collection/ArrayMap
    //   3902: dup
    //   3903: invokespecial 88	androidx/collection/ArrayMap:<init>	()V
    //   3906: astore 14
    //   3908: aload 12
    //   3910: invokevirtual 179	com/google/android/gms/measurement/internal/zzai:zze	()Landroid/database/sqlite/SQLiteDatabase;
    //   3913: astore_2
    //   3914: aload_2
    //   3915: ldc_w 508
    //   3918: iconst_2
    //   3919: anewarray 116	java/lang/String
    //   3922: dup
    //   3923: iconst_0
    //   3924: aload 13
    //   3926: aastore
    //   3927: dup
    //   3928: iconst_1
    //   3929: aload 15
    //   3931: aastore
    //   3932: ldc_w 510
    //   3935: iconst_2
    //   3936: anewarray 116	java/lang/String
    //   3939: dup
    //   3940: iconst_0
    //   3941: aload 18
    //   3943: aastore
    //   3944: dup
    //   3945: iconst_1
    //   3946: aload 17
    //   3948: aastore
    //   3949: aconst_null
    //   3950: aconst_null
    //   3951: aconst_null
    //   3952: invokevirtual 231	android/database/sqlite/SQLiteDatabase:query	(Ljava/lang/String;[Ljava/lang/String;Ljava/lang/String;[Ljava/lang/String;Ljava/lang/String;Ljava/lang/String;Ljava/lang/String;)Landroid/database/Cursor;
    //   3955: astore_3
    //   3956: aload_1
    //   3957: astore_2
    //   3958: aload_3
    //   3959: astore 4
    //   3961: aload_3
    //   3962: invokeinterface 236 1 0
    //   3967: ifeq +216 -> 4183
    //   3970: aload_1
    //   3971: astore_2
    //   3972: aload_3
    //   3973: astore 4
    //   3975: aload_3
    //   3976: iconst_1
    //   3977: invokeinterface 240 2 0
    //   3982: astore 5
    //   3984: aload_1
    //   3985: astore_2
    //   3986: aload_3
    //   3987: astore 4
    //   3989: invokestatic 515	com/google/android/gms/internal/measurement/zzes:zzi	()Lcom/google/android/gms/internal/measurement/zzer;
    //   3992: aload 5
    //   3994: invokestatic 251	com/google/android/gms/measurement/internal/zzkp:zzt	(Lcom/google/android/gms/internal/measurement/zzlh;[B)Lcom/google/android/gms/internal/measurement/zzlh;
    //   3997: checkcast 517	com/google/android/gms/internal/measurement/zzer
    //   4000: invokevirtual 258	com/google/android/gms/internal/measurement/zzjz:zzaA	()Lcom/google/android/gms/internal/measurement/zzkd;
    //   4003: checkcast 512	com/google/android/gms/internal/measurement/zzes
    //   4006: astore 20
    //   4008: aload_1
    //   4009: astore_2
    //   4010: aload_3
    //   4011: astore 4
    //   4013: aload_3
    //   4014: iconst_0
    //   4015: invokeinterface 264 2 0
    //   4020: invokestatic 51	java/lang/Integer:valueOf	(I)Ljava/lang/Integer;
    //   4023: astore 21
    //   4025: aload_1
    //   4026: astore_2
    //   4027: aload_3
    //   4028: astore 4
    //   4030: aload 14
    //   4032: aload 21
    //   4034: invokeinterface 33 2 0
    //   4039: checkcast 94	java/util/List
    //   4042: astore 5
    //   4044: aload 5
    //   4046: ifnonnull +43 -> 4089
    //   4049: aload_1
    //   4050: astore_2
    //   4051: aload_3
    //   4052: astore 4
    //   4054: new 266	java/util/ArrayList
    //   4057: astore 5
    //   4059: aload_1
    //   4060: astore_2
    //   4061: aload_3
    //   4062: astore 4
    //   4064: aload 5
    //   4066: invokespecial 267	java/util/ArrayList:<init>	()V
    //   4069: aload_1
    //   4070: astore_2
    //   4071: aload_3
    //   4072: astore 4
    //   4074: aload 14
    //   4076: aload 21
    //   4078: aload 5
    //   4080: invokeinterface 44 3 0
    //   4085: pop
    //   4086: goto +3 -> 4089
    //   4089: aload_1
    //   4090: astore_2
    //   4091: aload_3
    //   4092: astore 4
    //   4094: aload 5
    //   4096: aload 20
    //   4098: invokeinterface 270 2 0
    //   4103: pop
    //   4104: goto +43 -> 4147
    //   4107: astore 5
    //   4109: aload_1
    //   4110: astore_2
    //   4111: aload_3
    //   4112: astore 4
    //   4114: aload 12
    //   4116: getfield 129	com/google/android/gms/measurement/internal/zzgn:zzs	Lcom/google/android/gms/measurement/internal/zzfu;
    //   4119: invokevirtual 193	com/google/android/gms/measurement/internal/zzfu:zzau	()Lcom/google/android/gms/measurement/internal/zzem;
    //   4122: invokevirtual 198	com/google/android/gms/measurement/internal/zzem:zzb	()Lcom/google/android/gms/measurement/internal/zzek;
    //   4125: astore 20
    //   4127: aload_1
    //   4128: astore_2
    //   4129: aload_3
    //   4130: astore 4
    //   4132: aload 20
    //   4134: ldc_w 519
    //   4137: aload 18
    //   4139: invokestatic 204	com/google/android/gms/measurement/internal/zzem:zzl	(Ljava/lang/String;)Ljava/lang/Object;
    //   4142: aload 5
    //   4144: invokevirtual 209	com/google/android/gms/measurement/internal/zzek:zzc	(Ljava/lang/String;Ljava/lang/Object;Ljava/lang/Object;)V
    //   4147: aload_1
    //   4148: astore_2
    //   4149: aload_3
    //   4150: astore 4
    //   4152: aload_3
    //   4153: invokeinterface 273 1 0
    //   4158: istore 8
    //   4160: iload 8
    //   4162: ifne +18 -> 4180
    //   4165: aload_3
    //   4166: invokeinterface 276 1 0
    //   4171: aload 14
    //   4173: astore_2
    //   4174: aload_1
    //   4175: astore 4
    //   4177: goto +105 -> 4282
    //   4180: goto -210 -> 3970
    //   4183: aload_1
    //   4184: astore_2
    //   4185: aload_3
    //   4186: astore 4
    //   4188: invokestatic 215	java/util/Collections:emptyMap	()Ljava/util/Map;
    //   4191: astore 5
    //   4193: aload 5
    //   4195: astore_2
    //   4196: aload_3
    //   4197: invokeinterface 276 1 0
    //   4202: aload_1
    //   4203: astore 4
    //   4205: goto +77 -> 4282
    //   4208: astore 5
    //   4210: aload_2
    //   4211: astore_1
    //   4212: goto +20 -> 4232
    //   4215: astore 5
    //   4217: aload_2
    //   4218: astore_1
    //   4219: goto +13 -> 4232
    //   4222: astore_1
    //   4223: aconst_null
    //   4224: astore_2
    //   4225: goto +77 -> 4302
    //   4228: astore 5
    //   4230: aconst_null
    //   4231: astore_3
    //   4232: aload_3
    //   4233: astore 4
    //   4235: aload 12
    //   4237: getfield 129	com/google/android/gms/measurement/internal/zzgn:zzs	Lcom/google/android/gms/measurement/internal/zzfu;
    //   4240: invokevirtual 193	com/google/android/gms/measurement/internal/zzfu:zzau	()Lcom/google/android/gms/measurement/internal/zzem;
    //   4243: invokevirtual 198	com/google/android/gms/measurement/internal/zzem:zzb	()Lcom/google/android/gms/measurement/internal/zzek;
    //   4246: aload 11
    //   4248: aload 18
    //   4250: invokestatic 204	com/google/android/gms/measurement/internal/zzem:zzl	(Ljava/lang/String;)Ljava/lang/Object;
    //   4253: aload 5
    //   4255: invokevirtual 209	com/google/android/gms/measurement/internal/zzek:zzc	(Ljava/lang/String;Ljava/lang/Object;Ljava/lang/Object;)V
    //   4258: aload_3
    //   4259: astore 4
    //   4261: invokestatic 215	java/util/Collections:emptyMap	()Ljava/util/Map;
    //   4264: astore 5
    //   4266: aload 5
    //   4268: astore_2
    //   4269: aload_1
    //   4270: astore 4
    //   4272: aload_3
    //   4273: ifnull +9 -> 4282
    //   4276: aload 5
    //   4278: astore_2
    //   4279: goto -83 -> 4196
    //   4282: aload 6
    //   4284: aload 17
    //   4286: aload_2
    //   4287: invokeinterface 44 3 0
    //   4292: pop
    //   4293: aload_2
    //   4294: astore_1
    //   4295: goto +24 -> 4319
    //   4298: astore_1
    //   4299: aload 4
    //   4301: astore_2
    //   4302: aload_2
    //   4303: ifnull +9 -> 4312
    //   4306: aload_2
    //   4307: invokeinterface 276 1 0
    //   4312: aload_1
    //   4313: athrow
    //   4314: aload_1
    //   4315: astore 4
    //   4317: aload_2
    //   4318: astore_1
    //   4319: aload_1
    //   4320: invokeinterface 300 1 0
    //   4325: invokeinterface 314 1 0
    //   4330: astore_3
    //   4331: aload_3
    //   4332: invokeinterface 103 1 0
    //   4337: ifeq +401 -> 4738
    //   4340: aload_3
    //   4341: invokeinterface 109 1 0
    //   4346: checkcast 47	java/lang/Integer
    //   4349: invokevirtual 318	java/lang/Integer:intValue	()I
    //   4352: istore 7
    //   4354: aload_0
    //   4355: getfield 85	com/google/android/gms/measurement/internal/zzy:zzb	Ljava/util/Set;
    //   4358: astore 5
    //   4360: iload 7
    //   4362: invokestatic 51	java/lang/Integer:valueOf	(I)Ljava/lang/Integer;
    //   4365: astore_2
    //   4366: aload 5
    //   4368: aload_2
    //   4369: invokeinterface 481 2 0
    //   4374: ifeq +23 -> 4397
    //   4377: aload_0
    //   4378: getfield 129	com/google/android/gms/measurement/internal/zzgn:zzs	Lcom/google/android/gms/measurement/internal/zzfu;
    //   4381: invokevirtual 193	com/google/android/gms/measurement/internal/zzfu:zzau	()Lcom/google/android/gms/measurement/internal/zzem;
    //   4384: invokevirtual 403	com/google/android/gms/measurement/internal/zzem:zzk	()Lcom/google/android/gms/measurement/internal/zzek;
    //   4387: ldc_w 483
    //   4390: aload_2
    //   4391: invokevirtual 486	com/google/android/gms/measurement/internal/zzek:zzb	(Ljava/lang/String;Ljava/lang/Object;)V
    //   4394: goto +344 -> 4738
    //   4397: aload_1
    //   4398: aload_2
    //   4399: invokeinterface 33 2 0
    //   4404: checkcast 94	java/util/List
    //   4407: invokeinterface 98 1 0
    //   4412: astore 5
    //   4414: iconst_1
    //   4415: istore 8
    //   4417: aload 5
    //   4419: invokeinterface 103 1 0
    //   4424: ifeq +291 -> 4715
    //   4427: aload 5
    //   4429: invokeinterface 109 1 0
    //   4434: checkcast 512	com/google/android/gms/internal/measurement/zzes
    //   4437: astore 14
    //   4439: aload_0
    //   4440: getfield 129	com/google/android/gms/measurement/internal/zzgn:zzs	Lcom/google/android/gms/measurement/internal/zzfu;
    //   4443: invokevirtual 193	com/google/android/gms/measurement/internal/zzfu:zzau	()Lcom/google/android/gms/measurement/internal/zzem;
    //   4446: invokevirtual 521	com/google/android/gms/measurement/internal/zzem:zzn	()Ljava/lang/String;
    //   4449: iconst_2
    //   4450: invokestatic 527	android/util/Log:isLoggable	(Ljava/lang/String;I)Z
    //   4453: ifeq +97 -> 4550
    //   4456: aload_0
    //   4457: getfield 129	com/google/android/gms/measurement/internal/zzgn:zzs	Lcom/google/android/gms/measurement/internal/zzfu;
    //   4460: invokevirtual 193	com/google/android/gms/measurement/internal/zzfu:zzau	()Lcom/google/android/gms/measurement/internal/zzem;
    //   4463: invokevirtual 403	com/google/android/gms/measurement/internal/zzem:zzk	()Lcom/google/android/gms/measurement/internal/zzek;
    //   4466: astore 17
    //   4468: aload 14
    //   4470: invokevirtual 528	com/google/android/gms/internal/measurement/zzes:zza	()Z
    //   4473: ifeq +15 -> 4488
    //   4476: aload 14
    //   4478: invokevirtual 529	com/google/android/gms/internal/measurement/zzes:zzb	()I
    //   4481: invokestatic 51	java/lang/Integer:valueOf	(I)Ljava/lang/Integer;
    //   4484: astore_2
    //   4485: goto +5 -> 4490
    //   4488: aconst_null
    //   4489: astore_2
    //   4490: aload 17
    //   4492: ldc_w 531
    //   4495: iload 7
    //   4497: invokestatic 51	java/lang/Integer:valueOf	(I)Ljava/lang/Integer;
    //   4500: aload_2
    //   4501: aload_0
    //   4502: getfield 129	com/google/android/gms/measurement/internal/zzgn:zzs	Lcom/google/android/gms/measurement/internal/zzfu;
    //   4505: invokevirtual 441	com/google/android/gms/measurement/internal/zzfu:zzm	()Lcom/google/android/gms/measurement/internal/zzeh;
    //   4508: aload 14
    //   4510: invokevirtual 532	com/google/android/gms/internal/measurement/zzes:zzc	()Ljava/lang/String;
    //   4513: invokevirtual 534	com/google/android/gms/measurement/internal/zzeh:zze	(Ljava/lang/String;)Ljava/lang/String;
    //   4516: invokevirtual 291	com/google/android/gms/measurement/internal/zzek:zzd	(Ljava/lang/String;Ljava/lang/Object;Ljava/lang/Object;Ljava/lang/Object;)V
    //   4519: aload_0
    //   4520: getfield 129	com/google/android/gms/measurement/internal/zzgn:zzs	Lcom/google/android/gms/measurement/internal/zzfu;
    //   4523: invokevirtual 193	com/google/android/gms/measurement/internal/zzfu:zzau	()Lcom/google/android/gms/measurement/internal/zzem;
    //   4526: invokevirtual 403	com/google/android/gms/measurement/internal/zzem:zzk	()Lcom/google/android/gms/measurement/internal/zzek;
    //   4529: ldc_w 536
    //   4532: aload_0
    //   4533: getfield 155	com/google/android/gms/measurement/internal/zzkd:zzf	Lcom/google/android/gms/measurement/internal/zzkn;
    //   4536: invokevirtual 323	com/google/android/gms/measurement/internal/zzkn:zzm	()Lcom/google/android/gms/measurement/internal/zzkp;
    //   4539: aload 14
    //   4541: invokevirtual 539	com/google/android/gms/measurement/internal/zzkp:zzj	(Lcom/google/android/gms/internal/measurement/zzes;)Ljava/lang/String;
    //   4544: invokevirtual 486	com/google/android/gms/measurement/internal/zzek:zzb	(Ljava/lang/String;Ljava/lang/Object;)V
    //   4547: goto +3 -> 4550
    //   4550: aload 14
    //   4552: invokevirtual 528	com/google/android/gms/internal/measurement/zzes:zza	()Z
    //   4555: ifeq +100 -> 4655
    //   4558: aload 14
    //   4560: invokevirtual 529	com/google/android/gms/internal/measurement/zzes:zzb	()I
    //   4563: sipush 256
    //   4566: if_icmple +6 -> 4572
    //   4569: goto +86 -> 4655
    //   4572: new 541	com/google/android/gms/measurement/internal/zzx
    //   4575: dup
    //   4576: aload_0
    //   4577: aload_0
    //   4578: getfield 37	com/google/android/gms/measurement/internal/zzy:zza	Ljava/lang/String;
    //   4581: iload 7
    //   4583: aload 14
    //   4585: invokespecial 544	com/google/android/gms/measurement/internal/zzx:<init>	(Lcom/google/android/gms/measurement/internal/zzy;Ljava/lang/String;ILcom/google/android/gms/internal/measurement/zzes;)V
    //   4588: astore_2
    //   4589: aload_2
    //   4590: aload_0
    //   4591: getfield 90	com/google/android/gms/measurement/internal/zzy:zzd	Ljava/lang/Long;
    //   4594: aload_0
    //   4595: getfield 92	com/google/android/gms/measurement/internal/zzy:zze	Ljava/lang/Long;
    //   4598: aload 10
    //   4600: aload_0
    //   4601: iload 7
    //   4603: aload 14
    //   4605: invokevirtual 529	com/google/android/gms/internal/measurement/zzes:zzb	()I
    //   4608: invokespecial 493	com/google/android/gms/measurement/internal/zzy:zzd	(II)Z
    //   4611: invokevirtual 547	com/google/android/gms/measurement/internal/zzx:zzd	(Ljava/lang/Long;Ljava/lang/Long;Lcom/google/android/gms/internal/measurement/zzgh;Z)Z
    //   4614: istore 8
    //   4616: iload 8
    //   4618: ifeq +19 -> 4637
    //   4621: aload_0
    //   4622: iload 7
    //   4624: invokestatic 51	java/lang/Integer:valueOf	(I)Ljava/lang/Integer;
    //   4627: invokespecial 498	com/google/android/gms/measurement/internal/zzy:zzc	(Ljava/lang/Integer;)Lcom/google/android/gms/measurement/internal/zzt;
    //   4630: aload_2
    //   4631: invokevirtual 501	com/google/android/gms/measurement/internal/zzt:zza	(Lcom/google/android/gms/measurement/internal/zzw;)V
    //   4634: goto -217 -> 4417
    //   4637: aload_0
    //   4638: getfield 85	com/google/android/gms/measurement/internal/zzy:zzb	Ljava/util/Set;
    //   4641: iload 7
    //   4643: invokestatic 51	java/lang/Integer:valueOf	(I)Ljava/lang/Integer;
    //   4646: invokeinterface 502 2 0
    //   4651: pop
    //   4652: goto +63 -> 4715
    //   4655: aload_0
    //   4656: getfield 129	com/google/android/gms/measurement/internal/zzgn:zzs	Lcom/google/android/gms/measurement/internal/zzfu;
    //   4659: invokevirtual 193	com/google/android/gms/measurement/internal/zzfu:zzau	()Lcom/google/android/gms/measurement/internal/zzem;
    //   4662: invokevirtual 436	com/google/android/gms/measurement/internal/zzem:zze	()Lcom/google/android/gms/measurement/internal/zzek;
    //   4665: astore 5
    //   4667: aload_0
    //   4668: getfield 37	com/google/android/gms/measurement/internal/zzy:zza	Ljava/lang/String;
    //   4671: invokestatic 204	com/google/android/gms/measurement/internal/zzem:zzl	(Ljava/lang/String;)Ljava/lang/Object;
    //   4674: astore 17
    //   4676: aload 14
    //   4678: invokevirtual 528	com/google/android/gms/internal/measurement/zzes:zza	()Z
    //   4681: ifeq +15 -> 4696
    //   4684: aload 14
    //   4686: invokevirtual 529	com/google/android/gms/internal/measurement/zzes:zzb	()I
    //   4689: invokestatic 51	java/lang/Integer:valueOf	(I)Ljava/lang/Integer;
    //   4692: astore_2
    //   4693: goto +5 -> 4698
    //   4696: aconst_null
    //   4697: astore_2
    //   4698: aload 5
    //   4700: ldc_w 549
    //   4703: aload 17
    //   4705: aload_2
    //   4706: invokestatic 552	java/lang/String:valueOf	(Ljava/lang/Object;)Ljava/lang/String;
    //   4709: invokevirtual 209	com/google/android/gms/measurement/internal/zzek:zzc	(Ljava/lang/String;Ljava/lang/Object;Ljava/lang/Object;)V
    //   4712: goto +8 -> 4720
    //   4715: iload 8
    //   4717: ifne +18 -> 4735
    //   4720: aload_0
    //   4721: getfield 85	com/google/android/gms/measurement/internal/zzy:zzb	Ljava/util/Set;
    //   4724: iload 7
    //   4726: invokestatic 51	java/lang/Integer:valueOf	(I)Ljava/lang/Integer;
    //   4729: invokeinterface 502 2 0
    //   4734: pop
    //   4735: goto -404 -> 4331
    //   4738: aload 4
    //   4740: astore_1
    //   4741: goto -926 -> 3815
    //   4744: new 266	java/util/ArrayList
    //   4747: dup
    //   4748: invokespecial 267	java/util/ArrayList:<init>	()V
    //   4751: astore_3
    //   4752: aload_0
    //   4753: getfield 23	com/google/android/gms/measurement/internal/zzy:zzc	Ljava/util/Map;
    //   4756: invokeinterface 300 1 0
    //   4761: astore_1
    //   4762: aload_1
    //   4763: aload_0
    //   4764: getfield 85	com/google/android/gms/measurement/internal/zzy:zzb	Ljava/util/Set;
    //   4767: invokeinterface 556 2 0
    //   4772: pop
    //   4773: aload_1
    //   4774: invokeinterface 314 1 0
    //   4779: astore 4
    //   4781: aload 4
    //   4783: invokeinterface 103 1 0
    //   4788: ifeq +233 -> 5021
    //   4791: aload 4
    //   4793: invokeinterface 109 1 0
    //   4798: checkcast 47	java/lang/Integer
    //   4801: invokevirtual 318	java/lang/Integer:intValue	()I
    //   4804: istore 7
    //   4806: aload_0
    //   4807: getfield 23	com/google/android/gms/measurement/internal/zzy:zzc	Ljava/util/Map;
    //   4810: astore 5
    //   4812: iload 7
    //   4814: invokestatic 51	java/lang/Integer:valueOf	(I)Ljava/lang/Integer;
    //   4817: astore_1
    //   4818: aload 5
    //   4820: aload_1
    //   4821: invokeinterface 33 2 0
    //   4826: checkcast 35	com/google/android/gms/measurement/internal/zzt
    //   4829: astore 5
    //   4831: aload 5
    //   4833: invokestatic 78	com/google/android/gms/common/internal/Preconditions:checkNotNull	(Ljava/lang/Object;)Ljava/lang/Object;
    //   4836: pop
    //   4837: aload 5
    //   4839: iload 7
    //   4841: invokevirtual 559	com/google/android/gms/measurement/internal/zzt:zzb	(I)Lcom/google/android/gms/internal/measurement/zzfk;
    //   4844: astore 15
    //   4846: aload_3
    //   4847: aload 15
    //   4849: invokeinterface 270 2 0
    //   4854: pop
    //   4855: aload_0
    //   4856: getfield 155	com/google/android/gms/measurement/internal/zzkd:zzf	Lcom/google/android/gms/measurement/internal/zzkn;
    //   4859: invokevirtual 161	com/google/android/gms/measurement/internal/zzkn:zzi	()Lcom/google/android/gms/measurement/internal/zzai;
    //   4862: astore 13
    //   4864: aload_0
    //   4865: getfield 37	com/google/android/gms/measurement/internal/zzy:zza	Ljava/lang/String;
    //   4868: astore 5
    //   4870: aload 15
    //   4872: invokevirtual 564	com/google/android/gms/internal/measurement/zzfk:zzc	()Lcom/google/android/gms/internal/measurement/zzgd;
    //   4875: astore 15
    //   4877: aload 13
    //   4879: invokevirtual 163	com/google/android/gms/measurement/internal/zzke:zzZ	()V
    //   4882: aload 13
    //   4884: invokevirtual 166	com/google/android/gms/measurement/internal/zzgn:zzg	()V
    //   4887: aload 5
    //   4889: invokestatic 75	com/google/android/gms/common/internal/Preconditions:checkNotEmpty	(Ljava/lang/String;)Ljava/lang/String;
    //   4892: pop
    //   4893: aload 15
    //   4895: invokestatic 78	com/google/android/gms/common/internal/Preconditions:checkNotNull	(Ljava/lang/Object;)Ljava/lang/Object;
    //   4898: pop
    //   4899: aload 15
    //   4901: invokevirtual 570	com/google/android/gms/internal/measurement/zzio:zzbp	()[B
    //   4904: astore 14
    //   4906: new 168	android/content/ContentValues
    //   4909: dup
    //   4910: invokespecial 169	android/content/ContentValues:<init>	()V
    //   4913: astore 15
    //   4915: aload 15
    //   4917: ldc_w 572
    //   4920: aload 5
    //   4922: invokevirtual 575	android/content/ContentValues:put	(Ljava/lang/String;Ljava/lang/String;)V
    //   4925: aload 15
    //   4927: aload_2
    //   4928: aload_1
    //   4929: invokevirtual 174	android/content/ContentValues:put	(Ljava/lang/String;Ljava/lang/Integer;)V
    //   4932: aload 15
    //   4934: aload 16
    //   4936: aload 14
    //   4938: invokevirtual 578	android/content/ContentValues:put	(Ljava/lang/String;[B)V
    //   4941: aload 13
    //   4943: invokevirtual 179	com/google/android/gms/measurement/internal/zzai:zze	()Landroid/database/sqlite/SQLiteDatabase;
    //   4946: astore_1
    //   4947: aload_1
    //   4948: ldc_w 278
    //   4951: aconst_null
    //   4952: aload 15
    //   4954: iconst_5
    //   4955: invokevirtual 582	android/database/sqlite/SQLiteDatabase:insertWithOnConflict	(Ljava/lang/String;Ljava/lang/String;Landroid/content/ContentValues;I)J
    //   4958: ldc2_w 583
    //   4961: lcmp
    //   4962: ifne +56 -> 5018
    //   4965: aload 13
    //   4967: getfield 129	com/google/android/gms/measurement/internal/zzgn:zzs	Lcom/google/android/gms/measurement/internal/zzfu;
    //   4970: invokevirtual 193	com/google/android/gms/measurement/internal/zzfu:zzau	()Lcom/google/android/gms/measurement/internal/zzem;
    //   4973: invokevirtual 198	com/google/android/gms/measurement/internal/zzem:zzb	()Lcom/google/android/gms/measurement/internal/zzek;
    //   4976: ldc_w 586
    //   4979: aload 5
    //   4981: invokestatic 204	com/google/android/gms/measurement/internal/zzem:zzl	(Ljava/lang/String;)Ljava/lang/Object;
    //   4984: invokevirtual 486	com/google/android/gms/measurement/internal/zzek:zzb	(Ljava/lang/String;Ljava/lang/Object;)V
    //   4987: goto +31 -> 5018
    //   4990: astore_1
    //   4991: goto +4 -> 4995
    //   4994: astore_1
    //   4995: aload 13
    //   4997: getfield 129	com/google/android/gms/measurement/internal/zzgn:zzs	Lcom/google/android/gms/measurement/internal/zzfu;
    //   5000: invokevirtual 193	com/google/android/gms/measurement/internal/zzfu:zzau	()Lcom/google/android/gms/measurement/internal/zzem;
    //   5003: invokevirtual 198	com/google/android/gms/measurement/internal/zzem:zzb	()Lcom/google/android/gms/measurement/internal/zzek;
    //   5006: ldc_w 588
    //   5009: aload 5
    //   5011: invokestatic 204	com/google/android/gms/measurement/internal/zzem:zzl	(Ljava/lang/String;)Ljava/lang/Object;
    //   5014: aload_1
    //   5015: invokevirtual 209	com/google/android/gms/measurement/internal/zzek:zzc	(Ljava/lang/String;Ljava/lang/Object;Ljava/lang/Object;)V
    //   5018: goto -237 -> 4781
    //   5021: aload_3
    //   5022: areturn
    //   5023: astore_1
    //   5024: aload 15
    //   5026: astore_2
    //   5027: aload_2
    //   5028: ifnull +9 -> 5037
    //   5031: aload_2
    //   5032: invokeinterface 276 1 0
    //   5037: aload_1
    //   5038: athrow
    // Exception table:
    //   from	to	target	type
    //   203	226	229	android/database/sqlite/SQLiteException
    //   387	406	507	java/io/IOException
    //   363	372	584	finally
    //   375	384	584	finally
    //   387	406	584	finally
    //   409	417	584	finally
    //   423	435	584	finally
    //   438	452	584	finally
    //   460	465	584	finally
    //   468	473	584	finally
    //   476	488	584	finally
    //   494	504	584	finally
    //   512	535	584	finally
    //   538	546	584	finally
    //   566	571	584	finally
    //   607	630	584	finally
    //   633	638	584	finally
    //   363	372	588	android/database/sqlite/SQLiteException
    //   375	384	588	android/database/sqlite/SQLiteException
    //   387	406	588	android/database/sqlite/SQLiteException
    //   409	417	588	android/database/sqlite/SQLiteException
    //   423	435	588	android/database/sqlite/SQLiteException
    //   438	452	588	android/database/sqlite/SQLiteException
    //   460	465	588	android/database/sqlite/SQLiteException
    //   468	473	588	android/database/sqlite/SQLiteException
    //   476	488	588	android/database/sqlite/SQLiteException
    //   494	504	588	android/database/sqlite/SQLiteException
    //   512	535	588	android/database/sqlite/SQLiteException
    //   538	546	588	android/database/sqlite/SQLiteException
    //   566	571	588	android/database/sqlite/SQLiteException
    //   325	360	593	finally
    //   325	360	600	android/database/sqlite/SQLiteException
    //   899	918	947	java/io/IOException
    //   992	1009	1061	android/database/sqlite/SQLiteException
    //   1020	1029	1061	android/database/sqlite/SQLiteException
    //   981	988	1076	android/database/sqlite/SQLiteException
    //   757	767	1085	android/database/sqlite/SQLiteException
    //   779	783	1085	android/database/sqlite/SQLiteException
    //   813	818	1085	android/database/sqlite/SQLiteException
    //   830	835	1085	android/database/sqlite/SQLiteException
    //   857	867	1085	android/database/sqlite/SQLiteException
    //   878	888	1085	android/database/sqlite/SQLiteException
    //   899	918	1085	android/database/sqlite/SQLiteException
    //   929	944	1085	android/database/sqlite/SQLiteException
    //   960	973	1085	android/database/sqlite/SQLiteException
    //   708	745	1103	finally
    //   708	745	1109	android/database/sqlite/SQLiteException
    //   1319	1329	1478	finally
    //   1333	1346	1478	finally
    //   1350	1364	1478	finally
    //   1377	1382	1478	finally
    //   1386	1391	1478	finally
    //   1395	1407	1478	finally
    //   1411	1430	1478	finally
    //   1434	1443	1478	finally
    //   1466	1471	1478	finally
    //   1503	1527	1478	finally
    //   1531	1536	1478	finally
    //   1319	1329	1482	android/database/sqlite/SQLiteException
    //   1333	1346	1482	android/database/sqlite/SQLiteException
    //   1350	1364	1482	android/database/sqlite/SQLiteException
    //   1377	1382	1482	android/database/sqlite/SQLiteException
    //   1386	1391	1482	android/database/sqlite/SQLiteException
    //   1395	1407	1482	android/database/sqlite/SQLiteException
    //   1411	1430	1482	android/database/sqlite/SQLiteException
    //   1434	1443	1482	android/database/sqlite/SQLiteException
    //   1466	1471	1482	android/database/sqlite/SQLiteException
    //   1291	1315	1487	finally
    //   1291	1315	1494	android/database/sqlite/SQLiteException
    //   3096	3115	3209	java/io/IOException
    //   3159	3164	3311	android/database/sqlite/SQLiteException
    //   3168	3173	3311	android/database/sqlite/SQLiteException
    //   3177	3189	3311	android/database/sqlite/SQLiteException
    //   3196	3206	3311	android/database/sqlite/SQLiteException
    //   3218	3231	3311	android/database/sqlite/SQLiteException
    //   3235	3242	3311	android/database/sqlite/SQLiteException
    //   3082	3092	3316	android/database/sqlite/SQLiteException
    //   3096	3115	3316	android/database/sqlite/SQLiteException
    //   3119	3132	3316	android/database/sqlite/SQLiteException
    //   3136	3150	3316	android/database/sqlite/SQLiteException
    //   3253	3264	3359	android/database/sqlite/SQLiteException
    //   3274	3283	3359	android/database/sqlite/SQLiteException
    //   3334	3339	3359	android/database/sqlite/SQLiteException
    //   3061	3070	3370	android/database/sqlite/SQLiteException
    //   3014	3057	3386	android/database/sqlite/SQLiteException
    //   3014	3057	3391	finally
    //   3061	3070	3478	finally
    //   3082	3092	3478	finally
    //   3096	3115	3478	finally
    //   3119	3132	3478	finally
    //   3136	3150	3478	finally
    //   3159	3164	3478	finally
    //   3168	3173	3478	finally
    //   3177	3189	3478	finally
    //   3196	3206	3478	finally
    //   3218	3231	3478	finally
    //   3235	3242	3478	finally
    //   3253	3264	3478	finally
    //   3274	3283	3478	finally
    //   3334	3339	3478	finally
    //   3406	3429	3478	finally
    //   3433	3438	3478	finally
    //   3989	4008	4107	java/io/IOException
    //   4132	4147	4208	android/database/sqlite/SQLiteException
    //   4152	4160	4208	android/database/sqlite/SQLiteException
    //   4188	4193	4208	android/database/sqlite/SQLiteException
    //   3961	3970	4215	android/database/sqlite/SQLiteException
    //   3975	3984	4215	android/database/sqlite/SQLiteException
    //   3989	4008	4215	android/database/sqlite/SQLiteException
    //   4013	4025	4215	android/database/sqlite/SQLiteException
    //   4030	4044	4215	android/database/sqlite/SQLiteException
    //   4054	4059	4215	android/database/sqlite/SQLiteException
    //   4064	4069	4215	android/database/sqlite/SQLiteException
    //   4074	4086	4215	android/database/sqlite/SQLiteException
    //   4094	4104	4215	android/database/sqlite/SQLiteException
    //   4114	4127	4215	android/database/sqlite/SQLiteException
    //   3914	3956	4222	finally
    //   3914	3956	4228	android/database/sqlite/SQLiteException
    //   3961	3970	4298	finally
    //   3975	3984	4298	finally
    //   3989	4008	4298	finally
    //   4013	4025	4298	finally
    //   4030	4044	4298	finally
    //   4054	4059	4298	finally
    //   4064	4069	4298	finally
    //   4074	4086	4298	finally
    //   4094	4104	4298	finally
    //   4114	4127	4298	finally
    //   4132	4147	4298	finally
    //   4152	4160	4298	finally
    //   4188	4193	4298	finally
    //   4235	4258	4298	finally
    //   4261	4266	4298	finally
    //   4947	4987	4990	android/database/sqlite/SQLiteException
    //   4941	4947	4994	android/database/sqlite/SQLiteException
    //   757	767	5023	finally
    //   779	783	5023	finally
    //   813	818	5023	finally
    //   830	835	5023	finally
    //   857	867	5023	finally
    //   878	888	5023	finally
    //   899	918	5023	finally
    //   929	944	5023	finally
    //   960	973	5023	finally
    //   981	988	5023	finally
    //   992	1009	5023	finally
    //   1020	1029	5023	finally
    //   1124	1148	5023	finally
    //   1151	1156	5023	finally
  }
}


/* Location:              C:\Users\User\Desktop\decompile\jdgui110\Tapojar.jar!\com\google\android\gms\measurement\internal\zzy.class
 * Java compiler version: 6 (50.0)
 * JD-Core Version:       0.7.1
 */