package b.d.i.a.c;

import java.util.ArrayList;
import java.util.List;

public class a
{
  private String a = "DigestAuthorizationManager";
  private final List<Exception> b = new ArrayList();
  
  public static a a()
  {
    return b.a();
  }
  
  public List<Exception> b()
  {
    return this.b;
  }
  
  /* Error */
  public String c(String paramString1, String paramString2, String paramString3, String paramString4, java.util.Map<String, String> paramMap)
  {
    // Byte code:
    //   0: aload_0
    //   1: getfield 26	b/d/i/a/c/a:b	Ljava/util/List;
    //   4: invokeinterface 44 1 0
    //   9: aconst_null
    //   10: astore 6
    //   12: aconst_null
    //   13: astore 7
    //   15: aconst_null
    //   16: astore 8
    //   18: aconst_null
    //   19: astore 9
    //   21: aconst_null
    //   22: astore 10
    //   24: aload 8
    //   26: astore 11
    //   28: new 46	java/net/URL
    //   31: astore 12
    //   33: aload 8
    //   35: astore 11
    //   37: aload 12
    //   39: aload_1
    //   40: invokespecial 49	java/net/URL:<init>	(Ljava/lang/String;)V
    //   43: aload 8
    //   45: astore 11
    //   47: aload 12
    //   49: invokevirtual 53	java/net/URL:openConnection	()Ljava/net/URLConnection;
    //   52: checkcast 55	java/net/HttpURLConnection
    //   55: astore 8
    //   57: aload 7
    //   59: astore 11
    //   61: aload 8
    //   63: aload 4
    //   65: invokevirtual 58	java/net/HttpURLConnection:setRequestMethod	(Ljava/lang/String;)V
    //   68: aload 7
    //   70: astore 11
    //   72: aload 8
    //   74: sipush 30000
    //   77: invokevirtual 62	java/net/HttpURLConnection:setConnectTimeout	(I)V
    //   80: aload 7
    //   82: astore 11
    //   84: aload 8
    //   86: sipush 15000
    //   89: invokevirtual 65	java/net/HttpURLConnection:setReadTimeout	(I)V
    //   92: aload 5
    //   94: ifnull +91 -> 185
    //   97: aload 7
    //   99: astore 11
    //   101: aload 5
    //   103: invokeinterface 71 1 0
    //   108: ifne +77 -> 185
    //   111: aload 7
    //   113: astore 11
    //   115: aload 5
    //   117: invokeinterface 75 1 0
    //   122: invokeinterface 81 1 0
    //   127: astore 12
    //   129: aload 7
    //   131: astore 11
    //   133: aload 12
    //   135: invokeinterface 86 1 0
    //   140: ifeq +45 -> 185
    //   143: aload 7
    //   145: astore 11
    //   147: aload 12
    //   149: invokeinterface 90 1 0
    //   154: checkcast 92	java/lang/String
    //   157: astore 9
    //   159: aload 7
    //   161: astore 11
    //   163: aload 8
    //   165: aload 9
    //   167: aload 5
    //   169: aload 9
    //   171: invokeinterface 96 2 0
    //   176: checkcast 92	java/lang/String
    //   179: invokevirtual 100	java/net/HttpURLConnection:setRequestProperty	(Ljava/lang/String;Ljava/lang/String;)V
    //   182: goto -53 -> 129
    //   185: aload 7
    //   187: astore 11
    //   189: aload 8
    //   191: invokevirtual 104	java/net/HttpURLConnection:getResponseCode	()I
    //   194: istore 13
    //   196: sipush 401
    //   199: iload 13
    //   201: if_icmpne +287 -> 488
    //   204: aload 7
    //   206: astore 11
    //   208: aload_0
    //   209: getfield 21	b/d/i/a/c/a:a	Ljava/lang/String;
    //   212: astore 6
    //   214: aload 7
    //   216: astore 11
    //   218: new 106	java/lang/StringBuilder
    //   221: astore 5
    //   223: aload 7
    //   225: astore 11
    //   227: aload 5
    //   229: invokespecial 107	java/lang/StringBuilder:<init>	()V
    //   232: aload 7
    //   234: astore 11
    //   236: aload 5
    //   238: ldc 109
    //   240: invokevirtual 113	java/lang/StringBuilder:append	(Ljava/lang/String;)Ljava/lang/StringBuilder;
    //   243: pop
    //   244: aload 7
    //   246: astore 11
    //   248: aload 5
    //   250: aload_1
    //   251: invokevirtual 113	java/lang/StringBuilder:append	(Ljava/lang/String;)Ljava/lang/StringBuilder;
    //   254: pop
    //   255: aload 7
    //   257: astore 11
    //   259: aload 6
    //   261: aload 5
    //   263: invokevirtual 117	java/lang/StringBuilder:toString	()Ljava/lang/String;
    //   266: invokestatic 121	b/d/p/d:a	(Ljava/lang/String;Ljava/lang/String;)V
    //   269: aload 7
    //   271: astore 11
    //   273: aload 8
    //   275: invokevirtual 125	java/net/HttpURLConnection:getHeaderFields	()Ljava/util/Map;
    //   278: ldc 127
    //   280: invokeinterface 96 2 0
    //   285: checkcast 41	java/util/List
    //   288: astore 5
    //   290: aload 5
    //   292: ifnull +98 -> 390
    //   295: aload 7
    //   297: astore 11
    //   299: aload 5
    //   301: invokeinterface 130 1 0
    //   306: ifle +84 -> 390
    //   309: aload 7
    //   311: astore 11
    //   313: aload 5
    //   315: iconst_0
    //   316: invokeinterface 133 2 0
    //   321: checkcast 92	java/lang/String
    //   324: astore 6
    //   326: aload 7
    //   328: astore 11
    //   330: new 135	b/d/i/a/c/b/c
    //   333: astore 10
    //   335: aload 7
    //   337: astore 11
    //   339: aload 10
    //   341: aload_2
    //   342: aload_3
    //   343: aload_1
    //   344: aload 4
    //   346: invokespecial 138	b/d/i/a/c/b/c:<init>	(Ljava/lang/String;Ljava/lang/String;Ljava/lang/String;Ljava/lang/String;)V
    //   349: aload 7
    //   351: astore 11
    //   353: aload 6
    //   355: invokestatic 144	b/d/i/a/c/b/a:j	(Ljava/lang/String;)Lb/d/i/a/c/b/a;
    //   358: astore_1
    //   359: aload 7
    //   361: astore 11
    //   363: new 146	b/d/i/a/c/b/d
    //   366: astore_2
    //   367: aload 7
    //   369: astore 11
    //   371: aload_2
    //   372: aload 10
    //   374: aload_1
    //   375: invokespecial 149	b/d/i/a/c/b/d:<init>	(Lb/d/i/a/c/b/c;Lb/d/i/a/c/b/a;)V
    //   378: aload 7
    //   380: astore 11
    //   382: aload_2
    //   383: invokevirtual 152	b/d/i/a/c/b/d:k	()Ljava/lang/String;
    //   386: astore_1
    //   387: goto +45 -> 432
    //   390: aload 7
    //   392: astore 11
    //   394: aload_0
    //   395: getfield 26	b/d/i/a/c/a:b	Ljava/util/List;
    //   398: astore_1
    //   399: aload 7
    //   401: astore 11
    //   403: new 39	java/lang/Exception
    //   406: astore_2
    //   407: aload 7
    //   409: astore 11
    //   411: aload_2
    //   412: ldc -102
    //   414: invokespecial 155	java/lang/Exception:<init>	(Ljava/lang/String;)V
    //   417: aload 7
    //   419: astore 11
    //   421: aload_1
    //   422: aload_2
    //   423: invokeinterface 159 2 0
    //   428: pop
    //   429: aload 10
    //   431: astore_1
    //   432: aload_1
    //   433: astore 11
    //   435: aload_0
    //   436: getfield 21	b/d/i/a/c/a:a	Ljava/lang/String;
    //   439: astore_3
    //   440: aload_1
    //   441: astore 11
    //   443: new 106	java/lang/StringBuilder
    //   446: astore_2
    //   447: aload_1
    //   448: astore 11
    //   450: aload_2
    //   451: invokespecial 107	java/lang/StringBuilder:<init>	()V
    //   454: aload_1
    //   455: astore 11
    //   457: aload_2
    //   458: ldc -95
    //   460: invokevirtual 113	java/lang/StringBuilder:append	(Ljava/lang/String;)Ljava/lang/StringBuilder;
    //   463: pop
    //   464: aload_1
    //   465: astore 11
    //   467: aload_2
    //   468: aload 5
    //   470: invokevirtual 164	java/lang/StringBuilder:append	(Ljava/lang/Object;)Ljava/lang/StringBuilder;
    //   473: pop
    //   474: aload_1
    //   475: astore 11
    //   477: aload_3
    //   478: aload_2
    //   479: invokevirtual 117	java/lang/StringBuilder:toString	()Ljava/lang/String;
    //   482: invokestatic 121	b/d/p/d:a	(Ljava/lang/String;Ljava/lang/String;)V
    //   485: goto +104 -> 589
    //   488: aload 7
    //   490: astore 11
    //   492: aload_0
    //   493: getfield 21	b/d/i/a/c/a:a	Ljava/lang/String;
    //   496: astore_1
    //   497: aload 7
    //   499: astore 11
    //   501: new 106	java/lang/StringBuilder
    //   504: astore_2
    //   505: aload 7
    //   507: astore 11
    //   509: aload_2
    //   510: invokespecial 107	java/lang/StringBuilder:<init>	()V
    //   513: aload 7
    //   515: astore 11
    //   517: aload_2
    //   518: ldc -90
    //   520: invokevirtual 113	java/lang/StringBuilder:append	(Ljava/lang/String;)Ljava/lang/StringBuilder;
    //   523: pop
    //   524: aload 7
    //   526: astore 11
    //   528: aload_2
    //   529: iload 13
    //   531: invokevirtual 169	java/lang/StringBuilder:append	(I)Ljava/lang/StringBuilder;
    //   534: pop
    //   535: aload 7
    //   537: astore 11
    //   539: aload_1
    //   540: aload_2
    //   541: invokevirtual 117	java/lang/StringBuilder:toString	()Ljava/lang/String;
    //   544: invokestatic 121	b/d/p/d:a	(Ljava/lang/String;Ljava/lang/String;)V
    //   547: aload 7
    //   549: astore 11
    //   551: aload_0
    //   552: getfield 26	b/d/i/a/c/a:b	Ljava/util/List;
    //   555: astore_2
    //   556: aload 7
    //   558: astore 11
    //   560: new 39	java/lang/Exception
    //   563: astore_1
    //   564: aload 7
    //   566: astore 11
    //   568: aload_1
    //   569: ldc -85
    //   571: invokespecial 155	java/lang/Exception:<init>	(Ljava/lang/String;)V
    //   574: aload 7
    //   576: astore 11
    //   578: aload_2
    //   579: aload_1
    //   580: invokeinterface 159 2 0
    //   585: pop
    //   586: aload 6
    //   588: astore_1
    //   589: aload 8
    //   591: invokevirtual 174	java/net/HttpURLConnection:disconnect	()V
    //   594: goto +122 -> 716
    //   597: astore_1
    //   598: aload 8
    //   600: astore 11
    //   602: goto +116 -> 718
    //   605: astore_3
    //   606: aload 11
    //   608: astore_1
    //   609: aload 8
    //   611: astore_2
    //   612: goto +13 -> 625
    //   615: astore_1
    //   616: goto +102 -> 718
    //   619: astore_3
    //   620: aconst_null
    //   621: astore_1
    //   622: aload 9
    //   624: astore_2
    //   625: aload_2
    //   626: astore 11
    //   628: aload_3
    //   629: invokevirtual 177	java/lang/Exception:printStackTrace	()V
    //   632: aload_2
    //   633: astore 11
    //   635: aload_0
    //   636: getfield 26	b/d/i/a/c/a:b	Ljava/util/List;
    //   639: aload_3
    //   640: invokeinterface 159 2 0
    //   645: pop
    //   646: aload_2
    //   647: astore 11
    //   649: aload_0
    //   650: getfield 21	b/d/i/a/c/a:a	Ljava/lang/String;
    //   653: astore 4
    //   655: aload_2
    //   656: astore 11
    //   658: new 106	java/lang/StringBuilder
    //   661: astore 5
    //   663: aload_2
    //   664: astore 11
    //   666: aload 5
    //   668: invokespecial 107	java/lang/StringBuilder:<init>	()V
    //   671: aload_2
    //   672: astore 11
    //   674: aload 5
    //   676: ldc -77
    //   678: invokevirtual 113	java/lang/StringBuilder:append	(Ljava/lang/String;)Ljava/lang/StringBuilder;
    //   681: pop
    //   682: aload_2
    //   683: astore 11
    //   685: aload 5
    //   687: aload_3
    //   688: invokevirtual 180	java/lang/Exception:toString	()Ljava/lang/String;
    //   691: invokevirtual 113	java/lang/StringBuilder:append	(Ljava/lang/String;)Ljava/lang/StringBuilder;
    //   694: pop
    //   695: aload_2
    //   696: astore 11
    //   698: aload 4
    //   700: aload 5
    //   702: invokevirtual 117	java/lang/StringBuilder:toString	()Ljava/lang/String;
    //   705: invokestatic 121	b/d/p/d:a	(Ljava/lang/String;Ljava/lang/String;)V
    //   708: aload_2
    //   709: ifnull +7 -> 716
    //   712: aload_2
    //   713: invokevirtual 174	java/net/HttpURLConnection:disconnect	()V
    //   716: aload_1
    //   717: areturn
    //   718: aload 11
    //   720: ifnull +8 -> 728
    //   723: aload 11
    //   725: invokevirtual 174	java/net/HttpURLConnection:disconnect	()V
    //   728: aload_1
    //   729: athrow
    // Local variable table:
    //   start	length	slot	name	signature
    //   0	730	0	this	a
    //   0	730	1	paramString1	String
    //   0	730	2	paramString2	String
    //   0	730	3	paramString3	String
    //   0	730	4	paramString4	String
    //   0	730	5	paramMap	java.util.Map<String, String>
    //   10	577	6	str1	String
    //   13	562	7	localObject1	Object
    //   16	594	8	localHttpURLConnection	java.net.HttpURLConnection
    //   19	604	9	str2	String
    //   22	408	10	localc	b.d.i.a.c.b.c
    //   26	698	11	localObject2	Object
    //   31	117	12	localObject3	Object
    //   194	336	13	i	int
    // Exception table:
    //   from	to	target	type
    //   61	68	597	finally
    //   72	80	597	finally
    //   84	92	597	finally
    //   101	111	597	finally
    //   115	129	597	finally
    //   133	143	597	finally
    //   147	159	597	finally
    //   163	182	597	finally
    //   189	196	597	finally
    //   208	214	597	finally
    //   218	223	597	finally
    //   227	232	597	finally
    //   236	244	597	finally
    //   248	255	597	finally
    //   259	269	597	finally
    //   273	290	597	finally
    //   299	309	597	finally
    //   313	326	597	finally
    //   330	335	597	finally
    //   339	349	597	finally
    //   353	359	597	finally
    //   363	367	597	finally
    //   371	378	597	finally
    //   382	387	597	finally
    //   394	399	597	finally
    //   403	407	597	finally
    //   411	417	597	finally
    //   421	429	597	finally
    //   435	440	597	finally
    //   443	447	597	finally
    //   450	454	597	finally
    //   457	464	597	finally
    //   467	474	597	finally
    //   477	485	597	finally
    //   492	497	597	finally
    //   501	505	597	finally
    //   509	513	597	finally
    //   517	524	597	finally
    //   528	535	597	finally
    //   539	547	597	finally
    //   551	556	597	finally
    //   560	564	597	finally
    //   568	574	597	finally
    //   578	586	597	finally
    //   61	68	605	java/lang/Exception
    //   72	80	605	java/lang/Exception
    //   84	92	605	java/lang/Exception
    //   101	111	605	java/lang/Exception
    //   115	129	605	java/lang/Exception
    //   133	143	605	java/lang/Exception
    //   147	159	605	java/lang/Exception
    //   163	182	605	java/lang/Exception
    //   189	196	605	java/lang/Exception
    //   208	214	605	java/lang/Exception
    //   218	223	605	java/lang/Exception
    //   227	232	605	java/lang/Exception
    //   236	244	605	java/lang/Exception
    //   248	255	605	java/lang/Exception
    //   259	269	605	java/lang/Exception
    //   273	290	605	java/lang/Exception
    //   299	309	605	java/lang/Exception
    //   313	326	605	java/lang/Exception
    //   330	335	605	java/lang/Exception
    //   339	349	605	java/lang/Exception
    //   353	359	605	java/lang/Exception
    //   363	367	605	java/lang/Exception
    //   371	378	605	java/lang/Exception
    //   382	387	605	java/lang/Exception
    //   394	399	605	java/lang/Exception
    //   403	407	605	java/lang/Exception
    //   411	417	605	java/lang/Exception
    //   421	429	605	java/lang/Exception
    //   435	440	605	java/lang/Exception
    //   443	447	605	java/lang/Exception
    //   450	454	605	java/lang/Exception
    //   457	464	605	java/lang/Exception
    //   467	474	605	java/lang/Exception
    //   477	485	605	java/lang/Exception
    //   492	497	605	java/lang/Exception
    //   501	505	605	java/lang/Exception
    //   509	513	605	java/lang/Exception
    //   517	524	605	java/lang/Exception
    //   528	535	605	java/lang/Exception
    //   539	547	605	java/lang/Exception
    //   551	556	605	java/lang/Exception
    //   560	564	605	java/lang/Exception
    //   568	574	605	java/lang/Exception
    //   578	586	605	java/lang/Exception
    //   28	33	615	finally
    //   37	43	615	finally
    //   47	57	615	finally
    //   628	632	615	finally
    //   635	646	615	finally
    //   649	655	615	finally
    //   658	663	615	finally
    //   666	671	615	finally
    //   674	682	615	finally
    //   685	695	615	finally
    //   698	708	615	finally
    //   28	33	619	java/lang/Exception
    //   37	43	619	java/lang/Exception
    //   47	57	619	java/lang/Exception
  }
  
  private static class b
  {
    private static final a a = new a(null);
  }
}


/* Location:              C:\Users\User\Desktop\decompile\jdgui110\Tapojar.jar!\b\d\i\a\c\a.class
 * Java compiler version: 6 (50.0)
 * JD-Core Version:       0.7.1
 */