package b.d.w.d;

import android.content.Context;
import androidx.annotation.NonNull;
import androidx.annotation.RequiresPermission;
import com.google.gson.Gson;
import com.google.gson.JsonSyntaxException;
import java.io.File;
import java.io.FileFilter;
import java.lang.reflect.ParameterizedType;
import java.lang.reflect.Type;
import java.util.ArrayList;
import java.util.HashMap;
import java.util.List;
import java.util.Map;
import java.util.concurrent.locks.ReadWriteLock;
import org.json.JSONObject;

public class a
{
  private static volatile String a;
  private static volatile com.tplink.libtputility.security.a b;
  private static Gson c = new Gson();
  private static final Map<String, ReadWriteLock> d = new HashMap();
  
  public static Object a(String paramString1, String paramString2, String paramString3)
  {
    return i(d(paramString1, paramString2), paramString3);
  }
  
  public static <T> T b(String paramString1, String paramString2, String paramString3, Class<T> paramClass)
  {
    paramString1 = a(paramString1, paramString2, paramString3);
    if ((paramString1 instanceof String)) {
      try
      {
        paramString1 = c.l((String)paramString1, paramClass);
        return paramString1;
      }
      catch (JsonSyntaxException paramString1)
      {
        b.d.w.c.a.d(paramString1.toString());
      }
    }
    return null;
  }
  
  public static <T> List<T> c(String paramString1, String paramString2, String paramString3, Class<T> paramClass)
  {
    paramString2 = a(paramString1, paramString2, paramString3);
    if ((paramString2 instanceof String)) {
      try
      {
        paramString1 = c;
        paramString2 = (String)paramString2;
        paramString3 = new b/d/w/d/a$b;
        paramString3.<init>(new Class[] { paramClass });
        paramString1 = (List)paramString1.m(paramString2, paramString3);
        return paramString1;
      }
      catch (JsonSyntaxException paramString1)
      {
        b.d.w.c.a.d(paramString1.toString());
      }
    }
    return new ArrayList();
  }
  
  private static String d(String paramString1, String paramString2)
  {
    StringBuilder localStringBuilder = new StringBuilder();
    localStringBuilder.append(a);
    String str = File.separator;
    localStringBuilder.append(str);
    localStringBuilder.append(b.d.w.h.a.g(paramString1));
    localStringBuilder.append(str);
    localStringBuilder.append(paramString2);
    return localStringBuilder.toString();
  }
  
  @Deprecated
  @RequiresPermission("android.permission.ACCESS_WIFI_STATE")
  public static void e(Context paramContext)
  {
    if (a == null) {
      try
      {
        Object localObject1 = paramContext.getCacheDir().getAbsolutePath();
        Object localObject2 = new java/lang/StringBuilder;
        ((StringBuilder)localObject2).<init>();
        ((StringBuilder)localObject2).append((String)localObject1);
        ((StringBuilder)localObject2).append(File.separator);
        ((StringBuilder)localObject2).append("model_cache");
        a = ((StringBuilder)localObject2).toString();
        File localFile = new java/io/File;
        localFile.<init>(a);
        if (!localFile.exists()) {
          localFile.mkdirs();
        }
        localObject2 = com.tplink.libtputility.security.b.c();
        if (((com.tplink.libtputility.security.b)localObject2).f("deco_model_file_key"))
        {
          localObject1 = f();
          paramContext = null;
          if (localObject1 != null)
          {
            paramContext = ((com.tplink.libtputility.security.b)localObject2).a(((JSONObject)localObject1).optString("DECO_TPSERIALIZEUTILS_AES_KEY", ""), "deco_model_file_key");
            localObject1 = ((com.tplink.libtputility.security.b)localObject2).a(((JSONObject)localObject1).optString("DECO_TPSERIALIZEUTILS_AES_VECTOR", ""), "deco_model_file_key");
          }
          else
          {
            localObject1 = null;
          }
          if ((!b.d.w.h.b.d(paramContext)) && (!b.d.w.h.b.d((CharSequence)localObject1)))
          {
            localObject2 = new com/tplink/libtputility/security/a;
            ((com.tplink.libtputility.security.a)localObject2).<init>(paramContext, (String)localObject1);
            b = (com.tplink.libtputility.security.a)localObject2;
          }
          else
          {
            b.d.w.b.b.c(localFile);
            paramContext = new com/tplink/libtputility/security/a;
            paramContext.<init>();
            b = paramContext;
            j(((com.tplink.libtputility.security.b)localObject2).b(b.h(), "deco_model_file_key"), ((com.tplink.libtputility.security.b)localObject2).b(b.g(), "deco_model_file_key"));
          }
        }
        else
        {
          ((com.tplink.libtputility.security.b)localObject2).e(paramContext, "deco_model_file_key");
          h(paramContext, (String)localObject1);
          paramContext = new com/tplink/libtputility/security/a;
          paramContext.<init>();
          b = paramContext;
          j(((com.tplink.libtputility.security.b)localObject2).b(b.h(), "deco_model_file_key"), ((com.tplink.libtputility.security.b)localObject2).b(b.g(), "deco_model_file_key"));
        }
      }
      finally {}
    }
  }
  
  /* Error */
  private static JSONObject f()
  {
    // Byte code:
    //   0: new 85	java/lang/StringBuilder
    //   3: dup
    //   4: invokespecial 86	java/lang/StringBuilder:<init>	()V
    //   7: astore_0
    //   8: aload_0
    //   9: getstatic 88	b/d/w/d/a:a	Ljava/lang/String;
    //   12: invokevirtual 92	java/lang/StringBuilder:append	(Ljava/lang/String;)Ljava/lang/StringBuilder;
    //   15: pop
    //   16: getstatic 97	java/io/File:separator	Ljava/lang/String;
    //   19: astore_1
    //   20: aload_0
    //   21: aload_1
    //   22: invokevirtual 92	java/lang/StringBuilder:append	(Ljava/lang/String;)Ljava/lang/StringBuilder;
    //   25: pop
    //   26: aload_0
    //   27: ldc -58
    //   29: invokevirtual 92	java/lang/StringBuilder:append	(Ljava/lang/String;)Ljava/lang/StringBuilder;
    //   32: pop
    //   33: aload_0
    //   34: aload_1
    //   35: invokevirtual 92	java/lang/StringBuilder:append	(Ljava/lang/String;)Ljava/lang/StringBuilder;
    //   38: pop
    //   39: aload_0
    //   40: ldc -58
    //   42: invokevirtual 92	java/lang/StringBuilder:append	(Ljava/lang/String;)Ljava/lang/StringBuilder;
    //   45: pop
    //   46: new 94	java/io/File
    //   49: dup
    //   50: aload_0
    //   51: invokevirtual 104	java/lang/StringBuilder:toString	()Ljava/lang/String;
    //   54: invokespecial 123	java/io/File:<init>	(Ljava/lang/String;)V
    //   57: astore_1
    //   58: aconst_null
    //   59: astore_2
    //   60: new 200	java/io/FileReader
    //   63: astore_0
    //   64: aload_0
    //   65: aload_1
    //   66: invokespecial 203	java/io/FileReader:<init>	(Ljava/io/File;)V
    //   69: new 205	java/io/BufferedReader
    //   72: astore_1
    //   73: aload_1
    //   74: aload_0
    //   75: invokespecial 208	java/io/BufferedReader:<init>	(Ljava/io/Reader;)V
    //   78: aload_1
    //   79: astore_3
    //   80: aload_0
    //   81: astore 4
    //   83: new 85	java/lang/StringBuilder
    //   86: astore 5
    //   88: aload_1
    //   89: astore_3
    //   90: aload_0
    //   91: astore 4
    //   93: aload 5
    //   95: invokespecial 86	java/lang/StringBuilder:<init>	()V
    //   98: aload_1
    //   99: astore_3
    //   100: aload_0
    //   101: astore 4
    //   103: aload_1
    //   104: invokevirtual 211	java/io/BufferedReader:readLine	()Ljava/lang/String;
    //   107: astore 6
    //   109: aload 6
    //   111: ifnull +19 -> 130
    //   114: aload_1
    //   115: astore_3
    //   116: aload_0
    //   117: astore 4
    //   119: aload 5
    //   121: aload 6
    //   123: invokevirtual 92	java/lang/StringBuilder:append	(Ljava/lang/String;)Ljava/lang/StringBuilder;
    //   126: pop
    //   127: goto -29 -> 98
    //   130: aload_1
    //   131: astore_3
    //   132: aload_0
    //   133: astore 4
    //   135: new 150	org/json/JSONObject
    //   138: dup
    //   139: aload 5
    //   141: invokevirtual 104	java/lang/StringBuilder:toString	()Ljava/lang/String;
    //   144: invokespecial 212	org/json/JSONObject:<init>	(Ljava/lang/String;)V
    //   147: astore 6
    //   149: aload_1
    //   150: invokevirtual 215	java/io/BufferedReader:close	()V
    //   153: aload_0
    //   154: invokevirtual 216	java/io/FileReader:close	()V
    //   157: goto +11 -> 168
    //   160: astore_1
    //   161: aload_1
    //   162: invokevirtual 217	java/io/IOException:toString	()Ljava/lang/String;
    //   165: invokestatic 65	b/d/w/c/a:d	(Ljava/lang/String;)V
    //   168: aload 6
    //   170: astore_1
    //   171: goto +114 -> 285
    //   174: astore_3
    //   175: aload_0
    //   176: astore 6
    //   178: aload_3
    //   179: astore_0
    //   180: goto +51 -> 231
    //   183: astore_3
    //   184: aload_0
    //   185: astore 6
    //   187: aload_3
    //   188: astore_0
    //   189: goto +42 -> 231
    //   192: astore_1
    //   193: aconst_null
    //   194: astore_3
    //   195: goto +96 -> 291
    //   198: astore_3
    //   199: goto +4 -> 203
    //   202: astore_3
    //   203: aconst_null
    //   204: astore_1
    //   205: aload_0
    //   206: astore 6
    //   208: aload_3
    //   209: astore_0
    //   210: goto +21 -> 231
    //   213: astore_1
    //   214: aconst_null
    //   215: astore_0
    //   216: aload_0
    //   217: astore_3
    //   218: goto +73 -> 291
    //   221: astore_0
    //   222: goto +4 -> 226
    //   225: astore_0
    //   226: aconst_null
    //   227: astore_1
    //   228: aload_1
    //   229: astore 6
    //   231: aload_1
    //   232: astore_3
    //   233: aload 6
    //   235: astore 4
    //   237: aload_0
    //   238: invokevirtual 220	java/lang/Exception:toString	()Ljava/lang/String;
    //   241: invokestatic 65	b/d/w/c/a:d	(Ljava/lang/String;)V
    //   244: aload_1
    //   245: ifnull +14 -> 259
    //   248: aload_1
    //   249: invokevirtual 215	java/io/BufferedReader:close	()V
    //   252: goto +7 -> 259
    //   255: astore_1
    //   256: goto +20 -> 276
    //   259: aload_2
    //   260: astore_1
    //   261: aload 6
    //   263: ifnull +22 -> 285
    //   266: aload 6
    //   268: invokevirtual 216	java/io/FileReader:close	()V
    //   271: aload_2
    //   272: astore_1
    //   273: goto +12 -> 285
    //   276: aload_1
    //   277: invokevirtual 217	java/io/IOException:toString	()Ljava/lang/String;
    //   280: invokestatic 65	b/d/w/c/a:d	(Ljava/lang/String;)V
    //   283: aload_2
    //   284: astore_1
    //   285: aload_1
    //   286: areturn
    //   287: astore_1
    //   288: aload 4
    //   290: astore_0
    //   291: aload_3
    //   292: ifnull +14 -> 306
    //   295: aload_3
    //   296: invokevirtual 215	java/io/BufferedReader:close	()V
    //   299: goto +7 -> 306
    //   302: astore_0
    //   303: goto +14 -> 317
    //   306: aload_0
    //   307: ifnull +17 -> 324
    //   310: aload_0
    //   311: invokevirtual 216	java/io/FileReader:close	()V
    //   314: goto +10 -> 324
    //   317: aload_0
    //   318: invokevirtual 217	java/io/IOException:toString	()Ljava/lang/String;
    //   321: invokestatic 65	b/d/w/c/a:d	(Ljava/lang/String;)V
    //   324: aload_1
    //   325: athrow
    // Local variable table:
    //   start	length	slot	name	signature
    //   7	210	0	localObject1	Object
    //   221	1	0	localJSONException1	org.json.JSONException
    //   225	13	0	localIOException1	java.io.IOException
    //   290	1	0	localObject2	Object
    //   302	16	0	localIOException2	java.io.IOException
    //   19	131	1	localObject3	Object
    //   160	2	1	localIOException3	java.io.IOException
    //   170	1	1	localObject4	Object
    //   192	1	1	localObject5	Object
    //   204	1	1	localObject6	Object
    //   213	1	1	localObject7	Object
    //   227	22	1	localObject8	Object
    //   255	1	1	localIOException4	java.io.IOException
    //   260	26	1	localObject9	Object
    //   287	38	1	localObject10	Object
    //   59	225	2	localObject11	Object
    //   79	53	3	localObject12	Object
    //   174	5	3	localJSONException2	org.json.JSONException
    //   183	5	3	localIOException5	java.io.IOException
    //   194	1	3	localObject13	Object
    //   198	1	3	localJSONException3	org.json.JSONException
    //   202	7	3	localIOException6	java.io.IOException
    //   217	79	3	localObject14	Object
    //   81	208	4	localObject15	Object
    //   86	54	5	localStringBuilder	StringBuilder
    //   107	160	6	localObject16	Object
    // Exception table:
    //   from	to	target	type
    //   149	157	160	java/io/IOException
    //   83	88	174	org/json/JSONException
    //   93	98	174	org/json/JSONException
    //   103	109	174	org/json/JSONException
    //   119	127	174	org/json/JSONException
    //   135	149	174	org/json/JSONException
    //   83	88	183	java/io/IOException
    //   93	98	183	java/io/IOException
    //   103	109	183	java/io/IOException
    //   119	127	183	java/io/IOException
    //   135	149	183	java/io/IOException
    //   69	78	192	finally
    //   69	78	198	org/json/JSONException
    //   69	78	202	java/io/IOException
    //   60	69	213	finally
    //   60	69	221	org/json/JSONException
    //   60	69	225	java/io/IOException
    //   248	252	255	java/io/IOException
    //   266	271	255	java/io/IOException
    //   83	88	287	finally
    //   93	98	287	finally
    //   103	109	287	finally
    //   119	127	287	finally
    //   135	149	287	finally
    //   237	244	287	finally
    //   295	299	302	java/io/IOException
    //   310	314	302	java/io/IOException
  }
  
  /* Error */
  @RequiresPermission("android.permission.ACCESS_WIFI_STATE")
  private static void g(Context paramContext, File paramFile, String paramString1, String paramString2)
  {
    // Byte code:
    //   0: aload_1
    //   1: invokevirtual 127	java/io/File:exists	()Z
    //   4: ifeq +451 -> 455
    //   7: aload_1
    //   8: invokevirtual 224	java/io/File:isFile	()Z
    //   11: ifeq +444 -> 455
    //   14: aload_1
    //   15: invokevirtual 228	java/io/File:length	()J
    //   18: lconst_0
    //   19: lcmp
    //   20: ifne +6 -> 26
    //   23: goto +432 -> 455
    //   26: new 94	java/io/File
    //   29: dup
    //   30: aload_2
    //   31: invokespecial 123	java/io/File:<init>	(Ljava/lang/String;)V
    //   34: astore 4
    //   36: aload 4
    //   38: invokevirtual 127	java/io/File:exists	()Z
    //   41: ifne +9 -> 50
    //   44: aload 4
    //   46: invokevirtual 130	java/io/File:mkdirs	()Z
    //   49: pop
    //   50: new 85	java/lang/StringBuilder
    //   53: dup
    //   54: invokespecial 86	java/lang/StringBuilder:<init>	()V
    //   57: astore 4
    //   59: aload 4
    //   61: aload_2
    //   62: invokevirtual 92	java/lang/StringBuilder:append	(Ljava/lang/String;)Ljava/lang/StringBuilder;
    //   65: pop
    //   66: aload 4
    //   68: getstatic 97	java/io/File:separator	Ljava/lang/String;
    //   71: invokevirtual 92	java/lang/StringBuilder:append	(Ljava/lang/String;)Ljava/lang/StringBuilder;
    //   74: pop
    //   75: aload 4
    //   77: aload_3
    //   78: invokevirtual 92	java/lang/StringBuilder:append	(Ljava/lang/String;)Ljava/lang/StringBuilder;
    //   81: pop
    //   82: new 94	java/io/File
    //   85: dup
    //   86: aload 4
    //   88: invokevirtual 104	java/lang/StringBuilder:toString	()Ljava/lang/String;
    //   91: invokespecial 123	java/io/File:<init>	(Ljava/lang/String;)V
    //   94: astore_3
    //   95: aconst_null
    //   96: astore 5
    //   98: aconst_null
    //   99: astore_2
    //   100: new 230	java/io/FileInputStream
    //   103: astore 4
    //   105: aload 4
    //   107: aload_1
    //   108: invokespecial 231	java/io/FileInputStream:<init>	(Ljava/io/File;)V
    //   111: aload_1
    //   112: invokevirtual 228	java/io/File:length	()J
    //   115: l2i
    //   116: newarray <illegal type>
    //   118: astore_1
    //   119: aload 4
    //   121: aload_1
    //   122: invokevirtual 235	java/io/FileInputStream:read	([B)I
    //   125: pop
    //   126: aload_0
    //   127: invokestatic 240	com/tplink/libtputility/security/PlainEncryptKeyDelegate:a	(Landroid/content/Context;)Ljava/lang/String;
    //   130: ldc -14
    //   132: invokevirtual 246	java/lang/String:getBytes	(Ljava/lang/String;)[B
    //   135: invokestatic 249	b/d/w/h/a:f	([B)[B
    //   138: astore_0
    //   139: new 164	com/tplink/libtputility/security/a
    //   142: astore_2
    //   143: aload_2
    //   144: aload_0
    //   145: aconst_null
    //   146: ldc -5
    //   148: invokespecial 254	com/tplink/libtputility/security/a:<init>	([B[BLjava/lang/String;)V
    //   151: aload_2
    //   152: aload_1
    //   153: invokevirtual 256	com/tplink/libtputility/security/a:b	([B)[B
    //   156: astore_1
    //   157: new 258	java/io/FileOutputStream
    //   160: astore_2
    //   161: aload_2
    //   162: aload_3
    //   163: invokespecial 259	java/io/FileOutputStream:<init>	(Ljava/io/File;)V
    //   166: new 261	java/io/BufferedOutputStream
    //   169: astore_0
    //   170: aload_0
    //   171: aload_2
    //   172: invokespecial 264	java/io/BufferedOutputStream:<init>	(Ljava/io/OutputStream;)V
    //   175: aload_0
    //   176: getstatic 169	b/d/w/d/a:b	Lcom/tplink/libtputility/security/a;
    //   179: aload_1
    //   180: invokevirtual 266	com/tplink/libtputility/security/a:d	([B)[B
    //   183: invokevirtual 270	java/io/BufferedOutputStream:write	([B)V
    //   186: aload_0
    //   187: invokevirtual 273	java/io/BufferedOutputStream:flush	()V
    //   190: aload_2
    //   191: invokevirtual 274	java/io/FileOutputStream:flush	()V
    //   194: aload 4
    //   196: invokevirtual 275	java/io/FileInputStream:close	()V
    //   199: aload_0
    //   200: invokevirtual 276	java/io/BufferedOutputStream:close	()V
    //   203: aload_2
    //   204: invokevirtual 277	java/io/FileOutputStream:close	()V
    //   207: aload 4
    //   209: invokevirtual 275	java/io/FileInputStream:close	()V
    //   212: goto +11 -> 223
    //   215: astore_1
    //   216: aload_1
    //   217: invokevirtual 217	java/io/IOException:toString	()Ljava/lang/String;
    //   220: invokestatic 65	b/d/w/c/a:d	(Ljava/lang/String;)V
    //   223: aload_0
    //   224: invokevirtual 276	java/io/BufferedOutputStream:close	()V
    //   227: goto +11 -> 238
    //   230: astore_0
    //   231: aload_0
    //   232: invokevirtual 217	java/io/IOException:toString	()Ljava/lang/String;
    //   235: invokestatic 65	b/d/w/c/a:d	(Ljava/lang/String;)V
    //   238: aload_2
    //   239: invokevirtual 277	java/io/FileOutputStream:close	()V
    //   242: goto +139 -> 381
    //   245: astore_1
    //   246: aload_2
    //   247: astore_3
    //   248: goto +30 -> 278
    //   251: astore_3
    //   252: aload_0
    //   253: astore_1
    //   254: aload_3
    //   255: astore_0
    //   256: goto +34 -> 290
    //   259: astore_1
    //   260: aconst_null
    //   261: astore_0
    //   262: aload_2
    //   263: astore_3
    //   264: goto +14 -> 278
    //   267: astore_0
    //   268: aconst_null
    //   269: astore_1
    //   270: goto +20 -> 290
    //   273: astore_1
    //   274: aconst_null
    //   275: astore_3
    //   276: aload_3
    //   277: astore_0
    //   278: aload_0
    //   279: astore_2
    //   280: aload_1
    //   281: astore_0
    //   282: goto +112 -> 394
    //   285: astore_0
    //   286: aconst_null
    //   287: astore_2
    //   288: aload_2
    //   289: astore_1
    //   290: aload_0
    //   291: astore_3
    //   292: aload_2
    //   293: astore_0
    //   294: aload 4
    //   296: astore_2
    //   297: goto +20 -> 317
    //   300: astore_0
    //   301: aconst_null
    //   302: astore_3
    //   303: aload_3
    //   304: astore_2
    //   305: aload 5
    //   307: astore 4
    //   309: goto +85 -> 394
    //   312: astore_3
    //   313: aconst_null
    //   314: astore_0
    //   315: aload_0
    //   316: astore_1
    //   317: aload_3
    //   318: invokevirtual 220	java/lang/Exception:toString	()Ljava/lang/String;
    //   321: invokestatic 65	b/d/w/c/a:d	(Ljava/lang/String;)V
    //   324: aload_2
    //   325: ifnull +18 -> 343
    //   328: aload_2
    //   329: invokevirtual 275	java/io/FileInputStream:close	()V
    //   332: goto +11 -> 343
    //   335: astore_2
    //   336: aload_2
    //   337: invokevirtual 217	java/io/IOException:toString	()Ljava/lang/String;
    //   340: invokestatic 65	b/d/w/c/a:d	(Ljava/lang/String;)V
    //   343: aload_1
    //   344: ifnull +18 -> 362
    //   347: aload_1
    //   348: invokevirtual 276	java/io/BufferedOutputStream:close	()V
    //   351: goto +11 -> 362
    //   354: astore_1
    //   355: aload_1
    //   356: invokevirtual 217	java/io/IOException:toString	()Ljava/lang/String;
    //   359: invokestatic 65	b/d/w/c/a:d	(Ljava/lang/String;)V
    //   362: aload_0
    //   363: ifnull +18 -> 381
    //   366: aload_0
    //   367: invokevirtual 277	java/io/FileOutputStream:close	()V
    //   370: goto +11 -> 381
    //   373: astore_0
    //   374: aload_0
    //   375: invokevirtual 217	java/io/IOException:toString	()Ljava/lang/String;
    //   378: invokestatic 65	b/d/w/c/a:d	(Ljava/lang/String;)V
    //   381: return
    //   382: astore 5
    //   384: aload_2
    //   385: astore 4
    //   387: aload_0
    //   388: astore_3
    //   389: aload 5
    //   391: astore_0
    //   392: aload_1
    //   393: astore_2
    //   394: aload 4
    //   396: ifnull +19 -> 415
    //   399: aload 4
    //   401: invokevirtual 275	java/io/FileInputStream:close	()V
    //   404: goto +11 -> 415
    //   407: astore_1
    //   408: aload_1
    //   409: invokevirtual 217	java/io/IOException:toString	()Ljava/lang/String;
    //   412: invokestatic 65	b/d/w/c/a:d	(Ljava/lang/String;)V
    //   415: aload_2
    //   416: ifnull +18 -> 434
    //   419: aload_2
    //   420: invokevirtual 276	java/io/BufferedOutputStream:close	()V
    //   423: goto +11 -> 434
    //   426: astore_1
    //   427: aload_1
    //   428: invokevirtual 217	java/io/IOException:toString	()Ljava/lang/String;
    //   431: invokestatic 65	b/d/w/c/a:d	(Ljava/lang/String;)V
    //   434: aload_3
    //   435: ifnull +18 -> 453
    //   438: aload_3
    //   439: invokevirtual 277	java/io/FileOutputStream:close	()V
    //   442: goto +11 -> 453
    //   445: astore_1
    //   446: aload_1
    //   447: invokevirtual 217	java/io/IOException:toString	()Ljava/lang/String;
    //   450: invokestatic 65	b/d/w/c/a:d	(Ljava/lang/String;)V
    //   453: aload_0
    //   454: athrow
    //   455: return
    // Local variable table:
    //   start	length	slot	name	signature
    //   0	456	0	paramContext	Context
    //   0	456	1	paramFile	File
    //   0	456	2	paramString1	String
    //   0	456	3	paramString2	String
    //   34	366	4	localObject1	Object
    //   96	210	5	localObject2	Object
    //   382	8	5	localObject3	Object
    // Exception table:
    //   from	to	target	type
    //   207	212	215	java/io/IOException
    //   223	227	230	java/io/IOException
    //   175	207	245	finally
    //   175	207	251	java/lang/Exception
    //   166	175	259	finally
    //   166	175	267	java/lang/Exception
    //   111	166	273	finally
    //   111	166	285	java/lang/Exception
    //   100	111	300	finally
    //   100	111	312	java/lang/Exception
    //   328	332	335	java/io/IOException
    //   347	351	354	java/io/IOException
    //   238	242	373	java/io/IOException
    //   366	370	373	java/io/IOException
    //   317	324	382	finally
    //   399	404	407	java/io/IOException
    //   419	423	426	java/io/IOException
    //   438	442	445	java/io/IOException
  }
  
  @RequiresPermission("android.permission.ACCESS_WIFI_STATE")
  private static void h(Context paramContext, String paramString)
  {
    File[] arrayOfFile1 = new File(paramString).listFiles(new c(null));
    if (arrayOfFile1 != null)
    {
      int i = arrayOfFile1.length;
      for (int j = 0; j < i; j++)
      {
        paramString = arrayOfFile1[j];
        Object localObject1 = new StringBuilder();
        ((StringBuilder)localObject1).append("com");
        Object localObject2 = File.separator;
        ((StringBuilder)localObject1).append((String)localObject2);
        ((StringBuilder)localObject1).append("tplink");
        ((StringBuilder)localObject1).append((String)localObject2);
        ((StringBuilder)localObject1).append("model");
        ((StringBuilder)localObject1).append((String)localObject2);
        ((StringBuilder)localObject1).append("MessageV2Model");
        localObject1 = ((StringBuilder)localObject1).toString();
        Object localObject3 = new StringBuilder();
        ((StringBuilder)localObject3).append(paramString.getAbsolutePath());
        ((StringBuilder)localObject3).append((String)localObject2);
        ((StringBuilder)localObject3).append((String)localObject1);
        localObject2 = new File(((StringBuilder)localObject3).toString());
        if (((File)localObject2).isDirectory())
        {
          File[] arrayOfFile2 = ((File)localObject2).listFiles();
          if (arrayOfFile2 != null)
          {
            int k = arrayOfFile2.length;
            for (int m = 0; m < k; m++)
            {
              localObject2 = arrayOfFile2[m];
              StringBuilder localStringBuilder = new StringBuilder();
              localStringBuilder.append(a);
              localObject3 = File.separator;
              localStringBuilder.append((String)localObject3);
              localStringBuilder.append(b.d.w.h.a.g(paramString.getName()));
              localStringBuilder.append((String)localObject3);
              localStringBuilder.append((String)localObject1);
              g(paramContext, (File)localObject2, localStringBuilder.toString(), ((File)localObject2).getName());
            }
          }
        }
        else
        {
          b.d.w.b.b.c(paramString);
        }
      }
    }
  }
  
  /* Error */
  private static Object i(String paramString1, String paramString2)
  {
    // Byte code:
    //   0: aload_0
    //   1: invokestatic 162	b/d/w/h/b:d	(Ljava/lang/CharSequence;)Z
    //   4: istore_2
    //   5: aconst_null
    //   6: astore_3
    //   7: aconst_null
    //   8: astore 4
    //   10: aconst_null
    //   11: astore 5
    //   13: iload_2
    //   14: ifne +473 -> 487
    //   17: aload_1
    //   18: invokestatic 162	b/d/w/h/b:d	(Ljava/lang/CharSequence;)Z
    //   21: ifeq +6 -> 27
    //   24: goto +463 -> 487
    //   27: new 85	java/lang/StringBuilder
    //   30: dup
    //   31: invokespecial 86	java/lang/StringBuilder:<init>	()V
    //   34: astore 6
    //   36: aload 6
    //   38: aload_0
    //   39: invokevirtual 92	java/lang/StringBuilder:append	(Ljava/lang/String;)Ljava/lang/StringBuilder;
    //   42: pop
    //   43: aload 6
    //   45: getstatic 97	java/io/File:separator	Ljava/lang/String;
    //   48: invokevirtual 92	java/lang/StringBuilder:append	(Ljava/lang/String;)Ljava/lang/StringBuilder;
    //   51: pop
    //   52: aload 6
    //   54: aload_1
    //   55: invokevirtual 92	java/lang/StringBuilder:append	(Ljava/lang/String;)Ljava/lang/StringBuilder;
    //   58: pop
    //   59: new 94	java/io/File
    //   62: dup
    //   63: aload 6
    //   65: invokevirtual 104	java/lang/StringBuilder:toString	()Ljava/lang/String;
    //   68: invokespecial 123	java/io/File:<init>	(Ljava/lang/String;)V
    //   71: astore 7
    //   73: aload 7
    //   75: invokevirtual 127	java/io/File:exists	()Z
    //   78: ifeq +409 -> 487
    //   81: aload 7
    //   83: invokevirtual 224	java/io/File:isFile	()Z
    //   86: ifeq +401 -> 487
    //   89: aload 7
    //   91: invokevirtual 228	java/io/File:length	()J
    //   94: lconst_0
    //   95: lcmp
    //   96: ifne +6 -> 102
    //   99: goto +388 -> 487
    //   102: getstatic 33	b/d/w/d/a:d	Ljava/util/Map;
    //   105: astore 8
    //   107: aload 8
    //   109: aload_0
    //   110: invokeinterface 309 2 0
    //   115: checkcast 311	java/util/concurrent/locks/ReadWriteLock
    //   118: astore_1
    //   119: aload_1
    //   120: astore 6
    //   122: aload_1
    //   123: ifnonnull +39 -> 162
    //   126: aload 8
    //   128: monitorenter
    //   129: new 313	java/util/concurrent/locks/ReentrantReadWriteLock
    //   132: astore 6
    //   134: aload 6
    //   136: invokespecial 314	java/util/concurrent/locks/ReentrantReadWriteLock:<init>	()V
    //   139: aload 8
    //   141: aload_0
    //   142: aload 6
    //   144: invokeinterface 318 3 0
    //   149: pop
    //   150: aload 8
    //   152: monitorexit
    //   153: goto +9 -> 162
    //   156: astore_0
    //   157: aload 8
    //   159: monitorexit
    //   160: aload_0
    //   161: athrow
    //   162: aload 6
    //   164: invokeinterface 322 1 0
    //   169: invokeinterface 327 1 0
    //   174: new 230	java/io/FileInputStream
    //   177: astore_0
    //   178: aload_0
    //   179: aload 7
    //   181: invokespecial 231	java/io/FileInputStream:<init>	(Ljava/io/File;)V
    //   184: aload 7
    //   186: invokevirtual 228	java/io/File:length	()J
    //   189: l2i
    //   190: newarray <illegal type>
    //   192: astore_1
    //   193: aload_0
    //   194: aload_1
    //   195: invokevirtual 235	java/io/FileInputStream:read	([B)I
    //   198: pop
    //   199: getstatic 169	b/d/w/d/a:b	Lcom/tplink/libtputility/security/a;
    //   202: aload_1
    //   203: invokevirtual 256	com/tplink/libtputility/security/a:b	([B)[B
    //   206: astore_3
    //   207: new 329	java/io/BufferedInputStream
    //   210: astore_1
    //   211: new 331	java/io/ByteArrayInputStream
    //   214: astore 4
    //   216: aload 4
    //   218: aload_3
    //   219: invokespecial 333	java/io/ByteArrayInputStream:<init>	([B)V
    //   222: aload_1
    //   223: aload 4
    //   225: invokespecial 336	java/io/BufferedInputStream:<init>	(Ljava/io/InputStream;)V
    //   228: new 338	java/io/ObjectInputStream
    //   231: astore_3
    //   232: aload_3
    //   233: aload_1
    //   234: invokespecial 339	java/io/ObjectInputStream:<init>	(Ljava/io/InputStream;)V
    //   237: aload 5
    //   239: astore_1
    //   240: aload_3
    //   241: invokevirtual 343	java/io/ObjectInputStream:readObject	()Ljava/lang/Object;
    //   244: astore 5
    //   246: aload 5
    //   248: astore_1
    //   249: aload_3
    //   250: invokevirtual 344	java/io/ObjectInputStream:close	()V
    //   253: aload_0
    //   254: invokevirtual 275	java/io/FileInputStream:close	()V
    //   257: goto +11 -> 268
    //   260: astore_0
    //   261: aload_0
    //   262: invokevirtual 217	java/io/IOException:toString	()Ljava/lang/String;
    //   265: invokestatic 65	b/d/w/c/a:d	(Ljava/lang/String;)V
    //   268: aload_3
    //   269: invokevirtual 344	java/io/ObjectInputStream:close	()V
    //   272: goto +11 -> 283
    //   275: astore_0
    //   276: aload_0
    //   277: invokevirtual 217	java/io/IOException:toString	()Ljava/lang/String;
    //   280: invokestatic 65	b/d/w/c/a:d	(Ljava/lang/String;)V
    //   283: aload 6
    //   285: invokeinterface 322 1 0
    //   290: invokeinterface 347 1 0
    //   295: goto +125 -> 420
    //   298: astore 5
    //   300: aload_3
    //   301: astore_1
    //   302: goto +17 -> 319
    //   305: astore 4
    //   307: aload_1
    //   308: astore 5
    //   310: aload_3
    //   311: astore_1
    //   312: goto +50 -> 362
    //   315: astore 5
    //   317: aconst_null
    //   318: astore_1
    //   319: aload_0
    //   320: astore 4
    //   322: aload 5
    //   324: astore_0
    //   325: aload 4
    //   327: astore 5
    //   329: goto +102 -> 431
    //   332: astore 4
    //   334: aconst_null
    //   335: astore_1
    //   336: aload_1
    //   337: astore 5
    //   339: goto +23 -> 362
    //   342: astore_0
    //   343: aconst_null
    //   344: astore_1
    //   345: aload 4
    //   347: astore 5
    //   349: goto +82 -> 431
    //   352: astore 4
    //   354: aconst_null
    //   355: astore 5
    //   357: aload 5
    //   359: astore_1
    //   360: aload_3
    //   361: astore_0
    //   362: aload 4
    //   364: invokevirtual 220	java/lang/Exception:toString	()Ljava/lang/String;
    //   367: invokestatic 65	b/d/w/c/a:d	(Ljava/lang/String;)V
    //   370: aload_0
    //   371: ifnull +18 -> 389
    //   374: aload_0
    //   375: invokevirtual 275	java/io/FileInputStream:close	()V
    //   378: goto +11 -> 389
    //   381: astore_0
    //   382: aload_0
    //   383: invokevirtual 217	java/io/IOException:toString	()Ljava/lang/String;
    //   386: invokestatic 65	b/d/w/c/a:d	(Ljava/lang/String;)V
    //   389: aload_1
    //   390: ifnull +18 -> 408
    //   393: aload_1
    //   394: invokevirtual 344	java/io/ObjectInputStream:close	()V
    //   397: goto +11 -> 408
    //   400: astore_0
    //   401: aload_0
    //   402: invokevirtual 217	java/io/IOException:toString	()Ljava/lang/String;
    //   405: invokestatic 65	b/d/w/c/a:d	(Ljava/lang/String;)V
    //   408: aload 6
    //   410: invokeinterface 322 1 0
    //   415: invokeinterface 347 1 0
    //   420: aload 5
    //   422: areturn
    //   423: astore 4
    //   425: aload_0
    //   426: astore 5
    //   428: aload 4
    //   430: astore_0
    //   431: aload 5
    //   433: ifnull +21 -> 454
    //   436: aload 5
    //   438: invokevirtual 275	java/io/FileInputStream:close	()V
    //   441: goto +13 -> 454
    //   444: astore 5
    //   446: aload 5
    //   448: invokevirtual 217	java/io/IOException:toString	()Ljava/lang/String;
    //   451: invokestatic 65	b/d/w/c/a:d	(Ljava/lang/String;)V
    //   454: aload_1
    //   455: ifnull +18 -> 473
    //   458: aload_1
    //   459: invokevirtual 344	java/io/ObjectInputStream:close	()V
    //   462: goto +11 -> 473
    //   465: astore_1
    //   466: aload_1
    //   467: invokevirtual 217	java/io/IOException:toString	()Ljava/lang/String;
    //   470: invokestatic 65	b/d/w/c/a:d	(Ljava/lang/String;)V
    //   473: aload 6
    //   475: invokeinterface 322 1 0
    //   480: invokeinterface 347 1 0
    //   485: aload_0
    //   486: athrow
    //   487: aconst_null
    //   488: areturn
    // Local variable table:
    //   start	length	slot	name	signature
    //   0	489	0	paramString1	String
    //   0	489	1	paramString2	String
    //   4	10	2	bool	boolean
    //   6	355	3	localObject1	Object
    //   8	216	4	localByteArrayInputStream	java.io.ByteArrayInputStream
    //   305	1	4	localException1	Exception
    //   320	6	4	str1	String
    //   332	14	4	localException2	Exception
    //   352	11	4	localException3	Exception
    //   423	6	4	localObject2	Object
    //   11	236	5	localObject3	Object
    //   298	1	5	localObject4	Object
    //   308	1	5	str2	String
    //   315	8	5	localObject5	Object
    //   327	110	5	localObject6	Object
    //   444	3	5	localIOException	java.io.IOException
    //   34	440	6	localObject7	Object
    //   71	114	7	localFile	File
    //   105	53	8	localMap	Map
    // Exception table:
    //   from	to	target	type
    //   129	153	156	finally
    //   157	160	156	finally
    //   253	257	260	java/io/IOException
    //   268	272	275	java/io/IOException
    //   240	246	298	finally
    //   249	253	298	finally
    //   240	246	305	java/lang/Exception
    //   249	253	305	java/lang/Exception
    //   184	237	315	finally
    //   184	237	332	java/lang/Exception
    //   174	184	342	finally
    //   174	184	352	java/lang/Exception
    //   374	378	381	java/io/IOException
    //   393	397	400	java/io/IOException
    //   362	370	423	finally
    //   436	441	444	java/io/IOException
    //   458	462	465	java/io/IOException
  }
  
  /* Error */
  private static void j(String paramString1, String paramString2)
  {
    // Byte code:
    //   0: new 85	java/lang/StringBuilder
    //   3: dup
    //   4: invokespecial 86	java/lang/StringBuilder:<init>	()V
    //   7: astore_2
    //   8: aload_2
    //   9: getstatic 88	b/d/w/d/a:a	Ljava/lang/String;
    //   12: invokevirtual 92	java/lang/StringBuilder:append	(Ljava/lang/String;)Ljava/lang/StringBuilder;
    //   15: pop
    //   16: aload_2
    //   17: getstatic 97	java/io/File:separator	Ljava/lang/String;
    //   20: invokevirtual 92	java/lang/StringBuilder:append	(Ljava/lang/String;)Ljava/lang/StringBuilder;
    //   23: pop
    //   24: aload_2
    //   25: ldc -58
    //   27: invokevirtual 92	java/lang/StringBuilder:append	(Ljava/lang/String;)Ljava/lang/StringBuilder;
    //   30: pop
    //   31: new 94	java/io/File
    //   34: dup
    //   35: aload_2
    //   36: invokevirtual 104	java/lang/StringBuilder:toString	()Ljava/lang/String;
    //   39: invokespecial 123	java/io/File:<init>	(Ljava/lang/String;)V
    //   42: astore_2
    //   43: aload_2
    //   44: invokevirtual 127	java/io/File:exists	()Z
    //   47: ifne +8 -> 55
    //   50: aload_2
    //   51: invokevirtual 130	java/io/File:mkdirs	()Z
    //   54: pop
    //   55: new 94	java/io/File
    //   58: dup
    //   59: aload_2
    //   60: ldc -58
    //   62: invokespecial 350	java/io/File:<init>	(Ljava/io/File;Ljava/lang/String;)V
    //   65: astore_2
    //   66: new 150	org/json/JSONObject
    //   69: astore_3
    //   70: aload_3
    //   71: invokespecial 351	org/json/JSONObject:<init>	()V
    //   74: aload_3
    //   75: ldc -110
    //   77: aload_0
    //   78: invokevirtual 354	org/json/JSONObject:put	(Ljava/lang/String;Ljava/lang/Object;)Lorg/json/JSONObject;
    //   81: pop
    //   82: aload_3
    //   83: ldc -99
    //   85: aload_1
    //   86: invokevirtual 354	org/json/JSONObject:put	(Ljava/lang/String;Ljava/lang/Object;)Lorg/json/JSONObject;
    //   89: pop
    //   90: new 356	java/io/FileWriter
    //   93: astore_1
    //   94: aload_1
    //   95: aload_2
    //   96: invokespecial 357	java/io/FileWriter:<init>	(Ljava/io/File;)V
    //   99: new 359	java/io/BufferedWriter
    //   102: astore 4
    //   104: aload 4
    //   106: aload_1
    //   107: invokespecial 362	java/io/BufferedWriter:<init>	(Ljava/io/Writer;)V
    //   110: aload_1
    //   111: astore_2
    //   112: aload 4
    //   114: astore 5
    //   116: aload 4
    //   118: aload_3
    //   119: invokevirtual 363	org/json/JSONObject:toString	()Ljava/lang/String;
    //   122: invokevirtual 365	java/io/BufferedWriter:write	(Ljava/lang/String;)V
    //   125: aload_1
    //   126: astore_2
    //   127: aload 4
    //   129: astore 5
    //   131: aload 4
    //   133: invokevirtual 366	java/io/BufferedWriter:flush	()V
    //   136: aload 4
    //   138: invokevirtual 367	java/io/BufferedWriter:close	()V
    //   141: aload_1
    //   142: invokevirtual 368	java/io/FileWriter:close	()V
    //   145: goto +106 -> 251
    //   148: astore_0
    //   149: aload_1
    //   150: astore_3
    //   151: aload 4
    //   153: astore_1
    //   154: goto +52 -> 206
    //   157: astore_0
    //   158: aload_1
    //   159: astore_3
    //   160: aload 4
    //   162: astore_1
    //   163: goto +43 -> 206
    //   166: astore_0
    //   167: aconst_null
    //   168: astore 5
    //   170: goto +85 -> 255
    //   173: astore_0
    //   174: goto +4 -> 178
    //   177: astore_0
    //   178: aconst_null
    //   179: astore_2
    //   180: aload_1
    //   181: astore_3
    //   182: aload_2
    //   183: astore_1
    //   184: goto +22 -> 206
    //   187: astore_0
    //   188: aconst_null
    //   189: astore 5
    //   191: aload 5
    //   193: astore_1
    //   194: goto +61 -> 255
    //   197: astore_0
    //   198: goto +4 -> 202
    //   201: astore_0
    //   202: aconst_null
    //   203: astore_1
    //   204: aload_1
    //   205: astore_3
    //   206: aload_3
    //   207: astore_2
    //   208: aload_1
    //   209: astore 5
    //   211: aload_0
    //   212: invokevirtual 220	java/lang/Exception:toString	()Ljava/lang/String;
    //   215: invokestatic 65	b/d/w/c/a:d	(Ljava/lang/String;)V
    //   218: aload_1
    //   219: ifnull +14 -> 233
    //   222: aload_1
    //   223: invokevirtual 367	java/io/BufferedWriter:close	()V
    //   226: goto +7 -> 233
    //   229: astore_0
    //   230: goto +14 -> 244
    //   233: aload_3
    //   234: ifnull +17 -> 251
    //   237: aload_3
    //   238: invokevirtual 368	java/io/FileWriter:close	()V
    //   241: goto +10 -> 251
    //   244: aload_0
    //   245: invokevirtual 217	java/io/IOException:toString	()Ljava/lang/String;
    //   248: invokestatic 65	b/d/w/c/a:d	(Ljava/lang/String;)V
    //   251: return
    //   252: astore_0
    //   253: aload_2
    //   254: astore_1
    //   255: aload 5
    //   257: ifnull +15 -> 272
    //   260: aload 5
    //   262: invokevirtual 367	java/io/BufferedWriter:close	()V
    //   265: goto +7 -> 272
    //   268: astore_1
    //   269: goto +14 -> 283
    //   272: aload_1
    //   273: ifnull +17 -> 290
    //   276: aload_1
    //   277: invokevirtual 368	java/io/FileWriter:close	()V
    //   280: goto +10 -> 290
    //   283: aload_1
    //   284: invokevirtual 217	java/io/IOException:toString	()Ljava/lang/String;
    //   287: invokestatic 65	b/d/w/c/a:d	(Ljava/lang/String;)V
    //   290: aload_0
    //   291: athrow
    // Local variable table:
    //   start	length	slot	name	signature
    //   0	292	0	paramString1	String
    //   0	292	1	paramString2	String
    //   7	247	2	localObject1	Object
    //   69	169	3	localObject2	Object
    //   102	59	4	localBufferedWriter	java.io.BufferedWriter
    //   114	147	5	localObject3	Object
    // Exception table:
    //   from	to	target	type
    //   116	125	148	org/json/JSONException
    //   131	136	148	org/json/JSONException
    //   116	125	157	java/io/IOException
    //   131	136	157	java/io/IOException
    //   99	110	166	finally
    //   99	110	173	org/json/JSONException
    //   99	110	177	java/io/IOException
    //   66	99	187	finally
    //   66	99	197	org/json/JSONException
    //   66	99	201	java/io/IOException
    //   136	145	229	java/io/IOException
    //   222	226	229	java/io/IOException
    //   237	241	229	java/io/IOException
    //   116	125	252	finally
    //   131	136	252	finally
    //   211	218	252	finally
    //   260	265	268	java/io/IOException
    //   276	280	268	java/io/IOException
  }
  
  public static void k(String paramString1, Object paramObject, String paramString2, String paramString3)
  {
    m(paramObject, d(paramString1, paramString2), paramString3);
  }
  
  public static void l(String paramString1, Object paramObject, String paramString2, String paramString3)
  {
    k(paramString1, c.u(paramObject), paramString2, paramString3);
  }
  
  /* Error */
  private static void m(Object paramObject, String paramString1, String paramString2)
  {
    // Byte code:
    //   0: aload_0
    //   1: ifnull +437 -> 438
    //   4: aload_1
    //   5: invokestatic 162	b/d/w/h/b:d	(Ljava/lang/CharSequence;)Z
    //   8: ifne +430 -> 438
    //   11: aload_2
    //   12: invokestatic 162	b/d/w/h/b:d	(Ljava/lang/CharSequence;)Z
    //   15: ifeq +6 -> 21
    //   18: goto +420 -> 438
    //   21: new 94	java/io/File
    //   24: dup
    //   25: aload_1
    //   26: invokespecial 123	java/io/File:<init>	(Ljava/lang/String;)V
    //   29: astore_3
    //   30: aload_3
    //   31: invokevirtual 127	java/io/File:exists	()Z
    //   34: ifne +8 -> 42
    //   37: aload_3
    //   38: invokevirtual 130	java/io/File:mkdirs	()Z
    //   41: pop
    //   42: new 85	java/lang/StringBuilder
    //   45: dup
    //   46: invokespecial 86	java/lang/StringBuilder:<init>	()V
    //   49: astore_3
    //   50: aload_3
    //   51: aload_1
    //   52: invokevirtual 92	java/lang/StringBuilder:append	(Ljava/lang/String;)Ljava/lang/StringBuilder;
    //   55: pop
    //   56: aload_3
    //   57: getstatic 97	java/io/File:separator	Ljava/lang/String;
    //   60: invokevirtual 92	java/lang/StringBuilder:append	(Ljava/lang/String;)Ljava/lang/StringBuilder;
    //   63: pop
    //   64: aload_3
    //   65: aload_2
    //   66: invokevirtual 92	java/lang/StringBuilder:append	(Ljava/lang/String;)Ljava/lang/StringBuilder;
    //   69: pop
    //   70: aload_3
    //   71: invokevirtual 104	java/lang/StringBuilder:toString	()Ljava/lang/String;
    //   74: astore_3
    //   75: getstatic 33	b/d/w/d/a:d	Ljava/util/Map;
    //   78: astore 4
    //   80: aload 4
    //   82: aload_1
    //   83: invokeinterface 309 2 0
    //   88: checkcast 311	java/util/concurrent/locks/ReadWriteLock
    //   91: astore_2
    //   92: aload_2
    //   93: astore 5
    //   95: aload_2
    //   96: ifnonnull +39 -> 135
    //   99: aload 4
    //   101: monitorenter
    //   102: new 313	java/util/concurrent/locks/ReentrantReadWriteLock
    //   105: astore 5
    //   107: aload 5
    //   109: invokespecial 314	java/util/concurrent/locks/ReentrantReadWriteLock:<init>	()V
    //   112: aload 4
    //   114: aload_1
    //   115: aload 5
    //   117: invokeinterface 318 3 0
    //   122: pop
    //   123: aload 4
    //   125: monitorexit
    //   126: goto +9 -> 135
    //   129: astore_0
    //   130: aload 4
    //   132: monitorexit
    //   133: aload_0
    //   134: athrow
    //   135: aload 5
    //   137: invokeinterface 382 1 0
    //   142: invokeinterface 327 1 0
    //   147: aconst_null
    //   148: astore 6
    //   150: aconst_null
    //   151: astore_2
    //   152: aconst_null
    //   153: astore 7
    //   155: new 94	java/io/File
    //   158: astore 4
    //   160: aload 4
    //   162: aload_3
    //   163: invokespecial 123	java/io/File:<init>	(Ljava/lang/String;)V
    //   166: new 258	java/io/FileOutputStream
    //   169: astore_1
    //   170: aload_1
    //   171: aload 4
    //   173: invokespecial 259	java/io/FileOutputStream:<init>	(Ljava/io/File;)V
    //   176: aload 6
    //   178: astore_2
    //   179: aload_1
    //   180: astore_3
    //   181: new 384	java/io/ByteArrayOutputStream
    //   184: astore 8
    //   186: aload 6
    //   188: astore_2
    //   189: aload_1
    //   190: astore_3
    //   191: aload 8
    //   193: invokespecial 385	java/io/ByteArrayOutputStream:<init>	()V
    //   196: aload 6
    //   198: astore_2
    //   199: aload_1
    //   200: astore_3
    //   201: new 387	java/io/ObjectOutputStream
    //   204: astore 4
    //   206: aload 6
    //   208: astore_2
    //   209: aload_1
    //   210: astore_3
    //   211: aload 4
    //   213: aload 8
    //   215: invokespecial 388	java/io/ObjectOutputStream:<init>	(Ljava/io/OutputStream;)V
    //   218: aload 4
    //   220: aload_0
    //   221: invokevirtual 392	java/io/ObjectOutputStream:writeObject	(Ljava/lang/Object;)V
    //   224: aload 4
    //   226: invokevirtual 393	java/io/ObjectOutputStream:flush	()V
    //   229: aload 4
    //   231: invokevirtual 394	java/io/ObjectOutputStream:close	()V
    //   234: aload 8
    //   236: invokevirtual 398	java/io/ByteArrayOutputStream:toByteArray	()[B
    //   239: astore_0
    //   240: aload_1
    //   241: getstatic 169	b/d/w/d/a:b	Lcom/tplink/libtputility/security/a;
    //   244: aload_0
    //   245: invokevirtual 266	com/tplink/libtputility/security/a:d	([B)[B
    //   248: invokevirtual 399	java/io/FileOutputStream:write	([B)V
    //   251: aload_1
    //   252: invokevirtual 274	java/io/FileOutputStream:flush	()V
    //   255: aload_1
    //   256: invokevirtual 277	java/io/FileOutputStream:close	()V
    //   259: aload 4
    //   261: invokevirtual 394	java/io/ObjectOutputStream:close	()V
    //   264: goto +11 -> 275
    //   267: astore_0
    //   268: aload_0
    //   269: invokevirtual 217	java/io/IOException:toString	()Ljava/lang/String;
    //   272: invokestatic 65	b/d/w/c/a:d	(Ljava/lang/String;)V
    //   275: aload_1
    //   276: invokevirtual 277	java/io/FileOutputStream:close	()V
    //   279: goto +91 -> 370
    //   282: astore_0
    //   283: goto +80 -> 363
    //   286: astore_0
    //   287: aload 4
    //   289: astore_2
    //   290: goto +96 -> 386
    //   293: astore_0
    //   294: goto +24 -> 318
    //   297: astore_0
    //   298: aload 7
    //   300: astore 4
    //   302: goto +16 -> 318
    //   305: astore_0
    //   306: aconst_null
    //   307: astore_1
    //   308: goto +78 -> 386
    //   311: astore_0
    //   312: aconst_null
    //   313: astore_1
    //   314: aload 7
    //   316: astore 4
    //   318: aload 4
    //   320: astore_2
    //   321: aload_1
    //   322: astore_3
    //   323: aload_0
    //   324: invokevirtual 220	java/lang/Exception:toString	()Ljava/lang/String;
    //   327: invokestatic 65	b/d/w/c/a:d	(Ljava/lang/String;)V
    //   330: aload 4
    //   332: ifnull +19 -> 351
    //   335: aload 4
    //   337: invokevirtual 394	java/io/ObjectOutputStream:close	()V
    //   340: goto +11 -> 351
    //   343: astore_0
    //   344: aload_0
    //   345: invokevirtual 217	java/io/IOException:toString	()Ljava/lang/String;
    //   348: invokestatic 65	b/d/w/c/a:d	(Ljava/lang/String;)V
    //   351: aload_1
    //   352: ifnull +18 -> 370
    //   355: aload_1
    //   356: invokevirtual 277	java/io/FileOutputStream:close	()V
    //   359: goto +11 -> 370
    //   362: astore_0
    //   363: aload_0
    //   364: invokevirtual 217	java/io/IOException:toString	()Ljava/lang/String;
    //   367: invokestatic 65	b/d/w/c/a:d	(Ljava/lang/String;)V
    //   370: aload 5
    //   372: invokeinterface 382 1 0
    //   377: invokeinterface 347 1 0
    //   382: return
    //   383: astore_0
    //   384: aload_3
    //   385: astore_1
    //   386: aload_2
    //   387: ifnull +18 -> 405
    //   390: aload_2
    //   391: invokevirtual 394	java/io/ObjectOutputStream:close	()V
    //   394: goto +11 -> 405
    //   397: astore_2
    //   398: aload_2
    //   399: invokevirtual 217	java/io/IOException:toString	()Ljava/lang/String;
    //   402: invokestatic 65	b/d/w/c/a:d	(Ljava/lang/String;)V
    //   405: aload_1
    //   406: ifnull +18 -> 424
    //   409: aload_1
    //   410: invokevirtual 277	java/io/FileOutputStream:close	()V
    //   413: goto +11 -> 424
    //   416: astore_1
    //   417: aload_1
    //   418: invokevirtual 217	java/io/IOException:toString	()Ljava/lang/String;
    //   421: invokestatic 65	b/d/w/c/a:d	(Ljava/lang/String;)V
    //   424: aload 5
    //   426: invokeinterface 382 1 0
    //   431: invokeinterface 347 1 0
    //   436: aload_0
    //   437: athrow
    //   438: return
    // Local variable table:
    //   start	length	slot	name	signature
    //   0	439	0	paramObject	Object
    //   0	439	1	paramString1	String
    //   0	439	2	paramString2	String
    //   29	356	3	localObject1	Object
    //   78	258	4	localObject2	Object
    //   93	332	5	localObject3	Object
    //   148	59	6	localObject4	Object
    //   153	162	7	localObject5	Object
    //   184	51	8	localByteArrayOutputStream	java.io.ByteArrayOutputStream
    // Exception table:
    //   from	to	target	type
    //   102	126	129	finally
    //   130	133	129	finally
    //   259	264	267	java/io/IOException
    //   275	279	282	java/io/IOException
    //   218	259	286	finally
    //   218	259	293	java/lang/Exception
    //   181	186	297	java/lang/Exception
    //   191	196	297	java/lang/Exception
    //   201	206	297	java/lang/Exception
    //   211	218	297	java/lang/Exception
    //   155	176	305	finally
    //   155	176	311	java/lang/Exception
    //   335	340	343	java/io/IOException
    //   355	359	362	java/io/IOException
    //   181	186	383	finally
    //   191	196	383	finally
    //   201	206	383	finally
    //   211	218	383	finally
    //   323	330	383	finally
    //   390	394	397	java/io/IOException
    //   409	413	416	java/io/IOException
  }
  
  private static class b
    implements ParameterizedType
  {
    private final Type[] c;
    
    b(Type[] paramArrayOfType)
    {
      this.c = paramArrayOfType;
    }
    
    @NonNull
    public Type[] getActualTypeArguments()
    {
      return this.c;
    }
    
    public Type getOwnerType()
    {
      return null;
    }
    
    @NonNull
    public Type getRawType()
    {
      return List.class;
    }
  }
  
  private static class c
    implements FileFilter
  {
    public boolean accept(File paramFile)
    {
      boolean bool1 = paramFile.isDirectory();
      boolean bool2 = false;
      boolean bool3 = bool2;
      if (bool1)
      {
        paramFile = paramFile.getName().split("_");
        bool3 = bool2;
        if (paramFile.length > 0)
        {
          bool3 = bool2;
          if (b.d.w.h.b.c(paramFile[0])) {
            bool3 = true;
          }
        }
      }
      return bool3;
    }
  }
}


/* Location:              C:\Users\User\Desktop\decompile\jdgui110\Tapojar.jar!\b\d\w\d\a.class
 * Java compiler version: 6 (50.0)
 * JD-Core Version:       0.7.1
 */