package com.tplink.libtpnetwork.Utils;

import android.content.Context;
import android.text.TextUtils;
import com.google.gson.Gson;
import com.google.gson.JsonSyntaxException;
import java.io.File;
import java.lang.reflect.ParameterizedType;
import java.lang.reflect.Type;
import java.util.ArrayList;
import java.util.HashMap;
import java.util.List;
import java.util.Map;
import java.util.concurrent.locks.ReadWriteLock;
import org.json.JSONObject;

public class s
{
  private static volatile String a;
  private static volatile com.tplink.libtputility.security.a b;
  private static Gson c = new Gson();
  private static final Map<String, ReadWriteLock> d = new HashMap();
  
  private static void a(File paramFile1, File paramFile2)
  {
    try
    {
      b.d.w.b.b.a(paramFile1, paramFile2);
    }
    catch (Exception paramFile1)
    {
      paramFile1.printStackTrace();
    }
  }
  
  private static void b(File paramFile)
  {
    if (paramFile != null) {
      try
      {
        if (!paramFile.exists()) {
          return;
        }
        if (paramFile.isFile())
        {
          paramFile.delete();
          return;
        }
        File[] arrayOfFile = paramFile.listFiles();
        if (arrayOfFile != null)
        {
          int i = arrayOfFile.length;
          for (int j = 0; j < i; j++) {
            b(arrayOfFile[j]);
          }
        }
        paramFile.delete();
      }
      catch (Exception paramFile)
      {
        paramFile.printStackTrace();
      }
    }
  }
  
  public static Object c(String paramString1, String paramString2, String paramString3)
  {
    return h(e(paramString1, paramString2), paramString3);
  }
  
  public static <T> List<T> d(String paramString1, String paramString2, String paramString3, Class<T> paramClass)
  {
    paramString2 = c(paramString1, paramString2, paramString3);
    if ((paramString2 instanceof String)) {
      try
      {
        paramString1 = c;
        paramString2 = (String)paramString2;
        paramString3 = new com/tplink/libtpnetwork/Utils/s$a;
        paramString3.<init>(new Class[] { paramClass });
        paramString1 = (List)paramString1.m(paramString2, paramString3);
        return paramString1;
      }
      catch (JsonSyntaxException paramString1)
      {
        b.d.w.c.a.d(paramString1.toString());
      }
    }
    return new ArrayList();
  }
  
  private static String e(String paramString1, String paramString2)
  {
    StringBuilder localStringBuilder = new StringBuilder();
    localStringBuilder.append(a);
    String str = File.separator;
    localStringBuilder.append(str);
    localStringBuilder.append(b.d.w.h.a.g(paramString1));
    localStringBuilder.append(str);
    localStringBuilder.append(paramString2);
    return localStringBuilder.toString();
  }
  
  public static void f(Context paramContext)
  {
    if (a == null) {
      try
      {
        Object localObject1 = new java/lang/StringBuilder;
        ((StringBuilder)localObject1).<init>();
        ((StringBuilder)localObject1).append(paramContext.getCacheDir().getAbsolutePath());
        Object localObject2 = File.separator;
        ((StringBuilder)localObject1).append((String)localObject2);
        ((StringBuilder)localObject1).append("model_cache");
        String str = ((StringBuilder)localObject1).toString();
        File localFile = paramContext.getExternalFilesDir("");
        if (localFile != null)
        {
          localObject1 = new java/lang/StringBuilder;
          ((StringBuilder)localObject1).<init>();
          ((StringBuilder)localObject1).append(localFile.getAbsolutePath());
          ((StringBuilder)localObject1).append((String)localObject2);
          ((StringBuilder)localObject1).append("model_cache");
          a = ((StringBuilder)localObject1).toString();
          l(str, a, localFile);
        }
        else
        {
          a = str;
        }
        localFile = new java/io/File;
        localFile.<init>(a);
        if (!localFile.exists()) {
          localFile.mkdirs();
        }
        localObject1 = com.tplink.libtputility.security.b.c();
        if (((com.tplink.libtputility.security.b)localObject1).f("deco_model_file_key"))
        {
          localObject2 = g();
          paramContext = null;
          if (localObject2 != null)
          {
            paramContext = ((com.tplink.libtputility.security.b)localObject1).a(((JSONObject)localObject2).optString("DECO_TPSERIALIZEUTILS_AES_KEY", ""), "deco_model_file_key");
            localObject2 = ((com.tplink.libtputility.security.b)localObject1).a(((JSONObject)localObject2).optString("DECO_TPSERIALIZEUTILS_AES_VECTOR", ""), "deco_model_file_key");
          }
          else
          {
            localObject2 = null;
          }
          if ((!TextUtils.isEmpty(paramContext)) && (!TextUtils.isEmpty((CharSequence)localObject2)))
          {
            localObject1 = new com/tplink/libtputility/security/a;
            ((com.tplink.libtputility.security.a)localObject1).<init>(paramContext, (String)localObject2);
            b = (com.tplink.libtputility.security.a)localObject1;
          }
          else
          {
            b(localFile);
            paramContext = new com/tplink/libtputility/security/a;
            paramContext.<init>();
            b = paramContext;
            i(((com.tplink.libtputility.security.b)localObject1).b(b.h(), "deco_model_file_key"), ((com.tplink.libtputility.security.b)localObject1).b(b.g(), "deco_model_file_key"));
          }
        }
        else
        {
          ((com.tplink.libtputility.security.b)localObject1).e(paramContext, "deco_model_file_key");
          paramContext = new com/tplink/libtputility/security/a;
          paramContext.<init>();
          b = paramContext;
          i(((com.tplink.libtputility.security.b)localObject1).b(b.h(), "deco_model_file_key"), ((com.tplink.libtputility.security.b)localObject1).b(b.g(), "deco_model_file_key"));
        }
      }
      finally {}
    }
  }
  
  /* Error */
  private static JSONObject g()
  {
    // Byte code:
    //   0: new 106	java/lang/StringBuilder
    //   3: dup
    //   4: invokespecial 107	java/lang/StringBuilder:<init>	()V
    //   7: astore_0
    //   8: aload_0
    //   9: getstatic 109	com/tplink/libtpnetwork/Utils/s:a	Ljava/lang/String;
    //   12: invokevirtual 113	java/lang/StringBuilder:append	(Ljava/lang/String;)Ljava/lang/StringBuilder;
    //   15: pop
    //   16: getstatic 116	java/io/File:separator	Ljava/lang/String;
    //   19: astore_1
    //   20: aload_0
    //   21: aload_1
    //   22: invokevirtual 113	java/lang/StringBuilder:append	(Ljava/lang/String;)Ljava/lang/StringBuilder;
    //   25: pop
    //   26: aload_0
    //   27: ldc -47
    //   29: invokevirtual 113	java/lang/StringBuilder:append	(Ljava/lang/String;)Ljava/lang/StringBuilder;
    //   32: pop
    //   33: aload_0
    //   34: aload_1
    //   35: invokevirtual 113	java/lang/StringBuilder:append	(Ljava/lang/String;)Ljava/lang/StringBuilder;
    //   38: pop
    //   39: aload_0
    //   40: ldc -47
    //   42: invokevirtual 113	java/lang/StringBuilder:append	(Ljava/lang/String;)Ljava/lang/StringBuilder;
    //   45: pop
    //   46: new 45	java/io/File
    //   49: dup
    //   50: aload_0
    //   51: invokevirtual 123	java/lang/StringBuilder:toString	()Ljava/lang/String;
    //   54: invokespecial 148	java/io/File:<init>	(Ljava/lang/String;)V
    //   57: astore_1
    //   58: aconst_null
    //   59: astore_2
    //   60: new 211	java/io/FileReader
    //   63: astore_0
    //   64: aload_0
    //   65: aload_1
    //   66: invokespecial 213	java/io/FileReader:<init>	(Ljava/io/File;)V
    //   69: new 215	java/io/BufferedReader
    //   72: astore_3
    //   73: aload_3
    //   74: aload_0
    //   75: invokespecial 218	java/io/BufferedReader:<init>	(Ljava/io/Reader;)V
    //   78: aload_3
    //   79: astore_1
    //   80: aload_0
    //   81: astore 4
    //   83: new 106	java/lang/StringBuilder
    //   86: astore 5
    //   88: aload_3
    //   89: astore_1
    //   90: aload_0
    //   91: astore 4
    //   93: aload 5
    //   95: invokespecial 107	java/lang/StringBuilder:<init>	()V
    //   98: aload_3
    //   99: astore_1
    //   100: aload_0
    //   101: astore 4
    //   103: aload_3
    //   104: invokevirtual 221	java/io/BufferedReader:readLine	()Ljava/lang/String;
    //   107: astore 6
    //   109: aload 6
    //   111: ifnull +19 -> 130
    //   114: aload_3
    //   115: astore_1
    //   116: aload_0
    //   117: astore 4
    //   119: aload 5
    //   121: aload 6
    //   123: invokevirtual 113	java/lang/StringBuilder:append	(Ljava/lang/String;)Ljava/lang/StringBuilder;
    //   126: pop
    //   127: goto -29 -> 98
    //   130: aload_3
    //   131: astore_1
    //   132: aload_0
    //   133: astore 4
    //   135: new 168	org/json/JSONObject
    //   138: dup
    //   139: aload 5
    //   141: invokevirtual 123	java/lang/StringBuilder:toString	()Ljava/lang/String;
    //   144: invokespecial 222	org/json/JSONObject:<init>	(Ljava/lang/String;)V
    //   147: astore 5
    //   149: aload_3
    //   150: invokevirtual 225	java/io/BufferedReader:close	()V
    //   153: aload_0
    //   154: invokevirtual 226	java/io/FileReader:close	()V
    //   157: goto +11 -> 168
    //   160: astore_0
    //   161: aload_0
    //   162: invokevirtual 227	java/io/IOException:toString	()Ljava/lang/String;
    //   165: invokestatic 99	b/d/w/c/a:d	(Ljava/lang/String;)V
    //   168: aload 5
    //   170: astore_1
    //   171: goto +197 -> 368
    //   174: astore 5
    //   176: goto +56 -> 232
    //   179: astore 5
    //   181: goto +93 -> 274
    //   184: astore 5
    //   186: goto +130 -> 316
    //   189: astore 4
    //   191: aconst_null
    //   192: astore_1
    //   193: goto +184 -> 377
    //   196: astore 5
    //   198: aconst_null
    //   199: astore_3
    //   200: goto +32 -> 232
    //   203: astore 5
    //   205: aconst_null
    //   206: astore_3
    //   207: goto +67 -> 274
    //   210: astore 5
    //   212: aconst_null
    //   213: astore_3
    //   214: goto +102 -> 316
    //   217: astore 4
    //   219: aconst_null
    //   220: astore_0
    //   221: aload_0
    //   222: astore_1
    //   223: goto +154 -> 377
    //   226: astore 5
    //   228: aconst_null
    //   229: astore_3
    //   230: aload_3
    //   231: astore_0
    //   232: aload_3
    //   233: astore_1
    //   234: aload_0
    //   235: astore 4
    //   237: aload 5
    //   239: invokevirtual 228	org/json/JSONException:toString	()Ljava/lang/String;
    //   242: invokestatic 99	b/d/w/c/a:d	(Ljava/lang/String;)V
    //   245: aload_3
    //   246: ifnull +7 -> 253
    //   249: aload_3
    //   250: invokevirtual 225	java/io/BufferedReader:close	()V
    //   253: aload_2
    //   254: astore_1
    //   255: aload_0
    //   256: ifnull +112 -> 368
    //   259: aload_0
    //   260: invokevirtual 226	java/io/FileReader:close	()V
    //   263: aload_2
    //   264: astore_1
    //   265: goto +103 -> 368
    //   268: astore 5
    //   270: aconst_null
    //   271: astore_3
    //   272: aload_3
    //   273: astore_0
    //   274: aload_3
    //   275: astore_1
    //   276: aload_0
    //   277: astore 4
    //   279: aload 5
    //   281: invokevirtual 227	java/io/IOException:toString	()Ljava/lang/String;
    //   284: invokestatic 99	b/d/w/c/a:d	(Ljava/lang/String;)V
    //   287: aload_3
    //   288: ifnull +7 -> 295
    //   291: aload_3
    //   292: invokevirtual 225	java/io/BufferedReader:close	()V
    //   295: aload_2
    //   296: astore_1
    //   297: aload_0
    //   298: ifnull +70 -> 368
    //   301: aload_0
    //   302: invokevirtual 226	java/io/FileReader:close	()V
    //   305: aload_2
    //   306: astore_1
    //   307: goto +61 -> 368
    //   310: astore 5
    //   312: aconst_null
    //   313: astore_3
    //   314: aload_3
    //   315: astore_0
    //   316: aload_3
    //   317: astore_1
    //   318: aload_0
    //   319: astore 4
    //   321: aload 5
    //   323: invokevirtual 229	java/io/FileNotFoundException:toString	()Ljava/lang/String;
    //   326: invokestatic 99	b/d/w/c/a:d	(Ljava/lang/String;)V
    //   329: aload_3
    //   330: ifnull +14 -> 344
    //   333: aload_3
    //   334: invokevirtual 225	java/io/BufferedReader:close	()V
    //   337: goto +7 -> 344
    //   340: astore_0
    //   341: goto +18 -> 359
    //   344: aload_2
    //   345: astore_1
    //   346: aload_0
    //   347: ifnull +21 -> 368
    //   350: aload_0
    //   351: invokevirtual 226	java/io/FileReader:close	()V
    //   354: aload_2
    //   355: astore_1
    //   356: goto +12 -> 368
    //   359: aload_0
    //   360: invokevirtual 227	java/io/IOException:toString	()Ljava/lang/String;
    //   363: invokestatic 99	b/d/w/c/a:d	(Ljava/lang/String;)V
    //   366: aload_2
    //   367: astore_1
    //   368: aload_1
    //   369: areturn
    //   370: astore_3
    //   371: aload 4
    //   373: astore_0
    //   374: aload_3
    //   375: astore 4
    //   377: aload_1
    //   378: ifnull +14 -> 392
    //   381: aload_1
    //   382: invokevirtual 225	java/io/BufferedReader:close	()V
    //   385: goto +7 -> 392
    //   388: astore_0
    //   389: goto +14 -> 403
    //   392: aload_0
    //   393: ifnull +17 -> 410
    //   396: aload_0
    //   397: invokevirtual 226	java/io/FileReader:close	()V
    //   400: goto +10 -> 410
    //   403: aload_0
    //   404: invokevirtual 227	java/io/IOException:toString	()Ljava/lang/String;
    //   407: invokestatic 99	b/d/w/c/a:d	(Ljava/lang/String;)V
    //   410: aload 4
    //   412: athrow
    // Local variable table:
    //   start	length	slot	name	signature
    //   7	147	0	localObject1	Object
    //   160	2	0	localIOException1	java.io.IOException
    //   220	99	0	localObject2	Object
    //   340	20	0	localIOException2	java.io.IOException
    //   373	1	0	localObject3	Object
    //   388	16	0	localIOException3	java.io.IOException
    //   19	363	1	localObject4	Object
    //   59	308	2	localObject5	Object
    //   72	262	3	localBufferedReader	java.io.BufferedReader
    //   370	5	3	localObject6	Object
    //   81	53	4	localObject7	Object
    //   189	1	4	localObject8	Object
    //   217	1	4	localObject9	Object
    //   235	176	4	localObject10	Object
    //   86	83	5	localObject11	Object
    //   174	1	5	localJSONException1	org.json.JSONException
    //   179	1	5	localIOException4	java.io.IOException
    //   184	1	5	localFileNotFoundException1	java.io.FileNotFoundException
    //   196	1	5	localJSONException2	org.json.JSONException
    //   203	1	5	localIOException5	java.io.IOException
    //   210	1	5	localFileNotFoundException2	java.io.FileNotFoundException
    //   226	12	5	localJSONException3	org.json.JSONException
    //   268	12	5	localIOException6	java.io.IOException
    //   310	12	5	localFileNotFoundException3	java.io.FileNotFoundException
    //   107	15	6	str	String
    // Exception table:
    //   from	to	target	type
    //   149	157	160	java/io/IOException
    //   83	88	174	org/json/JSONException
    //   93	98	174	org/json/JSONException
    //   103	109	174	org/json/JSONException
    //   119	127	174	org/json/JSONException
    //   135	149	174	org/json/JSONException
    //   83	88	179	java/io/IOException
    //   93	98	179	java/io/IOException
    //   103	109	179	java/io/IOException
    //   119	127	179	java/io/IOException
    //   135	149	179	java/io/IOException
    //   83	88	184	java/io/FileNotFoundException
    //   93	98	184	java/io/FileNotFoundException
    //   103	109	184	java/io/FileNotFoundException
    //   119	127	184	java/io/FileNotFoundException
    //   135	149	184	java/io/FileNotFoundException
    //   69	78	189	finally
    //   69	78	196	org/json/JSONException
    //   69	78	203	java/io/IOException
    //   69	78	210	java/io/FileNotFoundException
    //   60	69	217	finally
    //   60	69	226	org/json/JSONException
    //   60	69	268	java/io/IOException
    //   60	69	310	java/io/FileNotFoundException
    //   249	253	340	java/io/IOException
    //   259	263	340	java/io/IOException
    //   291	295	340	java/io/IOException
    //   301	305	340	java/io/IOException
    //   333	337	340	java/io/IOException
    //   350	354	340	java/io/IOException
    //   83	88	370	finally
    //   93	98	370	finally
    //   103	109	370	finally
    //   119	127	370	finally
    //   135	149	370	finally
    //   237	245	370	finally
    //   279	287	370	finally
    //   321	329	370	finally
    //   381	385	388	java/io/IOException
    //   396	400	388	java/io/IOException
  }
  
  /* Error */
  public static Object h(String paramString1, String paramString2)
  {
    // Byte code:
    //   0: aload_0
    //   1: invokestatic 181	android/text/TextUtils:isEmpty	(Ljava/lang/CharSequence;)Z
    //   4: istore_2
    //   5: aconst_null
    //   6: astore_3
    //   7: iload_2
    //   8: ifne +529 -> 537
    //   11: aload_1
    //   12: invokestatic 181	android/text/TextUtils:isEmpty	(Ljava/lang/CharSequence;)Z
    //   15: ifeq +6 -> 21
    //   18: goto +519 -> 537
    //   21: new 106	java/lang/StringBuilder
    //   24: dup
    //   25: invokespecial 107	java/lang/StringBuilder:<init>	()V
    //   28: astore 4
    //   30: aload 4
    //   32: aload_0
    //   33: invokevirtual 113	java/lang/StringBuilder:append	(Ljava/lang/String;)Ljava/lang/StringBuilder;
    //   36: pop
    //   37: aload 4
    //   39: getstatic 116	java/io/File:separator	Ljava/lang/String;
    //   42: invokevirtual 113	java/lang/StringBuilder:append	(Ljava/lang/String;)Ljava/lang/StringBuilder;
    //   45: pop
    //   46: aload 4
    //   48: aload_1
    //   49: invokevirtual 113	java/lang/StringBuilder:append	(Ljava/lang/String;)Ljava/lang/StringBuilder;
    //   52: pop
    //   53: new 45	java/io/File
    //   56: dup
    //   57: aload 4
    //   59: invokevirtual 123	java/lang/StringBuilder:toString	()Ljava/lang/String;
    //   62: invokespecial 148	java/io/File:<init>	(Ljava/lang/String;)V
    //   65: astore 4
    //   67: aload 4
    //   69: invokevirtual 49	java/io/File:exists	()Z
    //   72: ifeq +465 -> 537
    //   75: aload 4
    //   77: invokevirtual 52	java/io/File:isFile	()Z
    //   80: ifeq +457 -> 537
    //   83: aload 4
    //   85: invokevirtual 233	java/io/File:length	()J
    //   88: lconst_0
    //   89: lcmp
    //   90: ifne +6 -> 96
    //   93: goto +444 -> 537
    //   96: getstatic 29	com/tplink/libtpnetwork/Utils/s:d	Ljava/util/Map;
    //   99: astore 5
    //   101: aload 5
    //   103: aload_0
    //   104: invokeinterface 239 2 0
    //   109: checkcast 241	java/util/concurrent/locks/ReadWriteLock
    //   112: astore_1
    //   113: aload_1
    //   114: astore 6
    //   116: aload_1
    //   117: ifnonnull +39 -> 156
    //   120: aload 5
    //   122: monitorenter
    //   123: new 243	java/util/concurrent/locks/ReentrantReadWriteLock
    //   126: astore 6
    //   128: aload 6
    //   130: invokespecial 244	java/util/concurrent/locks/ReentrantReadWriteLock:<init>	()V
    //   133: aload 5
    //   135: aload_0
    //   136: aload 6
    //   138: invokeinterface 248 3 0
    //   143: pop
    //   144: aload 5
    //   146: monitorexit
    //   147: goto +9 -> 156
    //   150: astore_0
    //   151: aload 5
    //   153: monitorexit
    //   154: aload_0
    //   155: athrow
    //   156: aload 6
    //   158: invokeinterface 252 1 0
    //   163: invokeinterface 257 1 0
    //   168: new 259	java/io/FileInputStream
    //   171: astore_1
    //   172: aload_1
    //   173: aload 4
    //   175: invokespecial 260	java/io/FileInputStream:<init>	(Ljava/io/File;)V
    //   178: aload 4
    //   180: invokevirtual 233	java/io/File:length	()J
    //   183: l2i
    //   184: newarray <illegal type>
    //   186: astore_0
    //   187: aload_1
    //   188: aload_0
    //   189: invokevirtual 264	java/io/FileInputStream:read	([B)I
    //   192: pop
    //   193: getstatic 188	com/tplink/libtpnetwork/Utils/s:b	Lcom/tplink/libtputility/security/a;
    //   196: aload_0
    //   197: invokevirtual 267	com/tplink/libtputility/security/a:b	([B)[B
    //   200: astore 4
    //   202: new 269	java/io/BufferedInputStream
    //   205: astore_0
    //   206: new 271	java/io/ByteArrayInputStream
    //   209: astore_3
    //   210: aload_3
    //   211: aload 4
    //   213: invokespecial 274	java/io/ByteArrayInputStream:<init>	([B)V
    //   216: aload_0
    //   217: aload_3
    //   218: invokespecial 277	java/io/BufferedInputStream:<init>	(Ljava/io/InputStream;)V
    //   221: new 279	java/io/ObjectInputStream
    //   224: astore 7
    //   226: aload 7
    //   228: aload_0
    //   229: invokespecial 280	java/io/ObjectInputStream:<init>	(Ljava/io/InputStream;)V
    //   232: aload_1
    //   233: astore_3
    //   234: aload 7
    //   236: astore 4
    //   238: aload 7
    //   240: invokevirtual 284	java/io/ObjectInputStream:readObject	()Ljava/lang/Object;
    //   243: astore_0
    //   244: aload_1
    //   245: astore_3
    //   246: aload 7
    //   248: astore 4
    //   250: aload 7
    //   252: invokevirtual 285	java/io/ObjectInputStream:close	()V
    //   255: aload_1
    //   256: invokevirtual 286	java/io/FileInputStream:close	()V
    //   259: goto +8 -> 267
    //   262: astore_1
    //   263: aload_1
    //   264: invokevirtual 287	java/io/IOException:printStackTrace	()V
    //   267: aload 7
    //   269: invokevirtual 285	java/io/ObjectInputStream:close	()V
    //   272: aload_0
    //   273: astore_3
    //   274: goto +136 -> 410
    //   277: astore_1
    //   278: goto +126 -> 404
    //   281: astore 5
    //   283: aload_1
    //   284: astore 8
    //   286: aload 7
    //   288: astore_1
    //   289: goto +70 -> 359
    //   292: astore 5
    //   294: aconst_null
    //   295: astore_0
    //   296: aload_1
    //   297: astore 8
    //   299: aload 7
    //   301: astore_1
    //   302: goto +57 -> 359
    //   305: astore 5
    //   307: aload 7
    //   309: astore_0
    //   310: goto +120 -> 430
    //   313: astore_0
    //   314: aconst_null
    //   315: astore 4
    //   317: goto +172 -> 489
    //   320: astore 5
    //   322: aconst_null
    //   323: astore_0
    //   324: aload_0
    //   325: astore_3
    //   326: aload_1
    //   327: astore 8
    //   329: aload_3
    //   330: astore_1
    //   331: goto +28 -> 359
    //   334: astore 5
    //   336: aconst_null
    //   337: astore_0
    //   338: goto +92 -> 430
    //   341: astore_0
    //   342: aconst_null
    //   343: astore 4
    //   345: aload_3
    //   346: astore_1
    //   347: goto +142 -> 489
    //   350: astore 5
    //   352: aconst_null
    //   353: astore_1
    //   354: aload_1
    //   355: astore_0
    //   356: aload_0
    //   357: astore 8
    //   359: aload 8
    //   361: astore_3
    //   362: aload_1
    //   363: astore 4
    //   365: aload 5
    //   367: invokevirtual 42	java/lang/Exception:printStackTrace	()V
    //   370: aload 8
    //   372: ifnull +16 -> 388
    //   375: aload 8
    //   377: invokevirtual 286	java/io/FileInputStream:close	()V
    //   380: goto +8 -> 388
    //   383: astore_3
    //   384: aload_3
    //   385: invokevirtual 287	java/io/IOException:printStackTrace	()V
    //   388: aload_0
    //   389: astore_3
    //   390: aload_1
    //   391: ifnull +19 -> 410
    //   394: aload_1
    //   395: invokevirtual 285	java/io/ObjectInputStream:close	()V
    //   398: aload_0
    //   399: astore_3
    //   400: goto +10 -> 410
    //   403: astore_1
    //   404: aload_1
    //   405: invokevirtual 287	java/io/IOException:printStackTrace	()V
    //   408: aload_0
    //   409: astore_3
    //   410: aload 6
    //   412: invokeinterface 252 1 0
    //   417: invokeinterface 290 1 0
    //   422: aload_3
    //   423: areturn
    //   424: astore 5
    //   426: aconst_null
    //   427: astore_1
    //   428: aload_1
    //   429: astore_0
    //   430: aload_1
    //   431: astore_3
    //   432: aload_0
    //   433: astore 4
    //   435: aload 5
    //   437: invokevirtual 291	java/io/FileNotFoundException:printStackTrace	()V
    //   440: aload_1
    //   441: ifnull +15 -> 456
    //   444: aload_1
    //   445: invokevirtual 286	java/io/FileInputStream:close	()V
    //   448: goto +8 -> 456
    //   451: astore_1
    //   452: aload_1
    //   453: invokevirtual 287	java/io/IOException:printStackTrace	()V
    //   456: aload_0
    //   457: ifnull +15 -> 472
    //   460: aload_0
    //   461: invokevirtual 285	java/io/ObjectInputStream:close	()V
    //   464: goto +8 -> 472
    //   467: astore_0
    //   468: aload_0
    //   469: invokevirtual 287	java/io/IOException:printStackTrace	()V
    //   472: aload 6
    //   474: invokeinterface 252 1 0
    //   479: invokeinterface 290 1 0
    //   484: aconst_null
    //   485: areturn
    //   486: astore_0
    //   487: aload_3
    //   488: astore_1
    //   489: aload_1
    //   490: ifnull +15 -> 505
    //   493: aload_1
    //   494: invokevirtual 286	java/io/FileInputStream:close	()V
    //   497: goto +8 -> 505
    //   500: astore_1
    //   501: aload_1
    //   502: invokevirtual 287	java/io/IOException:printStackTrace	()V
    //   505: aload 4
    //   507: ifnull +16 -> 523
    //   510: aload 4
    //   512: invokevirtual 285	java/io/ObjectInputStream:close	()V
    //   515: goto +8 -> 523
    //   518: astore_1
    //   519: aload_1
    //   520: invokevirtual 287	java/io/IOException:printStackTrace	()V
    //   523: aload 6
    //   525: invokeinterface 252 1 0
    //   530: invokeinterface 290 1 0
    //   535: aload_0
    //   536: athrow
    //   537: aconst_null
    //   538: areturn
    // Local variable table:
    //   start	length	slot	name	signature
    //   0	539	0	paramString1	String
    //   0	539	1	paramString2	String
    //   4	4	2	bool	boolean
    //   6	356	3	localObject1	Object
    //   383	2	3	localIOException	java.io.IOException
    //   389	99	3	str1	String
    //   28	483	4	localObject2	Object
    //   99	53	5	localMap	Map
    //   281	1	5	localException1	Exception
    //   292	1	5	localException2	Exception
    //   305	1	5	localFileNotFoundException1	java.io.FileNotFoundException
    //   320	1	5	localException3	Exception
    //   334	1	5	localFileNotFoundException2	java.io.FileNotFoundException
    //   350	16	5	localException4	Exception
    //   424	12	5	localFileNotFoundException3	java.io.FileNotFoundException
    //   114	410	6	localObject3	Object
    //   224	84	7	localObjectInputStream	java.io.ObjectInputStream
    //   284	92	8	str2	String
    // Exception table:
    //   from	to	target	type
    //   123	147	150	finally
    //   151	154	150	finally
    //   255	259	262	java/io/IOException
    //   267	272	277	java/io/IOException
    //   250	255	281	java/lang/Exception
    //   238	244	292	java/lang/Exception
    //   238	244	305	java/io/FileNotFoundException
    //   250	255	305	java/io/FileNotFoundException
    //   178	232	313	finally
    //   178	232	320	java/lang/Exception
    //   178	232	334	java/io/FileNotFoundException
    //   168	178	341	finally
    //   168	178	350	java/lang/Exception
    //   375	380	383	java/io/IOException
    //   394	398	403	java/io/IOException
    //   168	178	424	java/io/FileNotFoundException
    //   444	448	451	java/io/IOException
    //   460	464	467	java/io/IOException
    //   238	244	486	finally
    //   250	255	486	finally
    //   365	370	486	finally
    //   435	440	486	finally
    //   493	497	500	java/io/IOException
    //   510	515	518	java/io/IOException
  }
  
  /* Error */
  private static void i(String paramString1, String paramString2)
  {
    // Byte code:
    //   0: new 106	java/lang/StringBuilder
    //   3: dup
    //   4: invokespecial 107	java/lang/StringBuilder:<init>	()V
    //   7: astore_2
    //   8: aload_2
    //   9: getstatic 109	com/tplink/libtpnetwork/Utils/s:a	Ljava/lang/String;
    //   12: invokevirtual 113	java/lang/StringBuilder:append	(Ljava/lang/String;)Ljava/lang/StringBuilder;
    //   15: pop
    //   16: aload_2
    //   17: getstatic 116	java/io/File:separator	Ljava/lang/String;
    //   20: invokevirtual 113	java/lang/StringBuilder:append	(Ljava/lang/String;)Ljava/lang/StringBuilder;
    //   23: pop
    //   24: aload_2
    //   25: ldc -47
    //   27: invokevirtual 113	java/lang/StringBuilder:append	(Ljava/lang/String;)Ljava/lang/StringBuilder;
    //   30: pop
    //   31: new 45	java/io/File
    //   34: dup
    //   35: aload_2
    //   36: invokevirtual 123	java/lang/StringBuilder:toString	()Ljava/lang/String;
    //   39: invokespecial 148	java/io/File:<init>	(Ljava/lang/String;)V
    //   42: astore_2
    //   43: aload_2
    //   44: invokevirtual 49	java/io/File:exists	()Z
    //   47: ifne +8 -> 55
    //   50: aload_2
    //   51: invokevirtual 151	java/io/File:mkdirs	()Z
    //   54: pop
    //   55: new 45	java/io/File
    //   58: dup
    //   59: aload_2
    //   60: ldc -47
    //   62: invokespecial 294	java/io/File:<init>	(Ljava/io/File;Ljava/lang/String;)V
    //   65: astore_2
    //   66: new 168	org/json/JSONObject
    //   69: astore_3
    //   70: aload_3
    //   71: invokespecial 295	org/json/JSONObject:<init>	()V
    //   74: aload_3
    //   75: ldc -90
    //   77: aload_0
    //   78: invokevirtual 298	org/json/JSONObject:put	(Ljava/lang/String;Ljava/lang/Object;)Lorg/json/JSONObject;
    //   81: pop
    //   82: aload_3
    //   83: ldc -81
    //   85: aload_1
    //   86: invokevirtual 298	org/json/JSONObject:put	(Ljava/lang/String;Ljava/lang/Object;)Lorg/json/JSONObject;
    //   89: pop
    //   90: new 300	java/io/FileWriter
    //   93: astore_0
    //   94: aload_0
    //   95: aload_2
    //   96: invokespecial 301	java/io/FileWriter:<init>	(Ljava/io/File;)V
    //   99: new 303	java/io/BufferedWriter
    //   102: astore 4
    //   104: aload 4
    //   106: aload_0
    //   107: invokespecial 306	java/io/BufferedWriter:<init>	(Ljava/io/Writer;)V
    //   110: aload_0
    //   111: astore_1
    //   112: aload 4
    //   114: astore_2
    //   115: aload 4
    //   117: aload_3
    //   118: invokevirtual 307	org/json/JSONObject:toString	()Ljava/lang/String;
    //   121: invokevirtual 310	java/io/BufferedWriter:write	(Ljava/lang/String;)V
    //   124: aload_0
    //   125: astore_1
    //   126: aload 4
    //   128: astore_2
    //   129: aload 4
    //   131: invokevirtual 313	java/io/BufferedWriter:flush	()V
    //   134: aload 4
    //   136: invokevirtual 314	java/io/BufferedWriter:close	()V
    //   139: aload_0
    //   140: invokevirtual 315	java/io/FileWriter:close	()V
    //   143: goto +184 -> 327
    //   146: astore_3
    //   147: goto +53 -> 200
    //   150: astore_3
    //   151: goto +89 -> 240
    //   154: astore_3
    //   155: goto +125 -> 280
    //   158: astore_1
    //   159: aconst_null
    //   160: astore_2
    //   161: goto +174 -> 335
    //   164: astore_3
    //   165: aconst_null
    //   166: astore 4
    //   168: goto +32 -> 200
    //   171: astore_3
    //   172: aconst_null
    //   173: astore 4
    //   175: goto +65 -> 240
    //   178: astore_3
    //   179: aconst_null
    //   180: astore 4
    //   182: goto +98 -> 280
    //   185: astore_1
    //   186: aconst_null
    //   187: astore_2
    //   188: aload_2
    //   189: astore_0
    //   190: goto +145 -> 335
    //   193: astore_3
    //   194: aconst_null
    //   195: astore 4
    //   197: aload 4
    //   199: astore_0
    //   200: aload_0
    //   201: astore_1
    //   202: aload 4
    //   204: astore_2
    //   205: aload_3
    //   206: invokevirtual 228	org/json/JSONException:toString	()Ljava/lang/String;
    //   209: invokestatic 99	b/d/w/c/a:d	(Ljava/lang/String;)V
    //   212: aload 4
    //   214: ifnull +8 -> 222
    //   217: aload 4
    //   219: invokevirtual 314	java/io/BufferedWriter:close	()V
    //   222: aload_0
    //   223: ifnull +104 -> 327
    //   226: aload_0
    //   227: invokevirtual 315	java/io/FileWriter:close	()V
    //   230: goto +97 -> 327
    //   233: astore_3
    //   234: aconst_null
    //   235: astore 4
    //   237: aload 4
    //   239: astore_0
    //   240: aload_0
    //   241: astore_1
    //   242: aload 4
    //   244: astore_2
    //   245: aload_3
    //   246: invokevirtual 227	java/io/IOException:toString	()Ljava/lang/String;
    //   249: invokestatic 99	b/d/w/c/a:d	(Ljava/lang/String;)V
    //   252: aload 4
    //   254: ifnull +8 -> 262
    //   257: aload 4
    //   259: invokevirtual 314	java/io/BufferedWriter:close	()V
    //   262: aload_0
    //   263: ifnull +64 -> 327
    //   266: aload_0
    //   267: invokevirtual 315	java/io/FileWriter:close	()V
    //   270: goto +57 -> 327
    //   273: astore_3
    //   274: aconst_null
    //   275: astore 4
    //   277: aload 4
    //   279: astore_0
    //   280: aload_0
    //   281: astore_1
    //   282: aload 4
    //   284: astore_2
    //   285: aload_3
    //   286: invokevirtual 229	java/io/FileNotFoundException:toString	()Ljava/lang/String;
    //   289: invokestatic 99	b/d/w/c/a:d	(Ljava/lang/String;)V
    //   292: aload 4
    //   294: ifnull +15 -> 309
    //   297: aload 4
    //   299: invokevirtual 314	java/io/BufferedWriter:close	()V
    //   302: goto +7 -> 309
    //   305: astore_0
    //   306: goto +14 -> 320
    //   309: aload_0
    //   310: ifnull +17 -> 327
    //   313: aload_0
    //   314: invokevirtual 315	java/io/FileWriter:close	()V
    //   317: goto +10 -> 327
    //   320: aload_0
    //   321: invokevirtual 227	java/io/IOException:toString	()Ljava/lang/String;
    //   324: invokestatic 99	b/d/w/c/a:d	(Ljava/lang/String;)V
    //   327: return
    //   328: astore 4
    //   330: aload_1
    //   331: astore_0
    //   332: aload 4
    //   334: astore_1
    //   335: aload_2
    //   336: ifnull +14 -> 350
    //   339: aload_2
    //   340: invokevirtual 314	java/io/BufferedWriter:close	()V
    //   343: goto +7 -> 350
    //   346: astore_0
    //   347: goto +14 -> 361
    //   350: aload_0
    //   351: ifnull +17 -> 368
    //   354: aload_0
    //   355: invokevirtual 315	java/io/FileWriter:close	()V
    //   358: goto +10 -> 368
    //   361: aload_0
    //   362: invokevirtual 227	java/io/IOException:toString	()Ljava/lang/String;
    //   365: invokestatic 99	b/d/w/c/a:d	(Ljava/lang/String;)V
    //   368: aload_1
    //   369: athrow
    // Local variable table:
    //   start	length	slot	name	signature
    //   0	370	0	paramString1	String
    //   0	370	1	paramString2	String
    //   7	333	2	localObject1	Object
    //   69	49	3	localJSONObject	JSONObject
    //   146	1	3	localJSONException1	org.json.JSONException
    //   150	1	3	localIOException1	java.io.IOException
    //   154	1	3	localFileNotFoundException1	java.io.FileNotFoundException
    //   164	1	3	localJSONException2	org.json.JSONException
    //   171	1	3	localIOException2	java.io.IOException
    //   178	1	3	localFileNotFoundException2	java.io.FileNotFoundException
    //   193	13	3	localJSONException3	org.json.JSONException
    //   233	13	3	localIOException3	java.io.IOException
    //   273	13	3	localFileNotFoundException3	java.io.FileNotFoundException
    //   102	196	4	localBufferedWriter	java.io.BufferedWriter
    //   328	5	4	localObject2	Object
    // Exception table:
    //   from	to	target	type
    //   115	124	146	org/json/JSONException
    //   129	134	146	org/json/JSONException
    //   115	124	150	java/io/IOException
    //   129	134	150	java/io/IOException
    //   115	124	154	java/io/FileNotFoundException
    //   129	134	154	java/io/FileNotFoundException
    //   99	110	158	finally
    //   99	110	164	org/json/JSONException
    //   99	110	171	java/io/IOException
    //   99	110	178	java/io/FileNotFoundException
    //   66	99	185	finally
    //   66	99	193	org/json/JSONException
    //   66	99	233	java/io/IOException
    //   66	99	273	java/io/FileNotFoundException
    //   134	143	305	java/io/IOException
    //   217	222	305	java/io/IOException
    //   226	230	305	java/io/IOException
    //   257	262	305	java/io/IOException
    //   266	270	305	java/io/IOException
    //   297	302	305	java/io/IOException
    //   313	317	305	java/io/IOException
    //   115	124	328	finally
    //   129	134	328	finally
    //   205	212	328	finally
    //   245	252	328	finally
    //   285	292	328	finally
    //   339	343	346	java/io/IOException
    //   354	358	346	java/io/IOException
  }
  
  public static void j(String paramString1, Object paramObject, String paramString2, String paramString3)
  {
    m(paramObject, e(paramString1, paramString2), paramString3);
  }
  
  public static void k(String paramString1, Object paramObject, String paramString2, String paramString3)
  {
    j(paramString1, c.u(paramObject), paramString2, paramString3);
  }
  
  private static void l(String paramString1, String paramString2, File paramFile)
  {
    paramString1 = new File(paramString1);
    if ((!new File(paramString2).exists()) && (paramString1.exists())) {
      a(paramString1, paramFile);
    }
  }
  
  /* Error */
  public static void m(Object paramObject, String paramString1, String paramString2)
  {
    // Byte code:
    //   0: aload_0
    //   1: ifnonnull +4 -> 5
    //   4: return
    //   5: aload_1
    //   6: invokestatic 181	android/text/TextUtils:isEmpty	(Ljava/lang/CharSequence;)Z
    //   9: ifne +476 -> 485
    //   12: aload_2
    //   13: invokestatic 181	android/text/TextUtils:isEmpty	(Ljava/lang/CharSequence;)Z
    //   16: ifeq +6 -> 22
    //   19: goto +466 -> 485
    //   22: new 45	java/io/File
    //   25: dup
    //   26: aload_1
    //   27: invokespecial 148	java/io/File:<init>	(Ljava/lang/String;)V
    //   30: astore_3
    //   31: aload_3
    //   32: invokevirtual 49	java/io/File:exists	()Z
    //   35: ifne +8 -> 43
    //   38: aload_3
    //   39: invokevirtual 151	java/io/File:mkdirs	()Z
    //   42: pop
    //   43: new 106	java/lang/StringBuilder
    //   46: dup
    //   47: invokespecial 107	java/lang/StringBuilder:<init>	()V
    //   50: astore_3
    //   51: aload_3
    //   52: aload_1
    //   53: invokevirtual 113	java/lang/StringBuilder:append	(Ljava/lang/String;)Ljava/lang/StringBuilder;
    //   56: pop
    //   57: aload_3
    //   58: getstatic 116	java/io/File:separator	Ljava/lang/String;
    //   61: invokevirtual 113	java/lang/StringBuilder:append	(Ljava/lang/String;)Ljava/lang/StringBuilder;
    //   64: pop
    //   65: aload_3
    //   66: aload_2
    //   67: invokevirtual 113	java/lang/StringBuilder:append	(Ljava/lang/String;)Ljava/lang/StringBuilder;
    //   70: pop
    //   71: aload_3
    //   72: invokevirtual 123	java/lang/StringBuilder:toString	()Ljava/lang/String;
    //   75: astore_3
    //   76: getstatic 29	com/tplink/libtpnetwork/Utils/s:d	Ljava/util/Map;
    //   79: astore 4
    //   81: aload 4
    //   83: aload_1
    //   84: invokeinterface 239 2 0
    //   89: checkcast 241	java/util/concurrent/locks/ReadWriteLock
    //   92: astore_2
    //   93: aload_2
    //   94: astore 5
    //   96: aload_2
    //   97: ifnonnull +39 -> 136
    //   100: aload 4
    //   102: monitorenter
    //   103: new 243	java/util/concurrent/locks/ReentrantReadWriteLock
    //   106: astore 5
    //   108: aload 5
    //   110: invokespecial 244	java/util/concurrent/locks/ReentrantReadWriteLock:<init>	()V
    //   113: aload 4
    //   115: aload_1
    //   116: aload 5
    //   118: invokeinterface 248 3 0
    //   123: pop
    //   124: aload 4
    //   126: monitorexit
    //   127: goto +9 -> 136
    //   130: astore_0
    //   131: aload 4
    //   133: monitorexit
    //   134: aload_0
    //   135: athrow
    //   136: aload 5
    //   138: invokeinterface 332 1 0
    //   143: invokeinterface 257 1 0
    //   148: aconst_null
    //   149: astore 6
    //   151: aconst_null
    //   152: astore 7
    //   154: aconst_null
    //   155: astore_2
    //   156: aconst_null
    //   157: astore 8
    //   159: new 45	java/io/File
    //   162: astore 4
    //   164: aload 4
    //   166: aload_3
    //   167: invokespecial 148	java/io/File:<init>	(Ljava/lang/String;)V
    //   170: new 334	java/io/FileOutputStream
    //   173: astore_1
    //   174: aload_1
    //   175: aload 4
    //   177: invokespecial 335	java/io/FileOutputStream:<init>	(Ljava/io/File;)V
    //   180: aload 7
    //   182: astore_2
    //   183: aload_1
    //   184: astore_3
    //   185: new 337	java/io/ByteArrayOutputStream
    //   188: astore 9
    //   190: aload 7
    //   192: astore_2
    //   193: aload_1
    //   194: astore_3
    //   195: aload 9
    //   197: invokespecial 338	java/io/ByteArrayOutputStream:<init>	()V
    //   200: aload 7
    //   202: astore_2
    //   203: aload_1
    //   204: astore_3
    //   205: new 340	java/io/ObjectOutputStream
    //   208: astore 4
    //   210: aload 7
    //   212: astore_2
    //   213: aload_1
    //   214: astore_3
    //   215: aload 4
    //   217: aload 9
    //   219: invokespecial 343	java/io/ObjectOutputStream:<init>	(Ljava/io/OutputStream;)V
    //   222: aload 4
    //   224: aload_0
    //   225: invokevirtual 347	java/io/ObjectOutputStream:writeObject	(Ljava/lang/Object;)V
    //   228: aload 4
    //   230: invokevirtual 348	java/io/ObjectOutputStream:flush	()V
    //   233: aload 4
    //   235: invokevirtual 349	java/io/ObjectOutputStream:close	()V
    //   238: aload 9
    //   240: invokevirtual 353	java/io/ByteArrayOutputStream:toByteArray	()[B
    //   243: astore_0
    //   244: aload_1
    //   245: getstatic 188	com/tplink/libtpnetwork/Utils/s:b	Lcom/tplink/libtputility/security/a;
    //   248: aload_0
    //   249: invokevirtual 355	com/tplink/libtputility/security/a:d	([B)[B
    //   252: invokevirtual 357	java/io/FileOutputStream:write	([B)V
    //   255: aload_1
    //   256: invokevirtual 358	java/io/FileOutputStream:flush	()V
    //   259: aload_1
    //   260: invokevirtual 359	java/io/FileOutputStream:close	()V
    //   263: aload 4
    //   265: invokevirtual 349	java/io/ObjectOutputStream:close	()V
    //   268: goto +8 -> 276
    //   271: astore_0
    //   272: aload_0
    //   273: invokevirtual 287	java/io/IOException:printStackTrace	()V
    //   276: aload_1
    //   277: invokevirtual 359	java/io/FileOutputStream:close	()V
    //   280: goto +143 -> 423
    //   283: astore_0
    //   284: goto +135 -> 419
    //   287: astore_0
    //   288: aload 4
    //   290: astore_2
    //   291: goto +148 -> 439
    //   294: astore_0
    //   295: goto +36 -> 331
    //   298: astore_0
    //   299: goto +81 -> 380
    //   302: astore_0
    //   303: aload 8
    //   305: astore 4
    //   307: goto +24 -> 331
    //   310: astore_0
    //   311: aload 6
    //   313: astore 4
    //   315: goto +65 -> 380
    //   318: astore_0
    //   319: aconst_null
    //   320: astore_1
    //   321: goto +118 -> 439
    //   324: astore_0
    //   325: aconst_null
    //   326: astore_1
    //   327: aload 8
    //   329: astore 4
    //   331: aload 4
    //   333: astore_2
    //   334: aload_1
    //   335: astore_3
    //   336: aload_0
    //   337: invokevirtual 42	java/lang/Exception:printStackTrace	()V
    //   340: aload 4
    //   342: ifnull +16 -> 358
    //   345: aload 4
    //   347: invokevirtual 349	java/io/ObjectOutputStream:close	()V
    //   350: goto +8 -> 358
    //   353: astore_0
    //   354: aload_0
    //   355: invokevirtual 287	java/io/IOException:printStackTrace	()V
    //   358: aload_1
    //   359: ifnull +64 -> 423
    //   362: aload_1
    //   363: invokevirtual 359	java/io/FileOutputStream:close	()V
    //   366: goto +57 -> 423
    //   369: astore_0
    //   370: goto +49 -> 419
    //   373: astore_0
    //   374: aconst_null
    //   375: astore_1
    //   376: aload 6
    //   378: astore 4
    //   380: aload 4
    //   382: astore_2
    //   383: aload_1
    //   384: astore_3
    //   385: aload_0
    //   386: invokevirtual 287	java/io/IOException:printStackTrace	()V
    //   389: aload 4
    //   391: ifnull +16 -> 407
    //   394: aload 4
    //   396: invokevirtual 349	java/io/ObjectOutputStream:close	()V
    //   399: goto +8 -> 407
    //   402: astore_0
    //   403: aload_0
    //   404: invokevirtual 287	java/io/IOException:printStackTrace	()V
    //   407: aload_1
    //   408: ifnull +15 -> 423
    //   411: aload_1
    //   412: invokevirtual 359	java/io/FileOutputStream:close	()V
    //   415: goto +8 -> 423
    //   418: astore_0
    //   419: aload_0
    //   420: invokevirtual 287	java/io/IOException:printStackTrace	()V
    //   423: aload 5
    //   425: invokeinterface 332 1 0
    //   430: invokeinterface 290 1 0
    //   435: return
    //   436: astore_0
    //   437: aload_3
    //   438: astore_1
    //   439: aload_2
    //   440: ifnull +15 -> 455
    //   443: aload_2
    //   444: invokevirtual 349	java/io/ObjectOutputStream:close	()V
    //   447: goto +8 -> 455
    //   450: astore_2
    //   451: aload_2
    //   452: invokevirtual 287	java/io/IOException:printStackTrace	()V
    //   455: aload_1
    //   456: ifnull +15 -> 471
    //   459: aload_1
    //   460: invokevirtual 359	java/io/FileOutputStream:close	()V
    //   463: goto +8 -> 471
    //   466: astore_1
    //   467: aload_1
    //   468: invokevirtual 287	java/io/IOException:printStackTrace	()V
    //   471: aload 5
    //   473: invokeinterface 332 1 0
    //   478: invokeinterface 290 1 0
    //   483: aload_0
    //   484: athrow
    //   485: return
    // Local variable table:
    //   start	length	slot	name	signature
    //   0	486	0	paramObject	Object
    //   0	486	1	paramString1	String
    //   0	486	2	paramString2	String
    //   30	408	3	localObject1	Object
    //   79	316	4	localObject2	Object
    //   94	378	5	localObject3	Object
    //   149	228	6	localObject4	Object
    //   152	59	7	localObject5	Object
    //   157	171	8	localObject6	Object
    //   188	51	9	localByteArrayOutputStream	java.io.ByteArrayOutputStream
    // Exception table:
    //   from	to	target	type
    //   103	127	130	finally
    //   131	134	130	finally
    //   263	268	271	java/io/IOException
    //   276	280	283	java/io/IOException
    //   222	263	287	finally
    //   222	263	294	java/lang/Exception
    //   222	263	298	java/io/IOException
    //   185	190	302	java/lang/Exception
    //   195	200	302	java/lang/Exception
    //   205	210	302	java/lang/Exception
    //   215	222	302	java/lang/Exception
    //   185	190	310	java/io/IOException
    //   195	200	310	java/io/IOException
    //   205	210	310	java/io/IOException
    //   215	222	310	java/io/IOException
    //   159	180	318	finally
    //   159	180	324	java/lang/Exception
    //   345	350	353	java/io/IOException
    //   362	366	369	java/io/IOException
    //   159	180	373	java/io/IOException
    //   394	399	402	java/io/IOException
    //   411	415	418	java/io/IOException
    //   185	190	436	finally
    //   195	200	436	finally
    //   205	210	436	finally
    //   215	222	436	finally
    //   336	340	436	finally
    //   385	389	436	finally
    //   443	447	450	java/io/IOException
    //   459	463	466	java/io/IOException
  }
  
  static class a
    implements ParameterizedType
  {
    private final Type[] c;
    
    public a(Type[] paramArrayOfType)
    {
      this.c = paramArrayOfType;
    }
    
    public Type[] getActualTypeArguments()
    {
      return this.c;
    }
    
    public Type getOwnerType()
    {
      return null;
    }
    
    public Type getRawType()
    {
      return List.class;
    }
  }
}


/* Location:              C:\Users\User\Desktop\decompile\jdgui110\Tapojar.jar!\com\tplink\libtpnetwork\Utils\s.class
 * Java compiler version: 6 (50.0)
 * JD-Core Version:       0.7.1
 */